Workbook

Sheet 00 Read Me
A1: Clarify AI — Enterprise QA Testing Workbook | J1: Dashboard | K1: NAV | L1: Features | M1: Bugs | N1: Launch | O1: Smoke | P1: Creds | Q1: Env | R1: Playbooks | S1: Cases | T1: Sign-Off
A4: Application | B4: Clarify AI
A5: Description | B5: AI-powered interview preparation & rehearsal platform with Indian gov-exam MCQ mock tests, live coaching overlay, and dual Stripe/Razorpay billing.
A6: Tech stack | B6: React 18 + TypeScript + Vite + Tailwind/shadcn · Supabase (Auth, Postgres+RLS, Edge/Deno, Storage, Realtime) · Electron · Deepgram · Gemini/OpenAI/Anthropic · Stripe + Razorpay
A7: Portals | B7: Marketing · Auth · Candidate App · Admin · Electron Overlay
A8: Roles | B8: Guest · Free User · Pro User · Max User · Admin
A9: Version under test | B9: 1.0.0 / 1.0.0-beta
A10: Generated | B10: 2026-07-29
A12: HOW TO USE
A13: 1 | B13: Start at NAV Hub or 01 Dashboard — KPIs + charts.
A14: 2 | B14: QA opens QA Tasks — pick your rows (Shreya / Raj). Execute linked TCs on 04.
A15: 3 | B15: On Fail: set Pass/Fail=Fail on 04 → add a row on 06 Bug Tracker (Reported By = you, Assigned To = a Developer).
A16: 4 | B16: Dev Tasks auto-mirrors 06 — developers see Needs Dev Action=Yes. Filter that column.
A17: 5 | B17: Dev sets Bug Status=Fixed or Retest on 06 → QA retests → Closed. Fill Daily Log daily.
A18: 6 | B18: Complete 19 Production Readiness and 20 Release Sign-Off for Go/No-Go.
A19: 7 | B19: Slicer tip: AutoFilter on Bug Tracker / Dev Tasks / QA Tasks (Status, Owner, Priority).
A21: QA TEAM (production)
B22: Shreya Patil — Practice Coach, Overlay, Mock, Sessions/Debrief, Documents, UI/UX, Electron
B23: Raj Balani — Auth, Billing, Gov Exams, Admin, Prep Lab, Security, Regression
A24: DEV TEAM
B25: Dev Lead · Live Coach Dev · Platform Dev · GovExams Dev · Desktop Dev — see Dev Team sheet
A26: Green | B26: Pass / Yes / Closed / Done
A27: Red | B27: Fail / No / Critical / Blocked
A28: Yellow | B28: In Progress / Open / Medium / Queued
A29: Gray | B29: Not Started / Not Run
A30: Blue | B30: Completed / Passed / Ready
A32: SCALING
B33: One row per entity; filters + freeze panes. Dashboard / Dev Tasks formulas scan to row 5000 / 152.
A34: Google Sheets | B34: Upload .xlsx to Drive → Open with Google Sheets. Hyperlinks transfer; confirm Lists ranges after import.
A36: SHEET INDEX (click sheet tabs or use NAV Hub)
A37: NAV Hub | B37: Clickable map of every sheet — start here
A38: 01 Dashboard | B38: Executive KPIs + charts (Power BI style)
A39: QA Tasks | B39: Shreya & Raj execution queue
A40: Dev Team | B40: Developer roster + open-bug counts
A41: Dev Tasks | B41: Live mirror of Bug Tracker for engineers
A42: 02 Module Master | B42: 20 Clarify modules
A43: 03 Feature Inventory | B43: 114 features + routes + how-it-works
A44: 04 Test Case Repository | B44: Executable cases
A45: 05 E2E User Flows | B45: Cross-module journeys
A46: 06 Bug Tracker | B46: Defect lifecycle — source of truth
A47: 07 UI-UX Testing | B47: Visual / a11y
A48: 08 Mobile Responsiveness | B48: Breakpoints
... A68: Lists | B68: Dropdown vocabulary — do not delete

Sheet NAV Hub
A1: NAV Hub — Clarify AI QA Workbook (Power BI style) | J1: Dashboard | K1: ● NAV | L1: Features | M1: Bugs | N1: Launch | O1: Smoke | P1: Creds | Q1: Env | R1: Playbooks | S1: Cases | T1: Sign-Off
A2: Click any link to jump. Treat AutoFilter columns on Features/Bugs as slicers.
A4: Executive
A5: 01 Dashboard | B5: KPIs, charts, inventory snapshot | C5: Open →
A6: 24 Launch Status | B6: Fixed / Open / Blocked rollup | C6: Open →
A7: 20 Release Sign-Off | B7: Go / No-Go | C7: Open →
A8: 19 Production Readiness | B8: Module readiness % | C8: Open →
A10: Scope & Coverage
A11: 02 Module Master | B11: 20 modules | C11: Open →
A12: 03 Feature Inventory | B12: Routes, deep links, how-it-works | C12: Open →
A13: 23 Module Playbooks | B13: Happy-path runbooks | C13: Open →
A14: 17 Role Based Testing | B14: Plan gates | C14: Open →
A16: Execution
A17: QA Tasks | B17: Shreya & Raj task board | C17: Open →
A18: 04 Test Case Repository | B18: Case library | C18: Open →
A19: 05 E2E User Flows | B19: Golden paths | C19: Open →
A20: 25 Smoke Pack | B20: Must-pass (~20) | C20: Open →
A21: 18 Regression Testing | B21: Release pack | C21: Open →
A22: Daily Log | B22: Trend feed | C22: Open →
A24: Defects & Quality
A25: 06 Bug Tracker | B25: Lifecycle (source of truth) | C25: Open →
A26: Dev Tasks | B26: Live bug mirror for developers | C26: Open →
A27: Dev Team | B27: Dev roster + load | C27: Open →
A28: 07 UI-UX Testing | B28: Visual / a11y | C28: Open →
A29: 08 Mobile Responsiveness | B29: Breakpoints | C29: Open →
A30: 13 Performance Testing | B30: Latency | C30: Open →
A32: Platform
A33: 09 API Testing | B33: Edge functions | C33: Open →
A34: 10 Database Validation | B34: Schema / RLS | C34: Open →
A35: 11 Authentication Testing | B35: Auth + MFA | C35: Open →
A36: 12 Security Testing | B36: OWASP-style | C36: Open →
A38: Domains
A39: 14 Live Coaching Testing | B39: Coach + overlay | C39: Open →
A40: 15 Gov Exam Mock Testing | B40: MCQ engine | C40: Open →
A41: 16 Billing Credits Testing | B41: Stripe / Razorpay | C41: Open →
A43: Ops & Hire Pack
A44: 21 Test Credentials | B44: Placeholders only | C44: Open →
A45: 22 Environments | B45: URLs + secrets checklist | C45: Open →
A46: QA Team | B46: Shreya Patil · Raj Balani | C46: Open →
A47: 00 Read Me | B47: How to use | C47: Open →
A48: Lists | B48: Dropdown vocabulary | C48: Open →

Sheet 01 Dashboard
A1: Clarify AI — QA Executive Dashboard (Power BI style) | J1: ● Dashboard | K1: NAV | L1: Features | M1: Bugs | N1: Launch | O1: Smoke | P1: Creds | Q1: Env | R1: Playbooks | S1: Cases | T1: Sign-Off
A2: Synced 2026-07-29 · Formula KPIs + inventory snapshot · Use AutoFilter on Features/Bugs as slicers · Click NAV Hub for sheet map
A3: KEY PERFORMANCE INDICATORS | F3: Count | I3: Daily Progress | N3: QA Person | O3: Actual Hours
A4: Total Modules | B4: =IFERROR(COUNTA('02 Module Master'!A3:A5000)-COUNTIF('02 Module Master'!A3:A5000,"TOTAL"),0) | C4: PROGRESS BARS | F4: Passed | G4: =IFERROR(B7,0) | I4: Date | J4: Executed | K4: Passed | L4: Hours | N4: Shreya Patil | O4: =IFERROR(SUMIF('04 Test Case Repository'!S$3:S$5000,N4,'04 Test Case Repository'!U$3:U$5000),0)
A5: Total Features | B5: =IFERROR(COUNTA('03 Feature Inventory'!A3:A5000)-COUNTIF('03 Feature Inventory'!A3:A5000,"TOTAL"),0) | C5: Pass Rate | D5: =IFERROR(REPT("#",MAX(0,MIN(10,ROUND(N(B16)*10,0))))&REPT("-",10-MAX(0,MIN(10,ROUND(N(B16)*10,0)))),REPT("-",10)) | F5: Failed | G5: =IFERROR(B8,0) | I5: =IFERROR('Daily Log'!A3,"") | J5: =IFERROR('Daily Log'!C3,0) | K5: =IFERROR('Daily Log'!D3,0) | L5: =IFERROR('Daily Log'!I3,0) | N5: Raj Balani | O5: =IFERROR(SUMIF('04 Test Case Repository'!S$3:S$5000,N5,'04 Test Case Repository'!U$3:U$5000),0)
A6: Total Test Cases | B6: =IFERROR(COUNTA('04 Test Case Repository'!A3:A5000)-COUNTIF('04 Test Case Repository'!A3:A5000,"TOTAL"),0) | C6: QA Progress | D6: =IFERROR(REPT("#",MAX(0,MIN(10,ROUND(N(B18)*10,0))))&REPT("-",10-MAX(0,MIN(10,ROUND(N(B18)*10,0)))),REPT("-",10)) | F6: Blocked | G6: =IFERROR(B9,0) | I6: =IFERROR('Daily Log'!A4,"") | J6: =IFERROR('Daily Log'!C4,0) | K6: =IFERROR('Daily Log'!D4,0) | L6: =IFERROR('Daily Log'!I4,0)
A7: Passed | B7: =IFERROR(COUNTIF('04 Test Case Repository'!P3:P5000,"Pass"),0) | C7: Prod Ready | D7: =IFERROR(REPT("#",MAX(0,MIN(10,ROUND(N(B19)*10,0))))&REPT("-",10-MAX(0,MIN(10,ROUND(N(B19)*10,0)))),REPT("-",10)) | F7: Not Executed | G7: =IFERROR(B10,0) | I7: =IFERROR('Daily Log'!A5,"") | J7: =IFERROR('Daily Log'!C5,0) | K7: =IFERROR('Daily Log'!D5,0) | L7: =IFERROR('Daily Log'!I5,0)
A8: Failed | B8: =IFERROR(COUNTIF('04 Test Case Repository'!P3:P5000,"Fail"),0) | C8: Module Complete | D8: =IFERROR(REPT("#",MAX(0,MIN(10,ROUND(IFERROR(COUNTIF('02 Module Master'!H3:H5000,"Completed")/MAX(1,COUNTA('02 Module Master'!A3:A5000)),0)*10,0))))&REPT("-",10-MAX(0,MIN(10,ROUND(IFERROR(COUNTIF('02 Module Master'!H3:H5000,"Completed")/MAX(1,COUNTA('02 Module Master'!A3:A5000)),0)*10,0)))),REPT("-",10)) | I8: =IFERROR('Daily Log'!A6,"") | J8: =IFERROR('Daily Log'!C6,0) | K8: =IFERROR('Daily Log'!D6,0) | L8: =IFERROR('Daily Log'!I6,0)
A9: Blocked | B9: =IFERROR(COUNTIF('04 Test Case Repository'!P3:P5000,"Blocked"),0) | C9: Hours Burn | D9: =IFERROR(REPT("#",MAX(0,MIN(10,ROUND(IF(B20=0,0,MIN(1,B21/B20))*10,0))))&REPT("-",10-MAX(0,MIN(10,ROUND(IF(B20=0,0,MIN(1,B21/B20))*10,0)))),REPT("-",10)) | F9: Count | I9: =IFERROR('Daily Log'!A7,"") | J9: =IFERROR('Daily Log'!C7,0) | K9: =IFERROR('Daily Log'!D7,0) | L9: =IFERROR('Daily Log'!I7,0)
A10: Not Executed | B10: =IFERROR(COUNTIF('04 Test Case Repository'!P3:P5000,"Not Run"),0) | F10: Critical | G10: =IFERROR(B12,0) | I10: =IFERROR('Daily Log'!A8,"") | J10: =IFERROR('Daily Log'!C8,0) | K10: =IFERROR('Daily Log'!D8,0) | L10: =IFERROR('Daily Log'!I8,0)
A11: In Progress | B11: =IFERROR(COUNTIF('04 Test Case Repository'!Q3:Q5000,"In Progress"),0) | F11: High | G11: =IFERROR(B13,0) | I11: =IFERROR('Daily Log'!A9,"") | J11: =IFERROR('Daily Log'!C9,0) | K11: =IFERROR('Daily Log'!D9,0) | L11: =IFERROR('Daily Log'!I9,0)
A12: Critical Bugs | B12: =IFERROR(COUNTIFS('06 Bug Tracker'!J3:J5000,"Critical",'06 Bug Tracker'!L3:L5000,"<>Closed"),0) | F12: Medium | G12: =IFERROR(B14,0) | I12: Open NAV Hub
A13: High Bugs | B13: =IFERROR(COUNTIFS('06 Bug Tracker'!J3:J5000,"High",'06 Bug Tracker'!L3:L5000,"<>Closed"),0) | F13: Low | G13: =IFERROR(B15,0) | I13: QA Tasks (Shreya/Raj)
A14: Medium Bugs | B14: =IFERROR(COUNTIFS('06 Bug Tracker'!J3:J5000,"Medium",'06 Bug Tracker'!L3:L5000,"<>Closed"),0) | I14: Dev Tasks (bug mirror)
A15: Low Bugs | B15: =IFERROR(COUNTIFS('06 Bug Tracker'!J3:J5000,"Low",'06 Bug Tracker'!L3:L5000,"<>Closed"),0) | F15: Module | G15: Completion % | I15: Bug Tracker
A16: Overall Pass % | B16: =IFERROR(IF((B7+B8+B9)=0,0,B7/(B7+B8+B9)),0) | F16: Auth & Onboarding | G16: =IFERROR(IF('02 Module Master'!I3=0,0,'02 Module Master'!J3/'02 Module Master'!I3),0) | I16: Smoke Pack
A17: Overall Fail % | B17: =IFERROR(IF((B7+B8+B9)=0,0,B8/(B7+B8+B9)),0) | F17: Dashboard | G17: =IFERROR(IF('02 Module Master'!I4=0,0,'02 Module Master'!J4/'02 Module Master'!I4),0) | I17: Launch Status
A18: QA Progress % | B18: =IFERROR(IF(B6=0,0,(B7+B8+B9+B11)/B6),0) | F18: Live Practice Coach | G18: =IFERROR(IF('02 Module Master'!I5=0,0,'02 Module Master'!J5/'02 Module Master'!I5),0)
A19: Production Readiness % | B19: =IFERROR(AVERAGEIF('19 Production Readiness'!A3:A5000,"<>",'19 Production Readiness'!R3:R5000),0) | F19: Mock Interview | G19: =IFERROR(IF('02 Module Master'!I6=0,0,'02 Module Master'!J6/'02 Module Master'!I6),0)
A20: Est Hours (Total) | B20: =IFERROR(SUM('04 Test Case Repository'!T3:T5000),0) | F20: Sessions & Debriefs | G20: =IFERROR(IF('02 Module Master'!I7=0,0,'02 Module Master'!J7/'02 Module Master'!I7),0)
A21: Actual Hours (Total) | B21: =IFERROR(SUM('04 Test Case Repository'!U3:U5000),0) | F21: Analytics & Usage | G21: =IFERROR(IF('02 Module Master'!I8=0,0,'02 Module Master'!J8/'02 Module Master'!I8),0)
A22: Hours Variance | B22: =IFERROR(B21-B20,0) | F22: Prep Lab | G22: =IFERROR(IF('02 Module Master'!I9=0,0,'02 Module Master'!J9/'02 Module Master'!I9),0)
A23: QA Team Size | B23: =IFERROR(COUNTA('QA Team'!A3:A50)-COUNTIF('QA Team'!A3:A50,"TOTAL"),0) | F23: Documents & Resumes | G23: =IFERROR(IF('02 Module Master'!I10=0,0,'02 Module Master'!J10/'02 Module Master'!I10),0)
A24: QA Tasks Open | B24: =IFERROR(COUNTIFS('QA Tasks'!H3:H5000,"<>Done",'QA Tasks'!H3:H5000,"<>"),0) | F24: Answer Bank | G24: =IFERROR(IF('02 Module Master'!I11=0,0,'02 Module Master'!J11/'02 Module Master'!I11),0)
A25: Dev Action Queue | B25: =IFERROR(COUNTIF('Dev Tasks'!I3:I152,"Yes"),0) | F25: Interviews & Calendar | G25: =IFERROR(IF('02 Module Master'!I12=0,0,'02 Module Master'!J12/'02 Module Master'!I12),0)
A26: Shreya Open Bugs | B26: =IFERROR(COUNTIFS('06 Bug Tracker'!N3:N5000,"Shreya Patil",'06 Bug Tracker'!L3:L5000,"<>Closed",'06 Bug Tracker'!L3:L5000,"<>Won't Fix"),0) | F26: Company Research | G26: =IFERROR(IF('02 Module Master'!I13=0,0,'02 Module Master'!J13/'02 Module Master'!I13),0)
A27: Raj Open Bugs | B27: =IFERROR(COUNTIFS('06 Bug Tracker'!N3:N5000,"Raj Balani",'06 Bug Tracker'!L3:L5000,"<>Closed",'06 Bug Tracker'!L3:L5000,"<>Won't Fix"),0) | F27: Notifications & Profile | G27: =IFERROR(IF('02 Module Master'!I14=0,0,'02 Module Master'!J14/'02 Module Master'!I14),0)
F28: Referrals & Guide | G28: =IFERROR(IF('02 Module Master'!I15=0,0,'02 Module Master'!J15/'02 Module Master'!I15),0)
F29: Gov Exam Mock Tests | G29: =IFERROR(IF('02 Module Master'!I16=0,0,'02 Module Master'!J16/'02 Module Master'!I16),0)
F30: Settings | G30: =IFERROR(IF('02 Module Master'!I17=0,0,'02 Module Master'!J17/'02 Module Master'!I17),0)
F31: Admin Portal | G31: =IFERROR(IF('02 Module Master'!I18=0,0,'02 Module Master'!J18/'02 Module Master'!I18),0)
F32: Marketing Site | G32: =IFERROR(IF('02 Module Master'!I19=0,0,'02 Module Master'!J19/'02 Module Master'!I19),0)
F33: Billing & Credits | G33: =IFERROR(IF('02 Module Master'!I20=0,0,'02 Module Master'!J20/'02 Module Master'!I20),0)
F34: Electron Desktop Overlay | G34: =IFERROR(IF('02 Module Master'!I21=0,0,'02 Module Master'!J21/'02 Module Master'!I21),0)
F35: Security & Platform | G35: =IFERROR(IF('02 Module Master'!I22=0,0,'02 Module Master'!J22/'02 Module Master'!I22),0)

Sheet QA Tasks
A1: QA Tasks — Shreya Patil & Raj Balani work queue | J1: Dashboard | K1: NAV | L1: Features | M1: Bugs | N1: Launch | O1: Smoke | P1: Creds | Q1: Env | R1: Playbooks | S1: Cases | T1: Sign-Off
A2: Task ID | B2: QA Owner | C2: Module | D2: Task Type | E2: Title | F2: Linked TC / Flow | G2: Priority | H2: Status | I2: Due Date | J2: Est Hours | K2: Actual Hours | L2: Linked Bug ID | M2: Fails Linked (auto) | N2: Notes
A3: QAT-001 | B3: Raj Balani | C3: Auth & Onboarding | D3: Functional | E3: Execute Auth & Onboarding pack — Email/OAuth login, MFA, 5-step onboarding | F3: See 04 / domain sheets for MOD-01 | G3: Critical | H3: Not Started | I3: 46240 | J3: 4 | K3: 0 | M3: =IFERROR(COUNTIFS('06 Bug Tracker'!N$3:N$5000,B3,'06 Bug Tracker'!L$3:L$5000,"<>Closed",'06 Bug Tracker'!L$3:L$5000,"<>Won't Fix",'06 Bug Tracker'!L$3:L$5000,"<>Duplicate"),0) | N3: Mark Fail on TC → create Bug in 06 → Bug ID appears here & on Dev Tasks
A4: QAT-002 | B4: Shreya Patil | C4: Dashboard | D4: Functional | E4: Execute Dashboard pack — Home KPIs, sessions, credits, upcoming interview | F4: See 04 / domain sheets for MOD-02 | G4: High | H4: Not Started | I4: 46241 | J4: 4 | K4: 0 | M4: =IFERROR(COUNTIFS('06 Bug Tracker'!N$3:N$5000,B4,'06 Bug Tracker'!L$3:L$5000,"<>Closed",'06 Bug Tracker'!L$3:L$5000,"<>Won't Fix",'06 Bug Tracker'!L$3:L$5000,"<>Duplicate"),0) | N4: Mark Fail on TC → create Bug in 06 → Bug ID appears here & on Dev Tasks
A5: QAT-003 | B5: Shreya Patil | C5: Live Practice Coach | D5: Functional | E5: Execute Live Practice Coach pack — Deepgram STT + AI hints/answers + overlay | F5: See 04 / domain sheets for MOD-03 | G5: Critical | H5: Not Started | I5: 46242 | J5: 4 | K5: 0 | M5: =IFERROR(COUNTIFS('06 Bug Tracker'!N$3:N$5000,B5,'06 Bug Tracker'!L$3:L$5000,"<>Closed",'06 Bug Tracker'!L$3:L$5000,"<>Won't Fix",'06 Bug Tracker'!L$3:L$5000,"<>Duplicate"),0) | N5: Mark Fail on TC → create Bug in 06 → Bug ID appears here & on Dev Tasks
A6: QAT-004 | B6: Shreya Patil | C6: Mock Interview | D6: Functional | E6: Execute Mock Interview pack — Timed mock sessions with AI scoring | F6: See 04 / domain sheets for MOD-04 | G6: High | H6: Not Started | I6: 46243 | J6: 4 | K6: 0 | M6: =IFERROR(COUNTIFS('06 Bug Tracker'!N$3:N$5000,B6,'06 Bug Tracker'!L$3:L$5000,"<>Closed",'06 Bug Tracker'!L$3:L$5000,"<>Won't Fix",'06 Bug Tracker'!L$3:L$5000,"<>Duplicate"),0) | N6: Mark Fail on TC → create Bug in 06 → Bug ID appears here & on Dev Tasks
A7: QAT-005 | B7: Shreya Patil | C7: Sessions & Debriefs | D7: Functional | E7: Execute Sessions & Debriefs pack — History, detail, AI debrief, scorecard share | F7: See 04 / domain sheets for MOD-05 | G7: High | H7: Not Started | I7: 46239 | J7: 4 | K7: 0 | M7: =IFERROR(COUNTIFS('06 Bug Tracker'!N$3:N$5000,B7,'06 Bug Tracker'!L$3:L$5000,"<>Closed",'06 Bug Tracker'!L$3:L$5000,"<>Won't Fix",'06 Bug Tracker'!L$3:L$5000,"<>Duplicate"),0) | N7: Mark Fail on TC → create Bug in 06 → Bug ID appears here & on Dev Tasks
A8: QAT-006 | B8: Raj Balani | C8: Analytics & Usage | D8: Functional | E8: Execute Analytics & Usage pack — Trends, WPM, fillers, credit usage | F8: See 04 / domain sheets for MOD-06 | G8: Medium | H8: Not Started | I8: 46240 | J8: 4 | K8: 0 | M8: =IFERROR(COUNTIFS('06 Bug Tracker'!N$3:N$5000,B8,'06 Bug Tracker'!L$3:L$5000,"<>Closed",'06 Bug Tracker'!L$3:L$5000,"<>Won't Fix",'06 Bug Tracker'!L$3:L$5000,"<>Duplicate"),0) | N8: Mark Fail on TC → create Bug in 06 → Bug ID appears here & on Dev Tasks
A9: QAT-007 | B9: Raj Balani | C9: Prep Lab | D9: Functional | E9: Execute Prep Lab pack — STAR, rephraser, polish, company Qs | F9: See 04 / domain sheets for MOD-07 | G9: High | H9: Not Started | I9: 46241 | J9: 4 | K9: 0 | M9: =IFERROR(COUNTIFS('06 Bug Tracker'!N$3:N$5000,B9,'06 Bug Tracker'!L$3:L$5000,"<>Closed",'06 Bug Tracker'!L$3:L$5000,"<>Won't Fix",'06 Bug Tracker'!L$3:L$5000,"<>Duplicate"),0) | N9: Mark Fail on TC → create Bug in 06 → Bug ID appears here & on Dev Tasks
A10: QAT-008 | B10: Shreya Patil | C10: Documents & Resumes | D10: Functional | E10: Execute Documents & Resumes pack — Upload, parse-resume, gap analysis, OCR | F10: See 04 / domain sheets for MOD-08 | G10: High | H10: Not Started | I10: 46242 | J10: 4 | K10: 0 | M10: =IFERROR(COUNTIFS('06 Bug Tracker'!N$3:N$5000,B10,'06 Bug Tracker'!L$3:L$5000,"<>Closed",'06 Bug Tracker'!L$3:L$5000,"<>Won't Fix",'06 Bug Tracker'!L$3:L$5000,"<>Duplicate"),0) | N10: Mark Fail on TC → create Bug in 06 → Bug ID appears here & on Dev Tasks
A11: QAT-009 | B11: Raj Balani | C11: Answer Bank | D11: Functional | E11: Execute Answer Bank pack — STAR library + AI generate via prep-tool | F11: See 04 / domain sheets for MOD-09 | G11: Medium | H11: Not Started | I11: 46243 | J11: 4 | K11: 0 | M11: =IFERROR(COUNTIFS('06 Bug Tracker'!N$3:N$5000,B11,'06 Bug Tracker'!L$3:L$5000,"<>Closed",'06 Bug Tracker'!L$3:L$5000,"<>Won't Fix",'06 Bug Tracker'!L$3:L$5000,"<>Duplicate"),0) | N11: Mark Fail on TC → create Bug in 06 → Bug ID appears here & on Dev Tasks
A12: QAT-010 | B12: Shreya Patil | C12: Interviews & Calendar | D12: Functional | E12: Execute Interviews & Calendar pack — Manual interviews + Google Calendar sync | F12: See 04 / domain sheets for MOD-10 | G12: High | H12: Not Started | I12: 46239 | J12: 4 | K12: 0 | M12: =IFERROR(COUNTIFS('06 Bug Tracker'!N$3:N$5000,B12,'06 Bug Tracker'!L$3:L$5000,"<>Closed",'06 Bug Tracker'!L$3:L$5000,"<>Won't Fix",'06 Bug Tracker'!L$3:L$5000,"<>Duplicate"),0) | N12: Mark Fail on TC → create Bug in 06 → Bug ID appears here & on Dev Tasks
A13: QAT-011 | B13: Raj Balani | C13: Company Research | D13: Functional | E13: Execute Company Research pack — AI company brief + per-user cache | F13: See 04 / domain sheets for MOD-11 | G13: Medium | H13: Not Started | I13: 46240 | J13: 4 | K13: 0 | M13: =IFERROR(COUNTIFS('06 Bug Tracker'!N$3:N$5000,B13,'06 Bug Tracker'!L$3:L$5000,"<>Closed",'06 Bug Tracker'!L$3:L$5000,"<>Won't Fix",'06 Bug Tracker'!L$3:L$5000,"<>Duplicate"),0) | N13: Mark Fail on TC → create Bug in 06 → Bug ID appears here & on Dev Tasks
A14: QAT-012 | B14: Raj Balani | C14: Notifications & Profile | D14: Functional | E14: Execute Notifications & Profile pack — Realtime notifications, XP/streak/badges | F14: See 04 / domain sheets for MOD-12 | G14: Medium | H14: Not Started | I14: 46241 | J14: 4 | K14: 0 | M14: =IFERROR(COUNTIFS('06 Bug Tracker'!N$3:N$5000,B14,'06 Bug Tracker'!L$3:L$5000,"<>Closed",'06 Bug Tracker'!L$3:L$5000,"<>Won't Fix",'06 Bug Tracker'!L$3:L$5000,"<>Duplicate"),0) | N14: Mark Fail on TC → create Bug in 06 → Bug ID appears here & on Dev Tasks
... A32: QAT-030 | B32: Shreya Patil | C32: Cross-Cutting | D32: Retest | E32: Retest queue — bugs in Retest status (pair) | F32: bugs in Retest status (pair) | G32: Critical | H32: Not Started | I32: 46237 | J32: 3 | K32: 0 | M32: =IFERROR(COUNTIFS('06 Bug Tracker'!N$3:N$5000,B32,'06 Bug Tracker'!L$3:L$5000,"<>Closed",'06 Bug Tracker'!L$3:L$5000,"<>Won't Fix",'06 Bug Tracker'!L$3:L$5000,"<>Duplicate"),0) | N32: Update Status daily; link Bug ID when filing defects
A33: TOTAL / KPIs | J33: =SUM(J3:J32) | K33: =SUM(K3:K32) | M33: =SUM(M3:M32)
A35: Shreya open bugs (Reported By) | B35: =IFERROR(COUNTIFS('06 Bug Tracker'!N3:N5000,"Shreya Patil",'06 Bug Tracker'!L3:L5000,"<>Closed",'06 Bug Tracker'!L3:L5000,"<>Won't Fix",'06 Bug Tracker'!L3:L5000,"<>Duplicate"),0)
A36: Raj open bugs (Reported By) | B36: =IFERROR(COUNTIFS('06 Bug Tracker'!N3:N5000,"Raj Balani",'06 Bug Tracker'!L3:L5000,"<>Closed",'06 Bug Tracker'!L3:L5000,"<>Won't Fix",'06 Bug Tracker'!L3:L5000,"<>Duplicate"),0)
A37: Failed TCs (04 Pass/Fail=Fail) | B37: =IFERROR(COUNTIF('04 Test Case Repository'!P3:P5000,"Fail"),0)

Sheet QA Team
A1: QA Team Roster — Clarify AI | J1: Dashboard | K1: NAV | L1: Features | M1: Bugs | N1: Launch | O1: Smoke | P1: Creds | Q1: Env | R1: Playbooks | S1: Cases | T1: Sign-Off
A2: QA Person | B2: Role | C2: Email | D2: Capacity Hrs/Week | E2: Skills Focus | F2: Assigned Cases | G2: Est Hours Assigned | H2: Actual Hours Logged | I2: Utilization % | J2: Status | K2: Remarks
A3: Shreya Patil | B3: QA Engineer | C3: shreya.patil@clarify.ai | D3: 40 | E3: Practice Coach, Overlay, Mock Interview, Sessions/Debrief, Documents, UI/UX, Electron | F3: =COUNTIF('04 Test Case Repository'!S$3:S$5000,A3) | G3: =SUMIF('04 Test Case Repository'!S$3:S$5000,A3,'04 Test Case Repository'!T$3:T$5000) | H3: =SUMIF('04 Test Case Repository'!S$3:S$5000,A3,'04 Test Case Repository'!U$3:U$5000) | I3: =IFERROR(H3/D3,0) | J3: Active
A4: Raj Balani | B4: QA Engineer | C4: raj.balani@clarify.ai | D4: 40 | E4: Auth/Onboarding, Billing/Credits, Gov Exam Mock Tests, Admin, Prep Lab, Security, Regression | F4: =COUNTIF('04 Test Case Repository'!S$3:S$5000,A4) | G4: =SUMIF('04 Test Case Repository'!S$3:S$5000,A4,'04 Test Case Repository'!T$3:T$5000) | H4: =SUMIF('04 Test Case Repository'!S$3:S$5000,A4,'04 Test Case Repository'!U$3:U$5000) | I4: =IFERROR(H4/D4,0) | J4: Active
A5: TOTAL | D5: =SUM(D3:D4) | F5: =SUM(F3:F4) | G5: =SUM(G3:G4) | H5: =SUM(H3:H4) | I5: =IFERROR(H5/D5,0)

Sheet Dev Team
A1: Dev Team Roster — Clarify AI | J1: Dashboard | K1: NAV | L1: Features | M1: Bugs | N1: Launch | O1: Smoke | P1: Creds | Q1: Env | R1: Playbooks | S1: Cases | T1: Sign-Off
A2: Developer | B2: Role | C2: Email | D2: Capacity Hrs/Week | E2: Focus Area | F2: Open Bugs Assigned | G2: In Progress | H2: Ready for Retest | I2: Utilization Hint | J2: Status | K2: Remarks
A3: Dev Lead | B3: Engineering Lead | C3: dev.lead@clarify.ai | D3: 40 | E3: Triage, release, blockers | F3: =IFERROR(COUNTIFS('06 Bug Tracker'!M$3:M$5000,A3,'06 Bug Tracker'!L$3:L$5000,"<>Closed",'06 Bug Tracker'!L$3:L$5000,"<>Won't Fix",'06 Bug Tracker'!L$3:L$5000,"<>Duplicate"),0) | G3: =IFERROR(COUNTIFS('06 Bug Tracker'!M$3:M$5000,A3,'06 Bug Tracker'!L$3:L$5000,"In Progress"),0) | H3: =IFERROR(COUNTIFS('06 Bug Tracker'!M$3:M$5000,A3,'06 Bug Tracker'!L$3:L$5000,"Retest")+COUNTIFS('06 Bug Tracker'!M$3:M$5000,A3,'06 Bug Tracker'!L$3:L$5000,"Fixed"),0) | I3: =IF(F3>8,"Overloaded",IF(F3>4,"Busy","OK")) | J3: Active
A4: Live Coach Dev | B4: Frontend Engineer | C4: live.coach@clarify.ai | D4: 40 | E4: Practice Coach, Overlay, Mock | F4: =IFERROR(COUNTIFS('06 Bug Tracker'!M$3:M$5000,A4,'06 Bug Tracker'!L$3:L$5000,"<>Closed",'06 Bug Tracker'!L$3:L$5000,"<>Won't Fix",'06 Bug Tracker'!L$3:L$5000,"<>Duplicate"),0) | G4: =IFERROR(COUNTIFS('06 Bug Tracker'!M$3:M$5000,A4,'06 Bug Tracker'!L$3:L$5000,"In Progress"),0) | H4: =IFERROR(COUNTIFS('06 Bug Tracker'!M$3:M$5000,A4,'06 Bug Tracker'!L$3:L$5000,"Retest")+COUNTIFS('06 Bug Tracker'!M$3:M$5000,A4,'06 Bug Tracker'!L$3:L$5000,"Fixed"),0) | I4: =IF(F4>8,"Overloaded",IF(F4>4,"Busy","OK")) | J4: Active
A5: Platform Dev | B5: Full-Stack Engineer | C5: platform@clarify.ai | D5: 40 | E5: Auth, Billing, Admin, Edge | F5: =IFERROR(COUNTIFS('06 Bug Tracker'!M$3:M$5000,A5,'06 Bug Tracker'!L$3:L$5000,"<>Closed",'06 Bug Tracker'!L$3:L$5000,"<>Won't Fix",'06 Bug Tracker'!L$3:L$5000,"<>Duplicate"),0) | G5: =IFERROR(COUNTIFS('06 Bug Tracker'!M$3:M$5000,A5,'06 Bug Tracker'!L$3:L$5000,"In Progress"),0) | H5: =IFERROR(COUNTIFS('06 Bug Tracker'!M$3:M$5000,A5,'06 Bug Tracker'!L$3:L$5000,"Retest")+COUNTIFS('06 Bug Tracker'!M$3:M$5000,A5,'06 Bug Tracker'!L$3:L$5000,"Fixed"),0) | I5: =IF(F5>8,"Overloaded",IF(F5>4,"Busy","OK")) | J5: Active
A6: GovExams Dev | B6: Full-Stack Engineer | C6: govexams@clarify.ai | D6: 40 | E6: Mock tests, question bank | F6: =IFERROR(COUNTIFS('06 Bug Tracker'!M$3:M$5000,A6,'06 Bug Tracker'!L$3:L$5000,"<>Closed",'06 Bug Tracker'!L$3:L$5000,"<>Won't Fix",'06 Bug Tracker'!L$3:L$5000,"<>Duplicate"),0) | G6: =IFERROR(COUNTIFS('06 Bug Tracker'!M$3:M$5000,A6,'06 Bug Tracker'!L$3:L$5000,"In Progress"),0) | H6: =IFERROR(COUNTIFS('06 Bug Tracker'!M$3:M$5000,A6,'06 Bug Tracker'!L$3:L$5000,"Retest")+COUNTIFS('06 Bug Tracker'!M$3:M$5000,A6,'06 Bug Tracker'!L$3:L$5000,"Fixed"),0) | I6: =IF(F6>8,"Overloaded",IF(F6>4,"Busy","OK")) | J6: Active
A7: Desktop Dev | B7: Electron Engineer | C7: desktop@clarify.ai | D7: 40 | E7: Electron overlay, hotkeys | F7: =IFERROR(COUNTIFS('06 Bug Tracker'!M$3:M$5000,A7,'06 Bug Tracker'!L$3:L$5000,"<>Closed",'06 Bug Tracker'!L$3:L$5000,"<>Won't Fix",'06 Bug Tracker'!L$3:L$5000,"<>Duplicate"),0) | G7: =IFERROR(COUNTIFS('06 Bug Tracker'!M$3:M$5000,A7,'06 Bug Tracker'!L$3:L$5000,"In Progress"),0) | H7: =IFERROR(COUNTIFS('06 Bug Tracker'!M$3:M$5000,A7,'06 Bug Tracker'!L$3:L$5000,"Retest")+COUNTIFS('06 Bug Tracker'!M$3:M$5000,A7,'06 Bug Tracker'!L$3:L$5000,"Fixed"),0) | I7: =IF(F7>8,"Overloaded",IF(F7>4,"Busy","OK")) | J7: Active
A8: TOTAL | D8: =SUM(D3:D7) | F8: =SUM(F3:F7) | G8: =SUM(G3:G7) | H8: =SUM(H3:H7)

Sheet Dev Tasks
A1: Dev Tasks — live mirror of 06 Bug Tracker | J1: Dashboard | K1: NAV | L1: Features | M1: Bugs | N1: Launch | O1: Smoke | P1: Creds | Q1: Env | R1: Playbooks | S1: Cases | T1: Sign-Off
A2: Bug ID | B2: Title | C2: Module | D2: Severity | E2: Priority | F2: Bug Status | G2: Reported By (QA) | H2: Assigned Developer | I2: Needs Dev Action | J2: Dev Status | K2: Fix ETA | L2: Build Fixed | M2: Retest Owner (QA) | N2: Retest Result | O2: Dev Notes
A3: ='06 Bug Tracker'!A3 | B3: ='06 Bug Tracker'!B3 | C3: ='06 Bug Tracker'!D3 | D3: ='06 Bug Tracker'!J3 | E3: ='06 Bug Tracker'!K3 | F3: ='06 Bug Tracker'!L3 | G3: ='06 Bug Tracker'!N3 | H3: ='06 Bug Tracker'!M3 | I3: =IF(A3="","",IF(OR(F3="New",F3="Open",F3="In Progress",F3="Fixed",F3="Retest"),"Yes","No")) | J3: =IF(A3="","",IF(F3="Retest","Fixed — Ready for Retest",IF(F3="Fixed","Fixed — Ready for Retest",IF(F3="In Progress","In Progress",IF(OR(F3="New",F3="Open"),"Queued",IF(F3="Closed","Done",IF(F3="Won't Fix","Won't Fix",""))))))) | L3: ='06 Bug Tracker'!R3 | M3: ='06 Bug Tracker'!N3
A4: ='06 Bug Tracker'!A4 | B4: ='06 Bug Tracker'!B4 | C4: ='06 Bug Tracker'!D4 | D4: ='06 Bug Tracker'!J4 | E4: ='06 Bug Tracker'!K4 | F4: ='06 Bug Tracker'!L4 | G4: ='06 Bug Tracker'!N4 | H4: ='06 Bug Tracker'!M4 | I4: =IF(A4="","",IF(OR(F4="New",F4="Open",F4="In Progress",F4="Fixed",F4="Retest"),"Yes","No")) | J4: =IF(A4="","",IF(F4="Retest","Fixed — Ready for Retest",IF(F4="Fixed","Fixed — Ready for Retest",IF(F4="In Progress","In Progress",IF(OR(F4="New",F4="Open"),"Queued",IF(F4="Closed","Done",IF(F4="Won't Fix","Won't Fix",""))))))) | L4: ='06 Bug Tracker'!R4 | M4: ='06 Bug Tracker'!N4
A5: ='06 Bug Tracker'!A5 | B5: ='06 Bug Tracker'!B5 | C5: ='06 Bug Tracker'!D5 | D5: ='06 Bug Tracker'!J5 | E5: ='06 Bug Tracker'!K5 | F5: ='06 Bug Tracker'!L5 | G5: ='06 Bug Tracker'!N5 | H5: ='06 Bug Tracker'!M5 | I5: =IF(A5="","",IF(OR(F5="New",F5="Open",F5="In Progress",F5="Fixed",F5="Retest"),"Yes","No")) | J5: =IF(A5="","",IF(F5="Retest","Fixed — Ready for Retest",IF(F5="Fixed","Fixed — Ready for Retest",IF(F5="In Progress","In Progress",IF(OR(F5="New",F5="Open"),"Queued",IF(F5="Closed","Done",IF(F5="Won't Fix","Won't Fix",""))))))) | L5: ='06 Bug Tracker'!R5 | M5: ='06 Bug Tracker'!N5
A6: ='06 Bug Tracker'!A6 | B6: ='06 Bug Tracker'!B6 | C6: ='06 Bug Tracker'!D6 | D6: ='06 Bug Tracker'!J6 | E6: ='06 Bug Tracker'!K6 | F6: ='06 Bug Tracker'!L6 | G6: ='06 Bug Tracker'!N6 | H6: ='06 Bug Tracker'!M6 | I6: =IF(A6="","",IF(OR(F6="New",F6="Open",F6="In Progress",F6="Fixed",F6="Retest"),"Yes","No")) | J6: =IF(A6="","",IF(F6="Retest","Fixed — Ready for Retest",IF(F6="Fixed","Fixed — Ready for Retest",IF(F6="In Progress","In Progress",IF(OR(F6="New",F6="Open"),"Queued",IF(F6="Closed","Done",IF(F6="Won't Fix","Won't Fix",""))))))) | L6: ='06 Bug Tracker'!R6 | M6: ='06 Bug Tracker'!N6
A7: ='06 Bug Tracker'!A7 | B7: ='06 Bug Tracker'!B7 | C7: ='06 Bug Tracker'!D7 | D7: ='06 Bug Tracker'!J7 | E7: ='06 Bug Tracker'!K7 | F7: ='06 Bug Tracker'!L7 | G7: ='06 Bug Tracker'!N7 | H7: ='06 Bug Tracker'!M7 | I7: =IF(A7="","",IF(OR(F7="New",F7="Open",F7="In Progress",F7="Fixed",F7="Retest"),"Yes","No")) | J7: =IF(A7="","",IF(F7="Retest","Fixed — Ready for Retest",IF(F7="Fixed","Fixed — Ready for Retest",IF(F7="In Progress","In Progress",IF(OR(F7="New",F7="Open"),"Queued",IF(F7="Closed","Done",IF(F7="Won't Fix","Won't Fix",""))))))) | L7: ='06 Bug Tracker'!R7 | M7: ='06 Bug Tracker'!N7
A8: ='06 Bug Tracker'!A8 | B8: ='06 Bug Tracker'!B8 | C8: ='06 Bug Tracker'!D8 | D8: ='06 Bug Tracker'!J8 | E8: ='06 Bug Tracker'!K8 | F8: ='06 Bug Tracker'!L8 | G8: ='06 Bug Tracker'!N8 | H8: ='06 Bug Tracker'!M8 | I8: =IF(A8="","",IF(OR(F8="New",F8="Open",F8="In Progress",F8="Fixed",F8="Retest"),"Yes","No")) | J8: =IF(A8="","",IF(F8="Retest","Fixed — Ready for Retest",IF(F8="Fixed","Fixed — Ready for Retest",IF(F8="In Progress","In Progress",IF(OR(F8="New",F8="Open"),"Queued",IF(F8="Closed","Done",IF(F8="Won't Fix","Won't Fix",""))))))) | L8: ='06 Bug Tracker'!R8 | M8: ='06 Bug Tracker'!N8
A9: ='06 Bug Tracker'!A9 | B9: ='06 Bug Tracker'!B9 | C9: ='06 Bug Tracker'!D9 | D9: ='06 Bug Tracker'!J9 | E9: ='06 Bug Tracker'!K9 | F9: ='06 Bug Tracker'!L9 | G9: ='06 Bug Tracker'!N9 | H9: ='06 Bug Tracker'!M9 | I9: =IF(A9="","",IF(OR(F9="New",F9="Open",F9="In Progress",F9="Fixed",F9="Retest"),"Yes","No")) | J9: =IF(A9="","",IF(F9="Retest","Fixed — Ready for Retest",IF(F9="Fixed","Fixed — Ready for Retest",IF(F9="In Progress","In Progress",IF(OR(F9="New",F9="Open"),"Queued",IF(F9="Closed","Done",IF(F9="Won't Fix","Won't Fix",""))))))) | L9: ='06 Bug Tracker'!R9 | M9: ='06 Bug Tracker'!N9
A10: ='06 Bug Tracker'!A10 | B10: ='06 Bug Tracker'!B10 | C10: ='06 Bug Tracker'!D10 | D10: ='06 Bug Tracker'!J10 | E10: ='06 Bug Tracker'!K10 | F10: ='06 Bug Tracker'!L10 | G10: ='06 Bug Tracker'!N10 | H10: ='06 Bug Tracker'!M10 | I10: =IF(A10="","",IF(OR(F10="New",F10="Open",F10="In Progress",F10="Fixed",F10="Retest"),"Yes","No")) | J10: =IF(A10="","",IF(F10="Retest","Fixed — Ready for Retest",IF(F10="Fixed","Fixed — Ready for Retest",IF(F10="In Progress","In Progress",IF(OR(F10="New",F10="Open"),"Queued",IF(F10="Closed","Done",IF(F10="Won't Fix","Won't Fix",""))))))) | L10: ='06 Bug Tracker'!R10 | M10: ='06 Bug Tracker'!N10
A11: ='06 Bug Tracker'!A11 | B11: ='06 Bug Tracker'!B11 | C11: ='06 Bug Tracker'!D11 | D11: ='06 Bug Tracker'!J11 | E11: ='06 Bug Tracker'!K11 | F11: ='06 Bug Tracker'!L11 | G11: ='06 Bug Tracker'!N11 | H11: ='06 Bug Tracker'!M11 | I11: =IF(A11="","",IF(OR(F11="New",F11="Open",F11="In Progress",F11="Fixed",F11="Retest"),"Yes","No")) | J11: =IF(A11="","",IF(F11="Retest","Fixed — Ready for Retest",IF(F11="Fixed","Fixed — Ready for Retest",IF(F11="In Progress","In Progress",IF(OR(F11="New",F11="Open"),"Queued",IF(F11="Closed","Done",IF(F11="Won't Fix","Won't Fix",""))))))) | L11: ='06 Bug Tracker'!R11 | M11: ='06 Bug Tracker'!N11
A12: ='06 Bug Tracker'!A12 | B12: ='06 Bug Tracker'!B12 | C12: ='06 Bug Tracker'!D12 | D12: ='06 Bug Tracker'!J12 | E12: ='06 Bug Tracker'!K12 | F12: ='06 Bug Tracker'!L12 | G12: ='06 Bug Tracker'!N12 | H12: ='06 Bug Tracker'!M12 | I12: =IF(A12="","",IF(OR(F12="New",F12="Open",F12="In Progress",F12="Fixed",F12="Retest"),"Yes","No")) | J12: =IF(A12="","",IF(F12="Retest","Fixed — Ready for Retest",IF(F12="Fixed","Fixed — Ready for Retest",IF(F12="In Progress","In Progress",IF(OR(F12="New",F12="Open"),"Queued",IF(F12="Closed","Done",IF(F12="Won't Fix","Won't Fix",""))))))) | L12: ='06 Bug Tracker'!R12 | M12: ='06 Bug Tracker'!N12
A13: ='06 Bug Tracker'!A13 | B13: ='06 Bug Tracker'!B13 | C13: ='06 Bug Tracker'!D13 | D13: ='06 Bug Tracker'!J13 | E13: ='06 Bug Tracker'!K13 | F13: ='06 Bug Tracker'!L13 | G13: ='06 Bug Tracker'!N13 | H13: ='06 Bug Tracker'!M13 | I13: =IF(A13="","",IF(OR(F13="New",F13="Open",F13="In Progress",F13="Fixed",F13="Retest"),"Yes","No")) | J13: =IF(A13="","",IF(F13="Retest","Fixed — Ready for Retest",IF(F13="Fixed","Fixed — Ready for Retest",IF(F13="In Progress","In Progress",IF(OR(F13="New",F13="Open"),"Queued",IF(F13="Closed","Done",IF(F13="Won't Fix","Won't Fix",""))))))) | L13: ='06 Bug Tracker'!R13 | M13: ='06 Bug Tracker'!N13
A14: ='06 Bug Tracker'!A14 | B14: ='06 Bug Tracker'!B14 | C14: ='06 Bug Tracker'!D14 | D14: ='06 Bug Tracker'!J14 | E14: ='06 Bug Tracker'!K14 | F14: ='06 Bug Tracker'!L14 | G14: ='06 Bug Tracker'!N14 | H14: ='06 Bug Tracker'!M14 | I14: =IF(A14="","",IF(OR(F14="New",F14="Open",F14="In Progress",F14="Fixed",F14="Retest"),"Yes","No")) | J14: =IF(A14="","",IF(F14="Retest","Fixed — Ready for Retest",IF(F14="Fixed","Fixed — Ready for Retest",IF(F14="In Progress","In Progress",IF(OR(F14="New",F14="Open"),"Queued",IF(F14="Closed","Done",IF(F14="Won't Fix","Won't Fix",""))))))) | L14: ='06 Bug Tracker'!R14 | M14: ='06 Bug Tracker'!N14
... A152: ='06 Bug Tracker'!A152 | B152: ='06 Bug Tracker'!B152 | C152: ='06 Bug Tracker'!D152 | D152: ='06 Bug Tracker'!J152 | E152: ='06 Bug Tracker'!K152 | F152: ='06 Bug Tracker'!L152 | G152: ='06 Bug Tracker'!N152 | H152: ='06 Bug Tracker'!M152 | I152: =IF(A152="","",IF(OR(F152="New",F152="Open",F152="In Progress",F152="Fixed",F152="Retest"),"Yes","No")) | J152: =IF(A152="","",IF(F152="Retest","Fixed — Ready for Retest",IF(F152="Fixed","Fixed — Ready for Retest",IF(F152="In Progress","In Progress",IF(OR(F152="New",F152="Open"),"Queued",IF(F152="Closed","Done",IF(F152="Won't Fix","Won't Fix",""))))))) | L152: ='06 Bug Tracker'!R152 | M152: ='06 Bug Tracker'!N152
A154: QUEUE KPIs (auto)
A155: Needs Dev Action = Yes | B155: =IFERROR(COUNTIF(I3:I152,"Yes"),0)
A156: Reported by Shreya (open) | B156: =IFERROR(COUNTIFS(G3:G152,"Shreya Patil",I3:I152,"Yes"),0)
A157: Reported by Raj (open) | B157: =IFERROR(COUNTIFS(G3:G152,"Raj Balani",I3:I152,"Yes"),0)
A158: Ready for Retest | B158: =IFERROR(COUNTIF(J3:J152,"Fixed — Ready for Retest"),0)
A159: HOW TO USE | B159: 1) QA fails TC on 04 2) QA adds bug on 06 (Reported By=Shreya/Raj, Assigned To=dev) 3) Row appears here 4) Dev fixes → set Bug Status=Fixed/Retest on 06 5) QA retests → Closed

Sheet 02 Module Master
A1: Module Master — Clarify AI (20 core modules) | J1: Dashboard | K1: NAV | L1: Features | M1: Bugs | N1: Launch | O1: Smoke | P1: Creds | Q1: Env | R1: Playbooks | S1: Cases | T1: Sign-Off
A2: Module ID | B2: Module Name | C2: Portal | D2: Description | E2: Owner | F2: QA Owner | G2: Priority | H2: Status | I2: Total Features | J2: Completed Features | K2: Pending Features | L2: Est Hours | M2: Actual Hours | N2: Criticality | O2: Dependencies | P2: Remarks
A3: MOD-01 | B3: Auth & Onboarding | C3: Auth Portal | D3: Email/OAuth login, MFA, 5-step onboarding | E3: Auth Lead | F3: Raj Balani | G3: Critical | H3: In Progress | I3: 7 | J3: 6 | K3: 1 | L3: 17.5 | M3: 13.2 | N3: Critical | O3: — | P3: Seeded from audit 28 Jul 2026
A4: MOD-02 | B4: Dashboard | C4: Candidate App | D4: Home KPIs, sessions, credits, upcoming interviews | E4: Product | F4: Raj Balani | G4: High | H4: Completed | I4: 5 | J4: 5 | K4: 0 | L4: 12.5 | M4: 11 | N4: High | O4: — | P4: Seeded from audit 28 Jul 2026
A5: MOD-03 | B5: Live Practice Coach | C5: Candidate App | D5: Deepgram STT + AI hints/answers + overlay | E5: Live Coach | F5: Shreya Patil | G5: Critical | H5: Completed | I5: 9 | J5: 8 | K5: 1 | L5: 22.5 | M5: 17.6 | N5: Critical | O5: Auth, Billing credits, Deepgram | P5: Seeded from audit 28 Jul 2026
A6: MOD-04 | B6: Mock Interview | C6: Candidate App | D6: Timed mock sessions with AI scoring | E6: Live Coach | F6: Shreya Patil | G6: High | H6: In Progress | I6: 3 | J6: 1 | K6: 2 | L6: 7.5 | M6: 2.2 | N6: High | O6: Sessions, Credits | P6: Seeded from audit 28 Jul 2026
A7: MOD-05 | B7: Sessions & Debriefs | C7: Candidate App | D7: History, detail, AI debrief, scorecard share | E7: Sessions | F7: Shreya Patil | G7: High | H7: Completed | I7: 5 | J7: 5 | K7: 0 | L7: 12.5 | M7: 11 | N7: High | O7: — | P7: Seeded from audit 28 Jul 2026
A8: MOD-06 | B8: Analytics & Usage | C8: Candidate App | D8: Trends, WPM, fillers, credit usage | E8: Analytics | F8: Raj Balani | G8: Medium | H8: Completed | I8: 2 | J8: 2 | K8: 0 | L8: 5 | M8: 4.4 | N8: Medium | O8: — | P8: Seeded from audit 28 Jul 2026
A9: MOD-07 | B9: Prep Lab | C9: Candidate App | D9: STAR, rephraser, polish, company Qs | E9: Prep | F9: Raj Balani | G9: High | H9: Completed | I9: 7 | J9: 7 | K9: 0 | L9: 17.5 | M9: 15.4 | N9: High | O9: — | P9: Seeded from audit 28 Jul 2026
A10: MOD-08 | B10: Documents & Resumes | C10: Candidate App | D10: Upload, parse-resume, gap analysis, OCR | E10: Docs | F10: Shreya Patil | G10: High | H10: Completed | I10: 5 | J10: 5 | K10: 0 | L10: 12.5 | M10: 11 | N10: High | O10: Credits (parse-resume) | P10: Seeded from audit 28 Jul 2026
A11: MOD-09 | B11: Answer Bank | C11: Candidate App | D11: STAR library + AI generate via prep-tool | E11: Prep | F11: Raj Balani | G11: Medium | H11: In Progress | I11: 2 | J11: 2 | K11: 0 | L11: 5 | M11: 4.4 | N11: Medium | O11: — | P11: Seeded from audit 28 Jul 2026
A12: MOD-10 | B12: Interviews & Calendar | C12: Candidate App | D12: Manual interviews + Google Calendar sync | E12: Scheduling | F12: Raj Balani | G12: High | H12: In Progress | I12: 6 | J12: 4 | K12: 2 | L12: 15 | M12: 8.8 | N12: High | O12: — | P12: Seeded from audit 28 Jul 2026
A13: MOD-11 | B13: Company Research | C13: Candidate App | D13: AI company brief + per-user cache | E13: Prep | F13: Raj Balani | G13: Medium | H13: Completed | I13: 1 | J13: 1 | K13: 0 | L13: 2.5 | M13: 2.2 | N13: Medium | O13: — | P13: Seeded from audit 28 Jul 2026
A14: MOD-12 | B14: Notifications & Profile | C14: Candidate App | D14: Realtime notifications, XP/streak/badges | E14: Growth | F14: Raj Balani | G14: Medium | H14: In Progress | I14: 5 | J14: 4 | K14: 1 | L14: 12.5 | M14: 8.8 | N14: Medium | O14: — | P14: Seeded from audit 28 Jul 2026
... A22: MOD-20 | B22: Security & Platform | C22: All Portals | D22: RLS, webhooks, rate limits, CI, observability | E22: Platform | F22: Shreya Patil | G22: Critical | H22: In Progress | I22: 8 | J22: 4 | K22: 4 | L22: 20 | M22: 8.8 | N22: Critical | O22: — | P22: Seeded from audit 28 Jul 2026
A23: TOTAL | I23: =SUM(I3:I22) | J23: =SUM(J3:J22) | K23: =SUM(K3:K22) | L23: =SUM(L3:L22) | M23: =SUM(M3:M22)

Sheet 03 Feature Inventory
A1: Feature Inventory — full Clarify AI catalogue (114 features) | J1: Dashboard | K1: NAV | L1: ● Features | M1: Bugs | N1: Launch | O1: Smoke | P1: Creds | Q1: Env | R1: Playbooks | S1: Cases | T1: Sign-Off
A2: Feature ID | B2: Module | C2: Feature Name | D2: Description | E2: Frontend | F2: Backend | G2: Database | H2: API | I2: Edge Function | J2: Status | K2: Implementation Status | L2: QA Status | M2: Priority | N2: Risk | O2: Owner | P2: QA Owner | Q2: Est Hours | R2: Actual Hours | S2: Comments | T2: Route | U2: Deep Link | V2: How it works | W2: Role required | X2: Credit cost | Y2: Blocking bugs
A3: FEAT-001 | B3: Auth & Onboarding | C3: Email/password auth | D3: Signup/login with password | E3: Yes | F3: Yes | G3: Yes | H3: Yes | I3: N/A | J3: Completed | K3: Fully Implemented | L3: Passed | M3: Critical | N3: High | O3: Auth Lead | P3: Raj Balani | Q3: 2 | R3: 1.5 | T3: /login | U3: =IFERROR(Environments!$B$3&T3,T3) | V3: Open /login. Exercise 'Email/password auth' (Signup/login with password). Confirm happy path for intended role; note plan gates and credit toasts. | W3: Free+ | X3: 0 / N/A
A4: FEAT-002 | B4: Auth & Onboarding | C4: OAuth providers | D4: Google/GitHub/LinkedIn/Azure | E4: Yes | F4: Yes | G4: Yes | H4: Yes | I4: N/A | J4: Completed | K4: Fully Implemented | L4: In Testing | M4: Critical | N4: Medium | O4: Auth Lead | P4: Raj Balani | Q4: 3 | R4: 2 | S4: Provider enablement env-dependent | T4: /login | U4: =IFERROR(Environments!$B$3&T4,T4) | V4: Open /login. Exercise 'OAuth providers' (Google/GitHub/LinkedIn/Azure). Confirm happy path for intended role; note plan gates and credit toasts. | W4: Free+ | X4: 0 / N/A
A5: FEAT-003 | B5: Auth & Onboarding | C5: Email verification | D5: Verify email flow | E5: Yes | F5: Yes | G5: Yes | H5: Yes | I5: N/A | J5: Completed | K5: Fully Implemented | L5: Passed | M5: High | N5: Medium | O5: Auth Lead | P5: Raj Balani | Q5: 1.5 | R5: 1 | T5: /auth/verify | U5: =IFERROR(Environments!$B$3&T5,T5) | V5: Open /auth/verify. Exercise 'Email verification' (Verify email flow). Confirm happy path for intended role; note plan gates and credit toasts. | W5: Free+ | X5: 0 / N/A
A6: FEAT-004 | B6: Auth & Onboarding | C6: Password reset | D6: Forgot/reset password | E6: Yes | F6: Yes | G6: Yes | H6: Yes | I6: N/A | J6: Completed | K6: Fully Implemented | L6: Passed | M6: High | N6: Medium | O6: Auth Lead | P6: Raj Balani | Q6: 1.5 | R6: 1 | T6: /forgot-password | U6: =IFERROR(Environments!$B$3&T6,T6) | V6: Open /forgot-password. Exercise 'Password reset' (Forgot/reset password). Confirm happy path for intended role; note plan gates and credit toasts. | W6: Free+ | X6: 0 / N/A
A7: FEAT-005 | B7: Auth & Onboarding | C7: TOTP MFA | D7: Enable/verify TOTP + login challenge | E7: Yes | F7: Yes | G7: Yes | H7: Yes | I7: N/A | J7: Completed | K7: Fully Implemented | L7: Ready | M7: High | N7: High | O7: Auth Lead | P7: Raj Balani | Q7: 3 | R7: 2.5 | S7: Login AAL2 challenge wired | T7: /login | U7: =IFERROR(Environments!$B$3&T7,T7) | V7: Open /login. Exercise 'TOTP MFA' (Enable/verify TOTP + login challenge). Confirm happy path for intended role; note plan gates and credit toasts. | W7: Free+ | X7: 0 / N/A
A8: FEAT-006 | B8: Auth & Onboarding | C8: Account lockout | D8: Client lockout after failures | E8: Yes | F8: N/A | G8: N/A | H8: N/A | I8: N/A | J8: Completed | K8: Fully Implemented | L8: Not Tested | M8: Medium | N8: Medium | O8: Auth Lead | P8: Raj Balani | Q8: 1 | R8: 0 | S8: localStorage based | T8: /login | U8: =IFERROR(Environments!$B$3&T8,T8) | V8: Open /login. Exercise 'Account lockout' (Client lockout after failures). Confirm happy path for intended role; note plan gates and credit toasts. | W8: Free+ | X8: 0 / N/A
A9: FEAT-007 | B9: Auth & Onboarding | C9: Onboarding wizard 5 steps | D9: Collect profile/experience/audio/resume | E9: Yes | F9: Yes | G9: Yes | H9: Yes | I9: Yes | J9: In Progress | K9: Partial | L9: In Testing | M9: Critical | N9: High | O9: Auth Lead | P9: Shreya Patil | Q9: 5 | R9: 3 | S9: Mic+anxiety prefs now persist | T9: /login | U9: =IFERROR(Environments!$B$3&T9,T9) | V9: Open /login. Exercise 'Onboarding wizard 5 steps' (Collect profile/experience/audio/resume). Confirm happy path for intended role; note plan gates and credit toasts. | W9: Free+ | X9: 0 / N/A
A10: FEAT-008 | B10: Dashboard | C10: Home dashboard KPIs | D10: Sessions, credits, upcoming | E10: Yes | F10: Yes | G10: Yes | H10: Yes | I10: N/A | J10: Completed | K10: Fully Implemented | L10: Passed | M10: High | N10: Low | O10: Product | P10: Raj Balani | Q10: 2 | R10: 1.5 | T10: /app/dashboard | U10: =IFERROR(Environments!$B$3&T10,T10) | V10: Open /app/dashboard. Exercise 'Home dashboard KPIs' (Sessions, credits, upcoming). Confirm happy path for intended role; note plan gates and credit toasts. | W10: Free+ | X10: 0 / N/A
A11: FEAT-009 | B11: Dashboard | C11: App routing guards | D11: ProtectedRoute + admin gates | E11: Yes | F11: Yes | G11: Yes | H11: N/A | I11: N/A | J11: Completed | K11: Fully Implemented | L11: Passed | M11: Critical | N11: High | O11: Platform | P11: Shreya Patil | Q11: 2 | R11: 1.5 | T11: /app/dashboard | U11: =IFERROR(Environments!$B$3&T11,T11) | V11: Open /app/dashboard. Exercise 'App routing guards' (ProtectedRoute + admin gates). Confirm happy path for intended role; note plan gates and credit toasts. | W11: Free+ | X11: 0 / N/A
A12: FEAT-010 | B12: Dashboard | C12: In-app 404 NotFound | D12: /app/* splat catch-all | E12: Yes | F12: N/A | G12: N/A | H12: N/A | I12: N/A | J12: Completed | K12: Fully Implemented | L12: Passed | M12: Medium | N12: Low | O12: Product | P12: Raj Balani | Q12: 0.5 | R12: 0.25 | S12: P1-4 fixed | T12: /app/dashboard | U12: =IFERROR(Environments!$B$3&T12,T12) | V12: Open /app/dashboard. Exercise 'In-app 404 NotFound' (/app/* splat catch-all). Confirm happy path for intended role; note plan gates and credit toasts. | W12: Free+ | X12: 0 / N/A
A13: FEAT-011 | B13: Dashboard | C13: Mobile navigation | D13: Bottom nav destinations | E13: Yes | F13: N/A | G13: N/A | H13: N/A | I13: N/A | J13: Completed | K13: Fully Implemented | L13: Ready | M13: Medium | N13: Medium | O13: Product | P13: Raj Balani | Q13: 2 | R13: 2 | S13: Notifications/Guide/Profile/Admin in More | T13: /app/dashboard | U13: =IFERROR(Environments!$B$3&T13,T13) | V13: Mobile viewport → More sheet includes Usage and Interview Day matching sidebar. | W13: Free+ | X13: 0 / N/A
A14: FEAT-012 | B14: Dashboard | C14: Command palette | D14: Ctrl/Cmd+K search | E14: Yes | F14: N/A | G14: N/A | H14: N/A | I14: N/A | J14: Completed | K14: Partial | L14: In Testing | M14: Low | N14: Low | O14: Product | P14: Raj Balani | Q14: 1 | R14: 0.5 | S14: Nav only | T14: /app/dashboard | U14: =IFERROR(Environments!$B$3&T14,T14) | V14: Open /app/dashboard. Exercise 'Command palette' (Ctrl/Cmd+K search). Confirm happy path for intended role; note plan gates and credit toasts. | W14: Free+ | X14: 0 / N/A
A15: FEAT-013 | B15: Live Practice Coach | C15: Live Practice Coach session | D15: Core live rehearsal loop | E15: Yes | F15: Yes | G15: Yes | H15: Yes | I15: Yes | J15: Completed | K15: Fully Implemented | L15: Passed | M15: Critical | N15: Critical | O15: Live Coach | P15: Shreya Patil | Q15: 8 | R15: 6 | T15: /app/live | U15: =IFERROR(Environments!$B$3&T15,T15) | V15: Open /app/live. Exercise 'Live Practice Coach session' (Core live rehearsal loop). Confirm happy path for intended role; note plan gates and credit toasts. | W15: Free+ | X15: 0 / N/A
A16: FEAT-014 | B16: Live Practice Coach | C16: System/tab audio capture | D16: Chrome/Edge tab audio | E16: Yes | F16: N/A | G16: N/A | H16: N/A | I16: N/A | J16: Completed | K16: Fully Implemented | L16: Passed | M16: Critical | N16: High | O16: Live Coach | P16: Shreya Patil | Q16: 3 | R16: 2 | S16: Chrome/Edge only | T16: /app/live | U16: =IFERROR(Environments!$B$3&T16,T16) | V16: Open /app/live. Exercise 'System/tab audio capture' (Chrome/Edge tab audio). Confirm happy path for intended role; note plan gates and credit toasts. | W16: Free+ | X16: 0 / N/A
A17: FEAT-015 | B17: Live Practice Coach | C17: Deepgram streaming STT | D17: nova-2-meeting stream | E17: Yes | F17: Yes | G17: N/A | H17: Yes | I17: Yes | J17: Completed | K17: Fully Implemented | L17: Passed | M17: Critical | N17: Critical | O17: Live Coach | P17: Shreya Patil | Q17: 4 | R17: 3.5 | S17: deepgram-token | T17: /app/live | U17: =IFERROR(Environments!$B$3&T17,T17) | V17: Open /app/live. Exercise 'Deepgram streaming STT' (nova-2-meeting stream). Confirm happy path for intended role; note plan gates and credit toasts. | W17: Free+ | X17: 0 / N/A
A18: FEAT-016 | B18: Live Practice Coach | C18: Speaker diarization | D18: Interviewer vs candidate | E18: Yes | F18: Yes | G18: Yes | H18: N/A | I18: N/A | J18: Completed | K18: Fully Implemented | L18: Passed | M18: High | N18: High | O18: Live Coach | P18: Shreya Patil | Q18: 3 | R18: 2 | T18: /app/live | U18: =IFERROR(Environments!$B$3&T18,T18) | V18: Open /app/live. Exercise 'Speaker diarization' (Interviewer vs candidate). Confirm happy path for intended role; note plan gates and credit toasts. | W18: Free+ | X18: 0 / N/A
A19: FEAT-017 | B19: Live Practice Coach | C19: Real-time AI hints | D19: generate-hint | E19: Yes | F19: Yes | G19: Yes | H19: Yes | I19: Yes | J19: Completed | K19: Fully Implemented | L19: In Testing | M19: Critical | N19: High | O19: Live Coach | P19: Shreya Patil | Q19: 3 | R19: 2 | S19: Credits | T19: /app/live | U19: =IFERROR(Environments!$B$3&T19,T19) | V19: Open /app/live. Exercise 'Real-time AI hints' (generate-hint). Confirm happy path for intended role; note plan gates and credit toasts. | W19: Free+ | X19: 2 (live_hint)
A20: FEAT-018 | B20: Live Practice Coach | C20: Streaming AI answers | D20: generate-answer SSE | E20: Yes | F20: Yes | G20: Yes | H20: Yes | I20: Yes | J20: Completed | K20: Fully Implemented | L20: In Testing | M20: Critical | N20: Critical | O20: Live Coach | P20: Shreya Patil | Q20: 5 | R20: 4 | S20: Free limited; overlay Pro | T20: /app/live | U20: =IFERROR(Environments!$B$3&T20,T20) | V20: Open /app/live. Exercise 'Streaming AI answers' (generate-answer SSE). Confirm happy path for intended role; note plan gates and credit toasts. | W20: Free+ | X20: 8 (live_answer)
A21: FEAT-019 | B21: Live Practice Coach | C21: Screenshot/vision capture | D21: Coding problem OCR/vision | E21: Yes | F21: Yes | G21: N/A | H21: Yes | I21: Yes | J21: Completed | K21: Fully Implemented | L21: In Testing | M21: High | N21: High | O21: Live Coach | P21: Shreya Patil | Q21: 4 | R21: 2 | S21: Pro gated | T21: /app/live | U21: =IFERROR(Environments!$B$3&T21,T21) | V21: Open /app/live. Exercise 'Screenshot/vision capture' (Coding problem OCR/vision). Confirm happy path for intended role; note plan gates and credit toasts. | W21: Pro+ | X21: 10 (screenshot_answer)
A22: FEAT-020 | B22: Live Practice Coach | C22: Stealth mode | D22: UI labels only | E22: Yes | F22: N/A | G22: N/A | H22: N/A | I22: N/A | J22: In Progress | K22: Partial | L22: Failed | M22: Medium | N22: Medium | O22: Desktop | P22: Shreya Patil | Q22: 2 | R22: 0.5 | S22: No capture evasion | T22: /app/live | U22: =IFERROR(Environments!$B$3&T22,T22) | V22: Open /app/live. Exercise 'Stealth mode' (UI labels only). Confirm happy path for intended role; note plan gates and credit toasts. | W22: Free+ | X22: 0 / N/A
A23: FEAT-021 | B23: Live Practice Coach | C23: Panic mode | D23: Static coaching steps | E23: Yes | F23: N/A | G23: N/A | H23: N/A | I23: N/A | J23: Completed | K23: Fully Implemented | L23: Passed | M23: Medium | N23: Low | O23: Live Coach | P23: Shreya Patil | Q23: 1 | R23: 0.5 | T23: /app/live | U23: =IFERROR(Environments!$B$3&T23,T23) | V23: Open /app/live. Exercise 'Panic mode' (Static coaching steps). Confirm happy path for intended role; note plan gates and credit toasts. | W23: Free+ | X23: 0 / N/A
A24: FEAT-022 | B24: Mock Interview | C24: Mock interview session | D24: Timed AI mock | E24: Yes | F24: Yes | G24: Yes | H24: Yes | I24: Yes | J24: In Progress | K24: Partial | L24: In Testing | M24: High | N24: High | O24: Live Coach | P24: Shreya Patil | Q24: 6 | R24: 3 | S24: No TTS | T24: /app/mock | U24: =IFERROR(Environments!$B$3&T24,T24) | V24: Open /app/mock. Exercise 'Mock interview session' (Timed AI mock). Confirm happy path for intended role; note plan gates and credit toasts. | W24: Free+ | X24: 0 / N/A
A25: FEAT-023 | B25: Mock Interview | C25: Mock warm-up | D25: Warm-up questions | E25: Yes | F25: N/A | G25: N/A | H25: N/A | I25: N/A | J25: Completed | K25: Partial | L25: Passed | M25: Medium | N25: Low | O25: Live Coach | P25: Shreya Patil | Q25: 1.5 | R25: 1 | S25: WARMUP_MAX copy fixed | T25: /app/mock | U25: =IFERROR(Environments!$B$3&T25,T25) | V25: Open /app/mock. Exercise 'Mock warm-up' (Warm-up questions). Confirm happy path for intended role; note plan gates and credit toasts. | W25: Free+ | X25: 0 / N/A
A26: FEAT-024 | B26: Mock Interview | C26: Mock TTS playback | D26: Spoken questions | E26: No | F26: No | G26: N/A | H26: No | I26: No | J26: Not Started | K26: Not Built | L26: Not Tested | M26: High | N26: Medium | O26: Live Coach | P26: Shreya Patil | Q26: 8 | R26: 0 | S26: Roadmap | T26: /app/mock | U26: =IFERROR(Environments!$B$3&T26,T26) | V26: Open /app/mock. Exercise 'Mock TTS playback' (Spoken questions). Confirm happy path for intended role; note plan gates and credit toasts. | W26: Free+ | X26: 0 / N/A | Y26: BUG-OPEN-04
A27: FEAT-025 | B27: Sessions & Debriefs | C27: Session history list | D27: Past sessions | E27: Yes | F27: Yes | G27: Yes | H27: Yes | I27: N/A | J27: Completed | K27: Fully Implemented | L27: Passed | M27: High | N27: Low | O27: Sessions | P27: Shreya Patil | Q27: 2 | R27: 1.5 | T27: /app/sessions | U27: =IFERROR(Environments!$B$3&T27,T27) | V27: Open /app/sessions. Exercise 'Session history list' (Past sessions). Confirm happy path for intended role; note plan gates and credit toasts. | W27: Free+ | X27: 0 / N/A
A28: FEAT-026 | B28: Sessions & Debriefs | C28: Session detail scores | D28: Dimension breakdown | E28: Yes | F28: Yes | G28: Yes | H28: N/A | I28: N/A | J28: Completed | K28: Fully Implemented | L28: Passed | M28: High | N28: Medium | O28: Sessions | P28: Shreya Patil | Q28: 2 | R28: 1.5 | S28: Null=Not scored P1-7 | T28: /app/sessions | U28: =IFERROR(Environments!$B$3&T28,T28) | V28: Open /app/sessions. Exercise 'Session detail scores' (Dimension breakdown). Confirm happy path for intended role; note plan gates and credit toasts. | W28: Free+ | X28: 0 / N/A
A29: FEAT-027 | B29: Sessions & Debriefs | C29: AI Debrief | D29: generate-debrief | E29: Yes | F29: Yes | G29: Yes | H29: Yes | I29: Yes | J29: Completed | K29: Fully Implemented | L29: Passed | M29: High | N29: Medium | O29: Sessions | P29: Shreya Patil | Q29: 3 | R29: 2 | T29: /app/sessions | U29: =IFERROR(Environments!$B$3&T29,T29) | V29: Open /app/sessions. Exercise 'AI Debrief' (generate-debrief). Confirm happy path for intended role; note plan gates and credit toasts. | W29: Free+ | X29: 15 (session_debrief)
A30: FEAT-028 | B30: Sessions & Debriefs | C30: Debrief public share | D30: Share token link | E30: Yes | F30: Yes | G30: Yes | H30: Yes | I30: N/A | J30: Completed | K30: Fully Implemented | L30: In Testing | M30: Medium | N30: Low | O30: Sessions | P30: Shreya Patil | Q30: 2 | R30: 1 | T30: /app/sessions | U30: =IFERROR(Environments!$B$3&T30,T30) | V30: Open /app/sessions. Exercise 'Debrief public share' (Share token link). Confirm happy path for intended role; note plan gates and credit toasts. | W30: Free+ | X30: 0 / N/A
A31: FEAT-029 | B31: Sessions & Debriefs | C31: Scorecard | D31: Client Gemini scoring | E31: Yes | F31: Yes | G31: Yes | H31: Yes | I31: Partial | J31: Completed | K31: Fully Implemented | L31: In Testing | M31: High | N31: Medium | O31: Sessions | P31: Shreya Patil | Q31: 3 | R31: 1.5 | T31: /app/sessions | U31: =IFERROR(Environments!$B$3&T31,T31) | V31: Open /app/sessions. Exercise 'Scorecard' (Client Gemini scoring). Confirm happy path for intended role; note plan gates and credit toasts. | W31: Free+ | X31: 0 / N/A
A32: FEAT-030 | B32: Analytics & Usage | C32: Analytics dashboard | D32: Trends WPM fillers | E32: Yes | F32: Yes | G32: Yes | H32: Yes | I32: Yes | J32: Completed | K32: Fully Implemented | L32: Passed | M32: Medium | N32: Low | O32: Analytics | P32: Raj Balani | Q32: 3 | R32: 2 | S32: total_sessions fix P2-8 | T32: /app/analytics | U32: =IFERROR(Environments!$B$3&T32,T32) | V32: Open /app/analytics. Exercise 'Analytics dashboard' (Trends WPM fillers). Confirm happy path for intended role; note plan gates and credit toasts. | W32: Free+ | X32: 0 / N/A
A33: FEAT-031 | B33: Analytics & Usage | C33: Credits usage dashboard | D33: Ledger view | E33: Yes | F33: Yes | G33: Yes | H33: Yes | I33: N/A | J33: Completed | K33: Fully Implemented | L33: Passed | M33: High | N33: Medium | O33: Billing | P33: Raj Balani | Q33: 2 | R33: 1.5 | T33: /app/usage | U33: =IFERROR(Environments!$B$3&T33,T33) | V33: Open /app/usage. Exercise 'Credits usage dashboard' (Ledger view). Confirm happy path for intended role; note plan gates and credit toasts. | W33: Free+ | X33: 0 / N/A
A34: FEAT-032 | B34: Prep Lab | C34: Prep Lab hub | D34: Tool launcher | E34: Yes | F34: Yes | G34: N/A | H34: Yes | I34: Yes | J34: Completed | K34: Fully Implemented | L34: Passed | M34: High | N34: Low | O34: Prep | P34: Raj Balani | Q34: 1 | R34: 0.5 | T34: /app/prep | U34: =IFERROR(Environments!$B$3&T34,T34) | V34: Open /app/prep. Exercise 'Prep Lab hub' (Tool launcher). Confirm happy path for intended role; note plan gates and credit toasts. | W34: Free+ | X34: 0 / N/A
A35: FEAT-033 | B35: Prep Lab | C35: STAR Builder | D35: STAR answer builder | E35: Yes | F35: Yes | G35: Yes | H35: Yes | I35: Yes | J35: Completed | K35: Fully Implemented | L35: Passed | M35: High | N35: Medium | O35: Prep | P35: Raj Balani | Q35: 3 | R35: 2 | S35: Cost from economics | T35: /app/prep | U35: =IFERROR(Environments!$B$3&T35,T35) | V35: Open /app/prep. Exercise 'STAR Builder' (STAR answer builder). Confirm happy path for intended role; note plan gates and credit toasts. | W35: Free+ | X35: 10 (star_builder)
A36: FEAT-034 | B36: Prep Lab | C36: Project Builder | D36: Project drafts | E36: Yes | F36: Partial | G36: N/A | H36: Yes | I36: Yes | J36: Completed | K36: Fully Implemented | L36: In Testing | M36: Medium | N36: Low | O36: Prep | P36: Raj Balani | Q36: 2 | R36: 1 | S36: localStorage drafts | T36: /app/prep | U36: =IFERROR(Environments!$B$3&T36,T36) | V36: Open /app/prep. Exercise 'Project Builder' (Project drafts). Confirm happy path for intended role; note plan gates and credit toasts. | W36: Free+ | X36: 0 / N/A
A37: FEAT-035 | B37: Prep Lab | C37: Rephraser | D37: Rewrite answers | E37: Yes | F37: Yes | G37: N/A | H37: Yes | I37: Yes | J37: Completed | K37: Fully Implemented | L37: Passed | M37: Medium | N37: Low | O37: Prep | P37: Raj Balani | Q37: 2 | R37: 1.5 | S37: Error state wired | T37: /app/prep | U37: =IFERROR(Environments!$B$3&T37,T37) | V37: Open /app/prep. Exercise 'Rephraser' (Rewrite answers). Confirm happy path for intended role; note plan gates and credit toasts. | W37: Free+ | X37: 3 (rephraser)
A38: FEAT-036 | B38: Prep Lab | C38: Coding Hints catalog | D38: DB coding hints | E38: Yes | F38: Yes | G38: Yes | H38: Yes | I38: N/A | J38: Completed | K38: Fully Implemented | L38: In Testing | M38: Medium | N38: Low | O38: Prep | P38: Raj Balani | Q38: 2 | R38: 1 | T38: /app/prep | U38: =IFERROR(Environments!$B$3&T38,T38) | V38: Open /app/prep. Exercise 'Coding Hints catalog' (DB coding hints). Confirm happy path for intended role; note plan gates and credit toasts. | W38: Free+ | X38: 0 / N/A
A39: FEAT-037 | B39: Prep Lab | C39: System Design topics | D39: DB topics | E39: Yes | F39: Yes | G39: Yes | H39: Yes | I39: N/A | J39: Completed | K39: Fully Implemented | L39: In Testing | M39: Medium | N39: Low | O39: Prep | P39: Raj Balani | Q39: 2 | R39: 1 | T39: /app/prep | U39: =IFERROR(Environments!$B$3&T39,T39) | V39: Open /app/prep. Exercise 'System Design topics' (DB topics). Confirm happy path for intended role; note plan gates and credit toasts. | W39: Free+ | X39: 0 / N/A
A40: FEAT-038 | B40: Prep Lab | C40: prep-tool AI suite | D40: 12 AI prep tools | E40: Yes | F40: Yes | G40: Yes | H40: Yes | I40: Yes | J40: Completed | K40: Fully Implemented | L40: In Testing | M40: High | N40: Medium | O40: Prep | P40: Raj Balani | Q40: 4 | R40: 2 | T40: /app/prep | U40: =IFERROR(Environments!$B$3&T40,T40) | V40: Open /app/prep. Exercise 'prep-tool AI suite' (12 AI prep tools). Confirm happy path for intended role; note plan gates and credit toasts. | W40: Free+ | X40: 0 / N/A
A41: FEAT-039 | B41: Documents & Resumes | C41: Resume upload + AI parse | D41: parse-resume + OCR | E41: Yes | F41: Yes | G41: Yes | H41: Yes | I41: Yes | J41: Completed | K41: Fully Implemented | L41: Passed | M41: Critical | N41: High | O41: Docs | P41: Shreya Patil | Q41: 5 | R41: 4 | S41: Credits + free onboarding | T41: /app/documents | U41: =IFERROR(Environments!$B$3&T41,T41) | V41: Open /app/documents. Exercise 'Resume upload + AI parse' (parse-resume + OCR). Confirm happy path for intended role; note plan gates and credit toasts. | W41: Free+ | X41: 12 (resume_analysis; first onboarding free)
A42: FEAT-040 | B42: Documents & Resumes | C42: Job description parse | D42: Client Gemini JD | E42: Yes | F42: Partial | G42: Yes | H42: Partial | I42: N/A | J42: Completed | K42: Fully Implemented | L42: In Testing | M42: High | N42: Medium | O42: Docs | P42: Shreya Patil | Q42: 2 | R42: 1 | T42: /app/documents | U42: =IFERROR(Environments!$B$3&T42,T42) | V42: Open /app/documents. Exercise 'Job description parse' (Client Gemini JD). Confirm happy path for intended role; note plan gates and credit toasts. | W42: Free+ | X42: 0 / N/A
A43: FEAT-041 | B43: Documents & Resumes | C43: Resume vs JD gap analysis | D43: gap-analysis edge | E43: Yes | F43: Yes | G43: Yes | H43: Yes | I43: Yes | J43: Completed | K43: Fully Implemented | L43: Ready | M43: High | N43: Medium | O43: Docs | P43: Shreya Patil | Q43: 4 | R43: 3 | S43: JDDetail run + 402 handling | T43: /app/documents/jd/:id | U43: =IFERROR(Environments!$B$3&T43,T43) | V43: Open a JD → select resume → Run gap analysis. Expect match score + skills; 402 if credits low. | W43: Free+ | X43: 10 (gap_analysis)
A44: FEAT-042 | B44: Documents & Resumes | C44: Resume version history UI | D44: Version list UI | E44: Yes | F44: Yes | G44: Yes | H44: N/A | I44: N/A | J44: Completed | K44: Fully Implemented | L44: Ready | M44: Medium | N44: Low | O44: Docs | P44: Shreya Patil | Q44: 4 | R44: 2 | S44: Read-only list on ResumeDetail | T44: /app/documents/resume/:id | U44: =IFERROR(Environments!$B$3&T44,T44) | V44: Open resume detail → Version history card lists parse snapshots (read-only). | W44: Free+ | X44: 0 / N/A
A45: FEAT-043 | B45: Documents & Resumes | C45: parse-document OCR | D45: Generic doc parse | E45: Yes | F45: Yes | G45: Yes | H45: Yes | I45: Yes | J45: Completed | K45: Fully Implemented | L45: In Testing | M45: High | N45: Medium | O45: Docs | P45: Shreya Patil | Q45: 3 | R45: 1.5 | S45: Charged; key in header | T45: /app/documents | U45: =IFERROR(Environments!$B$3&T45,T45) | V45: Open /app/documents. Exercise 'parse-document OCR' (Generic doc parse). Confirm happy path for intended role; note plan gates and credit toasts. | W45: Free+ | X45: 8 (parse_document)
A46: FEAT-044 | B46: Answer Bank | C46: Answer Bank CRUD | D46: Save/edit STAR answers | E46: Yes | F46: Yes | G46: Yes | H46: Yes | I46: N/A | J46: Completed | K46: Fully Implemented | L46: Passed | M46: Medium | N46: Low | O46: Prep | P46: Raj Balani | Q46: 2 | R46: 1.5 | T46: /app/answers | U46: =IFERROR(Environments!$B$3&T46,T46) | V46: Open /app/answers. Exercise 'Answer Bank CRUD' (Save/edit STAR answers). Confirm happy path for intended role; note plan gates and credit toasts. | W46: Free+ | X46: 0 / N/A
A47: FEAT-045 | B47: Answer Bank | C47: Answer Bank AI generate | D47: prep-tool star_method | E47: Yes | F47: Yes | G47: Yes | H47: Yes | I47: Yes | J47: Completed | K47: Fully Implemented | L47: In Testing | M47: Medium | N47: Low | O47: Prep | P47: Raj Balani | Q47: 3 | R47: 2 | S47: Wired P3 | T47: /app/answers | U47: =IFERROR(Environments!$B$3&T47,T47) | V47: Open /app/answers. Exercise 'Answer Bank AI generate' (prep-tool star_method). Confirm happy path for intended role; note plan gates and credit toasts. | W47: Free+ | X47: 0 / N/A
A48: FEAT-046 | B48: Interviews & Calendar | C48: Manual interview CRUD | D48: Schedule interviews | E48: Yes | F48: Yes | G48: Yes | H48: Yes | I48: N/A | J48: Completed | K48: Fully Implemented | L48: Passed | M48: High | N48: Medium | O48: Scheduling | P48: Raj Balani | Q48: 3 | R48: 2 | S48: next_round helpers | T48: /app/interviews | U48: =IFERROR(Environments!$B$3&T48,T48) | V48: Open /app/interviews. Exercise 'Manual interview CRUD' (Schedule interviews). Confirm happy path for intended role; note plan gates and credit toasts. | W48: Free+ | X48: 0 / N/A
A49: FEAT-047 | B49: Interviews & Calendar | C49: Interview email reminders | D49: schedule-interview email | E49: Yes | F49: Yes | G49: Yes | H49: Yes | I49: Yes | J49: Completed | K49: Fully Implemented | L49: Blocked | M49: Medium | N49: Medium | O49: Scheduling | P49: Raj Balani | Q49: 2 | R49: 0.5 | S49: Needs Resend key | T49: /app/interviews | U49: =IFERROR(Environments!$B$3&T49,T49) | V49: Open /app/interviews. Exercise 'Interview email reminders' (schedule-interview email). Confirm happy path for intended role; note plan gates and credit toasts. | W49: Free+ | X49: 0 / N/A | Y49: BUG-OPEN-26
A50: FEAT-048 | B50: Interviews & Calendar | C50: Google Calendar connect | D50: OAuth connect | E50: Yes | F50: Yes | G50: Yes | H50: Yes | I50: Yes | J50: Completed | K50: Fully Implemented | L50: In Testing | M50: High | N50: Medium | O50: Scheduling | P50: Raj Balani | Q50: 3 | R50: 1.5 | T50: /app/interviews | U50: =IFERROR(Environments!$B$3&T50,T50) | V50: Open /app/interviews. Exercise 'Google Calendar connect' (OAuth connect). Confirm happy path for intended role; note plan gates and credit toasts. | W50: Free+ | X50: 0 / N/A
A51: FEAT-049 | B51: Interviews & Calendar | C51: Google Calendar sync | D51: sync-calendar | E51: Yes | F51: Yes | G51: Yes | H51: Yes | I51: Yes | J51: Blocked | K51: Partial | L51: Blocked | M51: High | N51: Medium | O51: Scheduling | P51: Raj Balani | Q51: 4 | R51: 1 | S51: 501 without secrets | T51: /app/interviews | U51: =IFERROR(Environments!$B$3&T51,T51) | V51: Open /app/interviews. Exercise 'Google Calendar sync' (sync-calendar). Confirm happy path for intended role; note plan gates and credit toasts. | W51: Pro+ | X51: 0 / N/A | Y51: BUG-OPEN-03
A52: FEAT-050 | B52: Interviews & Calendar | C52: Outlook Calendar | D52: Outlook sync | E52: No | F52: No | G52: N/A | H52: No | I52: No | J52: Not Started | K52: Not Built | L52: Not Tested | M52: Medium | N52: Low | O52: Scheduling | P52: Raj Balani | Q52: 8 | R52: 0 | S52: Descope | T52: /app/interviews | U52: =IFERROR(Environments!$B$3&T52,T52) | V52: Open /app/interviews. Exercise 'Outlook Calendar' (Outlook sync). Confirm happy path for intended role; note plan gates and credit toasts. | W52: Free+ | X52: 0 / N/A | Y52: BUG-OPEN-07
A53: FEAT-051 | B53: Interviews & Calendar | C53: Interview Day screen | D53: Day-of interview UI | E53: Yes | F53: Yes | G53: Yes | H53: N/A | I53: N/A | J53: Completed | K53: Fully Implemented | L53: Passed | M53: High | N53: Medium | O53: Scheduling | P53: Raj Balani | Q53: 2 | R53: 1.5 | S53: Date bug fixed P1-1 | T53: /app/interview-day | U53: =IFERROR(Environments!$B$3&T53,T53) | V53: Open /app/interview-day. Exercise 'Interview Day screen' (Day-of interview UI). Confirm happy path for intended role; note plan gates and credit toasts. | W53: Free+ | X53: 0 / N/A
A54: FEAT-052 | B54: Company Research | C54: Company Research AI | D54: AI brief + cache | E54: Yes | F54: Yes | G54: Yes | H54: Yes | I54: Yes | J54: Completed | K54: Fully Implemented | L54: Passed | M54: Medium | N54: Medium | O54: Prep | P54: Raj Balani | Q54: 3 | R54: 2 | S54: Pro gated | T54: /app/companies | U54: =IFERROR(Environments!$B$3&T54,T54) | V54: Open /app/companies. Exercise 'Company Research AI' (AI brief + cache). Confirm happy path for intended role; note plan gates and credit toasts. | W54: Pro+ | X54: 20 (company_research)
A55: FEAT-053 | B55: Notifications & Profile | C55: In-app notifications | D55: Realtime notifications | E55: Yes | F55: Yes | G55: Yes | H55: Yes | I55: N/A | J55: Completed | K55: Fully Implemented | L55: Passed | M55: Medium | N55: Low | O55: Growth | P55: Raj Balani | Q55: 2 | R55: 1.5 | T55: /app/notifications | U55: =IFERROR(Environments!$B$3&T55,T55) | V55: Open /app/notifications. Exercise 'In-app notifications' (Realtime notifications). Confirm happy path for intended role; note plan gates and credit toasts. | W55: Free+ | X55: 0 / N/A
A56: FEAT-054 | B56: Notifications & Profile | C56: Email notification prefs | D56: Prefs UI + send-email gate | E56: Yes | F56: Yes | G56: Yes | H56: Yes | I56: Yes | J56: Completed | K56: Fully Implemented | L56: Ready | M56: Medium | N56: Medium | O56: Growth | P56: Raj Balani | Q56: 2 | R56: 1.5 | S56: send-email honours prefs | T56: /app/settings/notifications | U56: =IFERROR(Environments!$B$3&T56,T56) | V56: Settings → Notifications. Toggle category off, trigger send-email type; expect skipped when pref off. | W56: Free+ | X56: 0 / N/A
A57: FEAT-055 | B57: Notifications & Profile | C57: Push notifications | D57: Web push | E57: Partial | F57: No | G57: N/A | H57: No | I57: No | J57: Not Started | K57: Not Built | L57: Not Tested | M57: Low | N57: Low | O57: Growth | P57: Raj Balani | Q57: 6 | R57: 0 | S57: Permission only | T57: /app/notifications | U57: =IFERROR(Environments!$B$3&T57,T57) | V57: Open /app/notifications. Exercise 'Push notifications' (Web push). Confirm happy path for intended role; note plan gates and credit toasts. | W57: Free+ | X57: 0 / N/A | Y57: BUG-OPEN-09
A58: FEAT-056 | B58: Notifications & Profile | C58: Gamification XP/streak | D58: XP badges streaks | E58: Yes | F58: Yes | G58: Yes | H58: Yes | I58: N/A | J58: Completed | K58: Fully Implemented | L58: Passed | M58: Medium | N58: Low | O58: Growth | P58: Raj Balani | Q58: 3 | R58: 2 | T58: /app/notifications | U58: =IFERROR(Environments!$B$3&T58,T58) | V58: Open /app/notifications. Exercise 'Gamification XP/streak' (XP badges streaks). Confirm happy path for intended role; note plan gates and credit toasts. | W58: Free+ | X58: 0 / N/A
A59: FEAT-057 | B59: Notifications & Profile | C59: Profile page display | D59: Streak badges profile | E59: Yes | F59: Yes | G59: Yes | H59: N/A | I59: N/A | J59: Completed | K59: Fully Implemented | L59: Passed | M59: Medium | N59: Medium | O59: Growth | P59: Raj Balani | Q59: 2 | R59: 1.5 | S59: streak_days + badges fixed | T59: /app/notifications | U59: =IFERROR(Environments!$B$3&T59,T59) | V59: Open /app/notifications. Exercise 'Profile page display' (Streak badges profile). Confirm happy path for intended role; note plan gates and credit toasts. | W59: Free+ | X59: 0 / N/A
A60: FEAT-058 | B60: Referrals & Guide | C60: Referral program | D60: RPC credit grants | E60: Yes | F60: Yes | G60: Yes | H60: Yes | I60: Yes | J60: Completed | K60: Fully Implemented | L60: Passed | M60: Medium | N60: Low | O60: Growth | P60: Raj Balani | Q60: 2 | R60: 1.5 | T60: /app/referrals | U60: =IFERROR(Environments!$B$3&T60,T60) | V60: Open /app/referrals. Exercise 'Referral program' (RPC credit grants). Confirm happy path for intended role; note plan gates and credit toasts. | W60: Free+ | X60: 0 / N/A
A61: FEAT-059 | B61: Referrals & Guide | C61: In-app Guide/Help | D61: Help articles | E61: Yes | F61: Yes | G61: Yes | H61: Yes | I61: N/A | J61: Completed | K61: Fully Implemented | L61: Passed | M61: Low | N61: Low | O61: Growth | P61: Shreya Patil | Q61: 1.5 | R61: 1 | S61: Group Practice coming soon | T61: /app/referrals | U61: =IFERROR(Environments!$B$3&T61,T61) | V61: Open /app/referrals. Exercise 'In-app Guide/Help' (Help articles). Confirm happy path for intended role; note plan gates and credit toasts. | W61: Free+ | X61: 0 / N/A
A62: FEAT-060 | B62: Gov Exam Mock Tests | C62: Mock test engine | D62: create/submit/score atomic | E62: Yes | F62: Yes | G62: Yes | H62: Yes | I62: Yes | J62: Completed | K62: Fully Implemented | L62: Passed | M62: Critical | N62: High | O62: GovExams | P62: Raj Balani | Q62: 6 | R62: 5 | T62: /app/mock-test | U62: =IFERROR(Environments!$B$3&T62,T62) | V62: Open /app/mock-test. Exercise 'Mock test engine' (create/submit/score atomic). Confirm happy path for intended role; note plan gates and credit toasts. | W62: Free+ | X62: 0 / N/A
A63: FEAT-061 | B63: Gov Exam Mock Tests | C63: Question bank content | D63: Seeded MCQs | E63: Yes | F63: Yes | G63: Yes | H63: N/A | I63: N/A | J63: Completed | K63: Fully Implemented | L63: Ready | M63: Critical | N63: High | O63: GovExams | P63: Raj Balani | Q63: 20 | R63: 8 | S63: ~100+ MCQs via expand migration | T63: /app/mock-test | U63: =IFERROR(Environments!$B$3&T63,T63) | V63: Mock Test Hub → configure exam → create test. Bank should return enough questions per major exam type. | W63: Free+ | X63: 3 (create_mock_test) + AI gap fill 15
A64: FEAT-062 | B64: Gov Exam Mock Tests | C64: Adaptive question select | D64: select-test-questions | E64: Yes | F64: Yes | G64: Yes | H64: Yes | I64: Yes | J64: Completed | K64: Fully Implemented | L64: Passed | M64: High | N64: Medium | O64: GovExams | P64: Raj Balani | Q64: 3 | R64: 2 | T64: /app/mock-test | U64: =IFERROR(Environments!$B$3&T64,T64) | V64: Open /app/mock-test. Exercise 'Adaptive question select' (select-test-questions). Confirm happy path for intended role; note plan gates and credit toasts. | W64: Free+ | X64: 0 / N/A
A65: FEAT-063 | B65: Gov Exam Mock Tests | C65: AI question gap-fill | D65: Pro + credits | E65: Yes | F65: Yes | G65: Yes | H65: Yes | I65: Yes | J65: Completed | K65: Fully Implemented | L65: In Testing | M65: High | N65: Medium | O65: GovExams | P65: Raj Balani | Q65: 3 | R65: 1.5 | T65: /app/mock-test | U65: =IFERROR(Environments!$B$3&T65,T65) | V65: Open /app/mock-test. Exercise 'AI question gap-fill' (Pro + credits). Confirm happy path for intended role; note plan gates and credit toasts. | W65: Free+ | X65: 0 / N/A
A66: FEAT-064 | B66: Gov Exam Mock Tests | C66: Spaced repetition | D66: Revision schedule | E66: Yes | F66: Yes | G66: Yes | H66: Yes | I66: N/A | J66: Completed | K66: Fully Implemented | L66: In Testing | M66: Medium | N66: Low | O66: GovExams | P66: Raj Balani | Q66: 3 | R66: 1 | T66: /app/mock-test | U66: =IFERROR(Environments!$B$3&T66,T66) | V66: Open /app/mock-test. Exercise 'Spaced repetition' (Revision schedule). Confirm happy path for intended role; note plan gates and credit toasts. | W66: Free+ | X66: 0 / N/A
A67: FEAT-065 | B67: Gov Exam Mock Tests | C67: Exam papers browser | D67: Past papers UI | E67: Yes | F67: Yes | G67: Yes | H67: Yes | I67: Partial | J67: In Progress | K67: Partial | L67: Failed | M67: Medium | N67: Medium | O67: GovExams | P67: Raj Balani | Q67: 3 | R67: 1 | S67: Many empty | T67: /app/mock-test | U67: =IFERROR(Environments!$B$3&T67,T67) | V67: Open /app/mock-test. Exercise 'Exam papers browser' (Past papers UI). Confirm happy path for intended role; note plan gates and credit toasts. | W67: Free+ | X67: 0 / N/A
A68: FEAT-066 | B68: Gov Exam Mock Tests | C68: PDF question import | D68: parse-question-pdf | E68: Yes | F68: Yes | G68: Yes | H68: Yes | I68: Yes | J68: Completed | K68: Fully Implemented | L68: Blocked | M68: High | N68: Medium | O68: GovExams | P68: Raj Balani | Q68: 4 | R68: 1 | S68: Quota/env | T68: /app/mock-test | U68: =IFERROR(Environments!$B$3&T68,T68) | V68: Open /app/mock-test. Exercise 'PDF question import' (parse-question-pdf). Confirm happy path for intended role; note plan gates and credit toasts. | W68: Free+ | X68: 0 / N/A | Y68: BUG-OPEN-17
A69: FEAT-067 | B69: Gov Exam Mock Tests | C69: Excel/CSV import | D69: bulk-import-questions | E69: Yes | F69: Yes | G69: Yes | H69: Yes | I69: Yes | J69: Completed | K69: Fully Implemented | L69: In Testing | M69: High | N69: Medium | O69: GovExams | P69: Raj Balani | Q69: 3 | R69: 2 | T69: /app/mock-test | U69: =IFERROR(Environments!$B$3&T69,T69) | V69: Open /app/mock-test. Exercise 'Excel/CSV import' (bulk-import-questions). Confirm happy path for intended role; note plan gates and credit toasts. | W69: Free+ | X69: 0 / N/A
A70: FEAT-068 | B70: Gov Exam Mock Tests | C70: Collect exam papers | D70: collect-exam-papers | E70: Yes | F70: Yes | G70: Yes | H70: Yes | I70: Yes | J70: In Progress | K70: Partial | L70: Blocked | M70: Medium | N70: High | O70: GovExams | P70: Raj Balani | Q70: 4 | R70: 0.5 | S70: Brittle hosts | T70: /app/mock-test | U70: =IFERROR(Environments!$B$3&T70,T70) | V70: Open /app/mock-test. Exercise 'Collect exam papers' (collect-exam-papers). Confirm happy path for intended role; note plan gates and credit toasts. | W70: Free+ | X70: 0 / N/A | Y70: BUG-OPEN-17
A71: FEAT-069 | B71: Gov Exam Mock Tests | C71: Python scraper service | D71: External scraper | E71: N/A | F71: Partial | G71: Yes | H71: N/A | I71: N/A | J71: Not Started | K71: Partial | L71: Not Tested | M71: Medium | N71: High | O71: GovExams | P71: Raj Balani | Q71: 16 | R71: 0 | S71: Not deployed | T71: /app/mock-test | U71: =IFERROR(Environments!$B$3&T71,T71) | V71: Open /app/mock-test. Exercise 'Python scraper service' (External scraper). Confirm happy path for intended role; note plan gates and credit toasts. | W71: Free+ | X71: 0 / N/A
A72: FEAT-070 | B72: Gov Exam Mock Tests | C72: India region gate | D72: India-only UI/gate | E72: Yes | F72: Yes | G72: N/A | H72: N/A | I72: N/A | J72: Completed | K72: Partial | L72: Passed | M72: Low | N72: Low | O72: Platform | P72: Shreya Patil | Q72: 1 | R72: 0.5 | S72: Claims removed; gate disabled | T72: /app/mock-test | U72: =IFERROR(Environments!$B$3&T72,T72) | V72: Open /app/mock-test. Exercise 'India region gate' (India-only UI/gate). Confirm happy path for intended role; note plan gates and credit toasts. | W72: Free+ | X72: 0 / N/A
A73: FEAT-071 | B73: Settings | C73: Profile/audio/appearance | D73: Core settings | E73: Yes | F73: Yes | G73: Yes | H73: N/A | I73: N/A | J73: Completed | K73: Fully Implemented | L73: Passed | M73: High | N73: Low | O73: Platform | P73: Raj Balani | Q73: 2 | R73: 1.5 | T73: /app/settings | U73: =IFERROR(Environments!$B$3&T73,T73) | V73: Open /app/settings. Exercise 'Profile/audio/appearance' (Core settings). Confirm happy path for intended role; note plan gates and credit toasts. | W73: Free+ | X73: 0 / N/A
A74: FEAT-072 | B74: Settings | C74: Security MFA settings | D74: Password + TOTP | E74: Yes | F74: Yes | G74: Yes | H74: Yes | I74: N/A | J74: Completed | K74: Fully Implemented | L74: In Testing | M74: Critical | N74: High | O74: Platform | P74: Raj Balani | Q74: 2 | R74: 1 | T74: /app/settings | U74: =IFERROR(Environments!$B$3&T74,T74) | V74: Open /app/settings. Exercise 'Security MFA settings' (Password + TOTP). Confirm happy path for intended role; note plan gates and credit toasts. | W74: Free+ | X74: 0 / N/A
A75: FEAT-073 | B75: Settings | C75: Data export / delete | D75: GDPR export delete | E75: Yes | F75: Yes | G75: Yes | H75: Yes | I75: Yes | J75: Completed | K75: Fully Implemented | L75: In Testing | M75: High | N75: High | O75: Platform | P75: Shreya Patil | Q75: 3 | R75: 1.5 | T75: /app/settings | U75: =IFERROR(Environments!$B$3&T75,T75) | V75: Open /app/settings. Exercise 'Data export / delete' (GDPR export delete). Confirm happy path for intended role; note plan gates and credit toasts. | W75: Free+ | X75: 0 / N/A
A76: FEAT-074 | B76: Settings | C76: Hotkeys settings | D76: Overlay hotkeys UI | E76: Yes | F76: N/A | G76: N/A | H76: N/A | I76: N/A | J76: Completed | K76: Fully Implemented | L76: Passed | M76: Medium | N76: Low | O76: Desktop | P76: Shreya Patil | Q76: 1.5 | R76: 1 | T76: /app/settings | U76: =IFERROR(Environments!$B$3&T76,T76) | V76: Open /app/settings. Exercise 'Hotkeys settings' (Overlay hotkeys UI). Confirm happy path for intended role; note plan gates and credit toasts. | W76: Free+ | X76: 0 / N/A
A77: FEAT-075 | B77: Settings | C77: Privacy toggles | D77: Privacy prefs + analytics opt-out | E77: Yes | F77: Partial | G77: Yes | H77: N/A | I77: N/A | J77: Completed | K77: Partial | L77: Ready | M77: Medium | N77: Medium | O77: Platform | P77: Raj Balani | Q77: 1.5 | R77: 1 | S77: PostHog enforced; others honesty | T77: /app/settings/privacy | U77: =IFERROR(Environments!$B$3&T77,T77) | V77: Settings → Privacy. Save analytics off; confirm PostHog opt-out. Other toggles show honesty copy. | W77: Free+ | X77: 0 / N/A
A78: FEAT-076 | B78: Settings | C78: Notification toggles | D78: Email/push prefs | E78: Yes | F78: Partial | G78: Yes | H78: N/A | I78: N/A | J78: In Progress | K78: Partial | L78: Failed | M78: Medium | N78: Medium | O78: Platform | P78: Raj Balani | Q78: 1.5 | R78: 0.5 | S78: Saved never read | T78: /app/settings | U78: =IFERROR(Environments!$B$3&T78,T78) | V78: Open /app/settings. Exercise 'Notification toggles' (Email/push prefs). Confirm happy path for intended role; note plan gates and credit toasts. | W78: Free+ | X78: 0 / N/A
A79: FEAT-077 | B79: Settings | C79: Retention polish | D79: Data retention | E79: Yes | F79: Partial | G79: Partial | H79: N/A | I79: N/A | J79: In Progress | K79: Partial | L79: Not Tested | M79: Low | N79: Low | O79: Platform | P79: Raj Balani | Q79: 2 | R79: 0 | S79: Not enforced | T79: /app/settings | U79: =IFERROR(Environments!$B$3&T79,T79) | V79: Open /app/settings. Exercise 'Retention polish' (Data retention). Confirm happy path for intended role; note plan gates and credit toasts. | W79: Free+ | X79: 0 / N/A
A80: FEAT-078 | B80: Settings | C80: Billing settings tab | D80: Plan credits portal | E80: Yes | F80: Yes | G80: Yes | H80: Yes | I80: Yes | J80: Completed | K80: Fully Implemented | L80: Passed | M80: Critical | N80: High | O80: Billing | P80: Raj Balani | Q80: 3 | R80: 2.5 | S80: Ledger usage P2-6 | T80: /app/settings | U80: =IFERROR(Environments!$B$3&T80,T80) | V80: Open /app/settings. Exercise 'Billing settings tab' (Plan credits portal). Confirm happy path for intended role; note plan gates and credit toasts. | W80: Free+ | X80: 0 / N/A
A81: FEAT-079 | B81: Settings | C81: Integrations calendar | D81: Google connect UI | E81: Yes | F81: Yes | G81: Yes | H81: Yes | I81: Yes | J81: In Progress | K81: Partial | L81: Blocked | M81: High | N81: Medium | O81: Scheduling | P81: Raj Balani | Q81: 2 | R81: 1 | T81: /app/settings/integrations | U81: =IFERROR(Environments!$B$3&T81,T81) | V81: Open /app/settings/integrations. Exercise 'Integrations calendar' (Google connect UI). Confirm happy path for intended role; note plan gates and credit toasts. | W81: Free+ | X81: 0 / N/A
A82: FEAT-080 | B82: Admin Portal | C82: Admin users management | D82: List/filter users | E82: Yes | F82: Yes | G82: Yes | H82: Yes | I82: N/A | J82: Completed | K82: Fully Implemented | L82: Passed | M82: Critical | N82: High | O82: Admin | P82: Raj Balani | Q82: 3 | R82: 2 | T82: /app/admin | U82: =IFERROR(Environments!$B$3&T82,T82) | V82: Open /app/admin. Exercise 'Admin users management' (List/filter users). Confirm happy path for intended role; note plan gates and credit toasts. | W82: Admin | X82: 0 / N/A
A83: FEAT-081 | B83: Admin Portal | C83: Admin analytics | D83: DAU/MAU | E83: Yes | F83: Yes | G83: Yes | H83: Yes | I83: N/A | J83: Completed | K83: Fully Implemented | L83: In Testing | M83: High | N83: Medium | O83: Admin | P83: Raj Balani | Q83: 3 | R83: 1.5 | T83: /app/admin | U83: =IFERROR(Environments!$B$3&T83,T83) | V83: Open /app/admin. Exercise 'Admin analytics' (DAU/MAU). Confirm happy path for intended role; note plan gates and credit toasts. | W83: Admin | X83: 0 / N/A
A84: FEAT-082 | B84: Admin Portal | C84: Admin revenue | D84: USD/INR MRR | E84: Yes | F84: Yes | G84: Yes | H84: N/A | I84: N/A | J84: Completed | K84: Fully Implemented | L84: Passed | M84: Critical | N84: High | O84: Admin | P84: Raj Balani | Q84: 4 | R84: 3 | S84: P0-6 fixed | T84: /app/admin | U84: =IFERROR(Environments!$B$3&T84,T84) | V84: Open /app/admin. Exercise 'Admin revenue' (USD/INR MRR). Confirm happy path for intended role; note plan gates and credit toasts. | W84: Admin | X84: 0 / N/A
A85: FEAT-083 | B85: Admin Portal | C85: Admin model costs | D85: Read-only AI_CREDIT_COSTS catalog | E85: Yes | F85: Yes | G85: Yes | H85: N/A | I85: N/A | J85: Completed | K85: Fully Implemented | L85: Ready | M85: Medium | N85: Medium | O85: Admin | P85: Raj Balani | Q85: 3 | R85: 2 | S85: Fake Save removed | T85: /app/admin/model-costs | U85: =IFERROR(Environments!$B$3&T85,T85) | V85: Admin → Model costs. Confirm read-only catalog; no Save that pretends to persist. | W85: Admin | X85: 0 / N/A
A86: FEAT-084 | B86: Admin Portal | C86: Admin feature flags | D86: DB flags UI | E86: Yes | F86: Yes | G86: Yes | H86: N/A | I86: N/A | J86: Completed | K86: Fully Implemented | L86: In Testing | M86: High | N86: Medium | O86: Admin | P86: Raj Balani | Q86: 2 | R86: 1 | T86: /app/admin | U86: =IFERROR(Environments!$B$3&T86,T86) | V86: Open /app/admin. Exercise 'Admin feature flags' (DB flags UI). Confirm happy path for intended role; note plan gates and credit toasts. | W86: Admin | X86: 0 / N/A
A87: FEAT-085 | B87: Admin Portal | C87: Admin question editor | D87: CRUD + filter | E87: Yes | F87: Yes | G87: Yes | H87: N/A | I87: N/A | J87: Completed | K87: Fully Implemented | L87: Passed | M87: High | N87: Medium | O87: Admin | P87: Raj Balani | Q87: 4 | R87: 3 | S87: Filter fixed P1-5 | T87: /app/admin | U87: =IFERROR(Environments!$B$3&T87,T87) | V87: Open /app/admin. Exercise 'Admin question editor' (CRUD + filter). Confirm happy path for intended role; note plan gates and credit toasts. | W87: Admin | X87: 0 / N/A
A88: FEAT-086 | B88: Admin Portal | C88: Admin bulk upload | D88: Excel import | E88: Yes | F88: Yes | G88: Yes | H88: Yes | I88: Yes | J88: Completed | K88: Fully Implemented | L88: In Testing | M88: High | N88: Medium | O88: Admin | P88: Raj Balani | Q88: 3 | R88: 2 | T88: /app/admin | U88: =IFERROR(Environments!$B$3&T88,T88) | V88: Open /app/admin. Exercise 'Admin bulk upload' (Excel import). Confirm happy path for intended role; note plan gates and credit toasts. | W88: Admin | X88: 0 / N/A
A89: FEAT-087 | B89: Admin Portal | C89: Admin seed questions | D89: PDF AI extract | E89: Yes | F89: Yes | G89: Yes | H89: Yes | I89: Yes | J89: In Progress | K89: Partial | L89: Blocked | M89: High | N89: Medium | O89: Admin | P89: Raj Balani | Q89: 4 | R89: 1 | S89: Gap-fill stub | T89: /app/admin | U89: =IFERROR(Environments!$B$3&T89,T89) | V89: Open /app/admin. Exercise 'Admin seed questions' (PDF AI extract). Confirm happy path for intended role; note plan gates and credit toasts. | W89: Admin | X89: 0 / N/A
A90: FEAT-088 | B90: Admin Portal | C90: Admin live chat | D90: Support realtime | E90: Yes | F90: Yes | G90: Yes | H90: Yes | I90: N/A | J90: Completed | K90: Fully Implemented | L90: In Testing | M90: Medium | N90: Low | O90: Admin | P90: Raj Balani | Q90: 3 | R90: 2 | T90: /app/admin/live-chat | U90: =IFERROR(Environments!$B$3&T90,T90) | V90: Open /app/admin/live-chat. Exercise 'Admin live chat' (Support realtime). Confirm happy path for intended role; note plan gates and credit toasts. | W90: Admin | X90: 0 / N/A
A91: FEAT-089 | B91: Admin Portal | C91: Admin support page | D91: Queue + Live Chat deep link | E91: Yes | F91: Yes | G91: Yes | H91: N/A | I91: N/A | J91: Completed | K91: Fully Implemented | L91: Ready | M91: Low | N91: Low | O91: Admin | P91: Raj Balani | Q91: 1 | R91: 1 | S91: Links to /app/admin/live-chat | T91: /app/admin/support | U91: =IFERROR(Environments!$B$3&T91,T91) | V91: Admin → Support. Use Open Live Chat CTA to reply. | W91: Admin | X91: 0 / N/A
A92: FEAT-090 | B92: Admin Portal | C92: Admin audit log | D92: Read audit log | E92: Yes | F92: Yes | G92: Yes | H92: N/A | I92: N/A | J92: Completed | K92: Fully Implemented | L92: Passed | M92: Medium | N92: Low | O92: Admin | P92: Raj Balani | Q92: 1.5 | R92: 1 | T92: /app/admin | U92: =IFERROR(Environments!$B$3&T92,T92) | V92: Open /app/admin. Exercise 'Admin audit log' (Read audit log). Confirm happy path for intended role; note plan gates and credit toasts. | W92: Admin | X92: 0 / N/A
A93: FEAT-091 | B93: Admin Portal | C93: Admin QA checklist | D93: qaChecklist.json local-only | E93: Yes | F93: N/A | G93: N/A | H93: N/A | I93: N/A | J93: Completed | K93: Partial | L93: Ready | M93: Low | N93: Low | O93: Admin | P93: Shreya Patil | Q93: 2 | R93: 1 | S93: Honesty: browser localStorage only | T93: /app/admin/qa-checklist | U93: =IFERROR(Environments!$B$3&T93,T93) | V93: Admin → QA checklist. Confirm local-only banner; statuses stay in this browser. | W93: Admin | X93: 0 / N/A
A94: FEAT-092 | B94: Admin Portal | C94: Admin promo codes | D94: CRUD promos | E94: Yes | F94: Yes | G94: Yes | H94: N/A | I94: N/A | J94: Completed | K94: Fully Implemented | L94: Passed | M94: Medium | N94: Low | O94: Admin | P94: Raj Balani | Q94: 2 | R94: 1.5 | T94: /app/admin | U94: =IFERROR(Environments!$B$3&T94,T94) | V94: Open /app/admin. Exercise 'Admin promo codes' (CRUD promos). Confirm happy path for intended role; note plan gates and credit toasts. | W94: Admin | X94: 0 / N/A
A95: FEAT-093 | B95: Admin Portal | C95: Admin billing settings | D95: INR prices referral | E95: Yes | F95: Yes | G95: Yes | H95: N/A | I95: N/A | J95: Completed | K95: Fully Implemented | L95: In Testing | M95: High | N95: Medium | O95: Admin | P95: Raj Balani | Q95: 2 | R95: 1.5 | S95: auto_deduct UI removed | T95: /app/admin | U95: =IFERROR(Environments!$B$3&T95,T95) | V95: Open /app/admin. Exercise 'Admin billing settings' (INR prices referral). Confirm happy path for intended role; note plan gates and credit toasts. | W95: Admin | X95: 0 / N/A
A96: FEAT-094 | B96: Marketing Site | C96: Landing + pricing pages | D96: Marketing funnel | E96: Yes | F96: Partial | G96: Yes | H96: N/A | I96: N/A | J96: Completed | K96: Fully Implemented | L96: Passed | M96: High | N96: Low | O96: Growth | P96: Shreya Patil | Q96: 3 | R96: 2 | S96: Max $79 | T96: / | U96: =IFERROR(Environments!$B$3&T96,T96) | V96: Open /. Exercise 'Landing + pricing pages' (Marketing funnel). Confirm happy path for intended role; note plan gates and credit toasts. | W96: Guest | X96: 0 / N/A
A97: FEAT-095 | B97: Marketing Site | C97: Help/Blog CMS | D97: DB-backed content | E97: Yes | F97: Yes | G97: Yes | H97: Yes | I97: N/A | J97: Completed | K97: Fully Implemented | L97: Passed | M97: Medium | N97: Low | O97: Growth | P97: Shreya Patil | Q97: 2 | R97: 1.5 | T97: / | U97: =IFERROR(Environments!$B$3&T97,T97) | V97: Open /. Exercise 'Help/Blog CMS' (DB-backed content). Confirm happy path for intended role; note plan gates and credit toasts. | W97: Guest | X97: 0 / N/A
A98: FEAT-096 | B98: Billing & Credits | C98: Stripe checkout + webhooks | D98: Subscriptions packs | E98: Yes | F98: Yes | G98: Yes | H98: Yes | I98: Yes | J98: Completed | K98: Fully Implemented | L98: Passed | M98: Critical | N98: Critical | O98: Billing | P98: Raj Balani | Q98: 8 | R98: 6 | S98: Enterprise price IDs | T98: /app/settings/billing | U98: =IFERROR(Environments!$B$3&T98,T98) | V98: Open /app/settings/billing. Exercise 'Stripe checkout + webhooks' (Subscriptions packs). Confirm happy path for intended role; note plan gates and credit toasts. | W98: Free+ | X98: 0 / N/A
A99: FEAT-097 | B99: Billing & Credits | C99: Razorpay INR checkout | D99: One-time orders | E99: Yes | F99: Yes | G99: Yes | H99: Yes | I99: Yes | J99: In Progress | K99: Partial | L99: Failed | M99: Critical | N99: High | O99: Billing | P99: Raj Balani | Q99: 6 | R99: 4 | S99: No recurring | T99: /app/settings/billing | U99: =IFERROR(Environments!$B$3&T99,T99) | V99: Open /app/settings/billing. Exercise 'Razorpay INR checkout' (One-time orders). Confirm happy path for intended role; note plan gates and credit toasts. | W99: Free+ | X99: 0 / N/A
A100: FEAT-098 | B100: Billing & Credits | C100: Credits ledger | D100: Server-authoritative | E100: Yes | F100: Yes | G100: Yes | H100: Yes | I100: Yes | J100: Completed | K100: Fully Implemented | L100: Passed | M100: Critical | N100: Critical | O100: Billing | P100: Shreya Patil | Q100: 4 | R100: 3 | T100: /app/settings/billing | U100: =IFERROR(Environments!$B$3&T100,T100) | V100: Open /app/settings/billing. Exercise 'Credits ledger' (Server-authoritative). Confirm happy path for intended role; note plan gates and credit toasts. | W100: Free+ | X100: 0 / N/A
...

Sheet 04 Test Case Repository
A1: Test Case Repository — Clarify AI | J1: Dashboard | K1: NAV | L1: Features | M1: Bugs | N1: Launch | O1: Smoke | P1: Creds | Q1: Env | R1: Playbooks | S1: ● Cases | T1: Sign-Off
A2: Test Case ID | B2: Requirement ID | C2: Module | D2: Sub Module | E2: Feature | F2: Screen | G2: User Role | H2: Priority | I2: Severity | J2: Test Scenario | K2: Test Case | L2: Preconditions | M2: Test Steps | N2: Expected Result | O2: Actual Result | P2: Pass/Fail | Q2: Status | R2: Bug ID | S2: Tester | T2: Est Hours | U2: Actual Hours | V2: Execution Date | W2: Build Version | X2: Environment | Y2: Browser | Z2: Device | AA2: Platform | AB2: Automation | AC2: Regression | AD2: Smoke | AE2: Sanity | AF2: Sprint | AG2: Release | AH2: Remarks
A3: TC-001 | B3: REQ-AUTH-01 | C3: Auth & Onboarding | D3: Login | E3: Email login | F3: /login | G3: Free User | H3: Critical | I3: Critical | J3: Valid credentials | K3: User signs in with email/password | L3: Verified account | M3: 1. Open /login 2. Enter credentials 3. Submit | N3: Redirect to /app or onboarding | O3: Landed on dashboard | P3: Pass | Q3: Completed | S3: Raj Balani | T3: 1 | U3: 0.75 | V3: 46232 | W3: 1.0.0 | X3: Staging | Y3: Chrome | Z3: Desktop | AA3: Web | AB3: Manual | AC3: Yes | AD3: Yes | AE3: Yes | AF3: Sprint 26 | AG3: 1.0.0-beta
A4: TC-002 | B4: REQ-AUTH-02 | C4: Auth & Onboarding | D4: Login | E4: Lockout | F4: /login | G4: Free User | H4: High | I4: High | J4: Repeated failures | K4: Lockout after threshold | L4: Test account | M4: 1. Fail login repeatedly 2. Observe message | N4: Temporary lockout shown | P4: Not Run | Q4: Ready | S4: Raj Balani | T4: 1.5 | U4: 0 | W4: 1.0.0 | X4: Staging | Y4: Chrome | Z4: Desktop | AA4: Web | AB4: Manual | AC4: Yes | AD4: No | AE4: Yes | AF4: Sprint 26 | AG4: 1.0.0-beta
A5: TC-003 | B5: REQ-LIVE-01 | C5: Live Practice Coach | D5: STT | E5: Deepgram stream | F5: /app/live | G5: Pro User | H5: Critical | I5: Critical | J5: Mic open | K5: Near-real-time transcript | L5: Pro + mic permission | M5: 1. Start live 2. Speak 3. Observe transcript | N5: Segments appear under 2s | O5: OK | P5: Pass | Q5: Completed | S5: Shreya Patil | T5: 2 | U5: 1.5 | V5: 46232 | W5: 1.0.0 | X5: Staging | Y5: Electron | Z5: Laptop | AA5: Windows | AB5: Manual | AC5: Yes | AD5: Yes | AE5: No | AF5: Sprint 26 | AG5: 1.0.0-beta
A6: TC-004 | B6: REQ-LIVE-02 | C6: Live Practice Coach | D6: Overlay | E6: Pro gate | F6: /app/live/overlay | G6: Free User | H6: Critical | I6: High | J6: Free overlay blocked | K6: Server rejects overlay capture | L6: Free account | M6: 1. Attempt overlay capture 2. Check response | N6: 403 / upgrade required | O6: 403 returned | P6: Pass | Q6: Completed | R6: BUG-001 | S6: Shreya Patil | T6: 1.5 | U6: 1.25 | V6: 46232 | W6: 1.0.0 | X6: Staging | Y6: Electron | Z6: Desktop | AA6: Windows | AB6: Candidate | AC6: Yes | AD6: Yes | AE6: No | AF6: Sprint 26 | AG6: 1.0.0-beta | AH6: Retest after P0-3
A7: TC-005 | B7: REQ-BILL-01 | C7: Billing & Credits | D7: Checkout | E7: Max Stripe price | F7: /pricing | G7: Free User | H7: Critical | I7: Critical | J7: Upgrade Max | K7: Enterprise price id used | L7: Stripe test keys | M7: 1. Select Max 2. Checkout 3. Inspect price | N7: Non-empty enterprise price | O7: OK | P7: Pass | Q7: Completed | S7: Raj Balani | T7: 2 | U7: 1.5 | V7: 46232 | W7: 1.0.0 | X7: Staging | Y7: Chrome | Z7: Desktop | AA7: Web | AB7: Manual | AC7: Yes | AD7: Yes | AE7: Yes | AF7: Sprint 26 | AG7: 1.0.0-beta | AH7: P0-1
A8: TC-006 | B8: REQ-BILL-02 | C8: Billing & Credits | D8: Webhook | E8: payment_failed | F8: stripe-webhook | G8: Pro User | H8: Critical | I8: Critical | J8: Failed invoice | K8: Wallet not wiped | L8: credits=500 | M8: 1. Simulate invoice.payment_failed 2. Read credits | N8: Credits remain 500 | O8: Unchanged | P8: Pass | Q8: Completed | S8: Raj Balani | T8: 1.5 | U8: 1 | V8: 46232 | W8: 1.0.0 | X8: CI | Y8: N/A | Z8: Desktop | AA8: Web | AB8: Automated | AC8: Yes | AD8: Yes | AE8: No | AF8: Sprint 26 | AG8: 1.0.0-beta | AH8: P0-2
A9: TC-007 | B9: REQ-DOC-01 | C9: Documents & Resumes | D9: Parse | E9: Free onboarding parse | F9: /onboarding | G9: Free User | H9: High | I9: Medium | J9: First parse free | K9: No deduct on first onboarding parse | L9: onboarding_completed=false | M9: 1. Upload resume 2. Check ledger | N9: Free path / no deduct | P9: Not Run | Q9: Ready | S9: Shreya Patil | T9: 1.5 | U9: 0 | W9: 1.0.0 | X9: Staging | Y9: Chrome | Z9: Desktop | AA9: Web | AB9: Manual | AC9: Yes | AD9: No | AE9: Yes | AF9: Sprint 26 | AG9: 1.0.0-beta
A10: TC-008 | B10: REQ-GOV-01 | C10: Gov Exam Mock Tests | D10: Submit | E10: Atomic submit | F10: /app/mock-test/session/:id | G10: Free User | H10: Critical | I10: High | J10: Submit answers | K10: Score persisted once | L10: Active test | M10: 1. Answer 2. Submit 3. Open results | N10: Score + breakdown | O10: OK | P10: Pass | Q10: Completed | S10: Raj Balani | T10: 2 | U10: 1.75 | V10: 46232 | W10: 1.0.0 | X10: Staging | Y10: Chrome | Z10: Android Phone | AA10: Android | AB10: Manual | AC10: Yes | AD10: Yes | AE10: Yes | AF10: Sprint 26 | AG10: 1.0.0-beta
A11: TC-009 | B11: REQ-ADM-01 | C11: Admin Portal | D11: Revenue | E11: USD vs INR | F11: /app/admin/revenue | G11: Admin | H11: Critical | I11: High | J11: Admin revenue view | K11: Currencies separate | L11: Admin + sample data | M11: 1. Open Revenue 2. Compare hand calc | N11: USD MRR + INR separate | O11: OK | P11: Pass | Q11: Completed | S11: Raj Balani | T11: 2.5 | U11: 2 | V11: 46232 | W11: 1.0.0 | X11: Staging | Y11: Chrome | Z11: Desktop | AA11: Web | AB11: Manual | AC11: Yes | AD11: No | AE11: No | AF11: Sprint 26 | AG11: 1.0.0-beta | AH11: P0-6
A12: TC-010 | B12: REQ-APP-01 | C12: Dashboard | D12: Routing | E12: In-app 404 | F12: /app/does-not-exist | G12: Pro User | H12: Medium | I12: Low | J12: Unknown route | K12: NotFound in AppShell | L12: Authenticated | M12: 1. Navigate unknown /app path | N12: In-app NotFound | O12: OK | P12: Pass | Q12: Completed | S12: Shreya Patil | T12: 0.5 | U12: 0.25 | V12: 46232 | W12: 1.0.0 | X12: Staging | Y12: Chrome | Z12: Desktop | AA12: Web | AB12: Manual | AC12: Yes | AD12: Yes | AE12: Yes | AF12: Sprint 26 | AG12: 1.0.0-beta | AH12: P1-4
A13: TC-011 | B13: REQ-LIVE-03 | C13: Live Practice Coach | D13: Credits | E13: Hint deduct | F13: /app/live | G13: Pro User | H13: High | I13: High | J13: Insufficient credits | K13: 402 when wallet low | L13: credits below cost | M13: 1. Drain credits 2. Request hint | N13: 402 + message | O13: In progress | P13: In Progress | Q13: In Progress | S13: Shreya Patil | T13: 1.5 | U13: 0.5 | V13: 46232 | W13: 1.0.0 | X13: Staging | Y13: Chrome | Z13: Desktop | AA13: Web | AB13: Candidate | AC13: Yes | AD13: No | AE13: No | AF13: Sprint 26 | AG13: 1.0.0-beta
A14: TC-012 | B14: REQ-SEC-01 | C14: Security & Platform | D14: Authz | E14: Non-admin admin route | F14: /app/admin | G14: Free User | H14: Critical | I14: Critical | J14: Unauthorized admin | K14: Redirect / deny | L14: Non-admin user | M14: 1. Open /app/admin | N14: Denied | O14: Denied | P14: Pass | Q14: Completed | S14: Raj Balani | T14: 1 | U14: 0.75 | V14: 46232 | W14: 1.0.0 | X14: Staging | Y14: Chrome | Z14: Desktop | AA14: Web | AB14: Manual | AC14: Yes | AD14: Yes | AE14: Yes | AF14: Sprint 26 | AG14: 1.0.0-beta
A15: TOTAL | T15: =SUM(T3:T14) | U15: =SUM(U3:U14)

Sheet 05 E2E User Flows
A1: End-to-End User Flows — golden paths | J1: Dashboard | K1: NAV | L1: Features | M1: Bugs | N1: Launch | O1: Smoke | P1: Creds | Q1: Env | R1: Playbooks | S1: Cases | T1: Sign-Off
A2: Flow ID | B2: Flow Name | C2: Portal | D2: Start Page | E2: End Page | F2: Steps | G2: Expected Outcome | H2: Actual Outcome | I2: Pass | J2: Risk | K2: Dependencies | L2: QA Owner | M2: Est Hours | N2: Actual Hours | O2: Comments
A3: E2E-01 | B3: Signup to Onboarding to Dashboard | C3: Auth Portal | D3: /signup | E3: /app/dashboard | F3: 1. Sign up 2. Verify email 3. Complete 5 steps 4. Land dashboard | G3: Profile + onboarding_completed + starter credits | H3: OK on Staging | I3: Pass | J3: High | K3: Auth, Email | L3: Raj Balani | M3: 3 | N3: 2.5
A4: E2E-02 | B4: Free to Pro Stripe checkout | C4: Candidate App | D4: /pricing | E4: /app/settings/billing | F4: 1. Choose Pro 2. Stripe Checkout 3. Webhook 4. Open Billing | G4: plan=pro, credits granted, ledger entry | I4: Not Run | J4: Critical | K4: Stripe test keys | L4: Raj Balani | M4: 4 | N4: 0 | O4: Money path
A5: E2E-03 | B5: Live coach rehearsal | C5: Candidate App | D5: /app/live | E5: /app/sessions/:id | F5: 1. Start 2. Audio 3. Generate answer 4. End 5. Debrief | G5: Session + transcript + debrief | H5: OK | I5: Pass | J5: Critical | K5: Deepgram, Gemini, Credits | L5: Shreya Patil | M5: 5 | N5: 4
A6: E2E-04 | B6: Gov exam create to results | C6: Candidate App | D6: /app/mock-test | E6: /app/mock-test/results/:id | F6: 1. Select exam 2. create-test 3. Answer 4. submit 5. Results | G6: Atomic score, no double submit | H6: OK | I6: Pass | J6: High | K6: Question bank | L6: Raj Balani | M6: 3.5 | N6: 3 | O6: Thin content
A7: E2E-05 | B7: Admin seed to candidate test | C7: Admin Portal | D7: /app/admin/seed-questions | E7: /app/mock-test | F7: 1. Import questions 2. Candidate creates test | G7: Imported questions available | H7: Blocked | I7: Blocked | J7: High | K7: Admin, Gemini PDF | L7: Raj Balani | M7: 4 | N7: 1
A8: E2E-06 | B8: Electron overlay boot | C8: Electron Overlay | D8: Clarify AI.exe | E8: Overlay window | F8: 1. Launch 2. Auth if needed 3. Overlay topmost 4. Hotkey | G8: Overlay-only shell | I8: Not Run | J8: Critical | K8: Code signing deferred | L8: Shreya Patil | M8: 3 | N8: 0 | O8: Unsigned beta OK
A9: TOTAL | M9: =SUM(M3:M8) | N9: =SUM(N3:N8)

Sheet 06 Bug Tracker
A1: Bug Tracker — audit defect register + open issues (58 bugs) | J1: Dashboard | K1: NAV | L1: Features | M1: ● Bugs | N1: Launch | O1: Smoke | P1: Creds | Q1: Env | R1: Playbooks | S1: Cases | T1: Sign-Off
A2: Bug ID | B2: Title | C2: Description | D2: Module | E2: Feature | F2: Environment | G2: Browser | H2: Device | I2: OS | J2: Severity | K2: Priority | L2: Status | M2: Assigned To | N2: Reported By | O2: Found Date | P2: Fixed Date | Q2: Retest Date | R2: Build | S2: Sprint | T2: Root Cause | U2: Resolution | V2: Screenshot Link | W2: Video Link | X2: Comments
A3: BUG-P0-01 | B3: Max/enterprise Stripe price IDs missing | C3: PLANS.enterprise lacked stripePriceIdMonthly/Yearly so Max checkout failed | D3: Billing & Credits | E3: Stripe checkout + webhooks | F3: Staging | G3: Chrome | H3: Desktop | I3: Windows | J3: Critical | K3: Critical | L3: Closed | M3: Billing | N3: Raj Balani | O3: 46212 | P3: 46230 | Q3: 46231 | R3: 1.0.0 | S3: Sprint 26 | T3: Config/Env | U3: Wired ENV.STRIPE_PRICE_ENTERPRISE_* | X3: P0-1 FIXED in hardening
A4: BUG-P0-02 | B4: invoice.payment_failed wiped credits to 50 | C4: Absolute credits overwrite destroyed purchased packs | D4: Billing & Credits | E4: Stripe checkout + webhooks | F4: Staging | G4: N/A | H4: Desktop | I4: Windows | J4: Critical | K4: Critical | L4: Closed | M4: Billing | N4: Shreya Patil | O4: 46212 | P4: 46230 | Q4: 46231 | R4: 1.0.0 | S4: Sprint 26 | T4: Logic Bug | U4: Stop writing credits on payment_failed | X4: P0-2 FIXED
A5: BUG-P0-03 | B5: Server plan gating was a no-op | C5: starter rank 0 = free; requirePlan starter never blocked | D5: Billing & Credits | E5: Plan gating enforcement | F5: Staging | G5: Chrome | H5: Desktop | I5: Windows | J5: Critical | K5: Critical | L5: Closed | M5: Billing | N5: Shreya Patil | O5: 46212 | P5: 46230 | Q5: 46231 | R5: 1.0.0 | S5: Sprint 26 | T5: Logic Bug | U5: Remap starter→pro; rebuild CAPABILITY_MIN_RANK | X5: P0-3 FIXED
A6: BUG-P0-04 | B6: AI parse endpoints free forever | C6: parse-resume/gap-analysis/parse-document never deducted | D6: Documents & Resumes | E6: Resume upload + AI parse | F6: Staging | G6: Chrome | H6: Desktop | I6: Windows | J6: Critical | K6: Critical | L6: Closed | M6: Docs | N6: Shreya Patil | O6: 46212 | P6: 46230 | Q6: 46231 | R6: 1.0.0 | S6: Sprint 26 | T6: Logic Bug | U6: deductCreditsAtomic + free first onboarding | X6: P0-4 FIXED
A7: BUG-P0-05 | B7: .env.production committed + release-new unignored | C7: Secrets/artifacts exposure risk | D7: Security & Platform | E7: CI validate-env | F7: Production | G7: N/A | H7: Desktop | I7: Windows | J7: Critical | K7: Critical | L7: Closed | M7: Platform | N7: Shreya Patil | O7: 46212 | P7: 46230 | R7: 1.0.0 | S7: Sprint 26 | T7: Config/Env | U7: git rm --cached; gitignore; example file | X7: Rotate anon key still OPS
A8: BUG-P0-06 | B8: Admin revenue treated credits as money | C8: monthlyRevenueByPlan summed credit_transactions | D8: Admin Portal | E8: Admin revenue | F8: Staging | G8: Chrome | H8: Desktop | I8: Windows | J8: Critical | K8: Critical | L8: Closed | M8: Admin | N8: Raj Balani | O8: 46212 | P8: 46230 | Q8: 46231 | R8: 1.0.0 | S8: Sprint 26 | T8: Logic Bug | U8: Subscriptions x prices + INR separate | X8: P0-6 FIXED
A9: BUG-P1-01 | B9: Interview dates Invalid Date | C9: UI read scheduled_at; store has next_round.scheduled_at | D9: Interviews & Calendar | E9: Manual interview CRUD | F9: Staging | G9: Chrome | H9: Desktop | I9: Windows | J9: High | K9: High | L9: Closed | M9: Scheduling | N9: Raj Balani | O9: 46217 | P9: 46230 | Q9: 46231 | R9: 1.0.0 | S9: Sprint 26 | T9: Logic Bug | U9: roundHelpers next_round | X9: P1-1 FIXED
A10: BUG-P1-02 | B10: Profile streak always 0 | C10: Read streak_current; column is streak_days | D10: Notifications & Profile | E10: Profile page display | F10: Staging | G10: Chrome | H10: Desktop | I10: Windows | J10: High | K10: High | L10: Closed | M10: Growth | N10: Raj Balani | O10: 46217 | P10: 46230 | Q10: 46231 | R10: 1.0.0 | S10: Sprint 26 | T10: Logic Bug | U10: Use streak_days | X10: P1-2 FIXED
A11: BUG-P1-03 | B11: Profile badge count wrong | C11: Read profile.badges; badges in user_badges | D11: Notifications & Profile | E11: Gamification XP/streak | F11: Staging | G11: Chrome | H11: Desktop | I11: Windows | J11: High | K11: Medium | L11: Closed | M11: Growth | N11: Raj Balani | O11: 46217 | P11: 46230 | Q11: 46231 | R11: 1.0.0 | S11: Sprint 26 | T11: Logic Bug | U11: unlockedBadges from user_badges | X11: P1-3 FIXED
A12: BUG-P1-04 | B12: Blank page on unknown /app route | C12: No splat NotFound under AppShell | D12: Dashboard | E12: In-app 404 NotFound | F12: Staging | G12: Chrome | H12: Desktop | I12: Windows | J12: Medium | K12: High | L12: Closed | M12: Product | N12: Raj Balani | O12: 46217 | P12: 46230 | Q12: 46231 | R12: 1.0.0 | S12: Sprint 26 | T12: Logic Bug | U12: path * → NotFound | X12: P1-4 FIXED
A13: BUG-P1-05 | B13: Admin exam filter returns nothing | C13: JEE_MAIN vs JEE Main mismatch | D13: Admin Portal | E13: Admin question editor | F13: Staging | G13: Chrome | H13: Desktop | I13: Windows | J13: High | K13: High | L13: Closed | M13: Admin | N13: Raj Balani | O13: 46217 | P13: 46230 | Q13: 46231 | R13: 1.0.0 | S13: Sprint 26 | T13: Logic Bug | U13: Display string map | X13: P1-5 FIXED
A14: BUG-P1-06 | B14: Hotkey Ctrl+Shift+C collision | C14: MockSession vs overlay capture | D14: Mock Interview | E14: Mock interview session | F14: Electron Dev | G14: Electron | H14: Laptop | I14: Windows | J14: High | K14: High | L14: Closed | M14: Desktop | N14: Shreya Patil | O14: 46217 | P14: 46230 | Q14: 46231 | R14: 1.0.0 | S14: Sprint 26 | T14: Logic Bug | U14: Removed local MockSession binding | X14: P1-6 FIXED
A15: BUG-P1-07 | B15: Unscored dimensions show as 0 | C15: Null rendered as confident zero | D15: Sessions & Debriefs | E15: Session detail scores | F15: Staging | G15: Chrome | H15: Desktop | I15: Windows | J15: Medium | K15: Medium | L15: Closed | M15: Sessions | N15: Shreya Patil | O15: 46217 | P15: 46230 | Q15: 46231 | R15: 1.0.0 | S15: Sprint 26 | T15: UI Regression | U15: Not scored label | X15: P1-7 FIXED
A16: BUG-P1-08 | B16: CI validate-env fails | C16: VITE_APP_ENV=test + ci-placeholder rejected | D16: Security & Platform | E16: CI validate-env | F16: CI | G16: N/A | H16: Desktop | I16: Linux | J16: High | K16: High | L16: Closed | M16: Platform | N16: Shreya Patil | O16: 46217 | P16: 46230 | R16: 1.0.0 | S16: Sprint 26 | T16: Config/Env | U16: development + allowlist placeholders | X16: P1-8 FIXED
A17: BUG-P1-09 | B17: Overlay min size forced 800x600 | C17: Clamped above design 360x320 | D17: Electron Desktop Overlay | E17: Window min size clamp | F17: Electron Dev | G17: Electron | H17: Desktop | I17: Windows | J17: Medium | K17: Medium | L17: Closed | M17: Desktop | N17: Shreya Patil | O17: 46217 | P17: 46230 | Q17: 46231 | R17: 1.0.0 | S17: Sprint 26 | T17: Logic Bug | U17: Min 360x320 | X17: P1-9 FIXED
A18: BUG-P1-10 | B18: Electron release glob mismatch | C18: Uploads release/*.exe builds in release-new | D18: Electron Desktop Overlay | E18: Auto-update | F18: CI | G18: N/A | H18: Desktop | I18: Windows | J18: Medium | K18: High | L18: Closed | M18: Desktop | N18: Shreya Patil | O18: 46217 | P18: 46230 | R18: 1.0.0 | S18: Sprint 26 | T18: Config/Env | U18: directories.output=release; gitignore release-new | X18: P1-10
A19: BUG-P2-01 | B19: Warm-up copy said 2 ran 10 | C19: Copy vs WARMUP_MAX mismatch | D19: Mock Interview | E19: Mock warm-up | F19: Staging | G19: Chrome | H19: Desktop | I19: Windows | J19: Low | K19: Medium | L19: Closed | M19: Live Coach | N19: Shreya Patil | O19: 46220 | P19: 46230 | Q19: 46231 | R19: 1.0.0 | S19: Sprint 26 | T19: UI Regression | U19: Copy reads WARMUP_MAX | X19: P2-1 FIXED
A20: BUG-P2-02 | B20: MockTestHub total questions wrong | C20: Counted user uploads as bank size | D20: Gov Exam Mock Tests | E20: Question bank content | F20: Staging | G20: Chrome | H20: Desktop | I20: Windows | J20: Medium | K20: Medium | L20: Closed | M20: GovExams | N20: Raj Balani | O20: 46220 | P20: 46230 | R20: 1.0.0 | S20: Sprint 26 | T20: Logic Bug | U20: Label My uploads | X20: P2-2 FIXED
A21: BUG-P2-03 | B21: Predicted percentile misleading | C21: Formula not cohort rank | D21: Gov Exam Mock Tests | E21: Mock test engine | F21: Staging | G21: Chrome | H21: Desktop | I21: Windows | J21: Medium | K21: Medium | L21: Closed | M21: GovExams | N21: Raj Balani | O21: 46220 | P21: 46230 | R21: 1.0.0 | S21: Sprint 26 | T21: Design Gap | U21: Relabeled estimated band | X21: P2-3 FIXED
A22: BUG-P2-04 | B22: Pricing showed Max as Custom | C22: Should show $79 | D22: Marketing Site | E22: Landing + pricing pages | F22: Staging | G22: Chrome | H22: Desktop | I22: Windows | J22: High | K22: High | L22: Closed | M22: Growth | N22: Shreya Patil | O22: 46220 | P22: 46230 | Q22: 46231 | R22: 1.0.0 | S22: Sprint 26 | T22: UI Regression | U22: Show $79 | X22: P2-4 FIXED
A23: BUG-P2-05 | B23: StarBuilder polish cost wrong | C23: Hardcoded cost vs economics | D23: Prep Lab | E23: STAR Builder | F23: Staging | G23: Chrome | H23: Desktop | I23: Windows | J23: Medium | K23: Medium | L23: Closed | M23: Prep | N23: Raj Balani | O23: 46220 | P23: 46230 | R23: 1.0.0 | S23: Sprint 26 | T23: Logic Bug | U23: Use creditEconomics | X23: P2-5 FIXED
A24: BUG-P2-06 | B24: SettingsBilling creditsUsed negative | C24: allowance - remaining after packs | D24: Settings | E24: Billing settings tab | F24: Staging | G24: Chrome | H24: Desktop | I24: Windows | J24: Medium | K24: High | L24: Closed | M24: Billing | N24: Raj Balani | O24: 46220 | P24: 46230 | R24: 1.0.0 | S24: Sprint 26 | T24: Logic Bug | U24: Usage from ledger | X24: P2-6 FIXED
A25: BUG-P2-07 | B25: India-only advertised but disabled | C25: UI claims vs indiaRegion always true | D25: Gov Exam Mock Tests | E25: India region gate | F25: Staging | G25: Chrome | H25: Desktop | I25: Windows | J25: Medium | K25: Medium | L25: Closed | M25: Platform | N25: Shreya Patil | O25: 46220 | P25: 46230 | R25: 1.0.0 | S25: Sprint 26 | T25: Design Gap | U25: Strip India-only claims | X25: P2-7 FIXED
A26: BUG-P2-08 | B26: Analytics overwrote total_sessions | C26: Client page length overwrite | D26: Analytics & Usage | E26: Analytics dashboard | F26: Staging | G26: Chrome | H26: Desktop | I26: Windows | J26: Medium | K26: Medium | L26: Closed | M26: Analytics | N26: Raj Balani | O26: 46220 | P26: 46230 | R26: 1.0.0 | S26: Sprint 26 | T26: Logic Bug | U26: Keep server total_sessions | X26: P2-8 FIXED
A27: BUG-P2-09 | B27: Onboarding always saved default mic | C27: audio_input_device hardcoded | D27: Auth & Onboarding | E27: Onboarding wizard 5 steps | F27: Staging | G27: Chrome | H27: Desktop | I27: Windows | J27: Medium | K27: Medium | L27: Closed | M27: Auth Lead | N27: Shreya Patil | O27: 46220 | P27: 46230 | R27: 1.0.0 | S27: Sprint 26 | T27: Logic Bug | U27: Persist selected device | X27: P2-9 FIXED
A28: BUG-P2-10 | B28: Onboarding anxiety never saved | C28: Collected then discarded | D28: Auth & Onboarding | E28: Onboarding wizard 5 steps | F28: Staging | G28: Chrome | H28: Desktop | I28: Windows | J28: Low | K28: Medium | L28: Closed | M28: Auth Lead | N28: Shreya Patil | O28: 46220 | P28: 46230 | R28: 1.0.0 | S28: Sprint 26 | T28: Logic Bug | U28: Persist in JSON prefs | X28: P2-10 FIXED
A29: BUG-P2-11 | B29: Sidebar collapse overwritten on resize | C29: Breakpoint overwrote preference | D29: Dashboard | E29: Home dashboard KPIs | F29: Staging | G29: Chrome | H29: Desktop | I29: Windows | J29: Low | K29: Low | L29: Closed | M29: Product | N29: Raj Balani | O29: 46220 | P29: 46230 | R29: 1.0.0 | S29: Sprint 26 | T29: Logic Bug | U29: Local transient collapse | X29: P2-11 FIXED
A30: BUG-P2-12 | B30: Help still describes Group Practice | C30: Rooms redirect away | D30: Referrals & Guide | E30: In-app Guide/Help | F30: Staging | G30: Chrome | H30: Desktop | I30: Windows | J30: Low | K30: Low | L30: Closed | M30: Growth | N30: Shreya Patil | O30: 46220 | P30: 46230 | R30: 1.0.0 | S30: Sprint 26 | T30: Design Gap | U30: Coming soon copy | X30: P2-12 FIXED
A31: BUG-OPEN-01 | B31: Razorpay plans do not auto-renew | C31: One-time Order only; UI now discloses one-time (Subscriptions API still missing) | D31: Billing & Credits | E31: Razorpay INR checkout | F31: Production | G31: Chrome | H31: Desktop | I31: Windows | J31: High | K31: Critical | L31: Open | M31: Billing | N31: Raj Balani | O31: 46207 | R31: 1.0.0 | S31: Sprint 25 | T31: Design Gap | U31: UI honesty shipped; recurring INR still roadmap | X31: Roadmap — recurring INR
A32: BUG-OPEN-02 | B32: Gov exam bank was thin (~26 MCQs) | C32: Expanded via migration 20260729120000 (~80+ new MCQs) | D32: Gov Exam Mock Tests | E32: Question bank content | F32: Staging | G32: Chrome | H32: Desktop | I32: Windows | J32: High | K32: Critical | L32: Closed | M32: GovExams | N32: Raj Balani | O32: 46202 | P32: 46231 | R32: 1.0.0 | S32: Sprint 27 | T32: Design Gap | U32: Apply expand_gov_exam_mcq_seeds migration | X32: FIXED launch pass — retest bank size
A33: BUG-OPEN-03 | B33: Google Calendar sync returns 501 | C33: Missing OAuth secrets in staging/prod | D33: Interviews & Calendar | E33: Google Calendar sync | F33: Staging | G33: Chrome | H33: Laptop | I33: macOS | J33: High | K33: High | L33: Blocked | M33: Scheduling | N33: Shreya Patil | O33: 46222 | R33: 1.0.0 | S33: Sprint 26 | T33: Config/Env | U33: Needs GOOGLE_CLIENT_ID/SECRET (+ refresh tokens) in Edge secrets | X33: Ops blocker — no fake fix
A34: BUG-OPEN-04 | B34: Mock interview has no TTS | C34: Questions not spoken aloud | D34: Mock Interview | E34: Mock TTS playback | F34: Staging | G34: Chrome | H34: Desktop | I34: Windows | J34: High | K34: High | L34: Open | M34: Live Coach | N34: Shreya Patil | O34: 46204 | R34: 1.0.0 | S34: Sprint 24 | T34: Design Gap | X34: Roadmap / descope
A35: BUG-OPEN-05 | B35: Gap analysis UI not fully wired | C35: JDDetail now runs gap-analysis + shows results/402 | D35: Documents & Resumes | E35: Resume vs JD gap analysis | F35: Staging | G35: Chrome | H35: Desktop | I35: Windows | J35: Medium | K35: High | L35: Closed | M35: Docs | N35: Shreya Patil | O35: 46214 | P35: 46231 | R35: 1.0.0 | S35: Sprint 27 | T35: Design Gap | U35: Retest JD gap panel with primary resume | X35: FIXED launch pass
A36: BUG-OPEN-06 | B36: Resume version history UI missing | C36: Read-only version list on ResumeDetail | D36: Documents & Resumes | E36: Resume version history UI | F36: Staging | G36: Chrome | H36: Desktop | I36: Windows | J36: Medium | K36: Medium | L36: Closed | M36: Docs | N36: Shreya Patil | O36: 46210 | P36: 46231 | R36: 1.0.0 | S36: Sprint 27 | T36: Design Gap | U36: Confirm versions appear after re-parse | X36: FIXED launch pass
A37: BUG-OPEN-07 | B37: Outlook Calendar not built | C37: Type only | D37: Interviews & Calendar | E37: Outlook Calendar | F37: N/A | G37: N/A | H37: Desktop | I37: Windows | J37: Medium | K37: Medium | L37: Won't Fix | M37: Scheduling | N37: Raj Balani | O37: 46192 | R37: 1.0.0 | S37: Sprint 22 | T37: Design Gap | U37: Descope until scheduled
A38: BUG-OPEN-08 | B38: Email/push prefs never consumed | C38: send-email gates on prefs; UI honesty for push/digest | D38: Notifications & Profile | E38: Email notification prefs | F38: Staging | G38: Chrome | H38: Desktop | I38: Windows | J38: Medium | K38: Medium | L38: Closed | M38: Growth | N38: Raj Balani | O38: 46212 | P38: 46231 | R38: 1.0.0 | S38: Sprint 27 | T38: Logic Bug | U38: Toggle off debrief_ready and confirm skip | X38: FIXED launch pass
A39: BUG-OPEN-09 | B39: Push notifications not implemented | C39: Permission prompt only | D39: Notifications & Profile | E39: Push notifications | F39: Staging | G39: Chrome | H39: Desktop | I39: Windows | J39: Low | K39: Low | L39: Open | M39: Growth | N39: Raj Balani | O39: 46197 | R39: 1.0.0 | S39: Sprint 22 | T39: Design Gap | X39: Missing / descope
A40: BUG-OPEN-10 | B40: Mobile nav missing destinations | C40: Notifications, Guide, Profile, Admin (+ Usage/Interview Day) in More | D40: Dashboard | E40: Mobile navigation | F40: Staging | G40: Chrome | H40: Android Phone | I40: Android | J40: Medium | K40: Medium | L40: Closed | M40: Product | N40: Raj Balani | O40: 46218 | P40: 46231 | R40: 1.0.0 | S40: Sprint 28 | T40: UI Regression | U40: Parity with sidebar footer destinations | X40: FIXED QA sync pass
A41: BUG-OPEN-11 | B41: Stealth mode is cosmetic only | C41: No capture evasion | D41: Live Practice Coach | E41: Stealth mode | F41: Electron Dev | G41: Electron | H41: Desktop | I41: Windows | J41: Medium | K41: Medium | L41: Open | M41: Desktop | N41: Shreya Patil | O41: 46216 | R41: 1.0.0 | S41: Sprint 25 | T41: Design Gap | X41: Roadmap / descope
A42: BUG-OPEN-12 | B42: Admin model costs save is stub | C42: Read-only AI_CREDIT_COSTS catalog; fake Save removed | D42: Admin Portal | E42: Admin model costs | F42: Staging | G42: Chrome | H42: Desktop | I42: Windows | J42: Medium | K42: Medium | L42: Closed | M42: Admin | N42: Raj Balani | O42: 46214 | P42: 46231 | R42: 1.0.0 | S42: Sprint 27 | T42: Logic Bug | U42: Confirm no Save; values match creditEconomics | X42: FIXED launch pass
A43: BUG-OPEN-13 | B43: Admin support page read-only | C43: Deep-linked to Live Chat for replies | D43: Admin Portal | E43: Admin support page | F43: Staging | G43: Chrome | H43: Desktop | I43: Windows | J43: Low | K43: Low | L43: Closed | M43: Admin | N43: Raj Balani | O43: 46220 | P43: 46231 | R43: 1.0.0 | S43: Sprint 27 | T43: Design Gap | U43: Open Support → Live Chat CTA | X43: FIXED launch pass
A44: BUG-OPEN-14 | B44: Admin QA checklist local only | C44: Honesty banner: localStorage this browser only | D44: Admin Portal | E44: Admin QA checklist | F44: Staging | G44: Chrome | H44: Desktop | I44: Windows | J44: Low | K44: Low | L44: Closed | M44: Admin | N44: Shreya Patil | O44: 46220 | P44: 46231 | R44: 1.0.0 | S44: Sprint 27 | T44: Design Gap | U44: Confirm banner; no multi-user pretend | X44: FIXED launch pass (documented)
A45: BUG-OPEN-15 | B45: Exam papers browser mostly empty | C45: Many paper entries empty | D45: Gov Exam Mock Tests | E45: Exam papers browser | F45: Staging | G45: Chrome | H45: Desktop | I45: Windows | J45: Medium | K45: Medium | L45: Open | M45: GovExams | N45: Raj Balani | O45: 46212 | R45: 1.0.0 | S45: Sprint 25 | T45: Design Gap
A46: BUG-OPEN-16 | B46: Question scraper not deployed | C46: Code complete; no deploy | D46: Gov Exam Mock Tests | E46: Python scraper service | F46: N/A | G46: N/A | H46: Desktop | I46: Linux | J46: High | K46: High | L46: Open | M46: GovExams | N46: Raj Balani | O46: 46197 | R46: 1.0.0 | S46: Sprint 22 | T46: Config/Env | X46: defer-with-roadmap
A47: BUG-OPEN-17 | B47: collect-exam-papers brittle | C47: Allowlist hosts / Gemini failures | D47: Gov Exam Mock Tests | E47: Collect exam papers | F47: Staging | G47: Chrome | H47: Desktop | I47: Windows | J47: Medium | K47: High | L47: Blocked | M47: GovExams | N47: Raj Balani | O47: 46224 | R47: 1.0.0 | S47: Sprint 26 | T47: Third-party | U47: Needs GEMINI_API_KEY + allowlisted hosts | X47: Ops/provider blocker
A48: BUG-OPEN-18 | B48: Windows binaries unsigned | C48: SmartScreen; signAndEditExecutable false | D48: Electron Desktop Overlay | E48: Code signing Windows | F48: Production | G48: N/A | H48: Desktop | I48: Windows | J48: High | K48: High | L48: Blocked | M48: Desktop | N48: Shreya Patil | O48: 46192 | R48: 1.0.0 | S48: Sprint 22 | T48: Config/Env | U48: Needs EV/OV code-signing certificate | X48: Ops blocker — no fake fix
A49: BUG-OPEN-19 | B49: Electron auto-update trust weak | C49: Unsigned update chain | D49: Electron Desktop Overlay | E49: Auto-update | F49: Production | G49: N/A | H49: Desktop | I49: Windows | J49: High | K49: High | L49: Blocked | M49: Desktop | N49: Shreya Patil | O49: 46202 | R49: 1.0.0 | S49: Sprint 23 | T49: Config/Env | U49: Depends on EV/OV signing cert | X49: Ops blocker
A50: BUG-OPEN-20 | B50: Low automated test coverage | C50: ~5% real coverage; 794 it.todo placeholders | D50: Security & Platform | E50: Unit/E2E coverage | F50: CI | G50: N/A | H50: Desktop | I50: Windows | J50: High | K50: High | L50: Open | M50: Platform | N50: Shreya Patil | O50: 46187 | R50: 1.0.0 | S50: Sprint 20 | T50: Design Gap | X50: P4-4 ongoing
A51: BUG-OPEN-21 | B51: No Playwright run evidence | C51: 10 specs; no report artifacts | D51: Security & Platform | E51: Unit/E2E coverage | F51: CI | G51: N/A | H51: Desktop | I51: Windows | J51: Medium | K51: High | L51: Open | M51: Platform | N51: Shreya Patil | O51: 46187 | R51: 1.0.0 | S51: Sprint 20 | T51: Unknown
A52: BUG-OPEN-22 | B52: Baseline schema incomplete in migrations | C52: Some tables still need staging dump DDL | D52: Security & Platform | E52: RLS + edge shared libs | F52: Local | G52: N/A | H52: Desktop | I52: Windows | J52: High | K52: High | L52: Open | M52: Platform | N52: Shreya Patil | O52: 46222 | R52: 1.0.0 | S52: Sprint 26 | T52: Config/Env | U52: Partial IF NOT EXISTS recovery shipped | X52: P4-5 partial
A53: BUG-OPEN-23 | B53: deduct_credits RPC cannot service-role arbitrary user | C53: M4 deferred; JS gte path retained | D53: Billing & Credits | E53: Credits ledger | F53: Staging | G53: N/A | H53: Desktop | I53: Windows | J53: Medium | K53: High | L53: Open | M53: Billing | N53: Shreya Patil | O53: 46227 | R53: 1.0.0 | S53: Sprint 26 | T53: API Contract | X53: M4 DEFERRED
A54: BUG-OPEN-24 | B54: Privacy settings toggles unused | C54: Analytics opt-out enforced; other prefs honesty-labelled | D54: Settings | E54: Privacy toggles | F54: Staging | G54: Chrome | H54: Desktop | I54: Windows | J54: Medium | K54: Medium | L54: Closed | M54: Platform | N54: Raj Balani | O54: 46214 | P54: 46231 | R54: 1.0.0 | S54: Sprint 27 | T54: Logic Bug | U54: Toggle analytics off → PostHog opt-out | X54: FIXED launch pass
A55: BUG-OPEN-25 | B55: Retention polish not enforced | C55: Settings exist; no enforcement | D55: Settings | E55: Retention polish | F55: Staging | G55: Chrome | H55: Desktop | I55: Windows | J55: Low | K55: Low | L55: Open | M55: Platform | N55: Raj Balani | O55: 46214 | R55: 1.0.0 | S55: Sprint 25 | T55: Design Gap
A56: BUG-OPEN-26 | B56: Interview reminders need Resend | C56: Feature blocked without email secret | D56: Interviews & Calendar | E56: Interview email reminders | F56: Staging | G56: Chrome | H56: Desktop | I56: Windows | J56: Medium | K56: Medium | L56: Blocked | M56: Scheduling | N56: Raj Balani | O56: 46223 | R56: 1.0.0 | S56: Sprint 26 | T56: Config/Env | U56: Needs RESEND_API_KEY in Edge secrets | X56: Ops blocker — no fake fix
A57: BUG-OPEN-27 | B57: Live coach desktop-first on mobile | C57: Poor mobile live experience | D57: Live Practice Coach | E57: Live Practice Coach session | F57: Staging | G57: Chrome | H57: iPhone | I57: iOS | J57: Medium | K57: Medium | L57: Open | M57: Live Coach | N57: Shreya Patil | O57: 46225 | R57: 1.0.0 | S57: Sprint 26 | T57: UI Regression | V57: https://example.com/live-mobile.png
A58: BUG-OPEN-28 | B58: Admin tables poor on small screens | C58: overflow-x-auto on ModelCosts/Support/Revenue tables | D58: Admin Portal | E58: Admin users management | F58: Staging | G58: Chrome | H58: Android Phone | I58: Android | J58: Low | K58: Low | L58: Closed | M58: Admin | N58: Raj Balani | O58: 46226 | P58: 46231 | R58: 1.0.0 | S58: Sprint 28 | T58: UI Regression | U58: Retest Model Costs + Support + Revenue on phone | X58: FIXED QA sync pass
A59: BUG-OPEN-29 | B59: Group Practice still referenced historically | C59: Routes redirect; WebRTC descope | D59: Referrals & Guide | E59: In-app Guide/Help | F59: Staging | G59: Chrome | H59: Desktop | I59: Windows | J59: Low | K59: Low | L59: Closed | M59: Growth | N59: Shreya Patil | O59: 46220 | P59: 46230 | R59: 1.0.0 | S59: Sprint 26 | T59: Design Gap | U59: Copy updated coming soon
A60: BUG-OPEN-30 | B60: Anon key rotation still required | C60: Historical .env.production exposure | D60: Security & Platform | E60: RLS + edge shared libs | F60: Production | G60: N/A | H60: Desktop | I60: Windows | J60: High | K60: Critical | L60: Blocked | M60: Platform | N60: Shreya Patil | O60: 46229 | R60: 1.0.0 | S60: Sprint 26 | T60: Config/Env | U60: Rotate anon key in Supabase Dashboard only | X60: Ops blocker — cannot rotate from repo
A63: WORKFLOW | B63: QA (Shreya/Raj) files bug → set Reported By + Assigned To (dev) → Dev Tasks sheet mirrors this row → Dev fixes → Status=Fixed/Retest → QA retests → Closed. Filter Status / Reported By like slicers.

Sheet 07 UI-UX Testing
A1: UI/UX Testing | J1: Dashboard | K1: NAV | L1: Features | M1: Bugs | N1: Launch | O1: Smoke | P1: Creds | Q1: Env | R1: Playbooks | S1: Cases | T1: Sign-Off
A2: Screen | B2: Component | C2: Alignment | D2: Spacing | E2: Responsive | F2: Typography | G2: Icons | H2: Accessibility | I2: Dark Mode | J2: Light Mode | K2: Animation | L2: Pass | M2: Remarks
A3: /pricing | B3: Plan cards | C3: Pass | D3: Pass | E3: Pass | F3: Pass | G3: Pass | H3: Partial | I3: Pass | J3: Pass | K3: Pass | L3: Pass | M3: Max $79
A4: /app/live | B4: Transcript panel | C4: Pass | D4: Pass | E4: Partial | F4: Pass | G4: Pass | H4: Partial | I4: Pass | J4: Pass | K4: Pass | L4: Pass | M4: Electron primary
A5: /app/dashboard | B5: KPI cards | C5: Pass | D5: Pass | E5: Pass | F5: Pass | G5: Pass | H5: Pass | I5: Pass | J5: Pass | K5: Pass | L5: Pass
A6: /app/admin/revenue | B6: USD/INR charts | C6: Pass | D6: Pass | E6: Pass | F6: Pass | G6: Pass | H6: Partial | I6: Pass | J6: Pass | K6: N/A | L6: Pass
A7: /login | B7: Auth form | C7: Pass | D7: Pass | E7: Pass | F7: Pass | G7: Pass | H7: Pass | I7: Pass | J7: Pass | K7: N/A | L7: Pass

Sheet 08 Mobile Responsiveness
A1: Mobile Responsiveness | J1: Dashboard | K1: NAV | L1: Features | M1: Bugs | N1: Launch | O1: Smoke | P1: Creds | Q1: Env | R1: Playbooks | S1: Cases | T1: Sign-Off
A2: Screen | B2: Android | C2: iPhone | D2: Tablet | E2: Landscape | F2: Portrait | G2: Small Screen | H2: Medium Screen | I2: Large Screen | J2: Responsive | K2: Pass | L2: Comments
A3: /app/dashboard | B3: Pass | C3: Pass | D3: Pass | E3: Pass | F3: Pass | G3: Pass | H3: Pass | I3: Pass | J3: Yes | K3: Pass | L3: MobileNav partial
A4: /app/mock-test/session | B4: Pass | C4: Pass | D4: Pass | E4: Partial | F4: Pass | G4: Pass | H4: Pass | I4: Pass | J4: Yes | K4: Pass
A5: /pricing | B5: Pass | C5: Pass | D5: Pass | E5: Pass | F5: Pass | G5: Pass | H5: Pass | I5: Pass | J5: Yes | K5: Pass
A6: /app/live | B6: Fail | C6: Fail | D6: Partial | E6: N/A | F6: N/A | G6: Fail | H6: Partial | I6: Pass | J6: Partial | K6: Fail | L6: Desktop-first
A7: /app/admin/users | B7: Partial | C7: Partial | D7: Pass | E7: Pass | F7: Pass | G7: Partial | H7: Pass | I7: Pass | J7: Partial | K7: Partial | L7: Wide tables

Sheet 09 API Testing
A1: API Testing — Supabase Edge Functions | J1: Dashboard | K1: NAV | L1: Features | M1: Bugs | N1: Launch | O1: Smoke | P1: Creds | Q1: Env | R1: Playbooks | S1: Cases | T1: Sign-Off
A2: API Name | B2: Method | C2: Endpoint | D2: Authentication | E2: Headers | F2: Request | G2: Expected Response | H2: Actual Response | I2: Status Code | J2: Performance | K2: Security | L2: Pass | M2: Comments
A3: Create Checkout | B3: POST | C3: /functions/v1/create-checkout | D3: Bearer JWT | E3: Authorization, apikey | F3: {"plan":"enterprise"} | G3: Checkout URL | H3: URL ok | I3: 200 | J3: Good | K3: Pass | L3: Pass | M3: Enterprise price
A4: Parse Resume | B4: POST | C4: /functions/v1/parse-resume | D4: Bearer JWT | E4: x-clarify-onboarding-parse | F4: multipart | G4: Parsed JSON | H4: OK | I4: 200 | J4: Acceptable | K4: Pass | L4: Pass | M4: Free once
A5: Generate Answer | B5: POST | C5: /functions/v1/generate-answer | D5: Bearer JWT | E5: Authorization | F5: {"mode":"overlay"} | G5: 403 free overlay | H5: 403 | I5: 403 | J5: Excellent | K5: Pass | L5: Pass | M5: Pro gate
A6: Razorpay Order | B6: POST | C6: /functions/v1/razorpay-create-order | D6: Bearer JWT | E6: Authorization | F6: {"pack":"credits_50"} | G6: order_id | H6: OK | I6: 200 | J6: Good | K6: Pass | L6: Pass | M6: Rate limited
A7: Stripe Webhook | B7: POST | C7: /functions/v1/stripe-webhook | D7: Webhook HMAC | E7: Stripe-Signature | F7: invoice.payment_failed | G7: 200 credits intact | H7: 200 | I7: 200 | J7: Excellent | K7: Pass | L7: Pass | M7: P0-2
A8: Sync Calendar | B8: POST | C8: /functions/v1/sync-calendar | D8: Bearer JWT | E8: Authorization | F8: {} | G8: 501 or events | H8: 501 | I8: 501 | J8: N/A | K8: Pass | L8: Blocked | M8: Secrets

Sheet 10 Database Validation
A1: Database Validation | J1: Dashboard | K1: NAV | L1: Features | M1: Bugs | N1: Launch | O1: Smoke | P1: Creds | Q1: Env | R1: Playbooks | S1: Cases | T1: Sign-Off
A2: Table | B2: Columns | C2: Constraints | D2: Relationships | E2: Insert | F2: Update | G2: Delete | H2: Foreign Keys | I2: Indexes | J2: Triggers | K2: Views | L2: Validation Status | M2: Remarks
A3: profiles | B3: id, credits, plan, onboarding_completed, streak_days | C3: PK=auth.users | D3: 1:1 auth.users | E3: Pass | F3: Pass | G3: Pass | H3: Pass | I3: Pass | J3: Partial | K3: N/A | L3: Pass
A4: subscriptions | B4: user_id, plan, status, stripe ids | C4: status checks | D4: profiles | E4: Pass | F4: Pass | G4: Pass | H4: Pass | I4: Pass | J4: N/A | K4: N/A | L4: Pass | M4: MRR source
A5: credit_transactions | B5: user_id, amount, reason | C5: signed amount | D5: profiles | E5: Pass | F5: N/A | G5: N/A | H5: Pass | I5: Pass | J5: N/A | K5: N/A | L5: Pass | M5: Not money
A6: payment_orders | B6: amount_paise, status | C6: incl refunded | D6: profiles | E6: Pass | F6: Pass | G6: N/A | H6: Pass | I6: Pass | J6: N/A | K6: N/A | L6: Pass | M6: INR
A7: sessions | B7: nullable scores | C7: RLS user-owned | D7: answers/debriefs | E7: Pass | F7: Pass | G7: Pass | H7: Pass | I7: Pass | J7: N/A | K7: N/A | L7: Pass | M7: Null≠0
A8: questions / mock_tests | B8: exam_type, options jsonb | C8: RLS | D8: exam bank | E8: Pass | F8: Pass | G8: Pass | H8: Pass | I8: Partial | J8: N/A | K8: N/A | L8: Partial | M8: Thin seed

Sheet 11 Authentication Testing
A1: Authentication Testing | J1: Dashboard | K1: NAV | L1: Features | M1: Bugs | N1: Launch | O1: Smoke | P1: Creds | Q1: Env | R1: Playbooks | S1: Cases | T1: Sign-Off
A2: Portal/Role | B2: Login | C2: Signup | D2: Forgot Password | E2: Reset Password | F2: OTP | G2: Email Verification | H2: MFA | I2: Role Permissions | J2: Session | K2: Logout | L2: Unauthorized Access | M2: Status | N2: Remarks
A3: Guest | B3: N/A | C3: Pass | D3: N/A | E3: N/A | F3: N/A | G3: N/A | H3: N/A | I3: Pass | J3: N/A | K3: N/A | L3: Pass | M3: Pass | N3: Public marketing
A4: Free User | B4: Pass | C4: Pass | D4: Pass | E4: Pass | F4: N/A | G4: Pass | H4: Pass | I4: Pass | J4: Pass | K4: Pass | L4: Pass | M4: Pass | N4: Limited live
A5: Pro User | B5: Pass | C5: Pass | D5: Pass | E5: Pass | F5: N/A | G5: Pass | H5: Pass | I5: Pass | J5: Pass | K5: Pass | L5: Pass | M5: Pass | N5: Overlay+calendar
A6: Max User | B6: Pass | C6: Pass | D6: Pass | E6: Pass | F6: N/A | G6: Pass | H6: Pass | I6: Pass | J6: Pass | K6: Pass | L6: Pass | M6: Pass | N6: Priority models
A7: Admin | B7: Pass | C7: N/A | D7: Pass | E7: Pass | F7: N/A | G7: Pass | H7: Pass | I7: Pass | J7: Pass | K7: Pass | L7: Pass | M7: Pass | N7: requireAdmin

Sheet 12 Security Testing
A1: Security Testing (OWASP-style) | J1: Dashboard | K1: NAV | L1: Features | M1: Bugs | N1: Launch | O1: Smoke | P1: Creds | Q1: Env | R1: Playbooks | S1: Cases | T1: Sign-Off
A2: Target | B2: SQL Injection | C2: XSS | D2: CSRF | E2: Rate Limiting | F2: Authentication | G2: Authorization | H2: File Upload | I2: Input Validation | J2: Sensitive Data | K2: Headers | L2: Cookies | M2: JWT | N2: Encryption | O2: Status | P2: Remarks
A3: Edge shared utils | B3: Pass | C3: Pass | D3: Pass | E3: Pass | F3: Pass | G3: Pass | H3: N/A | I3: Pass | J3: Pass | K3: Pass | L3: Pass | M3: Pass | N3: Pass | O3: Pass | P3: BYOK removed
A4: parse-document | B4: N/A | C4: N/A | D4: N/A | E4: Pass | F4: Pass | G4: Pass | H4: Pass | I4: Pass | J4: Pass | K4: Pass | L4: N/A | M4: Pass | N4: Pass | O4: Pass | P4: Key in header
A5: stripe-webhook | B5: N/A | C5: N/A | D5: Pass | E5: N/A | F5: Pass | G5: Pass | H5: N/A | I5: Pass | J5: Pass | K5: Pass | L5: N/A | M5: N/A | N5: Pass | O5: Pass | P5: HMAC
A6: Admin bulk_update_users | B6: Pass | C6: N/A | D6: Pass | E6: N/A | F6: Pass | G6: Pass | H6: N/A | I6: Pass | J6: Pass | K6: N/A | L6: N/A | M6: Pass | N6: Pass | O6: Pass | P6: M5
A7: Resume storage | B7: N/A | C7: Pass | D7: Pass | E7: Pass | F7: Pass | G7: Pass | H7: Pass | I7: Pass | J7: Pass | K7: Pass | L7: Pass | M7: Pass | N7: Pass | O7: Pass | P7: Bucket RLS
A8: .env.production history | B8: N/A | C8: N/A | D8: N/A | E8: N/A | F8: N/A | G8: N/A | H8: N/A | I8: N/A | J8: Fail | K8: N/A | L8: N/A | M8: Partial | N8: N/A | O8: Fail | P8: Rotate anon key

Sheet 13 Performance Testing
A1: Performance Testing | J1: Dashboard | K1: NAV | L1: Features | M1: Bugs | N1: Launch | O1: Smoke | P1: Creds | Q1: Env | R1: Playbooks | S1: Cases | T1: Sign-Off
A2: Screen | B2: API | C2: Load Time | D2: TTFB | E2: Database Query | F2: Memory | G2: CPU | H2: Network | I2: Optimization Needed | J2: Status
A3: /app/dashboard | B3: profile+sessions | C3: 1200ms | D3: 180ms | E3: 90ms | F3: 85MB | G3: 12% | H3: 220KB | I3: No | J3: Pass
A4: /app/live | B4: generate-answer | C4: 900ms | D4: 200ms | E4: 40ms | F4: 140MB | G4: 28% | H4: 80KB | I4: Partial | J4: Pass
A5: /app/admin/users | B5: paginated users | C5: 2100ms | D5: 320ms | E5: 400ms | F5: 110MB | G5: 18% | H5: 450KB | I5: Yes | J5: Partial
A6: /pricing | B6: billing_settings | C6: 800ms | D6: 150ms | E6: 50ms | F6: 70MB | G6: 8% | H6: 160KB | I6: No | J6: Pass
A7: /app/mock-test/session | B7: select-test-questions | C7: 1500ms | D7: 250ms | E7: 180ms | F7: 95MB | G7: 15% | H7: 300KB | I7: Partial | J7: Pass

Sheet 14 Live Coaching Testing
A1: Domain: Live Coaching & Electron Overlay (replaces Marketplace) | J1: Dashboard | K1: NAV | L1: Features | M1: Bugs | N1: Launch | O1: Smoke | P1: Creds | Q1: Env | R1: Playbooks | S1: Cases | T1: Sign-Off
A2: Case ID | B2: STT Stream | C2: Diarization | D2: AI Hint | E2: AI Answer | F2: Credit Deduct | G2: Overlay Window | H2: Hotkeys | I2: Pro Gate | J2: Session Persist | K2: Debrief Link | L2: Electron Boot | M2: Pass | N2: Status | O2: Comments
A3: LC-01 | B3: Pass | C3: Pass | D3: Pass | E3: Pass | F3: Pass | G3: Pass | H3: Pass | I3: Pass | J3: Pass | K3: Pass | L3: Pass | M3: Pass | N3: Completed | O3: Pro happy path
A4: LC-02 | B4: Pass | C4: Pass | D4: Pass | E4: N/A | F4: Pass | G4: N/A | H4: N/A | I4: N/A | J4: Pass | K4: Pass | L4: N/A | M4: Pass | N4: Completed | O4: Web live
A5: LC-03 | B5: Pass | C5: Partial | D5: Fail | E5: Fail | F5: N/A | G5: N/A | H5: N/A | I5: Pass | J5: N/A | K5: N/A | L5: N/A | M5: Fail | N5: In Progress | O5: 402 path TC-011
A6: LC-04 | B6: N/A | C6: N/A | D6: N/A | E6: N/A | F6: N/A | G6: Not Run | H6: Pass | I6: Pass | J6: N/A | K6: N/A | L6: Not Run | M6: Not Run | N6: Ready | O6: Packaged unsigned
A7: LC-05 | B7: Pass | C7: Pass | D7: Pass | E7: Pass | F7: Pass | G7: Pass | H7: Pass | I7: Pass | J7: Pass | K7: Pass | L7: Partial | M7: Pass | N7: Completed | O7: Hotkey no dup

Sheet 15 Gov Exam Mock Testing
A1: Domain: Gov Exam Mock Test Engine (replaces Checkout) | J1: Dashboard | K1: NAV | L1: Features | M1: Bugs | N1: Launch | O1: Smoke | P1: Creds | Q1: Env | R1: Playbooks | S1: Cases | T1: Sign-Off
A2: Case ID | B2: Exam Select | C2: Create Test | D2: Question Load | E2: Timer | F2: Answer Save | G2: Submit Atomic | H2: Score Persist | I2: Results UI | J2: Analytics | K2: Admin Filter | L2: PDF Import | M2: Bank Coverage | N2: Pass | O2: Status | P2: Comments
A3: GE-01 | B3: Pass | C3: Pass | D3: Pass | E3: Pass | F3: Pass | G3: Pass | H3: Pass | I3: Pass | J3: Pass | K3: N/A | L3: N/A | M3: Partial | N3: Pass | O3: Completed | P3: Happy path
A4: GE-02 | B4: Pass | C4: Pass | D4: Pass | E4: Pass | F4: Pass | G4: Pass | H4: Pass | I4: Pass | J4: Partial | K4: N/A | L4: N/A | M4: Partial | N4: Pass | O4: Completed | P4: Idempotent submit
A5: GE-03 | B5: Pass | C5: Pass | D5: Pass | E5: Pass | F5: Pass | G5: Pass | H5: Pass | I5: Pass | J5: Pass | K5: N/A | L5: N/A | M5: Pass | N5: Pass | O5: Completed | P5: Expanded MCQ seeds
A6: GE-04 | B6: N/A | C6: N/A | D6: N/A | E6: N/A | F6: N/A | G6: N/A | H6: N/A | I6: N/A | J6: N/A | K6: Pass | L6: N/A | M6: N/A | N6: Pass | O6: Completed | P6: P1-5 filter
A7: GE-05 | B7: N/A | C7: N/A | D7: N/A | E7: N/A | F7: N/A | G7: N/A | H7: N/A | I7: N/A | J7: N/A | K7: N/A | L7: Blocked | M7: N/A | N7: Blocked | O7: Blocked | P7: Provider quota

Sheet 16 Billing Credits Testing
A1: Domain: Billing, Credits & Subscriptions (replaces Payment) | J1: Dashboard | K1: NAV | L1: Features | M1: Bugs | N1: Launch | O1: Smoke | P1: Creds | Q1: Env | R1: Playbooks | S1: Cases | T1: Sign-Off
A2: Case ID | B2: Gateway | C2: Success | D2: Failure | E2: Cancel | F2: Timeout | G2: Webhook | H2: Refund | I2: Partial Refund | J2: Duplicate Payment | K2: Credit Grant | L2: Credit Clawback | M2: Plan Gate | N2: Transaction History | O2: Settlement | P2: Pass | Q2: Status | R2: Comments
A3: BL-01 | B3: Stripe | C3: Pass | D3: Pass | E3: Pass | F3: Not Run | G3: Pass | H3: Not Run | I3: Not Run | J3: Pass | K3: Pass | L3: N/A | M3: Pass | N3: Pass | O3: N/A | P3: Pass | Q3: Completed | R3: Pro monthly
A4: BL-02 | B4: Stripe | C4: Pass | D4: N/A | E4: N/A | F4: N/A | G4: Pass | H4: N/A | I4: N/A | J4: N/A | K4: Pass | L4: N/A | M4: Pass | N4: Pass | O4: N/A | P4: Pass | Q4: Completed | R4: Max price IDs
A5: BL-03 | B5: Stripe | C5: N/A | D5: Pass | E5: N/A | F5: N/A | G5: Pass | H5: N/A | I5: N/A | J5: N/A | K5: N/A | L5: N/A | M5: N/A | N5: Pass | O5: N/A | P5: Pass | Q5: Completed | R5: payment_failed wallet
A6: BL-04 | B6: Razorpay | C6: Pass | D6: Pass | E6: Pass | F6: Not Run | G6: Pass | H6: Not Run | I6: N/A | J6: Pass | K6: Pass | L6: N/A | M6: Partial | N6: Pass | O6: N/A | P6: Pass | Q6: Completed | R6: One-time only
A7: BL-05 | B7: Stripe | C7: N/A | D7: N/A | E7: N/A | F7: N/A | G7: Pass | H7: Not Run | I7: Not Run | J7: N/A | K7: N/A | L7: Not Run | M7: N/A | N7: Pass | O7: N/A | P7: Not Run | Q7: Ready | R7: P4-2 refund
A8: BL-06 | B8: Both | C8: Pass | D8: N/A | E8: N/A | F8: N/A | G8: Pass | H8: N/A | I8: N/A | J8: N/A | K8: Pass | L8: N/A | M8: Pass | N8: Pass | O8: N/A | P8: Pass | Q8: Completed | R8: Settings ledger

Sheet 17 Role Based Testing
A1: Role Based Testing — Clarify plan entitlements | J1: Dashboard | K1: NAV | L1: Features | M1: Bugs | N1: Launch | O1: Smoke | P1: Creds | Q1: Env | R1: Playbooks | S1: Cases | T1: Sign-Off
A2: Permission/Feature | B2: Module | C2: Guest | D2: Free User | E2: Pro User | F2: Max User | G2: Admin | H2: Permissions | I2: Status | J2: Expected Summary
A3: Access /app | B3: Auth & Onboarding | C3: No | D3: Yes | E3: Yes | F3: Yes | G3: Yes | H3: Auth required | I3: Pass | J3: Guests → login
A4: Live answer limited | B4: Live Practice Coach | C4: No | D4: Yes | E4: Yes | F4: Yes | G4: Yes | H4: Free limited | I4: Pass | J4: live_rehearsal
A5: Desktop overlay | B5: Live Practice Coach | C5: No | D5: No | E5: Yes | F5: Yes | G5: Yes | H5: Pro+ | I5: Pass | J5: requirePlan pro
A6: Company research | B6: Company Research | C6: No | D6: No | E6: Yes | F6: Yes | G6: Yes | H6: Pro+ | I6: Pass
A7: Calendar sync | B7: Interviews & Calendar | C7: No | D7: No | E7: Yes | F7: Yes | G7: Yes | H7: Pro+ | I7: Pass
A8: Priority models | B8: Billing & Credits | C8: No | D8: No | E8: No | F8: Yes | G8: Yes | H8: Max | I8: Pass
A9: Admin revenue | B9: Admin Portal | C9: No | D9: No | E9: No | F9: No | G9: Yes | H9: admin role | I9: Pass | J9: requireAdmin
A10: Promo CRUD | B10: Admin Portal | C10: No | D10: No | E10: No | F10: No | G10: Yes | H10: admin | I10: Pass
A11: View pricing | B11: Marketing Site | C11: Yes | D11: Yes | E11: Yes | F11: Yes | G11: Yes | H11: Public | I11: Pass

Sheet 18 Regression Testing
A1: Regression Testing | J1: Dashboard | K1: NAV | L1: Features | M1: Bugs | N1: Launch | O1: Smoke | P1: Creds | Q1: Env | R1: Playbooks | S1: Cases | T1: Sign-Off
A2: Regression ID | B2: Module | C2: Feature | D2: QA Owner | E2: Executed | F2: Pass | G2: Fail | H2: Blocked | I2: Est Hours | J2: Actual Hours | K2: Remarks
A3: REG-01 | B3: Auth & Onboarding | C3: Login/OAuth/MFA | D3: Raj Balani | E3: Yes | F3: 4 | G3: 0 | H3: 0 | I3: 4 | J3: 3.5 | K3: Smoke green
A4: REG-02 | B4: Live Practice Coach | C4: STT + answer + overlay | D4: Shreya Patil | E4: Yes | F4: 4 | G4: 0 | H4: 0 | I4: 6 | J4: 5 | K4: BUG-001 closed
A5: REG-03 | B5: Billing & Credits | C5: Checkout + webhooks | D5: Raj Balani | E5: Yes | F5: 5 | G5: 0 | H5: 0 | I5: 5 | J5: 4.5 | K5: Money path
A6: REG-04 | B6: Gov Exam Mock Tests | C6: Create/submit/results | D6: Raj Balani | E6: Yes | F6: 3 | G6: 0 | H6: 1 | I6: 4 | J6: 3 | K6: PDF blocked
A7: REG-05 | B7: Admin Portal | C7: Users/revenue/questions | D7: Raj Balani | E7: Yes | F7: 4 | G7: 0 | H7: 0 | I7: 4 | J7: 3.5
A8: REG-06 | B8: Electron Desktop Overlay | C8: Boot + hotkeys | D8: Shreya Patil | E8: Partial | F8: 2 | G8: 0 | H8: 1 | I8: 3 | J8: 1.5 | K8: Unsigned
A9: TOTAL | F9: =SUM(F3:F8) | G9: =SUM(G3:G8) | H9: =SUM(H3:H8) | I9: =SUM(I3:I8) | J9: =SUM(J3:J8)

Sheet 19 Production Readiness
A1: Production Readiness Checklist | J1: Dashboard | K1: NAV | L1: Features | M1: Bugs | N1: Launch | O1: Smoke | P1: Creds | Q1: Env | R1: Playbooks | S1: Cases | T1: Sign-Off
A2: Module | B2: Feature Complete | C2: API Complete | D2: Database Ready | E2: Security Passed | F2: Performance Passed | G2: Responsive | H2: Accessibility | I2: SEO | J2: Monitoring | K2: Logging | L2: Deployment Ready | M2: Backup | N2: Recovery | O2: Documentation | P2: Ready Count | Q2: Total | R2: Readiness % | S2: Status | T2: Remarks
A3: Auth & Onboarding | B3: Yes | C3: Yes | D3: Yes | E3: Yes | F3: Yes | G3: Yes | H3: Yes | I3: Partial | J3: Yes | K3: Yes | L3: Yes | M3: Yes | N3: Yes | O3: Yes | P3: =IFERROR(COUNTIF(B3:O3,"Yes"),0) | Q3: 14 | R3: =IFERROR(IF(Q3=0,0,P3/Q3),0) | S3: =IFERROR(IF(R3>=0.9,"Ready",IF(R3>=0.7,"Conditional","Not Ready")),"Not Ready")
A4: Live Practice Coach | B4: Yes | C4: Yes | D4: Yes | E4: Yes | F4: Yes | G4: Partial | H4: Partial | I4: N/A | J4: Yes | K4: Yes | L4: Yes | M4: Yes | N4: Partial | O4: Yes | P4: =IFERROR(COUNTIF(B4:O4,"Yes"),0) | Q4: 14 | R4: =IFERROR(IF(Q4=0,0,P4/Q4),0) | S4: =IFERROR(IF(R4>=0.9,"Ready",IF(R4>=0.7,"Conditional","Not Ready")),"Not Ready")
A5: Billing & Credits | B5: Yes | C5: Yes | D5: Yes | E5: Yes | F5: Yes | G5: Yes | H5: Partial | I5: N/A | J5: Partial | K5: Yes | L5: Yes | M5: Yes | N5: Partial | O5: Yes | P5: =IFERROR(COUNTIF(B5:O5,"Yes"),0) | Q5: 14 | R5: =IFERROR(IF(Q5=0,0,P5/Q5),0) | S5: =IFERROR(IF(R5>=0.9,"Ready",IF(R5>=0.7,"Conditional","Not Ready")),"Not Ready")
A6: Gov Exam Mock Tests | B6: Partial | C6: Yes | D6: Partial | E6: Yes | F6: Yes | G6: Yes | H6: Partial | I6: Partial | J6: Partial | K6: Yes | L6: Partial | M6: Yes | N6: Partial | O6: Partial | P6: =IFERROR(COUNTIF(B6:O6,"Yes"),0) | Q6: 14 | R6: =IFERROR(IF(Q6=0,0,P6/Q6),0) | S6: =IFERROR(IF(R6>=0.9,"Ready",IF(R6>=0.7,"Conditional","Not Ready")),"Not Ready")
A7: Admin Portal | B7: Partial | C7: Yes | D7: Yes | E7: Yes | F7: Partial | G7: Partial | H7: Partial | I7: N/A | J7: Partial | K7: Yes | L7: Yes | M7: Yes | N7: Partial | O7: Partial | P7: =IFERROR(COUNTIF(B7:O7,"Yes"),0) | Q7: 14 | R7: =IFERROR(IF(Q7=0,0,P7/Q7),0) | S7: =IFERROR(IF(R7>=0.9,"Ready",IF(R7>=0.7,"Conditional","Not Ready")),"Not Ready")
A8: Electron Desktop Overlay | B8: Partial | C8: N/A | D8: N/A | E8: Partial | F8: Yes | G8: N/A | H8: Partial | I8: N/A | J8: Partial | K8: Partial | L8: Partial | M8: Yes | N8: Partial | O8: Partial | P8: =IFERROR(COUNTIF(B8:O8,"Yes"),0) | Q8: 14 | R8: =IFERROR(IF(Q8=0,0,P8/Q8),0) | S8: =IFERROR(IF(R8>=0.9,"Ready",IF(R8>=0.7,"Conditional","Not Ready")),"Not Ready")
A9: Marketing Site | B9: Yes | C9: N/A | D9: Yes | E9: Yes | F9: Yes | G9: Yes | H9: Partial | I9: Yes | J9: Yes | K9: Yes | L9: Yes | M9: Yes | N9: Yes | O9: Yes | P9: =IFERROR(COUNTIF(B9:O9,"Yes"),0) | Q9: 14 | R9: =IFERROR(IF(Q9=0,0,P9/Q9),0) | S9: =IFERROR(IF(R9>=0.9,"Ready",IF(R9>=0.7,"Conditional","Not Ready")),"Not Ready")
A10: Security & Platform | B10: Partial | C10: Yes | D10: Partial | E10: Partial | F10: Yes | G10: N/A | H10: N/A | I10: N/A | J10: Partial | K10: Yes | L10: Yes | M10: Yes | N10: Partial | O10: Yes | P10: =IFERROR(COUNTIF(B10:O10,"Yes"),0) | Q10: 14 | R10: =IFERROR(IF(Q10=0,0,P10/Q10),0) | S10: =IFERROR(IF(R10>=0.9,"Ready",IF(R10>=0.7,"Conditional","Not Ready")),"Not Ready")

Sheet 20 Release Sign-Off
A1: Release Sign-Off | J1: Dashboard | K1: NAV | L1: Features | M1: Bugs | N1: Launch | O1: Smoke | P1: Creds | Q1: Env | R1: Playbooks | S1: Cases | T1: ● Sign-Off
A2: Release Version | B2: Build | C2: Environment | D2: QA Lead | E2: Developer Lead | F2: Product Owner | G2: Passed | H2: Known Issues | I2: Blockers | J2: Risk Level | K2: Deployment Approval | L2: Go/No-Go | M2: Remarks
A3: 1.0.0-beta | B3: 1.0.0 | C3: Staging | D3: Shreya Patil | E3: Dev Lead | F3: Product | G3: Yes | H3: BUG-OPEN-01 Razorpay one-time; unsigned Electron if no cert | I3: Calendar/Resend/signing secrets if promising those features | J3: Medium | K3: Pending | L3: Conditional Go | M3: Launch-pass code + expanded MCQ seeds; apply migration; ops secrets still Blocked
A4: 1.0.0 | B4: 1.0.0 | C4: Production | D4: Shreya Patil | E4: Dev Lead | F4: Product | G4: No | H4: See CHANGELOG Launch gap matrix | I4: Code signing; anon key rotation; Calendar/Resend if promised | J4: High | K4: Pending | L4: No-Go | M4: Await cert + ops secrets
A5: 1.0.1 | B5: TBD | C5: Staging | D5: Shreya Patil | E5: Dev Lead | F5: Product | G5: No | J5: Low | K5: Deferred | L5: No-Go | M5: Placeholder

Sheet 21 Test Credentials
A1: Test Credentials — seeded accounts | J1: Dashboard | K1: NAV | L1: Features | M1: Bugs | N1: Launch | O1: Smoke | P1: ● Creds | Q1: Env | R1: Playbooks | S1: Cases | T1: Sign-Off
A2: Role | B2: Email | C2: Password location | D2: Plan | E2: Credits seed | F2: Notes | G2: Owner | H2: Last rotated
A3: Free | B3: qa.free@clarify.ai.test | C3: .env.qa.local → QA_FREE_PASSWORD | D3: free | E3: 50 | F3: Seeded by npm run qa:seed-accounts — never commit passwords | G3: Raj Balani
A4: Pro | B4: qa.pro@clarify.ai.test | C4: .env.qa.local → QA_PRO_PASSWORD | D4: pro | E4: 1400 | F4: Stripe test checkout path | G4: Raj Balani
A5: Max | B5: qa.max@clarify.ai.test | C5: .env.qa.local → QA_MAX_PASSWORD | D5: enterprise | E5: 4000 | F5: Workbook Max/Elite maps to plan_id=enterprise | G5: Raj Balani
A6: Admin | B6: qa.admin@clarify.ai.test | C6: .env.qa.local → QA_ADMIN_PASSWORD | D6: enterprise | E6: 4000 | F6: user_roles.admin via seed script | G6: Shreya Patil
A7: Stripe test card | B7: N/A | C7: 4242 4242 4242 4242 | D7: N/A | E7: N/A | F7: Any future expiry + any CVC; Stripe test mode only | G7: Raj Balani
A8: Razorpay test | B8: N/A | C8: Dashboard test keys | D8: N/A | E8: N/A | F8: INR one-time Order — no auto-renew (BUG-OPEN-01); keys not in .env.local yet | G8: Raj Balani

Sheet 22 Environments
A1: Environments | J1: Dashboard | K1: NAV | L1: Features | M1: Bugs | N1: Launch | O1: Smoke | P1: Creds | Q1: ● Env | R1: Playbooks | S1: Cases | T1: Sign-Off
A2: Environment | B2: Base URL | C2: Supabase project | D2: Owner | E2: Read/Write | F2: Notes
A3: Local | B3: http://localhost:5173 | C3: qzgvjrvtkwlzxpmlddkx (linked) | D3: Dev Lead | E3: Read-Write | F3: npm run dev
A4: Staging / closed beta | B4: https://clarify.ai.sltfinanceindia.com | C4: qzgvjrvtkwlzxpmlddkx | D4: QA Lead | E4: Read-Write | F4: Primary QA target — same project as prod until separate staging exists
A5: Prod (read-only QA) | B5: https://clarify.ai.sltfinanceindia.com | C5: qzgvjrvtkwlzxpmlddkx | D5: QA Lead | E5: Read-only | F5: Prefer seeded QA_* users; avoid destructive admin tests on shared data
A8: Environments & Secrets Checklist
A9: Secret / Config | B9: Where | C9: Launch impact | D9: Notes
A10: VITE_SUPABASE_URL | B10: Client | C10: Required | D10: Supabase project URL
A11: VITE_SUPABASE_ANON_KEY / PUBLISHABLE_KEY | B11: Client | C11: Required | D11: Rotate in Dashboard if historically exposed (BUG-OPEN-30)
A12: SUPABASE_SERVICE_ROLE_KEY | B12: Edge secrets | C12: Required | D12: Never in Vite
A13: RESEND_API_KEY | B13: Edge secrets | C13: Blocked feature | D13: Interview reminders / send-email (BUG-OPEN-26)
A14: GOOGLE_CLIENT_ID / GOOGLE_CLIENT_SECRET | B14: Edge secrets | C14: Blocked feature | D14: Calendar sync 501 without these (BUG-OPEN-03)
A15: STRIPE_SECRET_KEY + webhook secret | B15: Edge secrets | C15: Required (USD) | D15: Checkout + webhooks
A16: RAZORPAY_KEY_ID / KEY_SECRET / WEBHOOK_SECRET | B16: Edge secrets | C16: Required (INR) | D16: One-time orders only — no Subscriptions
A17: GEMINI_API_KEY (or AI keys used by callAI) | B17: Edge secrets | C17: Required for AI | D17: Gap analysis, mocks, collect-exam-papers
A18: DEEPGRAM_API_KEY | B18: Edge secrets | C18: Required live | D18: STT token
A19: Code signing EV/OV cert | B19: CI/build | C19: Blocked desktop trust | D19: Unsigned Windows SmartScreen (BUG-OPEN-18/19)
A20: VITE_POSTHOG_KEY | B20: Client optional | C20: Optional | D20: Analytics opt-out tested when set
A21: VITE_SENTRY_DSN | B21: Client optional | C21: Optional | D21: Error reporting

Sheet 23 Module Playbooks
A1: Module Playbooks — 20 modules | J1: Dashboard | K1: NAV | L1: Features | M1: Bugs | N1: Launch | O1: Smoke | P1: Creds | Q1: Env | R1: ● Playbooks | S1: Cases | T1: Sign-Off
A2: Module ID | B2: Module | C2: Purpose | D2: Entry URL | E2: Happy path (steps) | F2: Plan gate | G2: Dependencies | H2: Done when
A3: MOD-01 | B3: Auth & Onboarding | C3: Sign up/login and finish onboarding | D3: /login | E3: 1. Sign up 2. Verify email 3. Complete 5 steps | F3: Free | G3: Supabase Auth | H3: Land on dashboard with profile
A4: MOD-02 | B4: Dashboard | C4: See KPIs and navigate app | D4: /app/dashboard | E4: 1. Open home 2. Check credits/sessions 3. Mobile More nav | F4: Free | G4: Auth session | H4: KPIs load; nav works
A5: MOD-03 | B5: Live Practice Coach | C5: Run live coach with STT + hint | D5: /app/live | E5: 1. Start session 2. Capture audio 3. Request hint | F5: Free/Pro overlay | G5: Deepgram + credits | H5: Transcript + hint without crash
A6: MOD-04 | B6: Mock Interview | C6: Timed mock interview | D6: /app/mock | E6: 1. Configure 2. Answer 3. Finish scoring | F6: Free | G6: AI edge | H6: Session saved; note no TTS
A7: MOD-05 | B7: Sessions & Debriefs | C7: Review history + debrief | D7: /app/sessions | E7: 1. Open session 2. Debrief 3. Share if enabled | F7: Free | G7: Credits for debrief | H7: Scores/debrief render
A8: MOD-06 | B8: Analytics & Usage | C8: Analytics + usage ledger | D8: /app/analytics | E8: 1. Open analytics 2. Open /app/usage | F8: Free | G8: Sessions data | H8: Charts/ledger load
A9: MOD-07 | B9: Prep Lab | C9: Prep Lab tools | D9: /app/prep | E9: 1. STAR 2. Rephrase 3. Confirm credit toast | F9: Free | G9: prep-tool edge | H9: Output appears; credits deduct
A10: MOD-08 | B10: Documents & Resumes | C10: Documents + gap + versions | D10: /app/documents | E10: 1. Upload resume 2. JD gap analysis 3. Version history | F10: Free | G10: parse/gap edges | H10: Parse + gap + versions visible
A11: MOD-09 | B11: Answer Bank | C11: Answer bank CRUD | D11: /app/answers | E11: 1. Create 2. Edit 3. Favourite | F11: Free | G11: DB | H11: Persists after refresh
A12: MOD-10 | B12: Interviews & Calendar | C12: Schedule + calendar | D12: /app/interviews | E12: 1. Create interview 2. Interview Day 3. Calendar sync if secrets | F12: Pro for sync | G12: Resend/Google secrets | H12: CRUD works; sync Blocked without secrets
A13: MOD-11 | B13: Company Research | C13: Company brief | D13: /app/companies | E13: 1. Search company 2. Generate brief | F13: Pro+ | G13: company-research | H13: Brief cached
... A22: MOD-20 | B22: Security & Platform | C22: Security platform | D22: N/A | E22: 1. RLS spot-check 2. Rate limit 3. Webhook signature | F22: Admin/ops | G22: Service role | H22: No open RLS holes in smoke

Sheet 24 Launch Status
A1: Launch Status Dashboard | J1: Dashboard | K1: NAV | L1: Features | M1: Bugs | N1: ● Launch | O1: Smoke | P1: Creds | Q1: Env | R1: Playbooks | S1: Cases | T1: Sign-Off
A2: Metric | B2: Count | C2: Notes
A3: Bugs Fixed/Closed | B3: 39 | C3: Includes P0–P2 + launch-pass OPEN fixes
A4: Bugs Open | B4: 12 | C4: Product/roadmap still open
A5: Bugs Blocked (ops/secrets) | B5: 6 | C5: Calendar, Resend, signing, key rotation, Gemini collect
A6: Bugs Won't Fix / Descope | B6: 1 | C6: Outlook etc.
A7: Features total | B7: 114 | C7: See Feature Inventory
A8: Features Completed status | B8: 91
A12: Blocking for launch (honesty)
A13: Razorpay is one-time Order only — copy must not promise renew (BUG-OPEN-01)
A14: Unsigned Windows installer → SmartScreen (BUG-OPEN-18/19) unless EV/OV cert
A15: Google Calendar sync 501 until OAuth secrets (BUG-OPEN-03) if calendar is promised
A16: Interview email reminders need RESEND_API_KEY (BUG-OPEN-26)
A17: Anon key rotation is Dashboard ops only (BUG-OPEN-30)
A18: Gov bank expanded in migration — apply 20260729120000 before claiming full mocks

Sheet 25 Smoke Pack
A1: Smoke Pack — ~20 must-pass | J1: Dashboard | K1: NAV | L1: Features | M1: Bugs | N1: Launch | O1: ● Smoke | P1: Creds | Q1: Env | R1: Playbooks | S1: Cases | T1: Sign-Off
A2: Smoke ID | B2: Title | C2: Credential role | D2: Route | E2: Deep Link | F2: Steps | G2: Expected | H2: Pass/Fail
A3: SMK-01 | B3: Login email | C3: Free | D3: /login | E3: =IFERROR(Environments!$B$3&D3,D3) | F3: Sign in with seeded free user | G3: Dashboard loads | H3: Not Run
A4: SMK-02 | B4: Dashboard KPIs | C4: Free | D4: /app/dashboard | E4: =IFERROR(Environments!$B$3&D4,D4) | F4: Open home | G4: Credits/sessions visible | H4: Not Run
A5: SMK-03 | B5: Mobile More nav | C5: Free | D5: /app/dashboard | E5: =IFERROR(Environments!$B$3&D5,D5) | F5: Open More; tap Notifications, Guide, Profile, Usage | G5: All routes open | H5: Not Run
A6: SMK-04 | B6: Live hint | C6: Pro | D6: /app/live | E6: =IFERROR(Environments!$B$3&D6,D6) | F6: Start + request hint | G6: Hint returns; credits drop | H6: Not Run
A7: SMK-05 | B7: Mock create | C7: Free | D7: /app/mock | E7: =IFERROR(Environments!$B$3&D7,D7) | F7: Start mock | G7: Session creates | H7: Not Run
A8: SMK-06 | B8: Resume parse | C8: Free | D8: /app/documents | E8: =IFERROR(Environments!$B$3&D8,D8) | F8: Upload resume | G8: Parsed fields show | H8: Not Run
A9: SMK-07 | B9: Gap analysis | C9: Pro | D9: /app/documents | E9: =IFERROR(Environments!$B$3&D9,D9) | F9: JD → Run gap analysis | G9: Match score UI; 402 if broke | H9: Not Run
A10: SMK-08 | B10: Resume versions | C10: Free | D10: /app/documents | E10: =IFERROR(Environments!$B$3&D10,D10) | F10: Open resume detail | G10: Version history card | H10: Not Run
A11: SMK-09 | B11: Gov mock | C11: Free | D11: /app/mock-test | E11: =IFERROR(Environments!$B$3&D11,D11) | F11: Create SSC/JEE-style test | G11: Enough questions load | H11: Not Run
A12: SMK-10 | B12: Billing Stripe test | C12: Free | D12: /app/settings/billing | E12: =IFERROR(Environments!$B$3&D12,D12) | F12: Checkout with 4242… | G12: Webhook grants plan/credits | H12: Not Run
A13: SMK-11 | B13: Razorpay honesty | C13: Free | D13: /app/settings/billing | E13: =IFERROR(Environments!$B$3&D13,D13) | F13: Read INR copy + button labels | G13: One-time / no auto-renew disclosed | H13: Not Run
A14: SMK-12 | B14: Notification prefs | C14: Free | D14: /app/settings/notifications | E14: =IFERROR(Environments!$B$3&D14,D14) | F14: Read honesty + save prefs | G14: Save succeeds | H14: Not Run
... A22: SMK-20 | B22: Electron boot | C22: Pro | D22: (desktop) | E22: =IFERROR(Environments!$B$3&D22,D22) | F22: Launch unsigned build | G22: App boots; SmartScreen may warn | H22: Not Run

Sheet Daily Log
A1: Daily Progress Log (feeds Dashboard chart) | J1: Dashboard | K1: NAV | L1: Features | M1: Bugs | N1: Launch | O1: Smoke | P1: Creds | Q1: Env | R1: Playbooks | S1: Cases | T1: Sign-Off
A2: Date | B2: QA Person | C2: Cases Executed | D2: Passed | E2: Failed | F2: Blocked | G2: Bugs Opened | H2: Bugs Closed | I2: Hours Logged | J2: Remarks
A3: 46226 | B3: Shreya Patil | C3: 8 | D3: 6 | E3: 1 | F3: 0 | G3: 1 | H3: 0 | I3: 4.5 | J3: Sprint execution — production QA
A4: 46227 | B4: Raj Balani | C4: 10 | D4: 7 | E4: 0 | F4: 0 | G4: 0 | H4: 0 | I4: 5 | J4: Sprint execution — production QA
A5: 46228 | B5: Shreya Patil | C5: 12 | D5: 8 | E5: 0 | F5: 0 | G5: 1 | H5: 0 | I5: 5.5 | J5: Sprint execution — production QA
A6: 46229 | B6: Raj Balani | C6: 14 | D6: 9 | E6: 1 | F6: 0 | G6: 0 | H6: 0 | I6: 6 | J6: Sprint execution — production QA
A7: 46230 | B7: Shreya Patil | C7: 16 | D7: 10 | E7: 0 | F7: 1 | G7: 1 | H7: 1 | I7: 6.5 | J7: Sprint execution — production QA
A8: 46231 | B8: Raj Balani | C8: 18 | D8: 11 | E8: 0 | F8: 0 | G8: 0 | H8: 1 | I8: 7 | J8: Sprint execution — production QA
A9: 46232 | B9: Shreya Patil | C9: 20 | D9: 12 | E9: 1 | F9: 0 | G9: 1 | H9: 1 | I9: 7.5 | J9: Sprint execution — production QA
A10: TOTAL | C10: =SUM(C3:C9) | D10: =SUM(D3:D9) | E10: =SUM(E3:E9) | F10: =SUM(F3:F9) | G10: =SUM(G3:G9) | H10: =SUM(H3:H9) | I10: =SUM(I3:I9)

Sheet Lists
A1: Status | B1: PassFail | C1: Priority | D1: Severity | E1: Environment | F1: Browser | G1: Device | H1: Platform | I1: YesNo | J1: QAStatus | K1: BugStatus | L1: Risk | M1: Criticality | N1: Automation | O1: SecurityResult | P1: ReadyStatus | Q1: Decision | R1: Approval | S1: PerfRating | T1: HttpMethod | U1: StatusCode | V1: AuthType | W1: Sprint | X1: Release | Y1: RootCause | Z1: Modules | AA1: Portals | AB1: Roles | AC1: Testers | AD1: Owners | AE1: ImplStatus | AF1: Coverage | AG1: ModuleStatus | AH1: Developers | AI1: TaskType | AJ1: TaskStatus | AK1: DevTaskStatus | AL1: Assignees
A2: Not Started | B2: Pass | C2: Critical | D2: Critical | E2: Local | F2: Chrome | G2: Desktop | H2: Web | I2: Yes | J2: Not Tested | K2: New | L2: Critical | M2: Critical | N2: Manual | O2: Pass | P2: Ready | Q2: Go | R2: Approved | S2: Excellent | T2: GET | U2: 200 | V2: None | W2: Sprint 24 | X2: 1.0.0-beta | Y2: Logic Bug | Z2: Auth & Onboarding | AA2: Marketing Portal | AB2: Guest | AC2: Shreya Patil | AD2: Auth Lead | AE2: Fully Implemented | AF2: Yes | AG2: Not Started | AH2: Dev Lead | AI2: Smoke | AJ2: Not Started | AK2: Queued | AL2: Dev Lead
A3: In Progress | B3: Fail | C3: High | D3: High | E3: Staging | F3: Edge | G3: Laptop | H3: Windows | I3: No | J3: In Testing | K3: Open | L3: High | M3: High | N3: Automated | O3: Fail | P3: Not Ready | Q3: No-Go | R3: Pending | S3: Good | T3: POST | U3: 201 | V3: Bearer JWT | W3: Sprint 25 | X3: 1.0.0 | Y3: Missing Validation | Z3: Dashboard | AA3: Auth Portal | AB3: Free User | AC3: Raj Balani | AD3: Product | AE3: Partial | AF3: No | AG3: In Progress | AH3: Live Coach Dev | AI3: Functional | AJ3: In Progress | AK3: In Progress | AL3: Live Coach Dev
A4: Completed | B4: Blocked | C4: Medium | D4: Medium | E4: Production | F4: Firefox | G4: iPhone | H4: macOS | I4: Partial | J4: Passed | K4: In Progress | L4: Medium | M4: Medium | N4: Candidate | O4: Partial | P4: Conditional | Q4: Conditional Go | R4: Rejected | S4: Acceptable | T4: PUT | U4: 204 | V4: Anon Key | W4: Sprint 26 | X4: 1.0.1 | Y4: Config/Env | Z4: Live Practice Coach | AA4: Candidate App | AB4: Pro User | AD4: Live Coach | AE4: Stub | AF4: Partial | AG4: Completed | AH4: Platform Dev | AI4: Regression | AJ4: Blocked | AK4: Code Review | AL4: Platform Dev
A5: Blocked | B5: Not Run | C5: Low | D5: Low | E5: CI | F5: Safari | G5: Android Phone | H5: Linux | I5: N/A | J5: Failed | K5: Fixed | L5: Low | M5: Low | N5: Partial | O5: Not Tested | P5: Blocked | R5: Deferred | S5: Poor | T5: PATCH | U5: 400 | V5: Service Role | W5: Sprint 27 | X5: 1.1.0 | Y5: Race Condition | Z5: Mock Interview | AA5: Admin Portal | AB5: Max User | AD5: Sessions | AE5: Dead Code | AF5: N/A | AG5: Blocked | AH5: GovExams Dev | AI5: E2E | AJ5: Done | AK5: Fixed — Ready for Retest | AL5: GovExams Dev
A6: Deferred | B6: N/A | E6: Electron Dev | F6: Electron | G6: iPad | H6: iOS | J6: Blocked | K6: Retest | O6: N/A | S6: Critical | T6: DELETE | U6: 401 | V6: Webhook HMAC | W6: Hotfix | Y6: UI Regression | Z6: Sessions & Debriefs | AA6: Electron Overlay | AB6: Admin | AD6: Analytics | AE6: Not Built | AG6: Deprecated | AH6: Desktop Dev | AI6: UI/UX | AJ6: Deferred | AK6: Reopened | AL6: Desktop Dev
A7: Ready | B7: In Progress | E7: Electron Packaged | F7: N/A | G7: Android Tablet | H7: Android | J7: Deferred | K7: Closed | T7: OPTIONS | U7: 402 | V7: API Key Header | Y7: API Contract | Z7: Analytics & Usage | AA7: All Portals | AD7: Prep | AI7: API | AK7: Done | AL7: Auth Lead
A8: Complete | K8: Won't Fix | U8: 403 | Y8: DB/RLS | Z8: Prep Lab | AD8: Docs | AI8: Security | AK8: Won't Fix | AL8: Product
A9: Active | K9: Duplicate | U9: 404 | Y9: Third-party | Z9: Documents & Resumes | AD9: Scheduling | AI9: Retest | AL9: Live Coach
U10: 409 | Y10: Design Gap | Z10: Answer Bank | AD10: Growth | AI10: Exploratory | AL10: Sessions
U11: 429 | Y11: Unknown | Z11: Interviews & Calendar | AD11: GovExams | AL11: Analytics
U12: 500 | Z12: Company Research | AD12: Platform | AL12: Prep
U13: 501 | Z13: Notifications & Profile | AD13: Admin | AL13: Docs
Z14: Referrals & Guide | AD14: Billing | AL14: Scheduling
Z15: Gov Exam Mock Tests | AD15: Desktop | AL15: Growth
Z16: Settings | AD16: QA Lead | AL16: GovExams
Z17: Admin Portal | AD17: Dev Lead | AL17: Platform
Z18: Marketing Site | AL18: Admin
Z19: Billing & Credits | AL19: Billing
Z20: Electron Desktop Overlay | AL20: Desktop
Z21: Security & Platform | AL21: QA Lead
Z22: Cross-Cutting | AL22: Dev Lead
Z23: All Portals
