Workbook

Sheet 00 Read Me
A1: Clarify AI — Enterprise QA Testing Workbook
A4: Application | B4: Clarify AI
A5: Description | B5: AI-powered interview preparation & rehearsal platform with Indian gov-exam MCQ mock tests, live coaching overlay, and dual Stripe/Razorpay billing.
A6: Tech stack | B6: React 18 + TypeScript + Vite + Tailwind/shadcn · Supabase (Auth, Postgres+RLS, Edge/Deno, Storage, Realtime) · Electron · Deepgram · Gemini/OpenAI/Anthropic · Stripe + Razorpay
A7: Portals | B7: Marketing · Auth · Candidate App · Admin · Electron Overlay
A8: Roles | B8: Guest · Free User · Pro User · Max User · Admin
A9: Version under test | B9: 1.0.0 / 1.0.0-beta
A10: Generated | B10: 2026-07-28
A12: HOW TO USE
A13: 1 | B13: Open 01 Dashboard — all KPIs and charts are formula-driven. Do not type numbers there.
A14: 2 | B14: Maintain Modules (02) and Features (03) as scope changes.
A15: 3 | B15: Author/execute cases in 04; link defects in 06 via Bug ID.
A16: 4 | B16: Run golden paths in 05 before every RC; fill Daily Log for progress charts.
A17: 5 | B17: Execute domain packs 14–16 (Live Coaching, Gov Exam, Billing) — not marketplace.
A18: 6 | B18: Complete 19 Production Readiness and 20 Release Sign-Off for Go/No-Go.
A19: 7 | B19: All enums use Lists dropdowns. Track Est Hours / Actual Hours on modules, features, cases, E2E, and regression. Use QA Team sheet for roster capacity.
A21: QA TEAM
B22: Kavya Iyer (QA Lead) · Asha Sharma (Senior QA) · Rohan Mehta (QA Engineer) · Priya Nair (QA Engineer) · Dev Patel (SDET)
A23: Green | B23: Pass / Yes
A24: Red | B24: Fail / No / Critical
A25: Yellow | B25: In Progress / Blocked / Medium
A26: Gray | B26: Not Started / Not Run
A27: Blue | B27: Completed / Passed / Ready
A29: SCALING
B30: Designed for hundreds of modules and tens of thousands of test cases. Keep one row per entity; use filters and freeze panes. Dashboard formulas scan to row 5000.
A31: Google Sheets | B31: Upload this .xlsx to Drive → Open with Google Sheets. Charts and data validation transfer; re-check named Lists ranges after import.
A33: SHEET INDEX
A34: 01 Dashboard | B34: Live KPIs + charts
A35: 02 Module Master | B35: 20 Clarify modules
A36: 03 Feature Inventory | B36: Feature coverage matrix
A37: 04 Test Case Repository | B37: Executable cases
A38: 05 E2E User Flows | B38: Cross-module journeys
A39: 06 Bug Tracker | B39: Defect lifecycle
A40: 07 UI-UX Testing | B40: Visual / a11y
A41: 08 Mobile Responsiveness | B41: Breakpoints
A42: 09 API Testing | B42: Edge functions
A43: 10 Database Validation | B43: Schema / RLS
A44: 11 Authentication Testing | B44: Auth matrix
A45: 12 Security Testing | B45: OWASP-style
... A55: Lists | B55: Dropdown vocabulary — do not delete

Sheet 01 Dashboard
A1: Clarify AI — QA Executive Dashboard
A2: Formula-driven · Do not edit KPI cells (protected intent) · Source sheets 02–20 + Daily Log
A3: KEY PERFORMANCE INDICATORS | F3: Count | I3: Daily Progress | N3: QA Person | O3: Actual Hours
A4: Total Modules | B4: =IFERROR(COUNTA('02 Module Master'!A3:A5000)-COUNTIF('02 Module Master'!A3:A5000,"TOTAL"),0) | C4: PROGRESS BARS | F4: Passed | G4: =IFERROR(B7,0) | I4: Date | J4: Executed | K4: Passed | L4: Hours | N4: Kavya Iyer | O4: =IFERROR(SUMIF('04 Test Case Repository'!S$3:S$5000,N4,'04 Test Case Repository'!U$3:U$5000),0)
A5: Total Features | B5: =IFERROR(COUNTA('03 Feature Inventory'!A3:A5000)-COUNTIF('03 Feature Inventory'!A3:A5000,"TOTAL"),0) | C5: Pass Rate | D5: =IFERROR(REPT("#",MAX(0,MIN(10,ROUND(N(B16)*10,0))))&REPT("-",10-MAX(0,MIN(10,ROUND(N(B16)*10,0)))),REPT("-",10)) | F5: Failed | G5: =IFERROR(B8,0) | I5: =IFERROR('Daily Log'!A3,"") | J5: =IFERROR('Daily Log'!C3,0) | K5: =IFERROR('Daily Log'!D3,0) | L5: =IFERROR('Daily Log'!I3,0) | N5: Asha Sharma | O5: =IFERROR(SUMIF('04 Test Case Repository'!S$3:S$5000,N5,'04 Test Case Repository'!U$3:U$5000),0)
A6: Total Test Cases | B6: =IFERROR(COUNTA('04 Test Case Repository'!A3:A5000)-COUNTIF('04 Test Case Repository'!A3:A5000,"TOTAL"),0) | C6: QA Progress | D6: =IFERROR(REPT("#",MAX(0,MIN(10,ROUND(N(B18)*10,0))))&REPT("-",10-MAX(0,MIN(10,ROUND(N(B18)*10,0)))),REPT("-",10)) | F6: Blocked | G6: =IFERROR(B9,0) | I6: =IFERROR('Daily Log'!A4,"") | J6: =IFERROR('Daily Log'!C4,0) | K6: =IFERROR('Daily Log'!D4,0) | L6: =IFERROR('Daily Log'!I4,0) | N6: Rohan Mehta | O6: =IFERROR(SUMIF('04 Test Case Repository'!S$3:S$5000,N6,'04 Test Case Repository'!U$3:U$5000),0)
A7: Passed | B7: =IFERROR(COUNTIF('04 Test Case Repository'!P3:P5000,"Pass"),0) | C7: Prod Ready | D7: =IFERROR(REPT("#",MAX(0,MIN(10,ROUND(N(B19)*10,0))))&REPT("-",10-MAX(0,MIN(10,ROUND(N(B19)*10,0)))),REPT("-",10)) | F7: Not Executed | G7: =IFERROR(B10,0) | I7: =IFERROR('Daily Log'!A5,"") | J7: =IFERROR('Daily Log'!C5,0) | K7: =IFERROR('Daily Log'!D5,0) | L7: =IFERROR('Daily Log'!I5,0) | N7: Priya Nair | O7: =IFERROR(SUMIF('04 Test Case Repository'!S$3:S$5000,N7,'04 Test Case Repository'!U$3:U$5000),0)
A8: Failed | B8: =IFERROR(COUNTIF('04 Test Case Repository'!P3:P5000,"Fail"),0) | C8: Module Complete | D8: =IFERROR(REPT("#",MAX(0,MIN(10,ROUND(IFERROR(COUNTIF('02 Module Master'!H3:H5000,"Completed")/MAX(1,COUNTA('02 Module Master'!A3:A5000)),0)*10,0))))&REPT("-",10-MAX(0,MIN(10,ROUND(IFERROR(COUNTIF('02 Module Master'!H3:H5000,"Completed")/MAX(1,COUNTA('02 Module Master'!A3:A5000)),0)*10,0)))),REPT("-",10)) | I8: =IFERROR('Daily Log'!A6,"") | J8: =IFERROR('Daily Log'!C6,0) | K8: =IFERROR('Daily Log'!D6,0) | L8: =IFERROR('Daily Log'!I6,0) | N8: Dev Patel | O8: =IFERROR(SUMIF('04 Test Case Repository'!S$3:S$5000,N8,'04 Test Case Repository'!U$3:U$5000),0)
A9: Blocked | B9: =IFERROR(COUNTIF('04 Test Case Repository'!P3:P5000,"Blocked"),0) | C9: Hours Burn | D9: =IFERROR(REPT("#",MAX(0,MIN(10,ROUND(IF(B20=0,0,MIN(1,B21/B20))*10,0))))&REPT("-",10-MAX(0,MIN(10,ROUND(IF(B20=0,0,MIN(1,B21/B20))*10,0)))),REPT("-",10)) | F9: Count | I9: =IFERROR('Daily Log'!A7,"") | J9: =IFERROR('Daily Log'!C7,0) | K9: =IFERROR('Daily Log'!D7,0) | L9: =IFERROR('Daily Log'!I7,0)
A10: Not Executed | B10: =IFERROR(COUNTIF('04 Test Case Repository'!P3:P5000,"Not Run"),0) | F10: Critical | G10: =IFERROR(B12,0) | I10: =IFERROR('Daily Log'!A8,"") | J10: =IFERROR('Daily Log'!C8,0) | K10: =IFERROR('Daily Log'!D8,0) | L10: =IFERROR('Daily Log'!I8,0)
A11: In Progress | B11: =IFERROR(COUNTIF('04 Test Case Repository'!Q3:Q5000,"In Progress"),0) | F11: High | G11: =IFERROR(B13,0) | I11: =IFERROR('Daily Log'!A9,"") | J11: =IFERROR('Daily Log'!C9,0) | K11: =IFERROR('Daily Log'!D9,0) | L11: =IFERROR('Daily Log'!I9,0)
A12: Critical Bugs | B12: =IFERROR(COUNTIFS('06 Bug Tracker'!J3:J5000,"Critical",'06 Bug Tracker'!L3:L5000,"<>Closed"),0) | F12: Medium | G12: =IFERROR(B14,0)
A13: High Bugs | B13: =IFERROR(COUNTIFS('06 Bug Tracker'!J3:J5000,"High",'06 Bug Tracker'!L3:L5000,"<>Closed"),0) | F13: Low | G13: =IFERROR(B15,0)
A14: Medium Bugs | B14: =IFERROR(COUNTIFS('06 Bug Tracker'!J3:J5000,"Medium",'06 Bug Tracker'!L3:L5000,"<>Closed"),0)
A15: Low Bugs | B15: =IFERROR(COUNTIFS('06 Bug Tracker'!J3:J5000,"Low",'06 Bug Tracker'!L3:L5000,"<>Closed"),0) | F15: Module | G15: Completion %
A16: Overall Pass % | B16: =IFERROR(IF((B7+B8+B9)=0,0,B7/(B7+B8+B9)),0) | F16: Auth & Onboarding | G16: =IFERROR(IF('02 Module Master'!I3=0,0,'02 Module Master'!J3/'02 Module Master'!I3),0)
A17: Overall Fail % | B17: =IFERROR(IF((B7+B8+B9)=0,0,B8/(B7+B8+B9)),0) | F17: Dashboard | G17: =IFERROR(IF('02 Module Master'!I4=0,0,'02 Module Master'!J4/'02 Module Master'!I4),0)
A18: QA Progress % | B18: =IFERROR(IF(B6=0,0,(B7+B8+B9+B11)/B6),0) | F18: Live Practice Coach | G18: =IFERROR(IF('02 Module Master'!I5=0,0,'02 Module Master'!J5/'02 Module Master'!I5),0)
A19: Production Readiness % | B19: =IFERROR(AVERAGEIF('19 Production Readiness'!A3:A5000,"<>",'19 Production Readiness'!R3:R5000),0) | F19: Mock Interview | G19: =IFERROR(IF('02 Module Master'!I6=0,0,'02 Module Master'!J6/'02 Module Master'!I6),0)
A20: Est Hours (Total) | B20: =IFERROR(SUM('04 Test Case Repository'!T3:T5000),0) | F20: Sessions & Debriefs | G20: =IFERROR(IF('02 Module Master'!I7=0,0,'02 Module Master'!J7/'02 Module Master'!I7),0)
A21: Actual Hours (Total) | B21: =IFERROR(SUM('04 Test Case Repository'!U3:U5000),0) | F21: Analytics & Usage | G21: =IFERROR(IF('02 Module Master'!I8=0,0,'02 Module Master'!J8/'02 Module Master'!I8),0)
A22: Hours Variance | B22: =IFERROR(B21-B20,0) | F22: Prep Lab | G22: =IFERROR(IF('02 Module Master'!I9=0,0,'02 Module Master'!J9/'02 Module Master'!I9),0)
A23: QA Team Size | B23: =IFERROR(COUNTA('QA Team'!A3:A50)-COUNTIF('QA Team'!A3:A50,"TOTAL"),0) | F23: Documents & Resumes | G23: =IFERROR(IF('02 Module Master'!I10=0,0,'02 Module Master'!J10/'02 Module Master'!I10),0)
F24: Answer Bank | G24: =IFERROR(IF('02 Module Master'!I11=0,0,'02 Module Master'!J11/'02 Module Master'!I11),0)
F25: Interviews & Calendar | G25: =IFERROR(IF('02 Module Master'!I12=0,0,'02 Module Master'!J12/'02 Module Master'!I12),0)
F26: Company Research | G26: =IFERROR(IF('02 Module Master'!I13=0,0,'02 Module Master'!J13/'02 Module Master'!I13),0)
F27: Notifications & Profile | G27: =IFERROR(IF('02 Module Master'!I14=0,0,'02 Module Master'!J14/'02 Module Master'!I14),0)
F28: Referrals & Guide | G28: =IFERROR(IF('02 Module Master'!I15=0,0,'02 Module Master'!J15/'02 Module Master'!I15),0)
F29: Gov Exam Mock Tests | G29: =IFERROR(IF('02 Module Master'!I16=0,0,'02 Module Master'!J16/'02 Module Master'!I16),0)
F30: Settings | G30: =IFERROR(IF('02 Module Master'!I17=0,0,'02 Module Master'!J17/'02 Module Master'!I17),0)
F31: Admin Portal | G31: =IFERROR(IF('02 Module Master'!I18=0,0,'02 Module Master'!J18/'02 Module Master'!I18),0)
F32: Marketing Site | G32: =IFERROR(IF('02 Module Master'!I19=0,0,'02 Module Master'!J19/'02 Module Master'!I19),0)
F33: Billing & Credits | G33: =IFERROR(IF('02 Module Master'!I20=0,0,'02 Module Master'!J20/'02 Module Master'!I20),0)
F34: Electron Desktop Overlay | G34: =IFERROR(IF('02 Module Master'!I21=0,0,'02 Module Master'!J21/'02 Module Master'!I21),0)
F35: Security & Platform | G35: =IFERROR(IF('02 Module Master'!I22=0,0,'02 Module Master'!J22/'02 Module Master'!I22),0)

Sheet 02 Module Master
A1: Module Master — Clarify AI (20 core modules)
A2: Module ID | B2: Module Name | C2: Portal | D2: Description | E2: Owner | F2: QA Owner | G2: Priority | H2: Status | I2: Total Features | J2: Completed Features | K2: Pending Features | L2: Est Hours | M2: Actual Hours | N2: Criticality | O2: Dependencies | P2: Remarks
A3: MOD-01 | B3: Auth & Onboarding | C3: Auth Portal | D3: Email/OAuth login, MFA, 5-step onboarding | E3: Auth Lead | F3: Asha Sharma | G3: Critical | H3: In Progress | I3: 8 | J3: 6 | K3: 2 | L3: 20 | M3: 13.2 | N3: Critical | O3: — | P3: Seeded from audit 28 Jul 2026
A4: MOD-02 | B4: Dashboard | C4: Candidate App | D4: Home KPIs, sessions, credits, upcoming interviews | E4: Product | F4: Rohan Mehta | G4: High | H4: Completed | I4: 5 | J4: 5 | K4: 0 | L4: 12.5 | M4: 11 | N4: High | O4: — | P4: Seeded from audit 28 Jul 2026
A5: MOD-03 | B5: Live Practice Coach | C5: Candidate App | D5: Deepgram STT + AI hints/answers + overlay | E5: Live Coach | F5: Priya Nair | G5: Critical | H5: Completed | I5: 10 | J5: 9 | K5: 1 | L5: 25 | M5: 19.8 | N5: Critical | O5: Auth, Billing credits, Deepgram | P5: Seeded from audit 28 Jul 2026
A6: MOD-04 | B6: Mock Interview | C6: Candidate App | D6: Timed mock sessions with AI scoring | E6: Live Coach | F6: Priya Nair | G6: High | H6: In Progress | I6: 7 | J6: 5 | K6: 2 | L6: 17.5 | M6: 11 | N6: High | O6: Sessions, Credits | P6: Seeded from audit 28 Jul 2026
A7: MOD-05 | B7: Sessions & Debriefs | C7: Candidate App | D7: History, detail, AI debrief, scorecard share | E7: Sessions | F7: Priya Nair | G7: High | H7: Completed | I7: 6 | J7: 5 | K7: 1 | L7: 15 | M7: 11 | N7: High | O7: — | P7: Seeded from audit 28 Jul 2026
A8: MOD-06 | B8: Analytics & Usage | C8: Candidate App | D8: Trends, WPM, fillers, credit usage | E8: Analytics | F8: Rohan Mehta | G8: Medium | H8: Completed | I8: 5 | J8: 5 | K8: 0 | L8: 12.5 | M8: 11 | N8: Medium | O8: — | P8: Seeded from audit 28 Jul 2026
A9: MOD-07 | B9: Prep Lab | C9: Candidate App | D9: STAR, rephraser, polish, company Qs | E9: Prep | F9: Asha Sharma | G9: High | H9: Completed | I9: 7 | J9: 7 | K9: 0 | L9: 17.5 | M9: 15.4 | N9: High | O9: — | P9: Seeded from audit 28 Jul 2026
A10: MOD-08 | B10: Documents & Resumes | C10: Candidate App | D10: Upload, parse-resume, gap analysis, OCR | E10: Docs | F10: Priya Nair | G10: High | H10: Completed | I10: 6 | J10: 5 | K10: 1 | L10: 15 | M10: 11 | N10: High | O10: Credits (parse-resume) | P10: Seeded from audit 28 Jul 2026
A11: MOD-09 | B11: Answer Bank | C11: Candidate App | D11: STAR library + AI generate via prep-tool | E11: Prep | F11: Asha Sharma | G11: Medium | H11: In Progress | I11: 4 | J11: 3 | K11: 1 | L11: 10 | M11: 6.6 | N11: Medium | O11: — | P11: Seeded from audit 28 Jul 2026
A12: MOD-10 | B12: Interviews & Calendar | C12: Candidate App | D12: Manual interviews + Google Calendar sync | E12: Scheduling | F12: Rohan Mehta | G12: High | H12: In Progress | I12: 6 | J12: 4 | K12: 2 | L12: 15 | M12: 8.8 | N12: High | O12: — | P12: Seeded from audit 28 Jul 2026
A13: MOD-11 | B13: Company Research | C13: Candidate App | D13: AI company brief + per-user cache | E13: Prep | F13: Asha Sharma | G13: Medium | H13: Completed | I13: 3 | J13: 3 | K13: 0 | L13: 7.5 | M13: 6.6 | N13: Medium | O13: — | P13: Seeded from audit 28 Jul 2026
A14: MOD-12 | B14: Notifications & Profile | C14: Candidate App | D14: Realtime notifications, XP/streak/badges | E14: Growth | F14: Rohan Mehta | G14: Medium | H14: In Progress | I14: 5 | J14: 3 | K14: 2 | L14: 12.5 | M14: 6.6 | N14: Medium | O14: — | P14: Seeded from audit 28 Jul 2026
... A22: MOD-20 | B22: Security & Platform | C22: All Portals | D22: RLS, webhooks, rate limits, CI, observability | E22: Platform | F22: Dev Patel | G22: Critical | H22: In Progress | I22: 8 | J22: 5 | K22: 3 | L22: 20 | M22: 11 | N22: Critical | O22: — | P22: Seeded from audit 28 Jul 2026
A23: TOTAL | I23: =SUM(I3:I22) | J23: =SUM(J3:J22) | K23: =SUM(K3:K22) | L23: =SUM(L3:L22) | M23: =SUM(M3:M22)

Sheet 03 Feature Inventory
A1: Feature Inventory — coverage matrix
A2: Feature ID | B2: Module | C2: Feature Name | D2: Description | E2: Frontend | F2: Backend | G2: Database | H2: API | I2: Edge Function | J2: Status | K2: Implementation Status | L2: QA Status | M2: Priority | N2: Risk | O2: Owner | P2: QA Owner | Q2: Est Hours | R2: Actual Hours | S2: Comments
A3: FEAT-001 | B3: Auth & Onboarding | C3: Email/password login | D3: Login with lockout | E3: Yes | F3: Yes | G3: Yes | H3: Yes | I3: N/A | J3: Completed | K3: Fully Implemented | L3: Passed | M3: Critical | N3: High | O3: Auth Lead | P3: Asha Sharma | Q3: 2 | R3: 1.5 | S3: zodResolver
A4: FEAT-002 | B4: Auth & Onboarding | C4: OAuth providers | D4: Google/GitHub OAuth | E4: Yes | F4: Yes | G4: Yes | H4: Yes | I4: N/A | J4: Completed | K4: Fully Implemented | L4: In Testing | M4: Critical | N4: Medium | O4: Auth Lead | P4: Asha Sharma | Q4: 3 | R4: 2
A5: FEAT-003 | B5: Auth & Onboarding | C5: TOTP MFA | D5: Settings security MFA | E5: Yes | F5: Yes | G5: Yes | H5: Yes | I5: N/A | J5: In Progress | K5: Fully Implemented | L5: Not Tested | M5: High | N5: High | O5: Auth Lead | P5: Asha Sharma | Q5: 4 | R5: 0
A6: FEAT-004 | B6: Live Practice Coach | C6: Deepgram streaming STT | D6: Mic + system audio | E6: Yes | F6: Yes | G6: Yes | H6: Yes | I6: Yes | J6: Completed | K6: Fully Implemented | L6: Passed | M6: Critical | N6: Critical | O6: Live Coach | P6: Priya Nair | Q6: 6 | R6: 5.5 | S6: deepgram-token
A7: FEAT-005 | B7: Live Practice Coach | C7: AI answer generation | D7: generate-answer + credits | E7: Yes | F7: Yes | G7: Yes | H7: Yes | I7: Yes | J7: Completed | K7: Fully Implemented | L7: In Testing | M7: Critical | N7: Critical | O7: Live Coach | P7: Priya Nair | Q7: 5 | R7: 3 | S7: Overlay requires Pro
A8: FEAT-006 | B8: Live Practice Coach | C8: Desktop overlay hotkeys | D8: Central hotkey registry | E8: Yes | F8: N/A | G8: N/A | H8: N/A | I8: N/A | J8: Completed | K8: Fully Implemented | L8: Passed | M8: High | N8: Medium | O8: Desktop | P8: Dev Patel | Q8: 2 | R8: 1.5 | S8: P1-6
A9: FEAT-007 | B9: Billing & Credits | C9: Stripe checkout Pro/Max | D9: create-checkout price IDs | E9: Yes | F9: Yes | G9: Yes | H9: Yes | I9: Yes | J9: Completed | K9: Fully Implemented | L9: In Testing | M9: Critical | N9: Critical | O9: Billing | P9: Asha Sharma | Q9: 5 | R9: 4 | S9: Enterprise IDs wired
A10: FEAT-008 | B10: Billing & Credits | C10: Razorpay INR order | D10: One-time order + webhook | E10: Yes | F10: Yes | G10: Yes | H10: Yes | I10: Yes | J10: In Progress | K10: Partial | L10: Failed | M10: Critical | N10: High | O10: Billing | P10: Asha Sharma | Q10: 4 | R10: 3.5 | S10: No recurring
A11: FEAT-009 | B11: Billing & Credits | C11: Credit ledger deduct | D11: deductCreditsAtomic | E11: Partial | F11: Yes | G11: Yes | H11: Yes | I11: Yes | J11: Completed | K11: Fully Implemented | L11: Passed | M11: Critical | N11: Critical | O11: Billing | P11: Dev Patel | Q11: 3 | R11: 2.5
A12: FEAT-010 | B12: Documents & Resumes | C12: Onboarding free parse | D12: First parse free once | E12: Yes | F12: Yes | G12: Yes | H12: Yes | I12: Yes | J12: Completed | K12: Fully Implemented | L12: Passed | M12: High | N12: High | O12: Docs | P12: Priya Nair | Q12: 3 | R12: 2 | S12: x-clarify-onboarding-parse
A13: FEAT-011 | B13: Documents & Resumes | C13: Gap analysis charge | D13: gap_analysis = 10 credits | E13: Yes | F13: Yes | G13: Yes | H13: Yes | I13: Yes | J13: Completed | K13: Fully Implemented | L13: In Testing | M13: High | N13: Medium | O13: Docs | P13: Priya Nair | Q13: 2.5 | R13: 1
A14: FEAT-012 | B14: Gov Exam Mock Tests | C14: Atomic create/submit | D14: create-test / submit-test | E14: Yes | F14: Yes | G14: Yes | H14: Yes | I14: Yes | J14: Completed | K14: Fully Implemented | L14: Passed | M14: Critical | N14: High | O14: GovExams | P14: Rohan Mehta | Q14: 5 | R14: 4.5 | S14: Thin bank
A15: FEAT-013 | B15: Gov Exam Mock Tests | C15: Admin exam filter | D15: Display string map | E15: Yes | F15: Yes | G15: Yes | H15: N/A | I15: Partial | J15: Completed | K15: Fully Implemented | L15: Passed | M15: High | N15: Medium | O15: Admin | P15: Rohan Mehta | Q15: 2 | R15: 1.5 | S15: P1-5
A16: FEAT-014 | B16: Admin Portal | C16: Revenue USD/INR | D16: Subscriptions + paise | E16: Yes | F16: Yes | G16: Yes | H16: N/A | I16: N/A | J16: Completed | K16: Fully Implemented | L16: Passed | M16: Critical | N16: High | O16: Admin | P16: Rohan Mehta | Q16: 4 | R16: 3 | S16: P0-6
A17: FEAT-015 | B17: Answer Bank | C17: Generate with AI | D17: prep-tool star_method | E17: Yes | F17: Yes | G17: Yes | H17: Yes | I17: Yes | J17: Completed | K17: Fully Implemented | L17: In Testing | M17: Medium | N17: Low | O17: Prep | P17: Asha Sharma | Q17: 3 | R17: 1.5 | S17: P3 wire
A18: FEAT-016 | B18: Interviews & Calendar | C18: Google Calendar sync | D18: sync-calendar Pro gate | E18: Yes | F18: Yes | G18: Yes | H18: Yes | I18: Yes | J18: Blocked | K18: Partial | L18: Blocked | M18: High | N18: Medium | O18: Scheduling | P18: Rohan Mehta | Q18: 4 | R18: 1 | S18: 501 w/o secrets
A19: FEAT-017 | B19: Sessions & Debriefs | C19: Null score display | D19: Not scored vs 0 | E19: Yes | F19: N/A | G19: Yes | H19: N/A | I19: N/A | J19: Completed | K19: Fully Implemented | L19: Passed | M19: Medium | N19: Low | O19: Sessions | P19: Priya Nair | Q19: 1.5 | R19: 1 | S19: P1-7
A20: FEAT-018 | B20: Marketing Site | C20: Pricing Max $79 | D20: enterprise monthlyPrice | E20: Yes | F20: N/A | G20: N/A | H20: N/A | I20: N/A | J20: Completed | K20: Fully Implemented | L20: Passed | M20: High | N20: Low | O20: Growth | P20: Kavya Iyer | Q20: 1 | R20: 0.5 | S20: P2-4
A21: FEAT-019 | B21: Electron Desktop Overlay | C21: Window min size | D21: 360×320 clamp | E21: Yes | F21: N/A | G21: N/A | H21: N/A | I21: N/A | J21: Completed | K21: Fully Implemented | L21: Passed | M21: Medium | N21: Low | O21: Desktop | P21: Dev Patel | Q21: 1.5 | R21: 1 | S21: P1-9
A22: FEAT-020 | B22: Security & Platform | C22: Refund clawback | D22: charge.refunded safe | E22: N/A | F22: Yes | G22: Yes | H22: Yes | I22: Yes | J22: In Progress | K22: Fully Implemented | L22: In Testing | M22: Critical | N22: High | O22: Platform | P22: Dev Patel | Q22: 4 | R22: 2 | S22: P4-2
A23: TOTAL | Q23: =SUM(Q3:Q22) | R23: =SUM(R3:R22)

Sheet 04 Test Case Repository
A1: Test Case Repository — Clarify AI
A2: Test Case ID | B2: Requirement ID | C2: Module | D2: Sub Module | E2: Feature | F2: Screen | G2: User Role | H2: Priority | I2: Severity | J2: Test Scenario | K2: Test Case | L2: Preconditions | M2: Test Steps | N2: Expected Result | O2: Actual Result | P2: Pass/Fail | Q2: Status | R2: Bug ID | S2: Tester | T2: Est Hours | U2: Actual Hours | V2: Execution Date | W2: Build Version | X2: Environment | Y2: Browser | Z2: Device | AA2: Platform | AB2: Automation | AC2: Regression | AD2: Smoke | AE2: Sanity | AF2: Sprint | AG2: Release | AH2: Remarks
A3: TC-001 | B3: REQ-AUTH-01 | C3: Auth & Onboarding | D3: Login | E3: Email login | F3: /login | G3: Free User | H3: Critical | I3: Critical | J3: Valid credentials | K3: User signs in with email/password | L3: Verified account | M3: 1. Open /login 2. Enter credentials 3. Submit | N3: Redirect to /app or onboarding | O3: Landed on dashboard | P3: Pass | Q3: Completed | S3: Asha Sharma | T3: 1 | U3: 0.75 | V3: 46231 | W3: 1.0.0 | X3: Staging | Y3: Chrome | Z3: Desktop | AA3: Web | AB3: Manual | AC3: Yes | AD3: Yes | AE3: Yes | AF3: Sprint 26 | AG3: 1.0.0-beta
A4: TC-002 | B4: REQ-AUTH-02 | C4: Auth & Onboarding | D4: Login | E4: Lockout | F4: /login | G4: Free User | H4: High | I4: High | J4: Repeated failures | K4: Lockout after threshold | L4: Test account | M4: 1. Fail login repeatedly 2. Observe message | N4: Temporary lockout shown | P4: Not Run | Q4: Ready | S4: Asha Sharma | T4: 1.5 | U4: 0 | W4: 1.0.0 | X4: Staging | Y4: Chrome | Z4: Desktop | AA4: Web | AB4: Manual | AC4: Yes | AD4: No | AE4: Yes | AF4: Sprint 26 | AG4: 1.0.0-beta
A5: TC-003 | B5: REQ-LIVE-01 | C5: Live Practice Coach | D5: STT | E5: Deepgram stream | F5: /app/live | G5: Pro User | H5: Critical | I5: Critical | J5: Mic open | K5: Near-real-time transcript | L5: Pro + mic permission | M5: 1. Start live 2. Speak 3. Observe transcript | N5: Segments appear under 2s | O5: OK | P5: Pass | Q5: Completed | S5: Priya Nair | T5: 2 | U5: 1.5 | V5: 46231 | W5: 1.0.0 | X5: Staging | Y5: Electron | Z5: Laptop | AA5: Windows | AB5: Manual | AC5: Yes | AD5: Yes | AE5: No | AF5: Sprint 26 | AG5: 1.0.0-beta
A6: TC-004 | B6: REQ-LIVE-02 | C6: Live Practice Coach | D6: Overlay | E6: Pro gate | F6: /app/live/overlay | G6: Free User | H6: Critical | I6: High | J6: Free overlay blocked | K6: Server rejects overlay capture | L6: Free account | M6: 1. Attempt overlay capture 2. Check response | N6: 403 / upgrade required | O6: 403 returned | P6: Pass | Q6: Completed | R6: BUG-001 | S6: Dev Patel | T6: 1.5 | U6: 1.25 | V6: 46231 | W6: 1.0.0 | X6: Staging | Y6: Electron | Z6: Desktop | AA6: Windows | AB6: Candidate | AC6: Yes | AD6: Yes | AE6: No | AF6: Sprint 26 | AG6: 1.0.0-beta | AH6: Retest after P0-3
A7: TC-005 | B7: REQ-BILL-01 | C7: Billing & Credits | D7: Checkout | E7: Max Stripe price | F7: /pricing | G7: Free User | H7: Critical | I7: Critical | J7: Upgrade Max | K7: Enterprise price id used | L7: Stripe test keys | M7: 1. Select Max 2. Checkout 3. Inspect price | N7: Non-empty enterprise price | O7: OK | P7: Pass | Q7: Completed | S7: Asha Sharma | T7: 2 | U7: 1.5 | V7: 46231 | W7: 1.0.0 | X7: Staging | Y7: Chrome | Z7: Desktop | AA7: Web | AB7: Manual | AC7: Yes | AD7: Yes | AE7: Yes | AF7: Sprint 26 | AG7: 1.0.0-beta | AH7: P0-1
A8: TC-006 | B8: REQ-BILL-02 | C8: Billing & Credits | D8: Webhook | E8: payment_failed | F8: stripe-webhook | G8: Pro User | H8: Critical | I8: Critical | J8: Failed invoice | K8: Wallet not wiped | L8: credits=500 | M8: 1. Simulate invoice.payment_failed 2. Read credits | N8: Credits remain 500 | O8: Unchanged | P8: Pass | Q8: Completed | S8: Dev Patel | T8: 1.5 | U8: 1 | V8: 46231 | W8: 1.0.0 | X8: CI | Y8: N/A | Z8: Desktop | AA8: Web | AB8: Automated | AC8: Yes | AD8: Yes | AE8: No | AF8: Sprint 26 | AG8: 1.0.0-beta | AH8: P0-2
A9: TC-007 | B9: REQ-DOC-01 | C9: Documents & Resumes | D9: Parse | E9: Free onboarding parse | F9: /onboarding | G9: Free User | H9: High | I9: Medium | J9: First parse free | K9: No deduct on first onboarding parse | L9: onboarding_completed=false | M9: 1. Upload resume 2. Check ledger | N9: Free path / no deduct | P9: Not Run | Q9: Ready | S9: Priya Nair | T9: 1.5 | U9: 0 | W9: 1.0.0 | X9: Staging | Y9: Chrome | Z9: Desktop | AA9: Web | AB9: Manual | AC9: Yes | AD9: No | AE9: Yes | AF9: Sprint 26 | AG9: 1.0.0-beta
A10: TC-008 | B10: REQ-GOV-01 | C10: Gov Exam Mock Tests | D10: Submit | E10: Atomic submit | F10: /app/mock-test/session/:id | G10: Free User | H10: Critical | I10: High | J10: Submit answers | K10: Score persisted once | L10: Active test | M10: 1. Answer 2. Submit 3. Open results | N10: Score + breakdown | O10: OK | P10: Pass | Q10: Completed | S10: Rohan Mehta | T10: 2 | U10: 1.75 | V10: 46231 | W10: 1.0.0 | X10: Staging | Y10: Chrome | Z10: Android Phone | AA10: Android | AB10: Manual | AC10: Yes | AD10: Yes | AE10: Yes | AF10: Sprint 26 | AG10: 1.0.0-beta
A11: TC-009 | B11: REQ-ADM-01 | C11: Admin Portal | D11: Revenue | E11: USD vs INR | F11: /app/admin/revenue | G11: Admin | H11: Critical | I11: High | J11: Admin revenue view | K11: Currencies separate | L11: Admin + sample data | M11: 1. Open Revenue 2. Compare hand calc | N11: USD MRR + INR separate | O11: OK | P11: Pass | Q11: Completed | S11: Kavya Iyer | T11: 2.5 | U11: 2 | V11: 46231 | W11: 1.0.0 | X11: Staging | Y11: Chrome | Z11: Desktop | AA11: Web | AB11: Manual | AC11: Yes | AD11: No | AE11: No | AF11: Sprint 26 | AG11: 1.0.0-beta | AH11: P0-6
A12: TC-010 | B12: REQ-APP-01 | C12: Dashboard | D12: Routing | E12: In-app 404 | F12: /app/does-not-exist | G12: Pro User | H12: Medium | I12: Low | J12: Unknown route | K12: NotFound in AppShell | L12: Authenticated | M12: 1. Navigate unknown /app path | N12: In-app NotFound | O12: OK | P12: Pass | Q12: Completed | S12: Asha Sharma | T12: 0.5 | U12: 0.25 | V12: 46231 | W12: 1.0.0 | X12: Staging | Y12: Chrome | Z12: Desktop | AA12: Web | AB12: Manual | AC12: Yes | AD12: Yes | AE12: Yes | AF12: Sprint 26 | AG12: 1.0.0-beta | AH12: P1-4
A13: TC-011 | B13: REQ-LIVE-03 | C13: Live Practice Coach | D13: Credits | E13: Hint deduct | F13: /app/live | G13: Pro User | H13: High | I13: High | J13: Insufficient credits | K13: 402 when wallet low | L13: credits below cost | M13: 1. Drain credits 2. Request hint | N13: 402 + message | O13: In progress | P13: In Progress | Q13: In Progress | S13: Dev Patel | T13: 1.5 | U13: 0.5 | V13: 46231 | W13: 1.0.0 | X13: Staging | Y13: Chrome | Z13: Desktop | AA13: Web | AB13: Candidate | AC13: Yes | AD13: No | AE13: No | AF13: Sprint 26 | AG13: 1.0.0-beta
A14: TC-012 | B14: REQ-SEC-01 | C14: Security & Platform | D14: Authz | E14: Non-admin admin route | F14: /app/admin | G14: Free User | H14: Critical | I14: Critical | J14: Unauthorized admin | K14: Redirect / deny | L14: Non-admin user | M14: 1. Open /app/admin | N14: Denied | O14: Denied | P14: Pass | Q14: Completed | S14: Kavya Iyer | T14: 1 | U14: 0.75 | V14: 46231 | W14: 1.0.0 | X14: Staging | Y14: Chrome | Z14: Desktop | AA14: Web | AB14: Manual | AC14: Yes | AD14: Yes | AE14: Yes | AF14: Sprint 26 | AG14: 1.0.0-beta
A15: TOTAL | T15: =SUM(T3:T14) | U15: =SUM(U3:U14)

Sheet 05 E2E User Flows
A1: End-to-End User Flows — golden paths
A2: Flow ID | B2: Flow Name | C2: Portal | D2: Start Page | E2: End Page | F2: Steps | G2: Expected Outcome | H2: Actual Outcome | I2: Pass | J2: Risk | K2: Dependencies | L2: QA Owner | M2: Est Hours | N2: Actual Hours | O2: Comments
A3: E2E-01 | B3: Signup to Onboarding to Dashboard | C3: Auth Portal | D3: /signup | E3: /app/dashboard | F3: 1. Sign up 2. Verify email 3. Complete 5 steps 4. Land dashboard | G3: Profile + onboarding_completed + starter credits | H3: OK on Staging | I3: Pass | J3: High | K3: Auth, Email | L3: Asha Sharma | M3: 3 | N3: 2.5
A4: E2E-02 | B4: Free to Pro Stripe checkout | C4: Candidate App | D4: /pricing | E4: /app/settings/billing | F4: 1. Choose Pro 2. Stripe Checkout 3. Webhook 4. Open Billing | G4: plan=pro, credits granted, ledger entry | I4: Not Run | J4: Critical | K4: Stripe test keys | L4: Asha Sharma | M4: 4 | N4: 0 | O4: Money path
A5: E2E-03 | B5: Live coach rehearsal | C5: Candidate App | D5: /app/live | E5: /app/sessions/:id | F5: 1. Start 2. Audio 3. Generate answer 4. End 5. Debrief | G5: Session + transcript + debrief | H5: OK | I5: Pass | J5: Critical | K5: Deepgram, Gemini, Credits | L5: Priya Nair | M5: 5 | N5: 4
A6: E2E-04 | B6: Gov exam create to results | C6: Candidate App | D6: /app/mock-test | E6: /app/mock-test/results/:id | F6: 1. Select exam 2. create-test 3. Answer 4. submit 5. Results | G6: Atomic score, no double submit | H6: OK | I6: Pass | J6: High | K6: Question bank | L6: Rohan Mehta | M6: 3.5 | N6: 3 | O6: Thin content
A7: E2E-05 | B7: Admin seed to candidate test | C7: Admin Portal | D7: /app/admin/seed-questions | E7: /app/mock-test | F7: 1. Import questions 2. Candidate creates test | G7: Imported questions available | H7: Blocked | I7: Blocked | J7: High | K7: Admin, Gemini PDF | L7: Rohan Mehta | M7: 4 | N7: 1
A8: E2E-06 | B8: Electron overlay boot | C8: Electron Overlay | D8: Clarify AI.exe | E8: Overlay window | F8: 1. Launch 2. Auth if needed 3. Overlay topmost 4. Hotkey | G8: Overlay-only shell | I8: Not Run | J8: Critical | K8: Code signing deferred | L8: Dev Patel | M8: 3 | N8: 0 | O8: Unsigned beta OK
A9: TOTAL | M9: =SUM(M3:M8) | N9: =SUM(N3:N8)

Sheet 06 Bug Tracker
A1: Bug Tracker
A2: Bug ID | B2: Title | C2: Description | D2: Module | E2: Feature | F2: Environment | G2: Browser | H2: Device | I2: OS | J2: Severity | K2: Priority | L2: Status | M2: Assigned To | N2: Reported By | O2: Found Date | P2: Fixed Date | Q2: Retest Date | R2: Build | S2: Sprint | T2: Root Cause | U2: Resolution | V2: Screenshot Link | W2: Video Link | X2: Comments
A3: BUG-001 | B3: Free user overlay capture allowed | C3: Overlay path succeeded for free before Pro gate | D3: Live Practice Coach | E3: Pro gate overlay | F3: Staging | G3: Electron | H3: Desktop | I3: Windows | J3: High | K3: Critical | L3: Closed | M3: Live Coach | N3: Dev Patel | O3: 46226 | P3: 46230 | Q3: 46231 | R3: 1.0.0 | S3: Sprint 26 | T3: Logic Bug | U3: requirePlan pro on overlay | X3: Retested TC-004
A4: BUG-002 | B4: Razorpay plan does not auto-renew | C4: pro_monthly is one-time Order only | D4: Billing & Credits | E4: Razorpay INR | F4: Production | G4: Chrome | H4: Desktop | I4: Windows | J4: High | K4: High | L4: Open | M4: Billing | N4: Asha Sharma | O4: 46221 | R4: 1.0.0 | S4: Sprint 25 | T4: Design Gap | X4: Roadmap — CHANGELOG
A5: BUG-003 | B5: Google Calendar sync 501 | C5: Missing OAuth secrets in staging | D5: Interviews & Calendar | E5: Google Calendar sync | F5: Staging | G5: Chrome | H5: Laptop | I5: macOS | J5: Medium | K5: High | L5: Blocked | M5: Scheduling | N5: Priya Nair | O5: 46228 | R5: 1.0.0 | S5: Sprint 26 | T5: Config/Env | X5: Need secrets
A6: BUG-004 | B6: Gov exam bank too thin | C6: ~26 seeded MCQs only | D6: Gov Exam Mock Tests | E6: Question bank | F6: Staging | G6: Chrome | H6: Desktop | I6: Windows | J6: Medium | K6: High | L6: Open | M6: GovExams | N6: Kavya Iyer | O6: 46217 | R6: 1.0.0 | S6: Sprint 24 | T6: Design Gap | X6: Content gap
A7: BUG-005 | B7: Unsigned Windows installer | C7: SmartScreen warn; signAndEditExecutable false | D7: Electron Desktop Overlay | E7: Code signing | F7: Production | G7: N/A | H7: Desktop | I7: Windows | J7: Low | K7: Medium | L7: Won't Fix | M7: Desktop | N7: Dev Patel | O7: 46211 | R7: 1.0.0 | S7: Sprint 24 | T7: Config/Env | U7: Deferred pending cert | X7: P4-6
A8: BUG-006 | B8: Admin table overflow on mobile | C8: Users table hard to use under 768px | D8: Admin Portal | E8: Admin users | F8: Staging | G8: Chrome | H8: Android Phone | I8: Android | J8: Low | K8: Low | L8: Open | M8: Admin | N8: Rohan Mehta | O8: 46229 | R8: 1.0.0 | S8: Sprint 26 | T8: UI Regression | V8: https://example.com/shot.png

Sheet 07 UI-UX Testing
A1: UI/UX Testing
A2: Screen | B2: Component | C2: Alignment | D2: Spacing | E2: Responsive | F2: Typography | G2: Icons | H2: Accessibility | I2: Dark Mode | J2: Light Mode | K2: Animation | L2: Pass | M2: Remarks
A3: /pricing | B3: Plan cards | C3: Pass | D3: Pass | E3: Pass | F3: Pass | G3: Pass | H3: Partial | I3: Pass | J3: Pass | K3: Pass | L3: Pass | M3: Max $79
A4: /app/live | B4: Transcript panel | C4: Pass | D4: Pass | E4: Partial | F4: Pass | G4: Pass | H4: Partial | I4: Pass | J4: Pass | K4: Pass | L4: Pass | M4: Electron primary
A5: /app/dashboard | B5: KPI cards | C5: Pass | D5: Pass | E5: Pass | F5: Pass | G5: Pass | H5: Pass | I5: Pass | J5: Pass | K5: Pass | L5: Pass
A6: /app/admin/revenue | B6: USD/INR charts | C6: Pass | D6: Pass | E6: Pass | F6: Pass | G6: Pass | H6: Partial | I6: Pass | J6: Pass | K6: N/A | L6: Pass
A7: /login | B7: Auth form | C7: Pass | D7: Pass | E7: Pass | F7: Pass | G7: Pass | H7: Pass | I7: Pass | J7: Pass | K7: N/A | L7: Pass

Sheet 08 Mobile Responsiveness
A1: Mobile Responsiveness
A2: Screen | B2: Android | C2: iPhone | D2: Tablet | E2: Landscape | F2: Portrait | G2: Small Screen | H2: Medium Screen | I2: Large Screen | J2: Responsive | K2: Pass | L2: Comments
A3: /app/dashboard | B3: Pass | C3: Pass | D3: Pass | E3: Pass | F3: Pass | G3: Pass | H3: Pass | I3: Pass | J3: Yes | K3: Pass | L3: MobileNav partial
A4: /app/mock-test/session | B4: Pass | C4: Pass | D4: Pass | E4: Partial | F4: Pass | G4: Pass | H4: Pass | I4: Pass | J4: Yes | K4: Pass
A5: /pricing | B5: Pass | C5: Pass | D5: Pass | E5: Pass | F5: Pass | G5: Pass | H5: Pass | I5: Pass | J5: Yes | K5: Pass
A6: /app/live | B6: Fail | C6: Fail | D6: Partial | E6: N/A | F6: N/A | G6: Fail | H6: Partial | I6: Pass | J6: Partial | K6: Fail | L6: Desktop-first
A7: /app/admin/users | B7: Partial | C7: Partial | D7: Pass | E7: Pass | F7: Pass | G7: Partial | H7: Pass | I7: Pass | J7: Partial | K7: Partial | L7: Wide tables

Sheet 09 API Testing
A1: API Testing — Supabase Edge Functions
A2: API Name | B2: Method | C2: Endpoint | D2: Authentication | E2: Headers | F2: Request | G2: Expected Response | H2: Actual Response | I2: Status Code | J2: Performance | K2: Security | L2: Pass | M2: Comments
A3: Create Checkout | B3: POST | C3: /functions/v1/create-checkout | D3: Bearer JWT | E3: Authorization, apikey | F3: {"plan":"enterprise"} | G3: Checkout URL | H3: URL ok | I3: 200 | J3: Good | K3: Pass | L3: Pass | M3: Enterprise price
A4: Parse Resume | B4: POST | C4: /functions/v1/parse-resume | D4: Bearer JWT | E4: x-clarify-onboarding-parse | F4: multipart | G4: Parsed JSON | H4: OK | I4: 200 | J4: Acceptable | K4: Pass | L4: Pass | M4: Free once
A5: Generate Answer | B5: POST | C5: /functions/v1/generate-answer | D5: Bearer JWT | E5: Authorization | F5: {"mode":"overlay"} | G5: 403 free overlay | H5: 403 | I5: 403 | J5: Excellent | K5: Pass | L5: Pass | M5: Pro gate
A6: Razorpay Order | B6: POST | C6: /functions/v1/razorpay-create-order | D6: Bearer JWT | E6: Authorization | F6: {"pack":"credits_50"} | G6: order_id | H6: OK | I6: 200 | J6: Good | K6: Pass | L6: Pass | M6: Rate limited
A7: Stripe Webhook | B7: POST | C7: /functions/v1/stripe-webhook | D7: Webhook HMAC | E7: Stripe-Signature | F7: invoice.payment_failed | G7: 200 credits intact | H7: 200 | I7: 200 | J7: Excellent | K7: Pass | L7: Pass | M7: P0-2
A8: Sync Calendar | B8: POST | C8: /functions/v1/sync-calendar | D8: Bearer JWT | E8: Authorization | F8: {} | G8: 501 or events | H8: 501 | I8: 501 | J8: N/A | K8: Pass | L8: Blocked | M8: Secrets

Sheet 10 Database Validation
A1: Database Validation
A2: Table | B2: Columns | C2: Constraints | D2: Relationships | E2: Insert | F2: Update | G2: Delete | H2: Foreign Keys | I2: Indexes | J2: Triggers | K2: Views | L2: Validation Status | M2: Remarks
A3: profiles | B3: id, credits, plan, onboarding_completed, streak_days | C3: PK=auth.users | D3: 1:1 auth.users | E3: Pass | F3: Pass | G3: Pass | H3: Pass | I3: Pass | J3: Partial | K3: N/A | L3: Pass
A4: subscriptions | B4: user_id, plan, status, stripe ids | C4: status checks | D4: profiles | E4: Pass | F4: Pass | G4: Pass | H4: Pass | I4: Pass | J4: N/A | K4: N/A | L4: Pass | M4: MRR source
A5: credit_transactions | B5: user_id, amount, reason | C5: signed amount | D5: profiles | E5: Pass | F5: N/A | G5: N/A | H5: Pass | I5: Pass | J5: N/A | K5: N/A | L5: Pass | M5: Not money
A6: payment_orders | B6: amount_paise, status | C6: incl refunded | D6: profiles | E6: Pass | F6: Pass | G6: N/A | H6: Pass | I6: Pass | J6: N/A | K6: N/A | L6: Pass | M6: INR
A7: sessions | B7: nullable scores | C7: RLS user-owned | D7: answers/debriefs | E7: Pass | F7: Pass | G7: Pass | H7: Pass | I7: Pass | J7: N/A | K7: N/A | L7: Pass | M7: Null≠0
A8: questions / mock_tests | B8: exam_type, options jsonb | C8: RLS | D8: exam bank | E8: Pass | F8: Pass | G8: Pass | H8: Pass | I8: Partial | J8: N/A | K8: N/A | L8: Partial | M8: Thin seed

Sheet 11 Authentication Testing
A1: Authentication Testing
A2: Portal/Role | B2: Login | C2: Signup | D2: Forgot Password | E2: Reset Password | F2: OTP | G2: Email Verification | H2: MFA | I2: Role Permissions | J2: Session | K2: Logout | L2: Unauthorized Access | M2: Status | N2: Remarks
A3: Guest | B3: N/A | C3: Pass | D3: N/A | E3: N/A | F3: N/A | G3: N/A | H3: N/A | I3: Pass | J3: N/A | K3: N/A | L3: Pass | M3: Pass | N3: Public marketing
A4: Free User | B4: Pass | C4: Pass | D4: Pass | E4: Pass | F4: N/A | G4: Pass | H4: Pass | I4: Pass | J4: Pass | K4: Pass | L4: Pass | M4: Pass | N4: Limited live
A5: Pro User | B5: Pass | C5: Pass | D5: Pass | E5: Pass | F5: N/A | G5: Pass | H5: Pass | I5: Pass | J5: Pass | K5: Pass | L5: Pass | M5: Pass | N5: Overlay+calendar
A6: Max User | B6: Pass | C6: Pass | D6: Pass | E6: Pass | F6: N/A | G6: Pass | H6: Pass | I6: Pass | J6: Pass | K6: Pass | L6: Pass | M6: Pass | N6: Priority models
A7: Admin | B7: Pass | C7: N/A | D7: Pass | E7: Pass | F7: N/A | G7: Pass | H7: Pass | I7: Pass | J7: Pass | K7: Pass | L7: Pass | M7: Pass | N7: requireAdmin

Sheet 12 Security Testing
A1: Security Testing (OWASP-style)
A2: Target | B2: SQL Injection | C2: XSS | D2: CSRF | E2: Rate Limiting | F2: Authentication | G2: Authorization | H2: File Upload | I2: Input Validation | J2: Sensitive Data | K2: Headers | L2: Cookies | M2: JWT | N2: Encryption | O2: Status | P2: Remarks
A3: Edge shared utils | B3: Pass | C3: Pass | D3: Pass | E3: Pass | F3: Pass | G3: Pass | H3: N/A | I3: Pass | J3: Pass | K3: Pass | L3: Pass | M3: Pass | N3: Pass | O3: Pass | P3: BYOK removed
A4: parse-document | B4: N/A | C4: N/A | D4: N/A | E4: Pass | F4: Pass | G4: Pass | H4: Pass | I4: Pass | J4: Pass | K4: Pass | L4: N/A | M4: Pass | N4: Pass | O4: Pass | P4: Key in header
A5: stripe-webhook | B5: N/A | C5: N/A | D5: Pass | E5: N/A | F5: Pass | G5: Pass | H5: N/A | I5: Pass | J5: Pass | K5: Pass | L5: N/A | M5: N/A | N5: Pass | O5: Pass | P5: HMAC
A6: Admin bulk_update_users | B6: Pass | C6: N/A | D6: Pass | E6: N/A | F6: Pass | G6: Pass | H6: N/A | I6: Pass | J6: Pass | K6: N/A | L6: N/A | M6: Pass | N6: Pass | O6: Pass | P6: M5
A7: Resume storage | B7: N/A | C7: Pass | D7: Pass | E7: Pass | F7: Pass | G7: Pass | H7: Pass | I7: Pass | J7: Pass | K7: Pass | L7: Pass | M7: Pass | N7: Pass | O7: Pass | P7: Bucket RLS
A8: .env.production history | B8: N/A | C8: N/A | D8: N/A | E8: N/A | F8: N/A | G8: N/A | H8: N/A | I8: N/A | J8: Fail | K8: N/A | L8: N/A | M8: Partial | N8: N/A | O8: Fail | P8: Rotate anon key

Sheet 13 Performance Testing
A1: Performance Testing
A2: Screen | B2: API | C2: Load Time | D2: TTFB | E2: Database Query | F2: Memory | G2: CPU | H2: Network | I2: Optimization Needed | J2: Status
A3: /app/dashboard | B3: profile+sessions | C3: 1200ms | D3: 180ms | E3: 90ms | F3: 85MB | G3: 12% | H3: 220KB | I3: No | J3: Pass
A4: /app/live | B4: generate-answer | C4: 900ms | D4: 200ms | E4: 40ms | F4: 140MB | G4: 28% | H4: 80KB | I4: Partial | J4: Pass
A5: /app/admin/users | B5: paginated users | C5: 2100ms | D5: 320ms | E5: 400ms | F5: 110MB | G5: 18% | H5: 450KB | I5: Yes | J5: Partial
A6: /pricing | B6: billing_settings | C6: 800ms | D6: 150ms | E6: 50ms | F6: 70MB | G6: 8% | H6: 160KB | I6: No | J6: Pass
A7: /app/mock-test/session | B7: select-test-questions | C7: 1500ms | D7: 250ms | E7: 180ms | F7: 95MB | G7: 15% | H7: 300KB | I7: Partial | J7: Pass

Sheet 14 Live Coaching Testing
A1: Domain: Live Coaching & Electron Overlay (replaces Marketplace)
A2: Case ID | B2: STT Stream | C2: Diarization | D2: AI Hint | E2: AI Answer | F2: Credit Deduct | G2: Overlay Window | H2: Hotkeys | I2: Pro Gate | J2: Session Persist | K2: Debrief Link | L2: Electron Boot | M2: Pass | N2: Status | O2: Comments
A3: LC-01 | B3: Pass | C3: Pass | D3: Pass | E3: Pass | F3: Pass | G3: Pass | H3: Pass | I3: Pass | J3: Pass | K3: Pass | L3: Pass | M3: Pass | N3: Completed | O3: Pro happy path
A4: LC-02 | B4: Pass | C4: Pass | D4: Pass | E4: N/A | F4: Pass | G4: N/A | H4: N/A | I4: N/A | J4: Pass | K4: Pass | L4: N/A | M4: Pass | N4: Completed | O4: Web live
A5: LC-03 | B5: Pass | C5: Partial | D5: Fail | E5: Fail | F5: N/A | G5: N/A | H5: N/A | I5: Pass | J5: N/A | K5: N/A | L5: N/A | M5: Fail | N5: In Progress | O5: 402 path TC-011
A6: LC-04 | B6: N/A | C6: N/A | D6: N/A | E6: N/A | F6: N/A | G6: Not Run | H6: Pass | I6: Pass | J6: N/A | K6: N/A | L6: Not Run | M6: Not Run | N6: Ready | O6: Packaged unsigned
A7: LC-05 | B7: Pass | C7: Pass | D7: Pass | E7: Pass | F7: Pass | G7: Pass | H7: Pass | I7: Pass | J7: Pass | K7: Pass | L7: Partial | M7: Pass | N7: Completed | O7: Hotkey no dup

Sheet 15 Gov Exam Mock Testing
A1: Domain: Gov Exam Mock Test Engine (replaces Checkout)
A2: Case ID | B2: Exam Select | C2: Create Test | D2: Question Load | E2: Timer | F2: Answer Save | G2: Submit Atomic | H2: Score Persist | I2: Results UI | J2: Analytics | K2: Admin Filter | L2: PDF Import | M2: Bank Coverage | N2: Pass | O2: Status | P2: Comments
A3: GE-01 | B3: Pass | C3: Pass | D3: Pass | E3: Pass | F3: Pass | G3: Pass | H3: Pass | I3: Pass | J3: Pass | K3: N/A | L3: N/A | M3: Partial | N3: Pass | O3: Completed | P3: Happy path
A4: GE-02 | B4: Pass | C4: Pass | D4: Pass | E4: Pass | F4: Pass | G4: Pass | H4: Pass | I4: Pass | J4: Partial | K4: N/A | L4: N/A | M4: Partial | N4: Pass | O4: Completed | P4: Idempotent submit
A5: GE-03 | B5: Pass | C5: Pass | D5: Partial | E5: Pass | F5: Pass | G5: Pass | H5: Pass | I5: Pass | J5: Pass | K5: N/A | L5: N/A | M5: Fail | N5: Partial | O5: In Progress | P5: Thin bank
A6: GE-04 | B6: N/A | C6: N/A | D6: N/A | E6: N/A | F6: N/A | G6: N/A | H6: N/A | I6: N/A | J6: N/A | K6: Pass | L6: N/A | M6: N/A | N6: Pass | O6: Completed | P6: P1-5 filter
A7: GE-05 | B7: N/A | C7: N/A | D7: N/A | E7: N/A | F7: N/A | G7: N/A | H7: N/A | I7: N/A | J7: N/A | K7: N/A | L7: Blocked | M7: N/A | N7: Blocked | O7: Blocked | P7: Provider quota

Sheet 16 Billing Credits Testing
A1: Domain: Billing, Credits & Subscriptions (replaces Payment)
A2: Case ID | B2: Gateway | C2: Success | D2: Failure | E2: Cancel | F2: Timeout | G2: Webhook | H2: Refund | I2: Partial Refund | J2: Duplicate Payment | K2: Credit Grant | L2: Credit Clawback | M2: Plan Gate | N2: Transaction History | O2: Settlement | P2: Pass | Q2: Status | R2: Comments
A3: BL-01 | B3: Stripe | C3: Pass | D3: Pass | E3: Pass | F3: Not Run | G3: Pass | H3: Not Run | I3: Not Run | J3: Pass | K3: Pass | L3: N/A | M3: Pass | N3: Pass | O3: N/A | P3: Pass | Q3: Completed | R3: Pro monthly
A4: BL-02 | B4: Stripe | C4: Pass | D4: N/A | E4: N/A | F4: N/A | G4: Pass | H4: N/A | I4: N/A | J4: N/A | K4: Pass | L4: N/A | M4: Pass | N4: Pass | O4: N/A | P4: Pass | Q4: Completed | R4: Max price IDs
A5: BL-03 | B5: Stripe | C5: N/A | D5: Pass | E5: N/A | F5: N/A | G5: Pass | H5: N/A | I5: N/A | J5: N/A | K5: N/A | L5: N/A | M5: N/A | N5: Pass | O5: N/A | P5: Pass | Q5: Completed | R5: payment_failed wallet
A6: BL-04 | B6: Razorpay | C6: Pass | D6: Pass | E6: Pass | F6: Not Run | G6: Pass | H6: Not Run | I6: N/A | J6: Pass | K6: Pass | L6: N/A | M6: Partial | N6: Pass | O6: N/A | P6: Pass | Q6: Completed | R6: One-time only
A7: BL-05 | B7: Stripe | C7: N/A | D7: N/A | E7: N/A | F7: N/A | G7: Pass | H7: Not Run | I7: Not Run | J7: N/A | K7: N/A | L7: Not Run | M7: N/A | N7: Pass | O7: N/A | P7: Not Run | Q7: Ready | R7: P4-2 refund
A8: BL-06 | B8: Both | C8: Pass | D8: N/A | E8: N/A | F8: N/A | G8: Pass | H8: N/A | I8: N/A | J8: N/A | K8: Pass | L8: N/A | M8: Pass | N8: Pass | O8: N/A | P8: Pass | Q8: Completed | R8: Settings ledger

Sheet 17 Role Based Testing
A1: Role Based Testing — Clarify plan entitlements
A2: Permission/Feature | B2: Module | C2: Guest | D2: Free User | E2: Pro User | F2: Max User | G2: Admin | H2: Permissions | I2: Status | J2: Expected Summary
A3: Access /app | B3: Auth & Onboarding | C3: No | D3: Yes | E3: Yes | F3: Yes | G3: Yes | H3: Auth required | I3: Pass | J3: Guests → login
A4: Live answer limited | B4: Live Practice Coach | C4: No | D4: Yes | E4: Yes | F4: Yes | G4: Yes | H4: Free limited | I4: Pass | J4: live_rehearsal
A5: Desktop overlay | B5: Live Practice Coach | C5: No | D5: No | E5: Yes | F5: Yes | G5: Yes | H5: Pro+ | I5: Pass | J5: requirePlan pro
A6: Company research | B6: Company Research | C6: No | D6: No | E6: Yes | F6: Yes | G6: Yes | H6: Pro+ | I6: Pass
A7: Calendar sync | B7: Interviews & Calendar | C7: No | D7: No | E7: Yes | F7: Yes | G7: Yes | H7: Pro+ | I7: Pass
A8: Priority models | B8: Billing & Credits | C8: No | D8: No | E8: No | F8: Yes | G8: Yes | H8: Max | I8: Pass
A9: Admin revenue | B9: Admin Portal | C9: No | D9: No | E9: No | F9: No | G9: Yes | H9: admin role | I9: Pass | J9: requireAdmin
A10: Promo CRUD | B10: Admin Portal | C10: No | D10: No | E10: No | F10: No | G10: Yes | H10: admin | I10: Pass
A11: View pricing | B11: Marketing Site | C11: Yes | D11: Yes | E11: Yes | F11: Yes | G11: Yes | H11: Public | I11: Pass

Sheet 18 Regression Testing
A1: Regression Testing
A2: Regression ID | B2: Module | C2: Feature | D2: QA Owner | E2: Executed | F2: Pass | G2: Fail | H2: Blocked | I2: Est Hours | J2: Actual Hours | K2: Remarks
A3: REG-01 | B3: Auth & Onboarding | C3: Login/OAuth/MFA | D3: Asha Sharma | E3: Yes | F3: 4 | G3: 0 | H3: 0 | I3: 4 | J3: 3.5 | K3: Smoke green
A4: REG-02 | B4: Live Practice Coach | C4: STT + answer + overlay | D4: Priya Nair | E4: Yes | F4: 4 | G4: 0 | H4: 0 | I4: 6 | J4: 5 | K4: BUG-001 closed
A5: REG-03 | B5: Billing & Credits | C5: Checkout + webhooks | D5: Asha Sharma | E5: Yes | F5: 5 | G5: 0 | H5: 0 | I5: 5 | J5: 4.5 | K5: Money path
A6: REG-04 | B6: Gov Exam Mock Tests | C6: Create/submit/results | D6: Rohan Mehta | E6: Yes | F6: 3 | G6: 0 | H6: 1 | I6: 4 | J6: 3 | K6: PDF blocked
A7: REG-05 | B7: Admin Portal | C7: Users/revenue/questions | D7: Rohan Mehta | E7: Yes | F7: 4 | G7: 0 | H7: 0 | I7: 4 | J7: 3.5
A8: REG-06 | B8: Electron Desktop Overlay | C8: Boot + hotkeys | D8: Dev Patel | E8: Partial | F8: 2 | G8: 0 | H8: 1 | I8: 3 | J8: 1.5 | K8: Unsigned
A9: TOTAL | F9: =SUM(F3:F8) | G9: =SUM(G3:G8) | H9: =SUM(H3:H8) | I9: =SUM(I3:I8) | J9: =SUM(J3:J8)

Sheet 19 Production Readiness
A1: Production Readiness Checklist
A2: Module | B2: Feature Complete | C2: API Complete | D2: Database Ready | E2: Security Passed | F2: Performance Passed | G2: Responsive | H2: Accessibility | I2: SEO | J2: Monitoring | K2: Logging | L2: Deployment Ready | M2: Backup | N2: Recovery | O2: Documentation | P2: Ready Count | Q2: Total | R2: Readiness % | S2: Status | T2: Remarks
A3: Auth & Onboarding | B3: Yes | C3: Yes | D3: Yes | E3: Yes | F3: Yes | G3: Yes | H3: Yes | I3: Partial | J3: Yes | K3: Yes | L3: Yes | M3: Yes | N3: Yes | O3: Yes | P3: =IFERROR(COUNTIF(B3:O3,"Yes"),0) | Q3: 14 | R3: =IFERROR(IF(Q3=0,0,P3/Q3),0) | S3: =IFERROR(IF(R3>=0.9,"Ready",IF(R3>=0.7,"Conditional","Not Ready")),"Not Ready")
A4: Live Practice Coach | B4: Yes | C4: Yes | D4: Yes | E4: Yes | F4: Yes | G4: Partial | H4: Partial | I4: N/A | J4: Yes | K4: Yes | L4: Yes | M4: Yes | N4: Partial | O4: Yes | P4: =IFERROR(COUNTIF(B4:O4,"Yes"),0) | Q4: 14 | R4: =IFERROR(IF(Q4=0,0,P4/Q4),0) | S4: =IFERROR(IF(R4>=0.9,"Ready",IF(R4>=0.7,"Conditional","Not Ready")),"Not Ready")
A5: Billing & Credits | B5: Yes | C5: Yes | D5: Yes | E5: Yes | F5: Yes | G5: Yes | H5: Partial | I5: N/A | J5: Partial | K5: Yes | L5: Yes | M5: Yes | N5: Partial | O5: Yes | P5: =IFERROR(COUNTIF(B5:O5,"Yes"),0) | Q5: 14 | R5: =IFERROR(IF(Q5=0,0,P5/Q5),0) | S5: =IFERROR(IF(R5>=0.9,"Ready",IF(R5>=0.7,"Conditional","Not Ready")),"Not Ready")
A6: Gov Exam Mock Tests | B6: Partial | C6: Yes | D6: Partial | E6: Yes | F6: Yes | G6: Yes | H6: Partial | I6: Partial | J6: Partial | K6: Yes | L6: Partial | M6: Yes | N6: Partial | O6: Partial | P6: =IFERROR(COUNTIF(B6:O6,"Yes"),0) | Q6: 14 | R6: =IFERROR(IF(Q6=0,0,P6/Q6),0) | S6: =IFERROR(IF(R6>=0.9,"Ready",IF(R6>=0.7,"Conditional","Not Ready")),"Not Ready")
A7: Admin Portal | B7: Partial | C7: Yes | D7: Yes | E7: Yes | F7: Partial | G7: Partial | H7: Partial | I7: N/A | J7: Partial | K7: Yes | L7: Yes | M7: Yes | N7: Partial | O7: Partial | P7: =IFERROR(COUNTIF(B7:O7,"Yes"),0) | Q7: 14 | R7: =IFERROR(IF(Q7=0,0,P7/Q7),0) | S7: =IFERROR(IF(R7>=0.9,"Ready",IF(R7>=0.7,"Conditional","Not Ready")),"Not Ready")
A8: Electron Desktop Overlay | B8: Partial | C8: N/A | D8: N/A | E8: Partial | F8: Yes | G8: N/A | H8: Partial | I8: N/A | J8: Partial | K8: Partial | L8: Partial | M8: Yes | N8: Partial | O8: Partial | P8: =IFERROR(COUNTIF(B8:O8,"Yes"),0) | Q8: 14 | R8: =IFERROR(IF(Q8=0,0,P8/Q8),0) | S8: =IFERROR(IF(R8>=0.9,"Ready",IF(R8>=0.7,"Conditional","Not Ready")),"Not Ready")
A9: Marketing Site | B9: Yes | C9: N/A | D9: Yes | E9: Yes | F9: Yes | G9: Yes | H9: Partial | I9: Yes | J9: Yes | K9: Yes | L9: Yes | M9: Yes | N9: Yes | O9: Yes | P9: =IFERROR(COUNTIF(B9:O9,"Yes"),0) | Q9: 14 | R9: =IFERROR(IF(Q9=0,0,P9/Q9),0) | S9: =IFERROR(IF(R9>=0.9,"Ready",IF(R9>=0.7,"Conditional","Not Ready")),"Not Ready")
A10: Security & Platform | B10: Partial | C10: Yes | D10: Partial | E10: Partial | F10: Yes | G10: N/A | H10: N/A | I10: N/A | J10: Partial | K10: Yes | L10: Yes | M10: Yes | N10: Partial | O10: Yes | P10: =IFERROR(COUNTIF(B10:O10,"Yes"),0) | Q10: 14 | R10: =IFERROR(IF(Q10=0,0,P10/Q10),0) | S10: =IFERROR(IF(R10>=0.9,"Ready",IF(R10>=0.7,"Conditional","Not Ready")),"Not Ready")

Sheet 20 Release Sign-Off
A1: Release Sign-Off
A2: Release Version | B2: Build | C2: Environment | D2: QA Lead | E2: Developer Lead | F2: Product Owner | G2: Passed | H2: Known Issues | I2: Blockers | J2: Risk Level | K2: Deployment Approval | L2: Go/No-Go | M2: Remarks
A3: 1.0.0-beta | B3: 1.0.0 | C3: Staging | D3: Kavya Iyer | E3: Dev Lead | F3: Product | G3: Yes | H3: BUG-002 no Razorpay renew; BUG-004 thin bank; unsigned Electron | I3: Calendar 501 without secrets | J3: Medium | K3: Pending | L3: Conditional Go | M3: Closed beta OK; hold full prod
A4: 1.0.0 | B4: 1.0.0 | C4: Production | D4: Kavya Iyer | E4: Dev Lead | F4: Product | G4: No | H4: See CHANGELOG deferred | I4: Code signing; anon key rotation | J4: High | K4: Pending | L4: No-Go | M4: Await cert + content seed
A5: 1.0.1 | B5: TBD | C5: Staging | D5: Kavya Iyer | E5: Dev Lead | F5: Product | G5: No | J5: Low | K5: Deferred | L5: No-Go | M5: Placeholder

Sheet QA Team
A1: QA Team Roster — Clarify AI
A2: QA Person | B2: Role | C2: Email | D2: Capacity Hrs/Week | E2: Skills Focus | F2: Assigned Cases | G2: Est Hours Assigned | H2: Actual Hours Logged | I2: Utilization % | J2: Status | K2: Remarks
A3: Kavya Iyer | B3: QA Lead | C3: kavya.iyer@clarify.ai | D3: 40 | E3: Sign-off, regression, UAT | F3: =COUNTIF('04 Test Case Repository'!S$3:S$5000,A3) | G3: =SUMIF('04 Test Case Repository'!S$3:S$5000,A3,'04 Test Case Repository'!T$3:T$5000) | H3: =SUMIF('04 Test Case Repository'!S$3:S$5000,A3,'04 Test Case Repository'!U$3:U$5000) | I3: =IFERROR(H3/D3,0) | J3: Active
A4: Asha Sharma | B4: Senior QA | C4: asha.sharma@clarify.ai | D4: 40 | E4: Billing, auth, API | F4: =COUNTIF('04 Test Case Repository'!S$3:S$5000,A4) | G4: =SUMIF('04 Test Case Repository'!S$3:S$5000,A4,'04 Test Case Repository'!T$3:T$5000) | H4: =SUMIF('04 Test Case Repository'!S$3:S$5000,A4,'04 Test Case Repository'!U$3:U$5000) | I4: =IFERROR(H4/D4,0) | J4: Active
A5: Rohan Mehta | B5: QA Engineer | C5: rohan.mehta@clarify.ai | D5: 40 | E5: Gov exams, mobile, admin | F5: =COUNTIF('04 Test Case Repository'!S$3:S$5000,A5) | G5: =SUMIF('04 Test Case Repository'!S$3:S$5000,A5,'04 Test Case Repository'!T$3:T$5000) | H5: =SUMIF('04 Test Case Repository'!S$3:S$5000,A5,'04 Test Case Repository'!U$3:U$5000) | I5: =IFERROR(H5/D5,0) | J5: Active
A6: Priya Nair | B6: QA Engineer | C6: priya.nair@clarify.ai | D6: 40 | E6: Live coach, documents, E2E | F6: =COUNTIF('04 Test Case Repository'!S$3:S$5000,A6) | G6: =SUMIF('04 Test Case Repository'!S$3:S$5000,A6,'04 Test Case Repository'!T$3:T$5000) | H6: =SUMIF('04 Test Case Repository'!S$3:S$5000,A6,'04 Test Case Repository'!U$3:U$5000) | I6: =IFERROR(H6/D6,0) | J6: Active
A7: Dev Patel | B7: SDET | C7: dev.patel@clarify.ai | D7: 40 | E7: Automation, webhooks, Electron | F7: =COUNTIF('04 Test Case Repository'!S$3:S$5000,A7) | G7: =SUMIF('04 Test Case Repository'!S$3:S$5000,A7,'04 Test Case Repository'!T$3:T$5000) | H7: =SUMIF('04 Test Case Repository'!S$3:S$5000,A7,'04 Test Case Repository'!U$3:U$5000) | I7: =IFERROR(H7/D7,0) | J7: Active
A8: TOTAL | D8: =SUM(D3:D7) | F8: =SUM(F3:F7) | G8: =SUM(G3:G7) | H8: =SUM(H3:H7) | I8: =IFERROR(H8/D8,0)

Sheet Daily Log
A1: Daily Progress Log (feeds Dashboard chart)
A2: Date | B2: QA Person | C2: Cases Executed | D2: Passed | E2: Failed | F2: Blocked | G2: Bugs Opened | H2: Bugs Closed | I2: Hours Logged | J2: Remarks
A3: 46225 | B3: Asha Sharma | C3: 8 | D3: 6 | E3: 1 | F3: 0 | G3: 1 | H3: 0 | I3: 4.5 | J3: Sprint 26 execution
A4: 46226 | B4: Priya Nair | C4: 10 | D4: 7 | E4: 0 | F4: 0 | G4: 0 | H4: 0 | I4: 5 | J4: Sprint 26 execution
A5: 46227 | B5: Rohan Mehta | C5: 12 | D5: 8 | E5: 0 | F5: 0 | G5: 1 | H5: 0 | I5: 5.5 | J5: Sprint 26 execution
A6: 46228 | B6: Dev Patel | C6: 14 | D6: 9 | E6: 1 | F6: 0 | G6: 0 | H6: 0 | I6: 6 | J6: Sprint 26 execution
A7: 46229 | B7: Kavya Iyer | C7: 16 | D7: 10 | E7: 0 | F7: 1 | G7: 1 | H7: 1 | I7: 6.5 | J7: Sprint 26 execution
A8: 46230 | B8: Asha Sharma | C8: 18 | D8: 11 | E8: 0 | F8: 0 | G8: 0 | H8: 1 | I8: 7 | J8: Sprint 26 execution
A9: 46231 | B9: Priya Nair | C9: 20 | D9: 12 | E9: 1 | F9: 0 | G9: 1 | H9: 1 | I9: 7.5 | J9: Sprint 26 execution
A10: TOTAL | C10: =SUM(C3:C9) | D10: =SUM(D3:D9) | E10: =SUM(E3:E9) | F10: =SUM(F3:F9) | G10: =SUM(G3:G9) | H10: =SUM(H3:H9) | I10: =SUM(I3:I9)

Sheet Lists
A1: Status | B1: PassFail | C1: Priority | D1: Severity | E1: Environment | F1: Browser | G1: Device | H1: Platform | I1: YesNo | J1: QAStatus | K1: BugStatus | L1: Risk | M1: Criticality | N1: Automation | O1: SecurityResult | P1: ReadyStatus | Q1: Decision | R1: Approval | S1: PerfRating | T1: HttpMethod | U1: StatusCode | V1: AuthType | W1: Sprint | X1: Release | Y1: RootCause | Z1: Modules | AA1: Portals | AB1: Roles | AC1: Testers | AD1: Owners | AE1: ImplStatus | AF1: Coverage | AG1: ModuleStatus
A2: Not Started | B2: Pass | C2: Critical | D2: Critical | E2: Local | F2: Chrome | G2: Desktop | H2: Web | I2: Yes | J2: Not Tested | K2: New | L2: Critical | M2: Critical | N2: Manual | O2: Pass | P2: Ready | Q2: Go | R2: Approved | S2: Excellent | T2: GET | U2: 200 | V2: None | W2: Sprint 24 | X2: 1.0.0-beta | Y2: Logic Bug | Z2: Auth & Onboarding | AA2: Marketing Portal | AB2: Guest | AC2: Kavya Iyer | AD2: Auth Lead | AE2: Fully Implemented | AF2: Yes | AG2: Not Started
A3: In Progress | B3: Fail | C3: High | D3: High | E3: Staging | F3: Edge | G3: Laptop | H3: Windows | I3: No | J3: In Testing | K3: Open | L3: High | M3: High | N3: Automated | O3: Fail | P3: Not Ready | Q3: No-Go | R3: Pending | S3: Good | T3: POST | U3: 201 | V3: Bearer JWT | W3: Sprint 25 | X3: 1.0.0 | Y3: Missing Validation | Z3: Dashboard | AA3: Auth Portal | AB3: Free User | AC3: Asha Sharma | AD3: Product | AE3: Partial | AF3: No | AG3: In Progress
A4: Completed | B4: Blocked | C4: Medium | D4: Medium | E4: Production | F4: Firefox | G4: iPhone | H4: macOS | I4: Partial | J4: Passed | K4: In Progress | L4: Medium | M4: Medium | N4: Candidate | O4: Partial | P4: Conditional | Q4: Conditional Go | R4: Rejected | S4: Acceptable | T4: PUT | U4: 204 | V4: Anon Key | W4: Sprint 26 | X4: 1.0.1 | Y4: Config/Env | Z4: Live Practice Coach | AA4: Candidate App | AB4: Pro User | AC4: Rohan Mehta | AD4: Live Coach | AE4: Stub | AF4: Partial | AG4: Completed
A5: Blocked | B5: Not Run | C5: Low | D5: Low | E5: CI | F5: Safari | G5: Android Phone | H5: Linux | I5: N/A | J5: Failed | K5: Fixed | L5: Low | M5: Low | N5: Partial | O5: Not Tested | P5: Blocked | R5: Deferred | S5: Poor | T5: PATCH | U5: 400 | V5: Service Role | W5: Sprint 27 | X5: 1.1.0 | Y5: Race Condition | Z5: Mock Interview | AA5: Admin Portal | AB5: Max User | AC5: Priya Nair | AD5: Sessions | AE5: Dead Code | AF5: N/A | AG5: Blocked
A6: Deferred | B6: N/A | E6: Electron Dev | F6: Electron | G6: iPad | H6: iOS | J6: Blocked | K6: Retest | O6: N/A | S6: Critical | T6: DELETE | U6: 401 | V6: Webhook HMAC | W6: Hotfix | Y6: UI Regression | Z6: Sessions & Debriefs | AA6: Electron Overlay | AB6: Admin | AC6: Dev Patel | AD6: Analytics | AE6: Not Built | AG6: Deprecated
A7: Ready | B7: In Progress | E7: Electron Packaged | F7: N/A | G7: Android Tablet | H7: Android | J7: Deferred | K7: Closed | T7: OPTIONS | U7: 402 | V7: API Key Header | Y7: API Contract | Z7: Analytics & Usage | AA7: All Portals | AD7: Prep
A8: Complete | K8: Won't Fix | U8: 403 | Y8: DB/RLS | Z8: Prep Lab | AD8: Docs
A9: Active | K9: Duplicate | U9: 404 | Y9: Third-party | Z9: Documents & Resumes | AD9: Scheduling
U10: 409 | Y10: Design Gap | Z10: Answer Bank | AD10: Growth
U11: 429 | Y11: Unknown | Z11: Interviews & Calendar | AD11: GovExams
U12: 500 | Z12: Company Research | AD12: Platform
U13: 501 | Z13: Notifications & Profile | AD13: Admin
Z14: Referrals & Guide | AD14: Billing
Z15: Gov Exam Mock Tests | AD15: Desktop
Z16: Settings | AD16: QA Lead
Z17: Admin Portal | AD17: Dev Lead
Z18: Marketing Site
Z19: Billing & Credits
Z20: Electron Desktop Overlay
Z21: Security & Platform
