Workbook

Sheet 00 Cover & Instructions
A1: Clarify AI — Black-Box Manual QA Workbook
A2: CYCLE 31 AUG 2026 | COMPLETE WITHIN 2 DAYS | 3 TESTERS PRE-ASSIGNED | UPDATE PEACH COLUMNS ONLY
A4: ⚠ CONFIDENTIAL — This workbook contains QA test account passwords for closed-beta testers only. Do not forward outside the QA team. Do not commit to a public repo.
A6: CYCLE
A7: Wave 2 — Retest after 30-08 remediation + live Gov exam proof.
A8: Window: complete within 2 days (31 Aug – 1 Sep 2026, IST). Testers pick their own hours.
A9: App: https://clarify.ai.sltfinanceindia.com
A11: TEAM (3 testers — every case is pre-assigned)
A12: 1. Anushka — Government Exams + live proof, AI Fallback, Practice Coach, Live Overlay, Mock Interview, Documents, Resume/JD, AI Chat, Module smoke, Journey 2, Admin gov ingest/review (TC-ADM-019–024)
A13: 2. Sultana — Billing, Credits, Dashboard, Prep Lab, Sessions, Reports, Analytics, Answer Bank, Learning/Community/Coding, Admin (non-gov), API, Regression, Journeys 1 and 4–5
A14: 3. Venkat — Authentication, Onboarding, Security, Public pages, Settings, Integrations, Scheduler, Accessibility, Responsive / Cross-Browser
A16: ENGINEERING STATUS (as of 31 Aug 2026) — NOT LIVE-PROVEN
... A59: RELEASE: Stay RELEASE BLOCKED until 00d TC-GOV-LIVE-06 (or Full Mock equivalent) produces a real completed paper on the live URL.

Sheet 00a Execution Window
A1: 00a — Execution Window (2 days)
A2: Complete within 2 days (31 Aug – 1 Sep 2026, IST). One row per tester. No day-by-day calendar and no time slots. Update Status as you go. Testers choose their own hours.
A4: Tester | B4: Assigned sheets / work | C4: Window | D4: Cycle start | E4: Cycle end | F4: Location / URL | G4: Status | H4: Section Gate Link | I4: Notes / blockers | J4: Updated By | K4: Updated At
A5: Anushka | B5: 05 Module Smoke; 10 Practice Coach; 11 Live Copilot; 12 Mock Interview; 13 Government Exams; 00d Live Gov Exam Proof; 14 AI Coach; 16 Documents; 17 Resume/JD; 36 AI Fallback; Admin gov TC-ADM-019–024; Journey 2; 00c Gov remediations | C5: Complete within 2 days (31 Aug – 1 Sep 2026, IST) | D5: 2026-08-31 | E5: 2026-09-01 | F5: https://clarify.ai.sltfinanceindia.com | G5: Not Started | H5: See 00b Section Completion Gate
A6: Sultana | B6: 09 Dashboard; 15 Prep Lab; 18 Answer Bank; 20 Sessions; 21 Reports; 22 Analytics; 23 Billing; 24 Credits; 26 Notifications; 28–30 Learning/Community/Coding; 31 Admin (non-gov); 35 API; 37 Regression; Journeys 1, 4–5; 00c credits/sessions remediations | C6: Complete within 2 days (31 Aug – 1 Sep 2026, IST) | D6: 2026-08-31 | E6: 2026-09-01 | F6: https://clarify.ai.sltfinanceindia.com | G6: Not Started | H6: See 00b Section Completion Gate
A7: Venkat | B7: 06 Public Pages; 07 Authentication; 08 Onboarding; 19 Scheduler; 25 Settings; 27 Integrations; 32 Security; 33 Accessibility; 34 Responsive; 00c auth/public/settings remediations | C7: Complete within 2 days (31 Aug – 1 Sep 2026, IST) | D7: 2026-08-31 | E7: 2026-09-01 | F7: https://clarify.ai.sltfinanceindia.com | G7: Not Started | H7: See 00b Section Completion Gate
A10: Testers | C10: Rule
A11: 1. Anushka | C11: P0/P1 first. P2+ if time remains in the same 2-day window.
A12: 2. Sultana
A13: 3. Venkat

Sheet 00b Section Completion Gate
A1: 00b — Section Completion Gate
A2: RULE: Set Section Status to 'ALL FILLED — READY TO CLOSE' ONLY when Ready? = YES. Ready? becomes YES when (a) every test case Pass/Fail is not 'Not Run' and (b) every Actual Result cell is non-empty. Do not close early.
A4: Sheet | B4: Assigned Tester | C4: Total Cases | D4: Not Run (count) | E4: Blank Actual (count) | F4: Ready? | G4: Section Status (select) | H4: Closed By | I4: Closed Date | J4: Notes
A5: 00d Live Gov Exam Proof | B5: Anushka | C5: 24 | D5: =COUNTIF('00d Live Gov Exam Proof'!U5:U28,"Not Run") | E5: =COUNTBLANK('00d Live Gov Exam Proof'!T5:T28) | F5: =IF(AND(D5=0,E5=0),"YES","NO") | G5: Not Started
A6: 05 Module Test Cases | B6: Anushka | C6: 22 | D6: =COUNTIF('05 Module Test Cases'!U5:U26,"Not Run") | E6: =COUNTBLANK('05 Module Test Cases'!T5:T26) | F6: =IF(AND(D6=0,E6=0),"YES","NO") | G6: Not Started
A7: 06 Public Pages | B7: Venkat | C7: 15 | D7: =COUNTIF('06 Public Pages'!U5:U19,"Not Run") | E7: =COUNTBLANK('06 Public Pages'!T5:T19) | F7: =IF(AND(D7=0,E7=0),"YES","NO") | G7: Not Started
A8: 07 Authentication | B8: Venkat | C8: 16 | D8: =COUNTIF('07 Authentication'!U5:U20,"Not Run") | E8: =COUNTBLANK('07 Authentication'!T5:T20) | F8: =IF(AND(D8=0,E8=0),"YES","NO") | G8: Not Started
A9: 08 Onboarding | B9: Venkat | C9: 8 | D9: =COUNTIF('08 Onboarding'!U5:U12,"Not Run") | E9: =COUNTBLANK('08 Onboarding'!T5:T12) | F9: =IF(AND(D9=0,E9=0),"YES","NO") | G9: Not Started
A10: 09 Dashboard | B10: Sultana | C10: 8 | D10: =COUNTIF('09 Dashboard'!U5:U12,"Not Run") | E10: =COUNTBLANK('09 Dashboard'!T5:T12) | F10: =IF(AND(D10=0,E10=0),"YES","NO") | G10: Not Started
A11: 10 Practice Coach | B11: Anushka | C11: 16 | D11: =COUNTIF('10 Practice Coach'!U5:U20,"Not Run") | E11: =COUNTBLANK('10 Practice Coach'!T5:T20) | F11: =IF(AND(D11=0,E11=0),"YES","NO") | G11: Not Started
A12: 11 Live Copilot | B12: Anushka | C12: 5 | D12: =COUNTIF('11 Live Copilot'!U5:U9,"Not Run") | E12: =COUNTBLANK('11 Live Copilot'!T5:T9) | F12: =IF(AND(D12=0,E12=0),"YES","NO") | G12: Not Started
A13: 12 Mock Interview | B13: Anushka | C13: 10 | D13: =COUNTIF('12 Mock Interview'!U5:U14,"Not Run") | E13: =COUNTBLANK('12 Mock Interview'!T5:T14) | F13: =IF(AND(D13=0,E13=0),"YES","NO") | G13: Not Started
A14: 13 Government Exams | B14: Anushka | C14: 25 | D14: =COUNTIF('13 Government Exams'!U5:U29,"Not Run") | E14: =COUNTBLANK('13 Government Exams'!T5:T29) | F14: =IF(AND(D14=0,E14=0),"YES","NO") | G14: Not Started
A15: 14 AI Coach Chatbot | B15: Anushka | C15: 8 | D15: =COUNTIF('14 AI Coach Chatbot'!U5:U12,"Not Run") | E15: =COUNTBLANK('14 AI Coach Chatbot'!T5:T12) | F15: =IF(AND(D15=0,E15=0),"YES","NO") | G15: Not Started
A16: 15 Prep Lab | B16: Sultana | C16: 8 | D16: =COUNTIF('15 Prep Lab'!U5:U12,"Not Run") | E16: =COUNTBLANK('15 Prep Lab'!T5:T12) | F16: =IF(AND(D16=0,E16=0),"YES","NO") | G16: Not Started
A17: 16 Documents | B17: Anushka | C17: 10 | D17: =COUNTIF('16 Documents'!U5:U14,"Not Run") | E17: =COUNTBLANK('16 Documents'!T5:T14) | F17: =IF(AND(D17=0,E17=0),"YES","NO") | G17: Not Started
A18: 17 Resume JD Parsing | B18: Anushka | C18: 4 | D18: =COUNTIF('17 Resume JD Parsing'!U5:U8,"Not Run") | E18: =COUNTBLANK('17 Resume JD Parsing'!T5:T8) | F18: =IF(AND(D18=0,E18=0),"YES","NO") | G18: Not Started
A19: 18 Answer Bank | B19: Sultana | C19: 6 | D19: =COUNTIF('18 Answer Bank'!U5:U10,"Not Run") | E19: =COUNTBLANK('18 Answer Bank'!T5:T10) | F19: =IF(AND(D19=0,E19=0),"YES","NO") | G19: Not Started
A20: 19 Interview Scheduler | B20: Venkat | C20: 5 | D20: =COUNTIF('19 Interview Scheduler'!U5:U9,"Not Run") | E20: =COUNTBLANK('19 Interview Scheduler'!T5:T9) | F20: =IF(AND(D20=0,E20=0),"YES","NO") | G20: Not Started
A21: 20 Sessions | B21: Sultana | C21: 5 | D21: =COUNTIF('20 Sessions'!U5:U9,"Not Run") | E21: =COUNTBLANK('20 Sessions'!T5:T9) | F21: =IF(AND(D21=0,E21=0),"YES","NO") | G21: Not Started
A22: 21 Reports | B22: Sultana | C22: 5 | D22: =COUNTIF('21 Reports'!U5:U9,"Not Run") | E22: =COUNTBLANK('21 Reports'!T5:T9) | F22: =IF(AND(D22=0,E22=0),"YES","NO") | G22: Not Started
A23: 22 Analytics | B23: Sultana | C23: 4 | D23: =COUNTIF('22 Analytics'!U5:U8,"Not Run") | E23: =COUNTBLANK('22 Analytics'!T5:T8) | F23: =IF(AND(D23=0,E23=0),"YES","NO") | G23: Not Started
A24: 23 Billing | B24: Sultana | C24: 8 | D24: =COUNTIF('23 Billing'!U5:U12,"Not Run") | E24: =COUNTBLANK('23 Billing'!T5:T12) | F24: =IF(AND(D24=0,E24=0),"YES","NO") | G24: Not Started
A25: 24 Credits | B25: Sultana | C25: 6 | D25: =COUNTIF('24 Credits'!U5:U10,"Not Run") | E25: =COUNTBLANK('24 Credits'!T5:T10) | F25: =IF(AND(D25=0,E25=0),"YES","NO") | G25: Not Started
A26: 25 Settings | B26: Venkat | C26: 15 | D26: =COUNTIF('25 Settings'!U5:U19,"Not Run") | E26: =COUNTBLANK('25 Settings'!T5:T19) | F26: =IF(AND(D26=0,E26=0),"YES","NO") | G26: Not Started
A27: 26 Notifications | B27: Sultana | C27: 4 | D27: =COUNTIF('26 Notifications'!U5:U8,"Not Run") | E27: =COUNTBLANK('26 Notifications'!T5:T8) | F27: =IF(AND(D27=0,E27=0),"YES","NO") | G27: Not Started
A28: 27 Integrations | B28: Venkat | C28: 5 | D28: =COUNTIF('27 Integrations'!U5:U9,"Not Run") | E28: =COUNTBLANK('27 Integrations'!T5:T9) | F28: =IF(AND(D28=0,E28=0),"YES","NO") | G28: Not Started
A29: 28 Learning Hub | B29: Sultana | C29: 3 | D29: =COUNTIF('28 Learning Hub'!U5:U7,"Not Run") | E29: =COUNTBLANK('28 Learning Hub'!T5:T7) | F29: =IF(AND(D29=0,E29=0),"YES","NO") | G29: Not Started
A30: 29 Community | B30: Sultana | C30: 4 | D30: =COUNTIF('29 Community'!U5:U8,"Not Run") | E30: =COUNTBLANK('29 Community'!T5:T8) | F30: =IF(AND(D30=0,E30=0),"YES","NO") | G30: Not Started
A31: 30 Coding Lab | B31: Sultana | C31: 5 | D31: =COUNTIF('30 Coding Lab'!U5:U9,"Not Run") | E31: =COUNTBLANK('30 Coding Lab'!T5:T9) | F31: =IF(AND(D31=0,E31=0),"YES","NO") | G31: Not Started
A32: 31 Admin Portal | B32: Sultana | C32: 28 | D32: =COUNTIF('31 Admin Portal'!U5:U32,"Not Run") | E32: =COUNTBLANK('31 Admin Portal'!T5:T32) | F32: =IF(AND(D32=0,E32=0),"YES","NO") | G32: Not Started
A33: 32 Security | B33: Venkat | C33: 6 | D33: =COUNTIF('32 Security'!U5:U10,"Not Run") | E33: =COUNTBLANK('32 Security'!T5:T10) | F33: =IF(AND(D33=0,E33=0),"YES","NO") | G33: Not Started
A34: 33 Accessibility | B34: Venkat | C34: 5 | D34: =COUNTIF('33 Accessibility'!U5:U9,"Not Run") | E34: =COUNTBLANK('33 Accessibility'!T5:T9) | F34: =IF(AND(D34=0,E34=0),"YES","NO") | G34: Not Started
A35: 34 Responsive Cross-Browser | B35: Venkat | C35: 11 | D35: =COUNTIF('34 Responsive Cross-Browser'!U5:U15,"Not Run") | E35: =COUNTBLANK('34 Responsive Cross-Browser'!T5:T15) | F35: =IF(AND(D35=0,E35=0),"YES","NO") | G35: Not Started
A36: 35 API Network Observation | B36: Sultana | C36: 6 | D36: =COUNTIF('35 API Network Observation'!U5:U10,"Not Run") | E36: =COUNTBLANK('35 API Network Observation'!T5:T10) | F36: =IF(AND(D36=0,E36=0),"YES","NO") | G36: Not Started
A37: 36 AI Fallback | B37: Anushka | C37: 5 | D37: =COUNTIF('36 AI Fallback'!U5:U9,"Not Run") | E37: =COUNTBLANK('36 AI Fallback'!T5:T9) | F37: =IF(AND(D37=0,E37=0),"YES","NO") | G37: Not Started
A38: 37 Regression | B38: Sultana | C38: 15 | D38: =COUNTIF('37 Regression'!U5:U19,"Not Run") | E38: =COUNTBLANK('37 Regression'!T5:T19) | F38: =IF(AND(D38=0,E38=0),"YES","NO") | G38: Not Started
A39: 38 Cross-Module Journeys | B39: Sultana | C39: 5 | D39: =COUNTIF('38 Cross-Module Journeys'!U5:U9,"Not Run") | E39: =COUNTBLANK('38 Cross-Module Journeys'!T5:T9) | F39: =IF(AND(D39=0,E39=0),"YES","NO") | G39: Not Started
A41: TEAM ROLL-UP
A42: Sections Ready (YES count) | B42: =COUNTIF(F5:F39,"YES")
A43: Sections marked ALL FILLED | B43: =COUNTIF(G5:G39,"ALL FILLED — READY TO CLOSE")
A44: Invalid ALL FILLED (Ready=NO) | B44: =COUNTIFS(G5:G39,"ALL FILLED — READY TO CLOSE",F5:F39,"NO")

Sheet 00c Retest Wave
A1: 00c — Retest Wave (31 Aug 2026)
A2: Retest engineering remediations from qa-evidence/30-08-2026-remediation.md. Opening a page is NOT Pass. Undeployed backend = Blocked + blocker code, not Fail.
A4: Test Case ID | B4: Module | C4: Tester | D4: Priority | E4: Previous result (if known) | F4: Fix claimed by eng | G4: Live proof required? | H4: Runnable now? (Yes / Blocked) | I4: Blocker | J4: Pass / Fail | K4: Actual Result | L4: Defect ID | M4: Evidence | N4: Notes
A5: TC-GOV-007 | B5: Government Exams | C5: Anushka | D5: P0 | E5: Fail / Blocked (poll + charge-before-paper) | F5: JOB_POLL backoff; reserve credits until paper exists | G5: Yes | H5: Blocked | I5: BLK-EDGE / BLK-PY / BLK-MIG until live paper exists | J5: Not Run | N5: Full Mock generate. If 404/timeout mark Blocked not Fail.
A6: TC-GOV-008 | B6: Government Exams | C6: Anushka | D6: P0 | E6: Fail / Blocked | F6: Custom Practice via unified factory; count not Full Mock clamp | G6: Yes — P0 release gate | H6: Blocked | I6: BLK-EDGE / BLK-PY / BLK-MIG | J6: Not Run | N6: Must produce a completed Custom Practice paper for GO.
A7: TC-GOV-010 | B7: Government Exams | C7: Anushka | D7: P0 | E7: Fail (refresh trap / bootstrap) | F7: Gov browse during recovery; truthful restore after refresh | G7: Yes | H7: Yes (hub/search); generate path maybe Blocked | I7: BLK-EDGE if still Generating forever | J7: Not Run | N7: DEF-013 / bootstrap: hub must not infinite-search.
A8: TC-GOV-011 | B8: Government Exams | C8: Anushka | D8: P0 | E8: Fail (no Retry / false insufficient credits) | F8: Retry UI; new idempotency only after terminal fail | G8: Yes | H8: Blocked | I8: BLK-EDGE / BLK-PY | J8: Not Run | N8: Retry must not claim insufficient credits if balance remains.
A9: TC-GOV-012 | B9: Government Exams | C9: Anushka | D9: P0 | E9: Not proven live | F9: AI fill Realistic/Custom only; Official fail-closed | G9: Yes | H9: Blocked | I9: BLK-PY / BLK-CFG (AI-down scenario needs QA-lead flag) | J9: Not Run | N9: Official must never be AI-labeled.
A10: TC-GOV-015 | B10: Government Exams | C10: Anushka | D10: P0 | E10: Blocked (no live paper) | F10: Server started_at / expires_at via start-exam | G10: Yes | H10: Blocked | I10: BLK-EDGE (start-exam 404 until deploy) | J10: Not Run | N10: Client must not forever-extend the clock.
A11: TC-GOV-016 | B11: Government Exams | C11: Anushka | D11: P0 | E11: Blocked | F11: Palette states restored from test_responses | G11: Yes | H11: Blocked | I11: BLK-EDGE / BLK-PY | J11: Not Run | N11: Unanswered / answered / marked / answered+marked.
A12: TC-GOV-017 | B12: Government Exams | C12: Anushka | D12: P0 | E12: Blocked | F12: Versioned autosave; stale skip; ATTEMPT_EXPIRED | G12: Yes | H12: Blocked | I12: BLK-EDGE (save-test-answer) | J12: Not Run | N12: Navigate + refresh must restore or warn honestly.
A13: TC-GOV-018 | B13: Government Exams | C13: Anushka | D13: P0 | E13: Blocked | F13: submit-test duplicate replay; no silent rescore | G13: Yes | H13: Blocked | I13: BLK-EDGE / BLK-PY | J13: Not Run | N13: Partial submit warning + stable result.
A14: TC-GOV-019 | B14: Government Exams | C14: Anushka | D14: P0 | E14: Blocked | F14: Results persist on mock_tests + history routes | G14: Yes | H14: Blocked | I14: BLK-EDGE / BLK-PY | J14: Not Run | N14: Logout/login must still show owner result.
A15: TC-GOV-020 | B15: Government Exams | C15: Anushka | D15: P0 | E15: Fail (charge before paper) | F15: reserve → finalize on completed; release on fail/cancel | G15: Yes | H15: Blocked | I15: BLK-MIG / BLK-EDGE | J15: Not Run | N15: Failed generate must not keep reserved credits.
A16: TC-GOV-024 | B16: Government Exams | C16: Anushka | D16: P1 | E16: Fail (duplicate Generate) | F16: Idempotency key; 409 replay no second reservation | G16: Yes | H16: Blocked | I16: BLK-EDGE / BLK-MIG | J16: Not Run | N16: Double-click Generate = one job.
... A18: TC-API-005 | B18: API / Network Observation | C18: Anushka | D18: P0 | E18: Fail (429 drops in-flight job) | F18: 429/5xx stay in-flight; 8 transient retries | G18: Yes | H18: Blocked | I18: BLK-EDGE | J18: Not Run | N18: Do not Fail a 429 that recovers.
A19: DEF-013 / TC-GOV-010 | B19: Government Exams | C19: Anushka | D19: P0 | E19: Fail (bootstrap trap / infinite Searching…) | F19: Gov browse during onboarding recovery; search abort/latest-wins | G19: Partial — hub is user-visible today | H19: Yes | J19: Not Run | N19: DEF-001 related. Hub must not infinite spinner.
A20: TC-ADM-022 | B20: Admin Portal | C20: Anushka | D20: P1 | E20: Fail (topic Apply-only + dual empty) | F20: Live debounce + one empty card | G20: No (admin UI) | H20: Yes | J20: Not Run | N20: Question review: one empty state, Apply live.
A21: TC-MOD-SMOKE-GOV | B21: Module Smoke | C21: Anushka | D21: P0 | E21: Fail — infinite search spinner on /app/mock-test | F21: Search debounce/abort; profile recovery browse | G21: No | H21: Yes | J21: Not Run | N21: Re-run module smoke on Gov hub. Opening hub ≠ Pass.
A22: TC-PREP-COACH-CREDITS | B22: Practice Coach | C22: Anushka | D22: P1 | E22: prep-tool 401/unknown looked like no credits | F22: JWT via fetchEdge; credit-first; raw_prompt alias | G22: No | H22: Yes | I22: BLK-EDGE if prep-tool 404 | J22: Not Run | N22: Coach/docs surface must not say insufficient credits on 401.
A23: TC-SES-002 | B23: Sessions | C23: Sultana | D23: P0 | E23: Fail (session detail 500) | F23: get_owned_session_detail owner RPC; Not scored empty | G23: Yes if migration unapplied | H23: Yes | I23: BLK-MIG if 500 persists | J23: Not Run | N23: Must show transcript/score OR honest empty — never 500.
A24: TC-CR-003 | B24: Credits | C24: Sultana | D24: P0 | E24: Fail (zero-credit 400 unknown tool) | F24: 402 before tool_id; raw_prompt alias | G24: No | H24: Yes | J24: Not Run | N24: ZERO_CREDIT_01. Block must be credits, not unknown tool.
A25: TC-CR-004 | B25: Credits | C25: Sultana | D25: P1 | E25: Fail (past-due reused as low-credit) | F25: Separate qa.lowcredit@ fixture | G25: No | H25: Yes | I25: BLK-CRED if qa.lowcredit@ missing | J25: Not Run | N25: Use LOW_CREDIT_01 only — not past-due.
A26: TC-CR-005 | B26: Credits | C26: Sultana | D26: P1 | E26: Fail (wrong fixture) | F26: qa.exactcredit@ exact-boundary | G26: No | H26: Yes | I26: BLK-CRED if qa.exactcredit@ missing | J26: Not Run | N26: Use EXACT_CREDIT_01.
A27: TC-BILL-007 | B27: Billing | C27: Sultana | D27: P1 | E27: N/A / not run | F27: BillingHistory refund filter from ledger | G27: No | H27: Yes | I27: BLK-CFG if no refund rows in sandbox | J27: Not Run | N27: Honest empty refund list is Pass if product has no refunds.
A28: TC-PREP-003 | B28: Prep Lab | C28: Sultana | D28: P1 | E28: Fail (prep-tool 401/unknown) | F28: JWT fetchEdge; credit-first | G28: No | H28: Yes | I28: BLK-EDGE if function 404 | J28: Not Run | N28: Unknown/401 must not look like no credits.
A29: DOCX-30-001/002 | B29: Credits | C29: Sultana | D29: P2 | E29: Fail (Help catalog drift) | F29: Help fallback from creditEconomics | G29: No | H29: Yes | J29: Not Run | N29: Help copy for free plan / extra credits matches product.
A30: TC-AUTH-008 | B30: Authentication | C30: Venkat | D30: P0 | E30: Fail (raw email_not_confirmed) | F30: formatSupabaseAuthError on login + OAuth | G30: No | H30: Yes | J30: Not Run | N30: Human-readable verify-email copy, not raw error code.
A31: TC-AUTH-014 | B31: Authentication | C31: Venkat | D31: P0 | E31: Fail (broken Google CTA) | F31: Hide CTA when isOAuthProviderEnabled is false | G31: No | H31: Yes | I31: BLK-CFG if Google enabled but 400 | J31: Not Run | N31: Visible dead Google button = Fail. Hidden = Pass.
A32: TC-AUTH-015 | B32: Authentication | C32: Venkat | D32: P1 | E32: Fail (MFA paused) | F32: MFA_ENFORCEMENT_PAUSED = false | G32: No | H32: Yes | J32: Not Run | N32: Security/MFA controls visible and consistent.
A33: TC-ONB-002 | B33: Onboarding | C33: Venkat | D33: P0 | E33: Fail (no fixture) | F33: Seed qa.onboarding@ | G33: No | H33: Yes | I33: BLK-CRED if NEW_USER_01 missing | J33: Not Run | N33: Use NEW_USER_01 / qa.onboarding@.
A34: TC-ONB-004 | B34: Onboarding | C34: Venkat | D34: P0 | E34: Fail (popstate / step lost) | F34: Persist onboarding_step on Next/Back | G34: No | H34: Yes | J34: Not Run | N34: Browser Back must restore step.
A35: TC-ONB-005 | B35: Onboarding | C35: Venkat | D35: P1 | E35: Fail | F35: onboarding_step persist | G35: No | H35: Yes | J35: Not Run | N35: Refresh mid-wizard restores step.
A36: TC-ONB-006 | B36: Onboarding | C36: Venkat | D36: P1 | E36: Fail | F36: onboarding_step persist | G36: No | H36: Yes | J36: Not Run | N36: Next/Back do not skip required fields.
A37: TC-ONB-007 | B37: Onboarding | C37: Venkat | D37: P1 | E37: Fail | F37: onboarding_step persist | G37: No | H37: Yes | J37: Not Run | N37: Complete onboarding lands in app.
A38: TC-AUTH-010 / D-012 | B38: Authentication | C38: Venkat | D38: P1 | E38: Fail (reset width + inbox copy) | F38: AuthShell max-w-md; spam/wait copy | G38: No | H38: Yes | J38: Not Run | N38: Reset form readable; copy mentions spam/wait.
A39: TC-SET-015 | B39: Settings | C39: Venkat | D39: P0 | E39: Fail (delete 429 on retry) | F39: Skip rate limit when existingOp exists | G39: No | H39: Yes | J39: Not Run | N39: DISPOSABLE_01 only. Re-seed after.
A40: TC-SCH-002 | B40: Interview Scheduler | C40: Venkat | D40: P1 | E40: Fail (local Date parse) | F40: IANA zonedWallTimeToUtc + Zod schema | G40: No | H40: Yes | J40: Not Run | N40: Edit/reschedule keeps intended IST wall time.
A41: TC-SCH-003 | B41: Interview Scheduler | C41: Venkat | D41: P1 | E41: Fail (timezone) | F41: IANA timezone validation | G41: No | H41: Yes | J41: Not Run | N41: Invalid date/timezone blocked with validation.
A42: TC-SCH-004 | B42: Interview Scheduler | C42: Venkat | D42: P1 | E42: Fail (Calendar Connect 501) | F42: Disabled Not configured when probe 501 | G42: No | H42: Yes | I42: BLK-CFG if Calendar later enabled | J42: Not Run | N42: Visible dead Connect = Fail. Not configured = Pass.
A43: TC-SCH-005 | B43: Interview Scheduler | C43: Venkat | D43: P2 | E43: Fail (reminder email silent) | F43: Honest email not configured when Resend missing | G43: No | H43: Yes | I43: BLK-CFG | J43: Not Run | N43: Do not Pass a silent missing email.
A44: TC-SET-010 | B44: Settings | C44: Venkat | D44: P1 | E44: Fail / Partial (integrations 501) | F44: Integrations list + Not configured | G44: No | H44: Yes | I44: BLK-CFG | J44: Not Run | N44: List can load; dead Connect is Fail.
A45: TC-PUB-004 | B45: Public Pages | C45: Venkat | D45: P1 | E45: Fail (FAB vs Login overlap) | F45: Marketing FAB bottom-20 md:bottom-6 | G45: No | H45: Yes | J45: Not Run | N45: Help/status FAB must not cover Login on mobile.
A46: TC-PUB-014 | B46: Public Pages | C46: Venkat | D46: P2 | E46: Fail (Contact Sales dead) | F46: Existing mailto in MarketingLayout | G46: No | H46: Yes | J46: Not Run | N46: Contact Sales must be mailto or working form.
A47: D-013 / TC-RSP-006/007 | B47: Responsive / Cross-Browser | C47: Venkat | D47: P1 | E47: Fail (blank band / PublicErrorState) | F47: Centered PublicErrorState + VerifyCertificate | G47: No | H47: Yes | J47: Not Run | N47: 360×800 and 1440. No blank band. Verify certificate error centered.
A48: DOCX-30-003 | B48: Accessibility | C48: Venkat | D48: P2 | E48: Fail (duplicate icons) | F48: Overlay GripVertical; Dashboard Coins vs TopBar Zap unique aria-labels | G48: No | H48: Yes | J48: Not Run | N48: Icons must not share the same accessible name.

Sheet 00d Live Gov Exam Proof
A1: 00d Live Gov Exam Proof
A2: PRE-FILLED for you. ONLY update peach columns: Actual Result | Pass/Fail | Defect ID | Execution Date | Notes. Tester is pre-assigned (Anushka / Sultana / Venkat). Complete assigned work within 2 days. Mark section ALL FILLED on '00b Section Completion Gate' ONLY when every case has Pass/Fail ≠ Not Run AND Actual Result filled. Black-box only — no source/DB/server access. Opening a page is NOT Pass.
A4: Test Case ID | B4: Module | C4: Sub-Module | D4: Feature | E4: Workflow | F4: Priority | G4: Severity | H4: Test Type | I4: User Type | J4: Role | K4: Account ID | L4: Preconditions | M4: Test Environment | N4: Test Data | O4: Exact Steps | P4: Expected Result (per step) | Q4: Final Expected Result | R4: Validation Points | S4: Screenshot / Evidence Requirement | T4: Actual Result | U4: Pass / Fail | V4: Defect ID | W4: Tester | X4: Execution Date | Y4: Notes
A5: TC-GOV-LIVE-01 | B5: Government Exams | C5: Live proof | D5: Hub loads, no infinite Searching… | E5: Hub loads, no infinite Searching… | F5: P0 | G5: Critical | H5: Positive | I5: Authenticated | J5: user | K5: PRO_USER_01 | L5: Logged in. App URL available. Browser DevTools permitted. | M5: Closed Beta / QA Target | N5: Use approved test credentials from Test Accounts sheet. | O5: 1. Login PRO_USER_01. 2. Open https://clarify.ai.sltfinanceindia.com/app/mock-test. 3. Wait ≤15s. 4. Type a letter in search; confirm spinner ends. | P5: 1. Auth ok. 2. Hub renders. 3. No infinite spinner/blank. 4. Search idle or results — not stuck Searching… | Q5: Gov hub is usable without infinite search. | R5: Observable UI state matches expected results; no unexplained spinner; no silent failure; persistence verified via refresh where applicable. | S5: Screenshot of final state. On fail: URL, visible error, Network status if DevTools allowed. | U5: Not Run | W5: Anushka | Y5: Runnable now. DEF-001 retest.
A6: TC-GOV-LIVE-02 | B6: Government Exams | C6: Live proof | D6: Search valid exam (SSC/IBPS/UPSC alias) | E6: Search valid exam (SSC/IBPS/UPSC alias) | F6: P0 | G6: Critical | H6: Positive | I6: Authenticated | J6: user | K6: PRO_USER_01 | L6: Logged in. App URL available. Browser DevTools permitted. | M6: Closed Beta / QA Target | N6: Use approved test credentials from Test Accounts sheet. | O6: 1. Search a known exam/alias (SSC, IBPS, UPSC if listed). 2. Select a result. 3. Open exam detail. | P6: 1. Suggestions appear (latest-wins; no stale overwrite). 2. Selection sticks. 3. Detail loads. | Q6: Valid exam search returns a selectable exam. | R6: Observable UI state matches expected results; no unexplained spinner; no silent failure; persistence verified via refresh where applicable. | S6: Screenshot of final state. On fail: URL, visible error, Network status if DevTools allowed. | U6: Not Run | W6: Anushka
A7: TC-GOV-LIVE-04 | B7: Government Exams | C7: Live proof | D7: Detail + pattern + syllabus | E7: Detail + pattern + syllabus | F7: P0 | G7: Critical | H7: Positive | I7: Authenticated | J7: user | K7: PRO_USER_01 | L7: Logged in. App URL available. Browser DevTools permitted. | M7: Closed Beta / QA Target | N7: Use approved test credentials from Test Accounts sheet. | O7: 1. Open exam detail. 2. Confirm pattern (sections/marks) visible. 3. Confirm syllabus OR honest SYLLABUS_NOT_AVAILABLE (no charge). | P7: 1. Detail loads. 2. Pattern shown. 3. Syllabus present or honest unavailable — not a silent charge. | Q7: Pattern/syllabus are honest. | R7: Observable UI state matches expected results; no unexplained spinner; no silent failure; persistence verified via refresh where applicable. | S7: Screenshot of final state. On fail: URL, visible error, Network status if DevTools allowed. | U7: Not Run | W7: Anushka
A8: TC-GOV-LIVE-05 | B8: Government Exams | C8: Live proof | D8: Review availability == Generate availability | E8: Review availability == Generate availability | F8: P0 | G8: Critical | H8: Positive | I8: Authenticated | J8: user | K8: PRO_USER_01 | L8: Logged in. App URL available. Browser DevTools permitted. | M8: Closed Beta / QA Target | N8: Use approved test credentials from Test Accounts sheet. | O8: 1. Record available count on Review. 2. Open Generate for same config. 3. Compare numbers. | P8: 1. Review number recorded. 2. Generate loads. 3. Same available count. Disagree = Fail. | Q8: Review and Generate share one availability snapshot. | R8: Observable UI state matches expected results; no unexplained spinner; no silent failure; persistence verified via refresh where applicable. | S8: Screenshot of final state. On fail: URL, visible error, Network status if DevTools allowed. | U8: Not Run | W8: Anushka | Y8: If Edge 404 / Python worker down / migrations missing: Pass/Fail = Blocked with BLK-EDGE, BLK-PY, or BLK-MIG. Do not Fail undeployed stack.
A9: TC-GOV-LIVE-06 | B9: Government Exams | C9: Live proof | D9: Custom Practice generate → completed paper | E9: Custom Practice generate → completed paper | F9: P0 | G9: Critical | H9: Positive | I9: Authenticated | J9: user | K9: SUFFICIENT_CREDIT_01 | L9: Logged in. App URL available. Browser DevTools permitted. | M9: Closed Beta / QA Target | N9: Use approved test credentials from Test Accounts sheet. | O9: 1. Note credits. 2. Custom Practice within min/max. 3. Generate once. 4. Wait until completed with mock_test_id. 5. Start Exam. | P9: 1. Balance recorded. 2. Config accepted. 3. Progress shown. 4. Terminal completed (not infinite Generating). 5. Runner opens. | Q9: P0 release gate: a real Custom Practice paper exists on the live URL. | R9: Observable UI state matches expected results; no unexplained spinner; no silent failure; persistence verified via refresh where applicable. | S9: Screenshot of final state. On fail: URL, visible error, Network status if DevTools allowed. | U9: Not Run | W9: Anushka | Y9: GO requires this Pass (or Full Mock equivalent). If Edge 404 / Python worker down / migrations missing: Pass/Fail = Blocked with BLK-EDGE, BLK-PY, or BLK-MIG. Do not Fail undeployed stack.
A10: TC-GOV-LIVE-07 | B10: Government Exams | C10: Live proof | D10: Full Mock startable or honest CONTENT_INSUFFICIENT | E10: Full Mock startable or honest CONTENT_INSUFFICIENT | F10: P0 | G10: Critical | H10: Positive | I10: Authenticated | J10: user | K10: SUFFICIENT_CREDIT_01 | L10: Logged in. App URL available. Browser DevTools permitted. | M10: Closed Beta / QA Target | N10: Use approved test credentials from Test Accounts sheet. | O10: 1. Choose Full Mock. 2. Generate. 3. If bank short, confirm fail-closed message. 4. If completed, Start Exam works even if count is short of pattern (toast OK). | P10: 1. Mode selected. 2. Job runs. 3. Honest CONTENT_INSUFFICIENT is Pass. 4. Infinite Generating is Fail. Completed+short still startable. | Q10: Full Mock does not trap the user. | R10: Observable UI state matches expected results; no unexplained spinner; no silent failure; persistence verified via refresh where applicable. | S10: Screenshot of final state. On fail: URL, visible error, Network status if DevTools allowed. | U10: Not Run | W10: Anushka | Y10: If Edge 404 / Python worker down / migrations missing: Pass/Fail = Blocked with BLK-EDGE, BLK-PY, or BLK-MIG. Do not Fail undeployed stack.
A11: TC-GOV-LIVE-08 | B11: Government Exams | C11: Live proof | D11: Official/PYQ fail-closed, never AI-labeled Official | E11: Official/PYQ fail-closed, never AI-labeled Official | F11: P0 | G11: Critical | H11: Negative | I11: Authenticated | J11: user | K11: SUFFICIENT_CREDIT_01 | L11: Logged in. App URL available. Browser DevTools permitted. | M11: Closed Beta / QA Target | N11: Use approved test credentials from Test Accounts sheet. | O11: 1. Choose Official / Previous Year if offered. 2. Generate or observe empty. 3. Confirm questions are not AI-written labeled Official. | P11: 1. Mode visible or hidden honestly. 2. Empty/fail-closed OR licensed PYQ. 3. AI fill labeled Official = Fail. | Q11: Official stays fail-closed. | R11: Observable UI state matches expected results; no unexplained spinner; no silent failure; persistence verified via refresh where applicable. | S11: Screenshot of final state. On fail: URL, visible error, Network status if DevTools allowed. | U11: Not Run | W11: Anushka | Y11: BLK-BANK accepted only AFTER LIVE-06 Pass.
A12: TC-GOV-LIVE-09 | B12: Government Exams | C12: Live proof | D12: Duplicate Generate = one job, no double charge | E12: Duplicate Generate = one job, no double charge | F12: P0 | G12: Critical | H12: Negative | I12: Authenticated | J12: user | K12: SUFFICIENT_CREDIT_01 | L12: Logged in. App URL available. Browser DevTools permitted. | M12: Closed Beta / QA Target | N12: Use approved test credentials from Test Accounts sheet. | O12: 1. Note credits. 2. Click Generate. 3. Immediately click Generate again. 4. Observe jobs and credits. | P12: 1. Baseline. 2. First job starts. 3. Second click does not create a second reservation. 4. One in-flight paper or 409 replay. | Q12: Duplicate Generate is safe. | R12: Observable UI state matches expected results; no unexplained spinner; no silent failure; persistence verified via refresh where applicable. | S12: Screenshot of final state. On fail: URL, visible error, Network status if DevTools allowed. | U12: Not Run | W12: Anushka | Y12: If Edge 404 / Python worker down / migrations missing: Pass/Fail = Blocked with BLK-EDGE, BLK-PY, or BLK-MIG. Do not Fail undeployed stack.
A13: TC-GOV-LIVE-10 | B13: Government Exams | C13: Live proof | D13: Refresh during Generating = restore, not trap | E13: Refresh during Generating = restore, not trap | F13: P0 | G13: Critical | H13: Negative | I13: Authenticated | J13: user | K13: SUFFICIENT_CREDIT_01 | L13: Logged in. App URL available. Browser DevTools permitted. | M13: Closed Beta / QA Target | N13: Use approved test credentials from Test Accounts sheet. | O13: 1. Start Generate. 2. Refresh while Generating. 3. Confirm restore or truthful fail/retry — not infinite Generating. | P13: 1. In-flight. 2. Refresh. 3. Recoverable truthful status. | Q13: Refresh does not trap generation. | R13: Observable UI state matches expected results; no unexplained spinner; no silent failure; persistence verified via refresh where applicable. | S13: Screenshot of final state. On fail: URL, visible error, Network status if DevTools allowed. | U13: Not Run | W13: Anushka | Y13: If Edge 404 / Python worker down / migrations missing: Pass/Fail = Blocked with BLK-EDGE, BLK-PY, or BLK-MIG. Do not Fail undeployed stack.
A14: TC-GOV-LIVE-11 | B14: Government Exams | C14: Live proof | D14: Retry after fail; no false insufficient-credits | E14: Retry after fail; no false insufficient-credits | F14: P0 | G14: Critical | H14: Negative | I14: Authenticated | J14: user | K14: SUFFICIENT_CREDIT_01 | L14: Logged in. App URL available. Browser DevTools permitted. | M14: Closed Beta / QA Target | N14: Use approved test credentials from Test Accounts sheet. | O14: 1. If job fails (or after cancel), read error. 2. Click Retry. 3. Confirm credit message matches real balance. | P14: 1. Clear failure. 2. Retry re-attempts. 3. No false insufficient credits. | Q14: Failures are retryable and truthful. | R14: Observable UI state matches expected results; no unexplained spinner; no silent failure; persistence verified via refresh where applicable. | S14: Screenshot of final state. On fail: URL, visible error, Network status if DevTools allowed. | U14: Not Run | W14: Anushka | Y14: If Edge 404 / Python worker down / migrations missing: Pass/Fail = Blocked with BLK-EDGE, BLK-PY, or BLK-MIG. Do not Fail undeployed stack.
A15: TC-GOV-LIVE-12 | B15: Government Exams | C15: Live proof | D15: Failed/cancelled generate refunds reserved credits | E15: Failed/cancelled generate refunds reserved credits | F15: P0 | G15: Critical | H15: Positive | I15: Authenticated | J15: user | K15: SUFFICIENT_CREDIT_01 | L15: Logged in. App URL available. Browser DevTools permitted. | M15: Closed Beta / QA Target | N15: Use approved test credentials from Test Accounts sheet. | O15: 1. Note balance. 2. Start generate then Cancel, or wait for fail. 3. Refresh balance. | P15: 1. Baseline. 2. Cancel/fail terminal. 3. Reserved credits released — balance restored. | Q15: Fail/cancel releases reservation. | R15: Observable UI state matches expected results; no unexplained spinner; no silent failure; persistence verified via refresh where applicable. | S15: Screenshot of final state. On fail: URL, visible error, Network status if DevTools allowed. | U15: Not Run | W15: Anushka | Y15: If Edge 404 / Python worker down / migrations missing: Pass/Fail = Blocked with BLK-EDGE, BLK-PY, or BLK-MIG. Do not Fail undeployed stack.
A16: TC-GOV-LIVE-13 | B16: Government Exams | C16: Live proof | D16: Successful generate finalizes credits only when paper exists | E16: Successful generate finalizes credits only when paper exists | F16: P0 | G16: Critical | H16: Positive | I16: Authenticated | J16: user | K16: SUFFICIENT_CREDIT_01 | L16: Logged in. App URL available. Browser DevTools permitted. | M16: Closed Beta / QA Target | N16: Use approved test credentials from Test Accounts sheet. | O16: 1. Note balance. 2. Complete a paper (LIVE-06). 3. Confirm deduction happens after completed+mock_test_id, not at click. | P16: 1. Baseline. 2. Paper exists. 3. Charge matches UI only on success path. | Q16: Credits finalize only on completed paper. | R16: Observable UI state matches expected results; no unexplained spinner; no silent failure; persistence verified via refresh where applicable. | S16: Screenshot of final state. On fail: URL, visible error, Network status if DevTools allowed. | U16: Not Run | W16: Anushka | Y16: If Edge 404 / Python worker down / migrations missing: Pass/Fail = Blocked with BLK-EDGE, BLK-PY, or BLK-MIG. Do not Fail undeployed stack.
A17: TC-GOV-LIVE-14 | B17: Government Exams | C17: Live proof | D17: Start Exam uses server timer | E17: Start Exam uses server timer | F17: P0 | G17: Critical | H17: Positive | I17: Authenticated | J17: user | K17: SUFFICIENT_CREDIT_01 | L17: Logged in. App URL available. Browser DevTools permitted. | M17: Closed Beta / QA Target | N17: Use approved test credentials from Test Accounts sheet. | O17: 1. Start Exam on a completed paper. 2. Note timer. 3. Refresh. 4. Confirm time did not reset/extend. | P17: 1. Runner starts. 2. Countdown visible. 3. Refresh. 4. Server started_at/expires_at honored. | Q17: Client cannot forever-extend the exam clock. | R17: Observable UI state matches expected results; no unexplained spinner; no silent failure; persistence verified via refresh where applicable. | S17: Screenshot of final state. On fail: URL, visible error, Network status if DevTools allowed. | U17: Not Run | W17: Anushka | Y17: start-exam 404 = BLK-EDGE.
A18: TC-GOV-LIVE-15 | B18: Government Exams | C18: Live proof | D18: Palette states | E18: Palette states | F18: P0 | G18: Critical | H18: Positive | I18: Authenticated | J18: user | K18: SUFFICIENT_CREDIT_01 | L18: Logged in. App URL available. Browser DevTools permitted. | M18: Closed Beta / QA Target | N18: Use approved test credentials from Test Accounts sheet. | O18: 1. Leave one unanswered. 2. Answer one. 3. Mark one unanswered. 4. Answer+mark one. 5. Observe current highlight. | P18: 1–5. Palette shows unanswered / answered / marked / answered+marked / current. | Q18: Palette states are complete and visible. | R18: Observable UI state matches expected results; no unexplained spinner; no silent failure; persistence verified via refresh where applicable. | S18: Screenshot of final state. On fail: URL, visible error, Network status if DevTools allowed. | U18: Not Run | W18: Anushka
A19: TC-GOV-LIVE-16 | B19: Government Exams | C19: Live proof | D19: Autosave + mark-for-review persist | E19: Autosave + mark-for-review persist | F19: P0 | G19: Critical | H19: Persistence | I19: Authenticated | J19: user | K19: SUFFICIENT_CREDIT_01 | L19: Logged in. App URL available. Browser DevTools permitted. | M19: Closed Beta / QA Target | N19: Use approved test credentials from Test Accounts sheet. | O19: 1. Answer Q1 and mark for review. 2. Jump to Q2 and back. 3. Refresh. 4. Confirm answer + marked restored. | P19: 1. Saved. 2. Retained on navigate. 3. Refresh. 4. Both answer and mark persist (or honest warning). | Q19: Autosave and mark-for-review survive navigate and refresh. | R19: Observable UI state matches expected results; no unexplained spinner; no silent failure; persistence verified via refresh where applicable. | S19: Screenshot of final state. On fail: URL, visible error, Network status if DevTools allowed. | U19: Not Run | W19: Anushka | Y19: BLK-EDGE if save-test-answer missing.
A20: TC-GOV-LIVE-17 | B20: Government Exams | C20: Live proof | D20: Submit + expiry + no corrupt double-submit | E20: Submit + expiry + no corrupt double-submit | F20: P0 | G20: Critical | H20: Positive | I20: Authenticated | J20: user | K20: SUFFICIENT_CREDIT_01 | L20: Logged in. App URL available. Browser DevTools permitted. | M20: Closed Beta / QA Target | N20: Use approved test credentials from Test Accounts sheet. | O20: 1. Leave some unanswered. 2. Submit (warning OK). 3. Try submit again. 4. On a second attempt, let timer expire if a short paper exists. | P20: 1. Partial paper. 2. Submitted; score shown. 3. Second submit does not change score. 4. Expiry auto-submits or locks. | Q20: Submit is stable; expiry is enforced. | R20: Observable UI state matches expected results; no unexplained spinner; no silent failure; persistence verified via refresh where applicable. | S20: Screenshot of final state. On fail: URL, visible error, Network status if DevTools allowed. | U20: Not Run | W20: Anushka
A21: TC-GOV-LIVE-18 | B21: Government Exams | C21: Live proof | D21: Result in history after logout/login | E21: Result in history after logout/login | F21: P0 | G21: Critical | H21: Persistence | I21: Authenticated | J21: user | K21: SUFFICIENT_CREDIT_01 | L21: Logged in. App URL available. Browser DevTools permitted. | M21: Closed Beta / QA Target | N21: Use approved test credentials from Test Accounts sheet. | O21: 1. After submit, open results. 2. Logout. 3. Login same user. 4. Open history/results. | P21: 1. Score visible. 2. Logged out. 3. Re-auth. 4. Same result still available to owner. | Q21: Results persist across sessions. | R21: Observable UI state matches expected results; no unexplained spinner; no silent failure; persistence verified via refresh where applicable. | S21: Screenshot of final state. On fail: URL, visible error, Network status if DevTools allowed. | U21: Not Run | W21: Anushka
A22: TC-GOV-LIVE-19 | B22: Government Exams | C22: Live proof | D22: USER_B cannot open USER_A paper/result URL | E22: USER_B cannot open USER_A paper/result URL | F22: P0 | G22: Critical | H22: Security | I22: Authenticated | J22: user | K22: USER_A_01 | L22: Logged in. App URL available. Browser DevTools permitted. | M22: Closed Beta / QA Target | N22: Use approved test credentials from Test Accounts sheet. | O22: 1. As USER_A copy results or session URL. 2. Login USER_B. 3. Paste URL. | P22: 1. A has URL. 2. B session. 3. Denied/not found — no A questions or scores. | Q22: Gov papers/results are owner-isolated. | R22: Observable UI state matches expected results; no unexplained spinner; no silent failure; persistence verified via refresh where applicable. | S22: Screenshot of final state. On fail: URL, visible error, Network status if DevTools allowed. | U22: Not Run | W22: Anushka
A23: TC-GOV-LIVE-20 | B23: Government Exams | C23: Live proof | D23: Free user plan gate | E23: Free user plan gate | F23: P0 | G23: Critical | H23: Security | I23: Authenticated | J23: user | K23: FREE_USER_01 | L23: Logged in. App URL available. Browser DevTools permitted. | M23: Closed Beta / QA Target | N23: Use approved test credentials from Test Accounts sheet. | O23: 1. As FREE_USER_01 open generate for a gated action. 2. Observe upgrade/gate. | P23: 1. Attempt. 2. Clear gate — no unauthorized full generate. | Q23: Free users cannot bypass paid gov-exam generate. | R23: Observable UI state matches expected results; no unexplained spinner; no silent failure; persistence verified via refresh where applicable. | S23: Screenshot of final state. On fail: URL, visible error, Network status if DevTools allowed. | U23: Not Run | W23: Anushka
A24: TC-GOV-LIVE-21 | B24: Government Exams | C24: Live proof | D24: Zero-credit / low-credit truthful | E24: Zero-credit / low-credit truthful | F24: P0 | G24: Critical | H24: Negative | I24: Authenticated | J24: user | K24: ZERO_CREDIT_01 | L24: Logged in. App URL available. Browser DevTools permitted. | M24: Closed Beta / QA Target | N24: Use approved test credentials from Test Accounts sheet. | O24: 1. As ZERO_CREDIT_01 attempt generate. 2. As LOW_CREDIT_01 (qa.lowcredit@) observe warning. 3. Confirm neither is the past-due account. | P24: 1. Zero blocked with buy/upgrade — not unknown tool. 2. Low-credit warning if product has threshold. 3. Fixtures are qa.zero@ / qa.lowcredit@ / qa.exactcredit@. | Q24: Credit fixtures are truthful and distinct from past-due. | R24: Observable UI state matches expected results; no unexplained spinner; no silent failure; persistence verified via refresh where applicable. | S24: Screenshot of final state. On fail: URL, visible error, Network status if DevTools allowed. | U24: Not Run | W24: Anushka | Y24: BLK-CRED if fixtures missing.
A25: TC-GOV-LIVE-23 | B25: Government Exams | C25: Live proof | D25: 429/409 during poll stays in-flight | E25: 429/409 during poll stays in-flight | F25: P0 | G25: Critical | H25: API Observation | I25: Authenticated | J25: user | K25: SUFFICIENT_CREDIT_01 | L25: Logged in. App URL available. Browser DevTools permitted. | M25: Closed Beta / QA Target | N25: Use approved test credentials from Test Accounts sheet. | O25: 1. Start Generate. 2. Watch Network for poll 429/409/5xx. 3. Confirm UI stays Generating (backoff) and is not SESSION_ACTION 20/min trapped. | P25: 1. Job in-flight. 2. Transient errors observed or documented as not seen. 3. Job recovers or fails honestly — not a 20/min session trap. | Q25: Poll uses JOB_POLL backoff; transient errors stay in-flight. | R25: Observable UI state matches expected results; no unexplained spinner; no silent failure; persistence verified via refresh where applicable. | S25: Screenshot of final state. On fail: URL, visible error, Network status if DevTools allowed. | U25: Not Run | W25: Anushka | Y25: If Edge 404 / Python worker down / migrations missing: Pass/Fail = Blocked with BLK-EDGE, BLK-PY, or BLK-MIG. Do not Fail undeployed stack.
A26: TC-GOV-LIVE-03 | B26: Government Exams | C26: Live proof | D26: Nonsense search empty, no crash | E26: Nonsense search empty, no crash | F26: P1 | G26: Major | H26: Negative | I26: Authenticated | J26: user | K26: PRO_USER_01 | L26: Logged in. App URL available. Browser DevTools permitted. | M26: Closed Beta / QA Target | N26: Use approved test credentials from Test Accounts sheet. | O26: 1. Search 'zzzz-not-an-exam-qqq'. 2. Observe empty state. | P26: 1. Query entered. 2. Empty/no-result; no crash; no random exam auto-selected. | Q26: Nonsense search is safe. | R26: Observable UI state matches expected results; no unexplained spinner; no silent failure; persistence verified via refresh where applicable. | S26: Screenshot of final state. On fail: URL, visible error, Network status if DevTools allowed. | U26: Not Run | W26: Anushka
A27: TC-GOV-LIVE-22 | B27: Government Exams | C27: Live proof | D27: AI-down fallback; Official stays fail-closed | E27: AI-down fallback; Official stays fail-closed | F27: P1 | G27: Major | H27: Negative | I27: Authenticated | J27: user | K27: SUFFICIENT_CREDIT_01 | L27: Logged in. App URL available. Browser DevTools permitted. | M27: Closed Beta / QA Target | N27: Use approved test credentials from Test Accounts sheet. | O27: 1. If QA lead marks AI-impaired, generate Realistic/Custom. 2. Observe fallback paper OR honest fail. 3. Official must still fail-closed. | P27: 1. Scenario started. 2. Not infinite Generating; no false credit error. 3. Official never AI-filled. | Q27: AI-down is honest; Official never uses AI. | R27: Observable UI state matches expected results; no unexplained spinner; no silent failure; persistence verified via refresh where applicable. | S27: Screenshot of final state. On fail: URL, visible error, Network status if DevTools allowed. | U27: Not Run | W27: Anushka | Y27: Coordinate AI-down with QA lead. If Edge 404 / Python worker down / migrations missing: Pass/Fail = Blocked with BLK-EDGE, BLK-PY, or BLK-MIG. Do not Fail undeployed stack.
A28: TC-GOV-LIVE-24 | B28: Government Exams | C28: Live proof | D28: Admin ingest never auto-publishes | E28: Admin ingest never auto-publishes | F28: P1 | G28: Major | H28: Positive | I28: Authenticated | J28: admin | K28: ADMIN_USER_01 | L28: Logged in. App URL available. Browser DevTools permitted. | M28: Closed Beta / QA Target | N28: Use approved test credentials from Test Accounts sheet. | O28: 1. Login ADMIN_USER_01. 2. Open https://clarify.ai.sltfinanceindia.com/app/admin/gov/ingest. 3. Upload a small PDF if allowed. 4. Confirm queued/needs_review — questions not live on hub. 5. On question-review, APPROVE/REJECT required before publish. | P28: 1. Admin auth. 2. Ingest UI loads. 3. 202 queued or honest size limit. 4. OCR/unpublished. 5. No auto-publish. | Q28: Ingest stays unpublished until review. | R28: Observable UI state matches expected results; no unexplained spinner; no silent failure; persistence verified via refresh where applicable. | S28: Screenshot of final state. On fail: URL, visible error, Network status if DevTools allowed. | U28: Not Run | W28: Anushka | Y28: Heavy PDF 502 with no refund is Fail if credits charged.

Sheet 01 Application Inventory
A1: 01 — Application Inventory (user-observable)
A2: Classify ONLY after manual execution. Opening a route ≠ Fully Working. All rows start as PENDING MANUAL CLASSIFICATION. Tester pre-assigned (Anushka / Sultana / Venkat).
A4: Area | B4: Feature / Surface | C4: Route / URL | D4: Observable Entry Point | E4: Primary Role | F4: Classification | G4: Evidence / Notes | H4: Tester | I4: Date | J4: Defect ID
A5: Public | B5: Landing page | C5: https://clarify.ai.sltfinanceindia.com/ | D5: Open site root | E5: Guest | F5: PENDING MANUAL CLASSIFICATION | G5: Marketing hero + CTAs | H5: Venkat
A6: Public | B6: Pricing | C6: https://clarify.ai.sltfinanceindia.com/pricing | D6: Nav → Pricing | E6: Guest | F6: PENDING MANUAL CLASSIFICATION | G6: Plans & CTAs | H6: Venkat
A7: Public | B7: Gov Exams marketing | C7: https://clarify.ai.sltfinanceindia.com/gov-exams | D7: Nav / CTA | E7: Guest | F7: PENDING MANUAL CLASSIFICATION | G7: Public marketing | H7: Venkat
A8: Public | B8: Help center | C8: https://clarify.ai.sltfinanceindia.com/help | D8: Footer / Help | E8: Guest | F8: PENDING MANUAL CLASSIFICATION | G8: Articles list | H8: Venkat
A9: Public | B9: Help article | C9: https://clarify.ai.sltfinanceindia.com/help/:slug | D9: Open article from Help | E9: Guest | F9: PENDING MANUAL CLASSIFICATION | G9: Article body | H9: Venkat
A10: Public | B10: Keyboard shortcuts | C10: https://clarify.ai.sltfinanceindia.com/shortcuts | D10: Footer / Help link | E10: Guest | F10: PENDING MANUAL CLASSIFICATION | G10: Shortcuts page | H10: Venkat
A11: Public | B11: Blog list | C11: https://clarify.ai.sltfinanceindia.com/blog | D11: Nav / footer | E11: Guest | F11: PENDING MANUAL CLASSIFICATION | G11: Posts list | H11: Venkat
A12: Public | B12: Blog post | C12: https://clarify.ai.sltfinanceindia.com/blog/:slug | D12: Open post | E12: Guest | F12: PENDING MANUAL CLASSIFICATION | G12: Post body | H12: Venkat
A13: Public | B13: Terms of Service | C13: https://clarify.ai.sltfinanceindia.com/terms | D13: Footer | E13: Guest | F13: PENDING MANUAL CLASSIFICATION | G13: Legal | H13: Venkat
A14: Public | B14: Privacy Policy | C14: https://clarify.ai.sltfinanceindia.com/privacy | D14: Footer | E14: Guest | F14: PENDING MANUAL CLASSIFICATION | G14: Legal | H14: Venkat
A15: Public | B15: Shared debrief | C15: https://clarify.ai.sltfinanceindia.com/share/:token | D15: Shared link | E15: Guest | F15: PENDING MANUAL CLASSIFICATION | G15: Token-gated share | H15: Venkat
A16: Public | B16: Certificate verification | C16: https://clarify.ai.sltfinanceindia.com/verify-certificate/:certificateId | D16: Public verify URL | E16: Guest | F16: PENDING MANUAL CLASSIFICATION | G16: Certificate check | H16: Venkat
... A130: Security | B130: Logged-out protected route | C130: https://clarify.ai.sltfinanceindia.com/app/dashboard | D130: Paste URL logged out | E130: Guest | F130: PENDING MANUAL CLASSIFICATION | G130: Must redirect login | H130: Venkat

Sheet 02 User Roles & Permissions
A1: 02 — User Roles & Permissions (black-box)
A2: Expected permissions as observed in the product UI/plan gates — not from source inspection.
A4: Role | B4: Description | C4: Can Access | D4: Cannot Access | E4: Primary Test Focus
A5: Guest | B5: Unauthenticated visitor | C5: Public pages, login/signup CTAs | D5: No app modules, no admin | E5: Public marketing & auth entry
A6: Unverified User | B6: Signed up, email not verified | C6: Verify-email screen | D6: Cannot enter /app until verified | E6: Email verification flow
A7: New / Onboarding User | B7: Verified, onboarding incomplete | C7: Onboarding wizard | D7: App shell blocked until complete | E7: Onboarding
A8: Free User | B8: plan free | C8: Core free features per plan gates | D8: Paid/pro-gated actions blocked or upgrade prompt | E8: Free plan QA
A9: Pro User | B9: plan pro | C9: Pro features + higher credits | D9: Enterprise-only if any | E9: Pro plan QA
A10: Max / Enterprise User | B10: plan enterprise / max | C10: Highest plan features & credits | D10: Admin still denied unless staff | E10: Max plan QA
A11: Zero Credit User | B11: Authenticated with 0 credits | C11: Browse UI; AI actions blocked gracefully | D11: Credit-consuming actions | E11: Credit exhaustion
A12: Low Credit User | B12: Credits near threshold | C12: Low-credit banners / warnings | D12: Actions that exceed balance | E12: Boundary credits
A13: Admin | B13: Staff role (admin) | C13: Full Admin portal + user app | D13: N/A | E13: Admin portal QA
A14: Moderator | B14: moderator role if assigned | C14: If UI exposes moderation tools | D14: Full admin may be denied | E14: Only if role is provisioned
A15: Banned / Suspended User | B15: Account banned | C15: Login rejected or safe ban message | D15: All app access | E15: Ban enforcement
A16: Expired Session User | B16: Valid account, stale session | C16: Re-auth / redirect to login | D16: Protected actions | E16: Session expiry

Sheet 03 Test Accounts
A1: 03 — Test Accounts (EMAIL + PASSWORD PRE-FILLED)
A2: Loaded from .env.qa.local for closed-beta QA. CONFIDENTIAL — QA team only. Use Account ID referenced in each test case.
A4: Test Account ID | B4: Role | C4: Plan | D4: Purpose | E4: Email / Username | F4: Password | G4: Credits (seed) | H4: Credential Location | I4: Environment | J4: Restrictions | K4: Expected Permissions | L4: Assigned Testers (shared)
A5: GUEST | B5: Guest | C5: none | D5: Public browsing — no login | E5: N/A — no login | F5: N/A | G5: — | H5: .env.qa.local (also copied here for closed-beta QA team only) | I5: Closed Beta / QA Target | J5: No credentials | K5: Public pages only | L5: Anushka, Sultana, Venkat
A6: FREE_USER_01 | B6: Free User | C6: free | D6: Free-plan feature testing | E6: qa.free@clarify.ai.test | F6: Qa!OWORccvwZOiv_jHC | G6: 50 | H6: .env.qa.local (also copied here for closed-beta QA team only) | I6: Closed Beta / QA Target | J6: Do not upgrade permanently | K6: Free entitlements | L6: Anushka, Sultana, Venkat
A7: FREE_USER_02 | B7: Free User (empty history) | C7: free | D7: Empty-state testing | E7: qa.free@clarify.ai.test | F7: Qa!OWORccvwZOiv_jHC | G7: 50 | H7: .env.qa.local (also copied here for closed-beta QA team only) | I7: Closed Beta / QA Target | J7: Prefer a clean/empty profile if available; else use FREE and skip history asserts | K7: Empty states | L7: Anushka, Sultana, Venkat
A8: PRO_USER_01 | B8: Pro User | C8: pro | D8: Pro features & credits | E8: qa.pro@clarify.ai.test | F8: Qa!AwHf4rrb5hLYudkp | G8: 1400 | H8: .env.qa.local (also copied here for closed-beta QA team only) | I8: Closed Beta / QA Target | J8: Primary product testing account | K8: Pro entitlements | L8: Anushka, Sultana, Venkat
A9: MAX_USER_01 | B9: Max/Enterprise User | C9: enterprise | D9: Max plan features | E9: qa.max@clarify.ai.test | F9: Qa!LkS_0RtB8I8uehUK | G9: 4000 | H9: .env.qa.local (also copied here for closed-beta QA team only) | I9: Closed Beta / QA Target | J9: Highest plan | K9: Max entitlements | L9: Anushka, Sultana, Venkat
A10: ADMIN_USER_01 | B10: Admin | C10: enterprise | D10: Admin portal testing | E10: qa.admin@clarify.ai.test | F10: Qa!TYw9VQk8y3KBZUnW | G10: 4000 | H10: .env.qa.local (also copied here for closed-beta QA team only) | I10: Closed Beta / QA Target | J10: Staff only — do not share outside QA team | K10: Admin + user app | L10: Anushka, Sultana, Venkat
A11: UNVERIFIED_01 | B11: Unverified | C11: free | D11: Email verification gate | E11: qa.unverified@clarify.ai.test | F11: Qa!3hXMIDuOJbS84CQx | G11: 50 | H11: .env.qa.local (also copied here for closed-beta QA team only) | I11: Closed Beta / QA Target | J11: Must remain unverified until AUTH-VERIFY cases done | K11: Verify-email only | L11: Anushka, Sultana, Venkat
A12: NEW_USER_01 | B12: Newly Registered / Onboarding | C12: free | D12: Signup + onboarding | E12: qa.onboarding@clarify.ai.test | F12: Qa!bYdJ5KfLTyQ68H79 | G12: 50 | H12: .env.qa.local (also copied here for closed-beta QA team only) | I12: Closed Beta / QA Target | J12: Reset onboarding state between runs if needed. Prefer qa.onboarding@ | K12: Onboarding flows | L12: Anushka, Sultana, Venkat
A13: DISPOSABLE_01 | B13: Disposable | C13: free | D13: Destructive tests (delete account) | E13: qa.disposable@clarify.ai.test | F13: Qa!lSomqsKXtHtOf9-V | G13: 10 | H13: .env.qa.local (also copied here for closed-beta QA team only) | I13: Closed Beta / QA Target | J13: May be deleted — re-seed after | K13: Destructive only | L13: Anushka, Sultana, Venkat
A14: BANNED_USER_01 | B14: Banned | C14: free | D14: Ban enforcement | E14: qa.banned@clarify.ai.test | F14: Qa!nTDcvPqI5RqhAQ3z | G14: 0 | H14: .env.qa.local (also copied here for closed-beta QA team only) | I14: Closed Beta / QA Target | J14: Must remain banned | K14: Login denied | L14: Anushka, Sultana, Venkat
A15: ZERO_CREDIT_01 | B15: Zero credits | C15: pro | D15: Credit exhaustion UX | E15: qa.zero@clarify.ai.test | F15: Qa!VPb4vQOR59Edm1aL | G15: 0 | H15: .env.qa.local (also copied here for closed-beta QA team only) | I15: Closed Beta / QA Target | J15: Keep balance at 0 | K15: AI actions blocked | L15: Anushka, Sultana, Venkat
A16: LOW_CREDIT_01 | B16: Low credits | C16: pro | D16: Low-credit boundary (qa.lowcredit@) | E16: (missing QA_LOW_CREDIT_EMAIL in .env.qa.local) | F16: (missing — run npm run qa:seed-accounts) | H16: .env.qa.local (also copied here for closed-beta QA team only) | I16: Closed Beta / QA Target | J16: Use qa.lowcredit@ only. Do NOT reuse the past-due account for this case. | K16: Warnings + limited actions | L16: Anushka, Sultana, Venkat
A17: EXACT_CREDIT_01 | B17: Exact credits | C17: pro | D17: Exact remaining-credit boundary (qa.exactcredit@) | E17: (missing QA_EXACT_CREDIT_EMAIL in .env.qa.local) | F17: (missing — run npm run qa:seed-accounts) | H17: .env.qa.local (also copied here for closed-beta QA team only) | I17: Closed Beta / QA Target | J17: Keep balance at exact tool cost. Do not drain to zero until TC-CR-005. | K17: Exact-spend then block | L17: Anushka, Sultana, Venkat
A18: SUFFICIENT_CREDIT_01 | B18: Sufficient credits | C18: pro | D18: Happy-path AI consume | E18: qa.pro@clarify.ai.test | F18: Qa!AwHf4rrb5hLYudkp | G18: 1400 | H18: .env.qa.local (also copied here for closed-beta QA team only) | I18: Closed Beta / QA Target | J18: Same as PRO — do not drain to zero | K18: Successful AI flows | L18: Anushka, Sultana, Venkat
A19: HISTORY_USER_01 | B19: User with history | C19: pro | D19: Sessions/reports/compare | E19: qa.pro@clarify.ai.test | F19: Qa!AwHf4rrb5hLYudkp | G19: 1400 | H19: .env.qa.local (also copied here for closed-beta QA team only) | I19: Closed Beta / QA Target | J19: Ensure prior sessions exist or create once | K19: History present | L19: Anushka, Sultana, Venkat
A20: NO_HISTORY_01 | B20: User with no history | C20: free | D20: Empty sessions/analytics | E20: qa.free@clarify.ai.test | F20: Qa!OWORccvwZOiv_jHC | G20: 50 | H20: .env.qa.local (also copied here for closed-beta QA team only) | I20: Closed Beta / QA Target | J20: Use free account with no sessions if possible | K20: Empty states | L20: Anushka, Sultana, Venkat
A21: USER_A_01 | B21: User A (isolation) | C21: pro | D21: Cross-user resource isolation | E21: qa.user-a@clarify.ai.test | F21: Qa!GyjQUOc9hufi4fwF | G21: 1400 | H21: .env.qa.local (also copied here for closed-beta QA team only) | I21: Closed Beta / QA Target | J21: Pair with USER_B_01 | K21: Own data only | L21: Anushka, Sultana, Venkat
A22: USER_B_01 | B22: User B (isolation) | C22: pro | D22: Cross-user resource isolation | E22: qa.user-b@clarify.ai.test | F22: Qa!1WgoI9EiuMHv29qi | G22: 1400 | H22: .env.qa.local (also copied here for closed-beta QA team only) | I22: Closed Beta / QA Target | J22: Pair with USER_A_01 | K22: Own data only | L22: Anushka, Sultana, Venkat
A23: EXPIRED_SESSION_01 | B23: Any valid user | C23: any | D23: Session expiry testing | E23: qa.free@clarify.ai.test | F23: Qa!OWORccvwZOiv_jHC | G23: 50 | H23: .env.qa.local (also copied here for closed-beta QA team only) | I23: Closed Beta / QA Target | J23: Expire session per playbook after login | K23: Re-auth required | L23: Anushka, Sultana, Venkat
A24: MOD_USER_01 | B24: Moderator (if available) | C24: pro | D24: Moderation UI if provisioned | E24: N/A — no login | F24: N/A | G24: — | H24: .env.qa.local (also copied here for closed-beta QA team only) | I24: Closed Beta / QA Target | J24: Skip / N/A if role not seeded | K24: Moderation only | L24: Anushka, Sultana, Venkat
A27: SANDBOX PAYMENT (pre-filled)
A28: Stripe test card | B28: 4242424242424242
A29: Stripe test expiry | B29: 12/34
A30: Stripe test CVC | B30: 123
A31: Payment mode | B31: SANDBOX / TEST ONLY — never live charges unless explicitly approved

Sheet 04 Test Environment
A1: 04 — Test Environment (PRE-FILLED)
A2: Core fields pre-filled. Testers only update Tester name / Test date / Browser version when executing.
A4: Field | B4: Value
A5: Web application URL | B5: https://clarify.ai.sltfinanceindia.com
A6: Admin URL | B6: https://clarify.ai.sltfinanceindia.com/app/admin
A7: Local URL (optional) | B7: http://localhost:5173
A8: Test environment name | B8: Closed Beta / QA Target
A9: Browser (primary) | B9: Chrome (latest stable)
A10: Browser version | B10: (tester updates at execution)
A11: Desktop resolution | B11: 1920 × 1080 (also 1440 × 900, 1366 × 768)
A12: Mobile resolution | B12: 360 × 800, 375 × 812, 414 × 896
A13: Tablet resolution | B13: 768 × 1024
A14: Supported browsers | B14: Chrome, Edge, Firefox, Safari (where available)
A15: Required extensions | B15: None required. Disable ad blockers for QA.
... A27: Secrets policy | B27: Do not screenshot full passwords in evidence; redact in defect attachments
A30: Tester acknowledgements (tick when starting)
A31: ☐ | B31: I will only edit peach columns on test-case sheets.
A32: ☐ | B32: I will mark ALL FILLED on Section Gate only when Ready?=YES.
A33: ☐ | B33: I will use sandbox payments only.
A34: ☐ | B34: I will not share this workbook outside the QA team.

Sheet 05 Module Test Cases
A1: 05 Module Test Cases
A2: PRE-FILLED for you. ONLY update peach columns: Actual Result | Pass/Fail | Defect ID | Execution Date | Notes. Tester is pre-assigned (Anushka / Sultana / Venkat). Complete assigned work within 2 days. Mark section ALL FILLED on '00b Section Completion Gate' ONLY when every case has Pass/Fail ≠ Not Run AND Actual Result filled. Black-box only — no source/DB/server access. Opening a page is NOT Pass.
A4: Test Case ID | B4: Module | C4: Sub-Module | D4: Feature | E4: Workflow | F4: Priority | G4: Severity | H4: Test Type | I4: User Type | J4: Role | K4: Account ID | L4: Preconditions | M4: Test Environment | N4: Test Data | O4: Exact Steps | P4: Expected Result (per step) | Q4: Final Expected Result | R4: Validation Points | S4: Screenshot / Evidence Requirement | T4: Actual Result | U4: Pass / Fail | V4: Defect ID | W4: Tester | X4: Execution Date | Y4: Notes
A5: TC-MOD-001 | B5: Module Smoke | C5: Module Smoke | D5: Practice Coach | E5: Practice Coach | F5: P1 | G5: Major | H5: Positive | I5: Authenticated | J5: user | K5: PRO_USER_01 | L5: Logged in. App URL available. Browser DevTools permitted. | M5: Closed Beta / QA Target | N5: Use approved test credentials from Test Accounts sheet. | O5: 1. Login PRO_USER_01. 2. Navigate to https://clarify.ai.sltfinanceindia.com/app/live via sidebar or URL. 3. Wait up to 15s. 4. Classify: Fully Working UI load / Plan gate / Feature flag / Error / Empty. | P5: 1. Authenticated. 2. Route resolves. 3. Page shows real UI, plan upgrade, disabled feature message, or clear error — not infinite spinner. 4. Classification recorded in Notes + Application Inventory. | Q5: Practice Coach surface is reachable and classifiable from user perspective. | R5: Observable UI state matches expected results; no unexplained spinner; no silent failure; persistence verified via refresh where applicable. | S5: Screenshot of final state. On fail: URL, visible error, Network status if DevTools allowed. | U5: Not Run | W5: Anushka | Y5: Opening a page ≠ feature works. Follow module sheets for functional depth.
A6: TC-MOD-002 | B6: Module Smoke | C6: Module Smoke | D6: Mock Interview | E6: Mock Interview | F6: P1 | G6: Major | H6: Positive | I6: Authenticated | J6: user | K6: PRO_USER_01 | L6: Logged in. App URL available. Browser DevTools permitted. | M6: Closed Beta / QA Target | N6: Use approved test credentials from Test Accounts sheet. | O6: 1. Login PRO_USER_01. 2. Navigate to https://clarify.ai.sltfinanceindia.com/app/mock via sidebar or URL. 3. Wait up to 15s. 4. Classify: Fully Working UI load / Plan gate / Feature flag / Error / Empty. | P6: 1. Authenticated. 2. Route resolves. 3. Page shows real UI, plan upgrade, disabled feature message, or clear error — not infinite spinner. 4. Classification recorded in Notes + Application Inventory. | Q6: Mock Interview surface is reachable and classifiable from user perspective. | R6: Observable UI state matches expected results; no unexplained spinner; no silent failure; persistence verified via refresh where applicable. | S6: Screenshot of final state. On fail: URL, visible error, Network status if DevTools allowed. | U6: Not Run | W6: Anushka | Y6: Opening a page ≠ feature works. Follow module sheets for functional depth.
A7: TC-MOD-003 | B7: Module Smoke | C7: Module Smoke | D7: Gov Exams hub | E7: Gov Exams hub | F7: P1 | G7: Major | H7: Positive | I7: Authenticated | J7: user | K7: PRO_USER_01 | L7: Logged in. App URL available. Browser DevTools permitted. | M7: Closed Beta / QA Target | N7: Use approved test credentials from Test Accounts sheet. | O7: 1. Login PRO_USER_01. 2. Navigate to https://clarify.ai.sltfinanceindia.com/app/mock-test via sidebar or URL. 3. Wait up to 15s. 4. Classify: Fully Working UI load / Plan gate / Feature flag / Error / Empty. | P7: 1. Authenticated. 2. Route resolves. 3. Page shows real UI, plan upgrade, disabled feature message, or clear error — not infinite spinner. 4. Classification recorded in Notes + Application Inventory. | Q7: Gov Exams hub surface is reachable and classifiable from user perspective. | R7: Observable UI state matches expected results; no unexplained spinner; no silent failure; persistence verified via refresh where applicable. | S7: Screenshot of final state. On fail: URL, visible error, Network status if DevTools allowed. | U7: Not Run | W7: Anushka | Y7: Opening a page ≠ feature works. Follow module sheets for functional depth.
A8: TC-MOD-004 | B8: Module Smoke | C8: Module Smoke | D8: Prep Lab | E8: Prep Lab | F8: P1 | G8: Major | H8: Positive | I8: Authenticated | J8: user | K8: PRO_USER_01 | L8: Logged in. App URL available. Browser DevTools permitted. | M8: Closed Beta / QA Target | N8: Use approved test credentials from Test Accounts sheet. | O8: 1. Login PRO_USER_01. 2. Navigate to https://clarify.ai.sltfinanceindia.com/app/prep via sidebar or URL. 3. Wait up to 15s. 4. Classify: Fully Working UI load / Plan gate / Feature flag / Error / Empty. | P8: 1. Authenticated. 2. Route resolves. 3. Page shows real UI, plan upgrade, disabled feature message, or clear error — not infinite spinner. 4. Classification recorded in Notes + Application Inventory. | Q8: Prep Lab surface is reachable and classifiable from user perspective. | R8: Observable UI state matches expected results; no unexplained spinner; no silent failure; persistence verified via refresh where applicable. | S8: Screenshot of final state. On fail: URL, visible error, Network status if DevTools allowed. | U8: Not Run | W8: Anushka | Y8: Opening a page ≠ feature works. Follow module sheets for functional depth.
A9: TC-MOD-005 | B9: Module Smoke | C9: Module Smoke | D9: Sessions | E9: Sessions | F9: P1 | G9: Major | H9: Positive | I9: Authenticated | J9: user | K9: PRO_USER_01 | L9: Logged in. App URL available. Browser DevTools permitted. | M9: Closed Beta / QA Target | N9: Use approved test credentials from Test Accounts sheet. | O9: 1. Login PRO_USER_01. 2. Navigate to https://clarify.ai.sltfinanceindia.com/app/sessions via sidebar or URL. 3. Wait up to 15s. 4. Classify: Fully Working UI load / Plan gate / Feature flag / Error / Empty. | P9: 1. Authenticated. 2. Route resolves. 3. Page shows real UI, plan upgrade, disabled feature message, or clear error — not infinite spinner. 4. Classification recorded in Notes + Application Inventory. | Q9: Sessions surface is reachable and classifiable from user perspective. | R9: Observable UI state matches expected results; no unexplained spinner; no silent failure; persistence verified via refresh where applicable. | S9: Screenshot of final state. On fail: URL, visible error, Network status if DevTools allowed. | U9: Not Run | W9: Anushka | Y9: Opening a page ≠ feature works. Follow module sheets for functional depth.
A10: TC-MOD-006 | B10: Module Smoke | C10: Module Smoke | D10: Documents | E10: Documents | F10: P1 | G10: Major | H10: Positive | I10: Authenticated | J10: user | K10: PRO_USER_01 | L10: Logged in. App URL available. Browser DevTools permitted. | M10: Closed Beta / QA Target | N10: Use approved test credentials from Test Accounts sheet. | O10: 1. Login PRO_USER_01. 2. Navigate to https://clarify.ai.sltfinanceindia.com/app/documents via sidebar or URL. 3. Wait up to 15s. 4. Classify: Fully Working UI load / Plan gate / Feature flag / Error / Empty. | P10: 1. Authenticated. 2. Route resolves. 3. Page shows real UI, plan upgrade, disabled feature message, or clear error — not infinite spinner. 4. Classification recorded in Notes + Application Inventory. | Q10: Documents surface is reachable and classifiable from user perspective. | R10: Observable UI state matches expected results; no unexplained spinner; no silent failure; persistence verified via refresh where applicable. | S10: Screenshot of final state. On fail: URL, visible error, Network status if DevTools allowed. | U10: Not Run | W10: Anushka | Y10: Opening a page ≠ feature works. Follow module sheets for functional depth.
A11: TC-MOD-007 | B11: Module Smoke | C11: Module Smoke | D11: Answer Bank | E11: Answer Bank | F11: P1 | G11: Major | H11: Positive | I11: Authenticated | J11: user | K11: PRO_USER_01 | L11: Logged in. App URL available. Browser DevTools permitted. | M11: Closed Beta / QA Target | N11: Use approved test credentials from Test Accounts sheet. | O11: 1. Login PRO_USER_01. 2. Navigate to https://clarify.ai.sltfinanceindia.com/app/answers via sidebar or URL. 3. Wait up to 15s. 4. Classify: Fully Working UI load / Plan gate / Feature flag / Error / Empty. | P11: 1. Authenticated. 2. Route resolves. 3. Page shows real UI, plan upgrade, disabled feature message, or clear error — not infinite spinner. 4. Classification recorded in Notes + Application Inventory. | Q11: Answer Bank surface is reachable and classifiable from user perspective. | R11: Observable UI state matches expected results; no unexplained spinner; no silent failure; persistence verified via refresh where applicable. | S11: Screenshot of final state. On fail: URL, visible error, Network status if DevTools allowed. | U11: Not Run | W11: Anushka | Y11: Opening a page ≠ feature works. Follow module sheets for functional depth.
A12: TC-MOD-008 | B12: Module Smoke | C12: Module Smoke | D12: Interviews scheduler | E12: Interviews scheduler | F12: P1 | G12: Major | H12: Positive | I12: Authenticated | J12: user | K12: PRO_USER_01 | L12: Logged in. App URL available. Browser DevTools permitted. | M12: Closed Beta / QA Target | N12: Use approved test credentials from Test Accounts sheet. | O12: 1. Login PRO_USER_01. 2. Navigate to https://clarify.ai.sltfinanceindia.com/app/interviews via sidebar or URL. 3. Wait up to 15s. 4. Classify: Fully Working UI load / Plan gate / Feature flag / Error / Empty. | P12: 1. Authenticated. 2. Route resolves. 3. Page shows real UI, plan upgrade, disabled feature message, or clear error — not infinite spinner. 4. Classification recorded in Notes + Application Inventory. | Q12: Interviews scheduler surface is reachable and classifiable from user perspective. | R12: Observable UI state matches expected results; no unexplained spinner; no silent failure; persistence verified via refresh where applicable. | S12: Screenshot of final state. On fail: URL, visible error, Network status if DevTools allowed. | U12: Not Run | W12: Anushka | Y12: Opening a page ≠ feature works. Follow module sheets for functional depth.
A13: TC-MOD-009 | B13: Module Smoke | C13: Module Smoke | D13: Companies | E13: Companies | F13: P1 | G13: Major | H13: Positive | I13: Authenticated | J13: user | K13: PRO_USER_01 | L13: Logged in. App URL available. Browser DevTools permitted. | M13: Closed Beta / QA Target | N13: Use approved test credentials from Test Accounts sheet. | O13: 1. Login PRO_USER_01. 2. Navigate to https://clarify.ai.sltfinanceindia.com/app/companies via sidebar or URL. 3. Wait up to 15s. 4. Classify: Fully Working UI load / Plan gate / Feature flag / Error / Empty. | P13: 1. Authenticated. 2. Route resolves. 3. Page shows real UI, plan upgrade, disabled feature message, or clear error — not infinite spinner. 4. Classification recorded in Notes + Application Inventory. | Q13: Companies surface is reachable and classifiable from user perspective. | R13: Observable UI state matches expected results; no unexplained spinner; no silent failure; persistence verified via refresh where applicable. | S13: Screenshot of final state. On fail: URL, visible error, Network status if DevTools allowed. | U13: Not Run | W13: Anushka | Y13: Opening a page ≠ feature works. Follow module sheets for functional depth.
A14: TC-MOD-010 | B14: Module Smoke | C14: Module Smoke | D14: Analytics | E14: Analytics | F14: P1 | G14: Major | H14: Positive | I14: Authenticated | J14: user | K14: PRO_USER_01 | L14: Logged in. App URL available. Browser DevTools permitted. | M14: Closed Beta / QA Target | N14: Use approved test credentials from Test Accounts sheet. | O14: 1. Login PRO_USER_01. 2. Navigate to https://clarify.ai.sltfinanceindia.com/app/analytics via sidebar or URL. 3. Wait up to 15s. 4. Classify: Fully Working UI load / Plan gate / Feature flag / Error / Empty. | P14: 1. Authenticated. 2. Route resolves. 3. Page shows real UI, plan upgrade, disabled feature message, or clear error — not infinite spinner. 4. Classification recorded in Notes + Application Inventory. | Q14: Analytics surface is reachable and classifiable from user perspective. | R14: Observable UI state matches expected results; no unexplained spinner; no silent failure; persistence verified via refresh where applicable. | S14: Screenshot of final state. On fail: URL, visible error, Network status if DevTools allowed. | U14: Not Run | W14: Anushka | Y14: Opening a page ≠ feature works. Follow module sheets for functional depth.
A15: TC-MOD-011 | B15: Module Smoke | C15: Module Smoke | D15: Debriefs | E15: Debriefs | F15: P1 | G15: Major | H15: Positive | I15: Authenticated | J15: user | K15: PRO_USER_01 | L15: Logged in. App URL available. Browser DevTools permitted. | M15: Closed Beta / QA Target | N15: Use approved test credentials from Test Accounts sheet. | O15: 1. Login PRO_USER_01. 2. Navigate to https://clarify.ai.sltfinanceindia.com/app/debriefs via sidebar or URL. 3. Wait up to 15s. 4. Classify: Fully Working UI load / Plan gate / Feature flag / Error / Empty. | P15: 1. Authenticated. 2. Route resolves. 3. Page shows real UI, plan upgrade, disabled feature message, or clear error — not infinite spinner. 4. Classification recorded in Notes + Application Inventory. | Q15: Debriefs surface is reachable and classifiable from user perspective. | R15: Observable UI state matches expected results; no unexplained spinner; no silent failure; persistence verified via refresh where applicable. | S15: Screenshot of final state. On fail: URL, visible error, Network status if DevTools allowed. | U15: Not Run | W15: Anushka | Y15: Opening a page ≠ feature works. Follow module sheets for functional depth.
A16: TC-MOD-012 | B16: Module Smoke | C16: Module Smoke | D16: Learning Hub | E16: Learning Hub | F16: P1 | G16: Major | H16: Positive | I16: Authenticated | J16: user | K16: PRO_USER_01 | L16: Logged in. App URL available. Browser DevTools permitted. | M16: Closed Beta / QA Target | N16: Use approved test credentials from Test Accounts sheet. | O16: 1. Login PRO_USER_01. 2. Navigate to https://clarify.ai.sltfinanceindia.com/app/learn via sidebar or URL. 3. Wait up to 15s. 4. Classify: Fully Working UI load / Plan gate / Feature flag / Error / Empty. | P16: 1. Authenticated. 2. Route resolves. 3. Page shows real UI, plan upgrade, disabled feature message, or clear error — not infinite spinner. 4. Classification recorded in Notes + Application Inventory. | Q16: Learning Hub surface is reachable and classifiable from user perspective. | R16: Observable UI state matches expected results; no unexplained spinner; no silent failure; persistence verified via refresh where applicable. | S16: Screenshot of final state. On fail: URL, visible error, Network status if DevTools allowed. | U16: Not Run | W16: Anushka | Y16: Opening a page ≠ feature works. Follow module sheets for functional depth.
... A26: TC-MOD-022 | B26: Module Smoke | C26: Module Smoke | D26: Guide | E26: Guide | F26: P1 | G26: Major | H26: Positive | I26: Authenticated | J26: user | K26: PRO_USER_01 | L26: Logged in. App URL available. Browser DevTools permitted. | M26: Closed Beta / QA Target | N26: Use approved test credentials from Test Accounts sheet. | O26: 1. Login PRO_USER_01. 2. Navigate to https://clarify.ai.sltfinanceindia.com/app/guide via sidebar or URL. 3. Wait up to 15s. 4. Classify: Fully Working UI load / Plan gate / Feature flag / Error / Empty. | P26: 1. Authenticated. 2. Route resolves. 3. Page shows real UI, plan upgrade, disabled feature message, or clear error — not infinite spinner. 4. Classification recorded in Notes + Application Inventory. | Q26: Guide surface is reachable and classifiable from user perspective. | R26: Observable UI state matches expected results; no unexplained spinner; no silent failure; persistence verified via refresh where applicable. | S26: Screenshot of final state. On fail: URL, visible error, Network status if DevTools allowed. | U26: Not Run | W26: Anushka | Y26: Opening a page ≠ feature works. Follow module sheets for functional depth.

Sheet 06 Public Pages
A1: 06 Public Pages
A2: PRE-FILLED for you. ONLY update peach columns: Actual Result | Pass/Fail | Defect ID | Execution Date | Notes. Tester is pre-assigned (Anushka / Sultana / Venkat). Complete assigned work within 2 days. Mark section ALL FILLED on '00b Section Completion Gate' ONLY when every case has Pass/Fail ≠ Not Run AND Actual Result filled. Black-box only — no source/DB/server access. Opening a page is NOT Pass.
A4: Test Case ID | B4: Module | C4: Sub-Module | D4: Feature | E4: Workflow | F4: Priority | G4: Severity | H4: Test Type | I4: User Type | J4: Role | K4: Account ID | L4: Preconditions | M4: Test Environment | N4: Test Data | O4: Exact Steps | P4: Expected Result (per step) | Q4: Final Expected Result | R4: Validation Points | S4: Screenshot / Evidence Requirement | T4: Actual Result | U4: Pass / Fail | V4: Defect ID | W4: Tester | X4: Execution Date | Y4: Notes
A5: TC-PUB-001 | B5: Public Pages | C5: Marketing | D5: Landing | E5: Landing | F5: P0 | G5: Critical | H5: Positive | I5: Guest | J5: guest | K5: GUEST | L5: Logged out. Incognito. No extensions blocking scripts. | M5: Closed Beta / QA Target | N5: URL=https://clarify.ai.sltfinanceindia.com/ | Login email/password: see sheet 03 Test Accounts for Account ID GUEST | O5: 1. Open https://clarify.ai.sltfinanceindia.com/ in a logged-out Incognito window. 2. Wait for page load (max 15s). 3. Scroll full page; click primary nav/footer links that stay on-site. 4. Note any console red errors (ignore 3rd-party noise). | P5: 1. URL is https://clarify.ai.sltfinanceindia.com/ (or intentional redirect). 2. Page content renders; no infinite spinner/blank screen. 3. Links navigate correctly; no broken chrome. 4. No app-breaking console errors. | Q5: Landing loads with brand, headline, primary CTA | R5: Observable UI state matches expected results; no unexplained spinner; no silent failure; persistence verified via refresh where applicable. | S5: Full-page screenshot + address bar. | U5: Not Run | W5: Venkat
A6: TC-PUB-013 | B6: Public Pages | C6: CTAs | D6: Public CTA to Signup/Login | E6: Public CTA to Signup/Login | F6: P0 | G6: Critical | H6: Positive | I6: Guest | J6: guest | K6: GUEST | L6: Logged in. App URL available. Browser DevTools permitted. | M6: Closed Beta / QA Target | N6: Use approved test credentials from Test Accounts sheet. | O6: 1. From landing, click primary Sign up / Get started CTA. 2. From pricing, click a plan CTA. 3. Use Login link from signup. | P6: 1. Navigates to /signup. 2. Navigates to signup/checkout/login as designed. 3. Login page loads. | Q6: Public CTAs reach correct auth entry points. | R6: Observable UI state matches expected results; no unexplained spinner; no silent failure; persistence verified via refresh where applicable. | S6: Screenshot of final state. On fail: URL, visible error, Network status if DevTools allowed. | U6: Not Run | W6: Venkat
A7: TC-PUB-002 | B7: Public Pages | C7: Marketing | D7: Pricing | E7: Pricing | F7: P1 | G7: Major | H7: Positive | I7: Guest | J7: guest | K7: GUEST | L7: Logged out. Incognito. No extensions blocking scripts. | M7: Closed Beta / QA Target | N7: URL=https://clarify.ai.sltfinanceindia.com/pricing | Login email/password: see sheet 03 Test Accounts for Account ID GUEST | O7: 1. Open https://clarify.ai.sltfinanceindia.com/pricing in a logged-out Incognito window. 2. Wait for page load (max 15s). 3. Scroll full page; click primary nav/footer links that stay on-site. 4. Note any console red errors (ignore 3rd-party noise). | P7: 1. URL is https://clarify.ai.sltfinanceindia.com/pricing (or intentional redirect). 2. Page content renders; no infinite spinner/blank screen. 3. Links navigate correctly; no broken chrome. 4. No app-breaking console errors. | Q7: Pricing plans and CTAs visible | R7: Observable UI state matches expected results; no unexplained spinner; no silent failure; persistence verified via refresh where applicable. | S7: Full-page screenshot + address bar. | U7: Not Run | W7: Venkat
A8: TC-PUB-003 | B8: Public Pages | C8: Marketing | D8: Gov Exams marketing | E8: Gov Exams marketing | F8: P1 | G8: Major | H8: Positive | I8: Guest | J8: guest | K8: GUEST | L8: Logged out. Incognito. No extensions blocking scripts. | M8: Closed Beta / QA Target | N8: URL=https://clarify.ai.sltfinanceindia.com/gov-exams | Login email/password: see sheet 03 Test Accounts for Account ID GUEST | O8: 1. Open https://clarify.ai.sltfinanceindia.com/gov-exams in a logged-out Incognito window. 2. Wait for page load (max 15s). 3. Scroll full page; click primary nav/footer links that stay on-site. 4. Note any console red errors (ignore 3rd-party noise). | P8: 1. URL is https://clarify.ai.sltfinanceindia.com/gov-exams (or intentional redirect). 2. Page content renders; no infinite spinner/blank screen. 3. Links navigate correctly; no broken chrome. 4. No app-breaking console errors. | Q8: Gov exam marketing content loads | R8: Observable UI state matches expected results; no unexplained spinner; no silent failure; persistence verified via refresh where applicable. | S8: Full-page screenshot + address bar. | U8: Not Run | W8: Venkat
A9: TC-PUB-004 | B9: Public Pages | C9: Marketing | D9: Help | E9: Help | F9: P1 | G9: Major | H9: Positive | I9: Guest | J9: guest | K9: GUEST | L9: Logged out. Incognito. No extensions blocking scripts. | M9: Closed Beta / QA Target | N9: URL=https://clarify.ai.sltfinanceindia.com/help | Login email/password: see sheet 03 Test Accounts for Account ID GUEST | O9: 1. Open https://clarify.ai.sltfinanceindia.com/help in a logged-out Incognito window. 2. Wait for page load (max 15s). 3. Scroll full page; click primary nav/footer links that stay on-site. 4. Note any console red errors (ignore 3rd-party noise). | P9: 1. URL is https://clarify.ai.sltfinanceindia.com/help (or intentional redirect). 2. Page content renders; no infinite spinner/blank screen. 3. Links navigate correctly; no broken chrome. 4. No app-breaking console errors. | Q9: Help center lists articles or empty-state | R9: Observable UI state matches expected results; no unexplained spinner; no silent failure; persistence verified via refresh where applicable. | S9: Full-page screenshot + address bar. | U9: Not Run | W9: Venkat
A10: TC-PUB-005 | B10: Public Pages | C10: Marketing | D10: Shortcuts | E10: Shortcuts | F10: P1 | G10: Major | H10: Positive | I10: Guest | J10: guest | K10: GUEST | L10: Logged out. Incognito. No extensions blocking scripts. | M10: Closed Beta / QA Target | N10: URL=https://clarify.ai.sltfinanceindia.com/shortcuts | Login email/password: see sheet 03 Test Accounts for Account ID GUEST | O10: 1. Open https://clarify.ai.sltfinanceindia.com/shortcuts in a logged-out Incognito window. 2. Wait for page load (max 15s). 3. Scroll full page; click primary nav/footer links that stay on-site. 4. Note any console red errors (ignore 3rd-party noise). | P10: 1. URL is https://clarify.ai.sltfinanceindia.com/shortcuts (or intentional redirect). 2. Page content renders; no infinite spinner/blank screen. 3. Links navigate correctly; no broken chrome. 4. No app-breaking console errors. | Q10: Shortcuts page loads | R10: Observable UI state matches expected results; no unexplained spinner; no silent failure; persistence verified via refresh where applicable. | S10: Full-page screenshot + address bar. | U10: Not Run | W10: Venkat
A11: TC-PUB-006 | B11: Public Pages | C11: Marketing | D11: Blog | E11: Blog | F11: P1 | G11: Major | H11: Positive | I11: Guest | J11: guest | K11: GUEST | L11: Logged out. Incognito. No extensions blocking scripts. | M11: Closed Beta / QA Target | N11: URL=https://clarify.ai.sltfinanceindia.com/blog | Login email/password: see sheet 03 Test Accounts for Account ID GUEST | O11: 1. Open https://clarify.ai.sltfinanceindia.com/blog in a logged-out Incognito window. 2. Wait for page load (max 15s). 3. Scroll full page; click primary nav/footer links that stay on-site. 4. Note any console red errors (ignore 3rd-party noise). | P11: 1. URL is https://clarify.ai.sltfinanceindia.com/blog (or intentional redirect). 2. Page content renders; no infinite spinner/blank screen. 3. Links navigate correctly; no broken chrome. 4. No app-breaking console errors. | Q11: Blog list loads | R11: Observable UI state matches expected results; no unexplained spinner; no silent failure; persistence verified via refresh where applicable. | S11: Full-page screenshot + address bar. | U11: Not Run | W11: Venkat
A12: TC-PUB-007 | B12: Public Pages | C12: Marketing | D12: Terms | E12: Terms | F12: P1 | G12: Major | H12: Positive | I12: Guest | J12: guest | K12: GUEST | L12: Logged out. Incognito. No extensions blocking scripts. | M12: Closed Beta / QA Target | N12: URL=https://clarify.ai.sltfinanceindia.com/terms | Login email/password: see sheet 03 Test Accounts for Account ID GUEST | O12: 1. Open https://clarify.ai.sltfinanceindia.com/terms in a logged-out Incognito window. 2. Wait for page load (max 15s). 3. Scroll full page; click primary nav/footer links that stay on-site. 4. Note any console red errors (ignore 3rd-party noise). | P12: 1. URL is https://clarify.ai.sltfinanceindia.com/terms (or intentional redirect). 2. Page content renders; no infinite spinner/blank screen. 3. Links navigate correctly; no broken chrome. 4. No app-breaking console errors. | Q12: Terms content loads | R12: Observable UI state matches expected results; no unexplained spinner; no silent failure; persistence verified via refresh where applicable. | S12: Full-page screenshot + address bar. | U12: Not Run | W12: Venkat
A13: TC-PUB-008 | B13: Public Pages | C13: Marketing | D13: Privacy | E13: Privacy | F13: P1 | G13: Major | H13: Positive | I13: Guest | J13: guest | K13: GUEST | L13: Logged out. Incognito. No extensions blocking scripts. | M13: Closed Beta / QA Target | N13: URL=https://clarify.ai.sltfinanceindia.com/privacy | Login email/password: see sheet 03 Test Accounts for Account ID GUEST | O13: 1. Open https://clarify.ai.sltfinanceindia.com/privacy in a logged-out Incognito window. 2. Wait for page load (max 15s). 3. Scroll full page; click primary nav/footer links that stay on-site. 4. Note any console red errors (ignore 3rd-party noise). | P13: 1. URL is https://clarify.ai.sltfinanceindia.com/privacy (or intentional redirect). 2. Page content renders; no infinite spinner/blank screen. 3. Links navigate correctly; no broken chrome. 4. No app-breaking console errors. | Q13: Privacy content loads | R13: Observable UI state matches expected results; no unexplained spinner; no silent failure; persistence verified via refresh where applicable. | S13: Full-page screenshot + address bar. | U13: Not Run | W13: Venkat
A14: TC-PUB-011 | B14: Public Pages | C14: Certificates | D14: Certificate verification — invalid ID | E14: Certificate verification — invalid ID | F14: P1 | G14: Major | H14: Negative | I14: Guest | J14: guest | K14: GUEST | L14: Logged in. App URL available. Browser DevTools permitted. | M14: Closed Beta / QA Target | N14: Use approved test credentials from Test Accounts sheet. | O14: 1. Open https://clarify.ai.sltfinanceindia.com/verify-certificate/invalid-test-id-000. 2. Observe message. | P14: 1. Page loads without crash. 2. Clear invalid/not-found message; no other users' data shown. | Q14: Invalid certificate ID fails safely with no data leak. | R14: Observable UI state matches expected results; no unexplained spinner; no silent failure; persistence verified via refresh where applicable. | S14: Screenshot of final state. On fail: URL, visible error, Network status if DevTools allowed. | U14: Not Run | W14: Venkat
A15: TC-PUB-012 | B15: Public Pages | C15: Sharing | D15: Shared debrief — invalid token | E15: Shared debrief — invalid token | F15: P1 | G15: Major | H15: Security | I15: Guest | J15: guest | K15: GUEST | L15: Logged in. App URL available. Browser DevTools permitted. | M15: Closed Beta / QA Target | N15: Use approved test credentials from Test Accounts sheet. | O15: 1. Open https://clarify.ai.sltfinanceindia.com/share/not-a-real-token. 2. Observe UI. | P15: 1. Safe error or not-found. 2. No private debrief content exposed. | Q15: Invalid share token does not leak session content. | R15: Observable UI state matches expected results; no unexplained spinner; no silent failure; persistence verified via refresh where applicable. | S15: Screenshot of final state. On fail: URL, visible error, Network status if DevTools allowed. | U15: Not Run | W15: Venkat
A16: TC-PUB-009 | B16: Public Pages | C16: Help | D16: Help article deep link | E16: Help article deep link | F16: P2 | G16: Minor | H16: Positive | I16: Guest | J16: guest | K16: GUEST | L16: Logged in. App URL available. Browser DevTools permitted. | M16: Closed Beta / QA Target | N16: Use approved test credentials from Test Accounts sheet. | O16: 1. Open https://clarify.ai.sltfinanceindia.com/help and click the first available article (or open a known slug). 2. Verify title, body, and back/nav. 3. Refresh the article URL. | P16: 1. Article opens. 2. Content readable; nav works. 3. Same article still loads after refresh. | Q16: Help article deep links work and persist on refresh. | R16: Observable UI state matches expected results; no unexplained spinner; no silent failure; persistence verified via refresh where applicable. | S16: Screenshot of final state. On fail: URL, visible error, Network status if DevTools allowed. | U16: Not Run | W16: Venkat
... A18: TC-PUB-015 | B18: Public Pages | C18: Errors | D18: 404 / unknown public path | E18: 404 / unknown public path | F18: P2 | G18: Minor | H18: Negative | I18: Guest | J18: guest | K18: GUEST | L18: Logged in. App URL available. Browser DevTools permitted. | M18: Closed Beta / QA Target | N18: Use approved test credentials from Test Accounts sheet. | O18: 1. Open https://clarify.ai.sltfinanceindia.com/this-page-does-not-exist-qa. 2. Observe not-found UI and navigation home. | P18: 1. Friendly 404 (not blank/crash). 2. User can navigate back to a valid page. | Q18: Unknown routes show safe 404. | R18: Observable UI state matches expected results; no unexplained spinner; no silent failure; persistence verified via refresh where applicable. | S18: Screenshot of final state. On fail: URL, visible error, Network status if DevTools allowed. | U18: Not Run | W18: Venkat
A19: TC-PUB-014 | B19: Public Pages | C19: Inventory | D19: Missing marketing routes (About/Contact/etc.) | E19: Missing marketing routes (About/Contact/etc.) | F19: P3 | G19: Cosmetic | H19: Positive | I19: Guest | J19: guest | K19: GUEST | L19: Logged in. App URL available. Browser DevTools permitted. | M19: Closed Beta / QA Target | N19: Use approved test credentials from Test Accounts sheet. | O19: 1. From landing & footer, look for About, Contact, Careers, Features, Industries, Cookies, FAQ. 2. For each missing route, record Unavailable. 3. For each present link, open and verify load. | P19: 1. Inventory updated honestly. 2. Missing ≠ Fail unless product promises the page. 3. Present pages load. | Q19: Public route inventory complete; no false 'working' claims. | R19: Observable UI state matches expected results; no unexplained spinner; no silent failure; persistence verified via refresh where applicable. | S19: Screenshot of final state. On fail: URL, visible error, Network status if DevTools allowed. | U19: Not Run | W19: Venkat | Y19: Mark Application Inventory accordingly.

Sheet 07 Authentication
A1: 07 Authentication
A2: PRE-FILLED for you. ONLY update peach columns: Actual Result | Pass/Fail | Defect ID | Execution Date | Notes. Tester is pre-assigned (Anushka / Sultana / Venkat). Complete assigned work within 2 days. Mark section ALL FILLED on '00b Section Completion Gate' ONLY when every case has Pass/Fail ≠ Not Run AND Actual Result filled. Black-box only — no source/DB/server access. Opening a page is NOT Pass.
A4: Test Case ID | B4: Module | C4: Sub-Module | D4: Feature | E4: Workflow | F4: Priority | G4: Severity | H4: Test Type | I4: User Type | J4: Role | K4: Account ID | L4: Preconditions | M4: Test Environment | N4: Test Data | O4: Exact Steps | P4: Expected Result (per step) | Q4: Final Expected Result | R4: Validation Points | S4: Screenshot / Evidence Requirement | T4: Actual Result | U4: Pass / Fail | V4: Defect ID | W4: Tester | X4: Execution Date | Y4: Notes
A5: TC-AUTH-001 | B5: Authentication | C5: Authentication | D5: Valid login | E5: Valid login | F5: P0 | G5: Critical | H5: Positive | I5: Authenticated | J5: user | K5: FREE_USER_01 | L5: Logged out. Valid FREE_USER_01 credentials available. | M5: Closed Beta / QA Target | N5: Email/password from credential store only (do not write password in Actual Result). | O5: 1. Open https://clarify.ai.sltfinanceindia.com/login. 2. Enter FREE_USER_01 email + password from credential store. 3. Submit Login. 4. Observe landing destination. | P5: 1. Login form visible. 2. Fields accept input; password masked. 3. No unexplained error. 4. Lands on dashboard or onboarding as appropriate. | Q5: Valid credentials sign the user in and reach the correct post-login page. | R5: Observable UI state matches expected results; no unexplained spinner; no silent failure; persistence verified via refresh where applicable. | S5: Screenshot of final state. On fail: URL, visible error, Network status if DevTools allowed. | U5: Not Run | W5: Venkat
A6: TC-AUTH-002 | B6: Authentication | C6: Authentication | D6: Invalid password | E6: Invalid password | F6: P0 | G6: Critical | H6: Negative | I6: Authenticated | J6: user | K6: FREE_USER_01 | L6: Logged in. App URL available. Browser DevTools permitted. | M6: Closed Beta / QA Target | N6: Use approved test credentials from Test Accounts sheet. | O6: 1. Open https://clarify.ai.sltfinanceindia.com/login. 2. Enter FREE_USER_01 email with wrong password. 3. Submit. | P6: 1. Form loads. 2. Input accepted. 3. Clear error; user not signed in; no stack trace. | Q6: Invalid password is rejected with a safe user-visible error. | R6: Observable UI state matches expected results; no unexplained spinner; no silent failure; persistence verified via refresh where applicable. | S6: Screenshot of final state. On fail: URL, visible error, Network status if DevTools allowed. | U6: Not Run | W6: Venkat
A7: TC-AUTH-006 | B7: Authentication | C7: Authentication | D7: Signup happy path | E7: Signup happy path | F7: P0 | G7: Critical | H7: Positive | I7: Guest | J7: guest | K7: NEW_USER_01 | L7: Logged in. App URL available. Browser DevTools permitted. | M7: Closed Beta / QA Target | N7: Fresh disposable email + strong password from QA playbook. | Login email/password: see sheet 03 Test Accounts for Account ID NEW_USER_01 | O7: 1. Open https://clarify.ai.sltfinanceindia.com/signup. 2. Register with a new approved disposable email. 3. Submit. 4. Observe next screen (verify email / onboarding). | P7: 1. Signup form loads. 2. Validation passes for valid data. 3. Success path (no silent fail). 4. User directed to verification or next step. | Q7: New user can register and reach verification/onboarding. | R7: Observable UI state matches expected results; no unexplained spinner; no silent failure; persistence verified via refresh where applicable. | S7: Screenshot of final state. On fail: URL, visible error, Network status if DevTools allowed. | U7: Not Run | W7: Venkat
A8: TC-AUTH-008 | B8: Authentication | C8: Authentication | D8: Unverified email login gate | E8: Unverified email login gate | F8: P0 | G8: Critical | H8: Negative | I8: Unverified | J8: user | K8: UNVERIFIED_01 | L8: Logged in. App URL available. Browser DevTools permitted. | M8: Closed Beta / QA Target | N8: Use approved test credentials from Test Accounts sheet. | O8: 1. Login as UNVERIFIED_01. 2. Attempt to open {B}/app/dashboard. | P8: 1. Login may succeed into verify gate or show verify prompt. 2. Protected app content not available until verified. | Q8: Unverified users cannot use protected app modules. | R8: Observable UI state matches expected results; no unexplained spinner; no silent failure; persistence verified via refresh where applicable. | S8: Screenshot of final state. On fail: URL, visible error, Network status if DevTools allowed. | U8: Not Run | W8: Venkat
A9: TC-AUTH-010 | B9: Authentication | C9: Authentication | D9: Reset password via email link | E9: Reset password via email link | F9: P0 | G9: Critical | H9: Positive | I9: Authenticated | J9: user | K9: FREE_USER_01 | L9: QA inbox access for reset email. Approved to rotate this account password. | M9: Closed Beta / QA Target | N9: Use approved test credentials from Test Accounts sheet. | O9: 1. Using QA inbox, open reset link for a test account. 2. Set a new password meeting rules. 3. Login with new password. 4. Confirm old password fails. | P9: 1. Reset page loads from link. 2. Password updated. 3. New password works. 4. Old password rejected. | Q9: Password reset works end-to-end via email link. | R9: Observable UI state matches expected results; no unexplained spinner; no silent failure; persistence verified via refresh where applicable. | S9: Screenshot of final state. On fail: URL, visible error, Network status if DevTools allowed. | U9: Not Run | W9: Venkat | Y9: Coordinate with QA lead before rotating shared passwords.
A10: TC-AUTH-011 | B10: Authentication | C10: Authentication | D10: Logout | E10: Logout | F10: P0 | G10: Critical | H10: Security | I10: Authenticated | J10: user | K10: FREE_USER_01 | L10: Logged in. App URL available. Browser DevTools permitted. | M10: Closed Beta / QA Target | N10: Use approved test credentials from Test Accounts sheet. | O10: 1. Login as FREE_USER_01. 2. Logout via profile/settings control. 3. Press browser Back. 4. Paste /app/dashboard. | P10: 1. Authenticated. 2. Session cleared; lands on public/login. 3. No protected content via Back. 4. Redirected to login. | Q10: Logout clears session; protected routes inaccessible. | R10: Observable UI state matches expected results; no unexplained spinner; no silent failure; persistence verified via refresh where applicable. | S10: Screenshot of final state. On fail: URL, visible error, Network status if DevTools allowed. | U10: Not Run | W10: Venkat
A11: TC-AUTH-013 | B11: Authentication | C11: Authentication | D11: Banned account login | E11: Banned account login | F11: P0 | G11: Critical | H11: Security | I11: Authenticated | J11: user | K11: BANNED_USER_01 | L11: Logged in. App URL available. Browser DevTools permitted. | M11: Closed Beta / QA Target | N11: Use approved test credentials from Test Accounts sheet. | O11: 1. Open https://clarify.ai.sltfinanceindia.com/login. 2. Login as BANNED_USER_01. 3. Observe result. | P11: 1. Form loads. 2. Credentials submitted. 3. Access denied/ban message; no dashboard access. | Q11: Banned users cannot access the application. | R11: Observable UI state matches expected results; no unexplained spinner; no silent failure; persistence verified via refresh where applicable. | S11: Screenshot of final state. On fail: URL, visible error, Network status if DevTools allowed. | U11: Not Run | W11: Venkat
A12: TC-AUTH-003 | B12: Authentication | C12: Authentication | D12: Invalid email format | E12: Invalid email format | F12: P1 | G12: Major | H12: Negative | I12: Guest | J12: guest | K12: GUEST | L12: Logged in. App URL available. Browser DevTools permitted. | M12: Closed Beta / QA Target | N12: Use approved test credentials from Test Accounts sheet. | O12: 1. Open https://clarify.ai.sltfinanceindia.com/login. 2. Enter 'not-an-email' and any password. 3. Submit. | P12: 1. Form loads. 2. Client validation or server error. 3. Not signed in. | Q12: Malformed email blocked with clear feedback. | R12: Observable UI state matches expected results; no unexplained spinner; no silent failure; persistence verified via refresh where applicable. | S12: Screenshot of final state. On fail: URL, visible error, Network status if DevTools allowed. | U12: Not Run | W12: Venkat
A13: TC-AUTH-004 | B13: Authentication | C13: Authentication | D13: Empty required fields | E13: Empty required fields | F13: P1 | G13: Major | H13: Negative | I13: Guest | J13: guest | K13: GUEST | L13: Logged in. App URL available. Browser DevTools permitted. | M13: Closed Beta / QA Target | N13: Use approved test credentials from Test Accounts sheet. | O13: 1. Open https://clarify.ai.sltfinanceindia.com/login. 2. Leave email and password empty. 3. Click Login. | P13: 1. Form loads. 2. Empty fields. 3. Inline validation; no request storm; not signed in. | Q13: Empty login fields show required-field validation. | R13: Observable UI state matches expected results; no unexplained spinner; no silent failure; persistence verified via refresh where applicable. | S13: Screenshot of final state. On fail: URL, visible error, Network status if DevTools allowed. | U13: Not Run | W13: Venkat
A14: TC-AUTH-007 | B14: Authentication | C14: Authentication | D14: Duplicate signup | E14: Duplicate signup | F14: P1 | G14: Major | H14: Negative | I14: Authenticated | J14: user | K14: FREE_USER_01 | L14: Logged in. App URL available. Browser DevTools permitted. | M14: Closed Beta / QA Target | N14: Use approved test credentials from Test Accounts sheet. | O14: 1. Open https://clarify.ai.sltfinanceindia.com/signup. 2. Attempt signup with FREE_USER_01 existing email. 3. Submit. | P14: 1. Form loads. 2. Existing email entered. 3. Clear duplicate/exists error; no second account created silently. | Q14: Duplicate email signup is rejected clearly. | R14: Observable UI state matches expected results; no unexplained spinner; no silent failure; persistence verified via refresh where applicable. | S14: Screenshot of final state. On fail: URL, visible error, Network status if DevTools allowed. | U14: Not Run | W14: Venkat
A15: TC-AUTH-009 | B15: Authentication | C15: Authentication | D15: Forgot password request | E15: Forgot password request | F15: P1 | G15: Major | H15: Positive | I15: Guest | J15: guest | K15: FREE_USER_01 | L15: Logged in. App URL available. Browser DevTools permitted. | M15: Closed Beta / QA Target | N15: Use approved test credentials from Test Accounts sheet. | O15: 1. Open https://clarify.ai.sltfinanceindia.com/forgot-password (or Login → Forgot). 2. Submit FREE_USER_01 email. 3. Observe confirmation message (do not expose whether email exists beyond product rules). | P15: 1. Form loads. 2. Request accepted. 3. User-facing confirmation; no crash. | Q15: Forgot-password request completes with clear confirmation. | R15: Observable UI state matches expected results; no unexplained spinner; no silent failure; persistence verified via refresh where applicable. | S15: Screenshot of final state. On fail: URL, visible error, Network status if DevTools allowed. | U15: Not Run | W15: Venkat
A16: TC-AUTH-012 | B16: Authentication | C16: Authentication | D16: Session persistence across refresh | E16: Session persistence across refresh | F16: P1 | G16: Major | H16: Persistence | I16: Authenticated | J16: user | K16: FREE_USER_01 | L16: Logged in. App URL available. Browser DevTools permitted. | M16: Closed Beta / QA Target | N16: Use approved test credentials from Test Accounts sheet. | O16: 1. Login as FREE_USER_01. 2. Open Dashboard. 3. Hard refresh. 4. Confirm still authenticated. | P16: 1. Logged in. 2. Dashboard visible. 3. Refresh completes. 4. Still logged in (unless product uses short-lived sessions — then re-auth is clear). | Q16: Session persists across refresh per product rules. | R16: Observable UI state matches expected results; no unexplained spinner; no silent failure; persistence verified via refresh where applicable. | S16: Screenshot of final state. On fail: URL, visible error, Network status if DevTools allowed. | U16: Not Run | W16: Venkat
A17: TC-AUTH-014 | B17: Authentication | C17: Authentication | D17: OAuth login (if configured) | E17: OAuth login (if configured) | F17: P1 | G17: Major | H17: Positive | I17: Guest | J17: guest | K17: GUEST | L17: Logged in. App URL available. Browser DevTools permitted. | M17: Closed Beta / QA Target | N17: Use approved test credentials from Test Accounts sheet. | O17: 1. On https://clarify.ai.sltfinanceindia.com/login, if Google/OAuth button is shown, click it. 2. Complete or cancel provider consent with approved test identity. 3. If button absent, mark Requires Configuration / N/A. | P17: 1. OAuth control visible or absent honestly. 2. Success returns to app; cancel returns safely. 3. N/A recorded if not configured — not a Pass. | Q17: OAuth works when configured; otherwise classified Requires Configuration. | R17: Observable UI state matches expected results; no unexplained spinner; no silent failure; persistence verified via refresh where applicable. | S17: Screenshot of final state. On fail: URL, visible error, Network status if DevTools allowed. | U17: Not Run | W17: Venkat | Y17: Do not mark Pass merely because the button exists.
A18: TC-AUTH-016 | B18: Authentication | C18: Authentication | D18: Expired / invalid session action | E18: Expired / invalid session action | F18: P1 | G18: Major | H18: Security | I18: Authenticated | J18: user | K18: EXPIRED_SESSION_01 | L18: Logged in. App URL available. Browser DevTools permitted. | M18: Closed Beta / QA Target | N18: Use approved test credentials from Test Accounts sheet. | O18: 1. Login as FREE_USER_01. 2. Per QA playbook, expire session (idle wait or clear auth storage as instructed — do not reverse-engineer tokens). 3. Attempt a protected action (open Sessions, start Practice). | P18: 1. Initially authenticated. 2. Session becomes invalid. 3. User prompted to re-login; no partial private data flash. | Q18: Expired sessions force safe re-authentication. | R18: Observable UI state matches expected results; no unexplained spinner; no silent failure; persistence verified via refresh where applicable. | S18: Screenshot of final state. On fail: URL, visible error, Network status if DevTools allowed. | U18: Not Run | W18: Venkat
A19: TC-AUTH-015 | B19: Authentication | C19: Authentication | D19: MFA (if configured) | E19: MFA (if configured) | F19: P2 | G19: Major | H19: Security | I19: Authenticated | J19: user | K19: PRO_USER_01 | L19: Logged in. App URL available. Browser DevTools permitted. | M19: Closed Beta / QA Target | N19: Use approved test credentials from Test Accounts sheet. | O19: 1. Login with an MFA-enabled account if provided. 2. Complete MFA challenge. 3. If MFA UI absent, record Unavailable / Requires Configuration. | P19: 1. MFA prompt appears when enabled. 2. Valid code grants access; invalid denied. 3. Honest classification if not present. | Q19: MFA enforced when enabled for the account. | R19: Observable UI state matches expected results; no unexplained spinner; no silent failure; persistence verified via refresh where applicable. | S19: Screenshot of final state. On fail: URL, visible error, Network status if DevTools allowed. | U19: Not Run | W19: Venkat
A20: TC-AUTH-005 | B20: Authentication | C20: Authentication | D20: Password visibility toggle | E20: Password visibility toggle | F20: P3 | G20: Minor | H20: Positive | I20: Guest | J20: guest | K20: GUEST | L20: Logged in. App URL available. Browser DevTools permitted. | M20: Closed Beta / QA Target | N20: Use approved test credentials from Test Accounts sheet. | O20: 1. Open https://clarify.ai.sltfinanceindia.com/login. 2. Type a password. 3. Toggle show/hide if control exists. | P20: 1. Form loads. 2. Password masked by default. 3. Toggle reveals/hides; does not clear value unexpectedly. | Q20: Password visibility control works if present. | R20: Observable UI state matches expected results; no unexplained spinner; no silent failure; persistence verified via refresh where applicable. | S20: Screenshot of final state. On fail: URL, visible error, Network status if DevTools allowed. | U20: Not Run | W20: Venkat

Sheet 08 Onboarding
A1: 08 Onboarding
A2: PRE-FILLED for you. ONLY update peach columns: Actual Result | Pass/Fail | Defect ID | Execution Date | Notes. Tester is pre-assigned (Anushka / Sultana / Venkat). Complete assigned work within 2 days. Mark section ALL FILLED on '00b Section Completion Gate' ONLY when every case has Pass/Fail ≠ Not Run AND Actual Result filled. Black-box only — no source/DB/server access. Opening a page is NOT Pass.
A4: Test Case ID | B4: Module | C4: Sub-Module | D4: Feature | E4: Workflow | F4: Priority | G4: Severity | H4: Test Type | I4: User Type | J4: Role | K4: Account ID | L4: Preconditions | M4: Test Environment | N4: Test Data | O4: Exact Steps | P4: Expected Result (per step) | Q4: Final Expected Result | R4: Validation Points | S4: Screenshot / Evidence Requirement | T4: Actual Result | U4: Pass / Fail | V4: Defect ID | W4: Tester | X4: Execution Date | Y4: Notes
A5: TC-ONB-001 | B5: Onboarding | C5: Onboarding | D5: First-time user completes onboarding | E5: First-time user completes onboarding | F5: P0 | G5: Critical | H5: Positive | I5: Authenticated | J5: user | K5: NEW_USER_01 | L5: Verified email; onboarding incomplete. | M5: Closed Beta / QA Target | N5: Use approved test credentials from Test Accounts sheet. | O5: 1. Login as a verified new user who has not finished onboarding. 2. Complete required steps with valid data. 3. Finish and land on dashboard. 4. Refresh; confirm onboarding does not restart. | P5: 1. Onboarding shown. 2. Required fields validated; progress works. 3. Dashboard reachable. 4. Onboarding stays completed after refresh. | Q5: New user can complete onboarding and reach the app. | R5: Observable UI state matches expected results; no unexplained spinner; no silent failure; persistence verified via refresh where applicable. | S5: Screenshot of final state. On fail: URL, visible error, Network status if DevTools allowed. | U5: Not Run | W5: Venkat
A6: TC-ONB-007 | B6: Onboarding | C6: Onboarding | D6: Incomplete onboarding cannot access app modules | E6: Incomplete onboarding cannot access app modules | F6: P0 | G6: Critical | H6: Security | I6: Authenticated | J6: user | K6: NEW_USER_01 | L6: Logged in. App URL available. Browser DevTools permitted. | M6: Closed Beta / QA Target | N6: Use approved test credentials from Test Accounts sheet. | O6: 1. As incomplete onboarding user, paste https://clarify.ai.sltfinanceindia.com/app/live. 2. Observe gate. | P6: 1. Forced back to onboarding or blocked with message. 2. Live module not usable. | Q6: App modules blocked until onboarding complete. | R6: Observable UI state matches expected results; no unexplained spinner; no silent failure; persistence verified via refresh where applicable. | S6: Screenshot of final state. On fail: URL, visible error, Network status if DevTools allowed. | U6: Not Run | W6: Venkat
A7: TC-ONB-002 | B7: Onboarding | C7: Onboarding | D7: Required field validation | E7: Required field validation | F7: P1 | G7: Major | H7: Negative | I7: Authenticated | J7: user | K7: NEW_USER_01 | L7: Logged in. App URL available. Browser DevTools permitted. | M7: Closed Beta / QA Target | N7: Use approved test credentials from Test Accounts sheet. | O7: 1. On a required onboarding step, leave required fields empty. 2. Attempt Next/Continue. | P7: 1. Step visible. 2. Clear validation; cannot proceed. | Q7: Required onboarding fields block progress until valid. | R7: Observable UI state matches expected results; no unexplained spinner; no silent failure; persistence verified via refresh where applicable. | S7: Screenshot of final state. On fail: URL, visible error, Network status if DevTools allowed. | U7: Not Run | W7: Venkat
A8: TC-ONB-005 | B8: Onboarding | C8: Onboarding | D8: Refresh mid-onboarding | E8: Refresh mid-onboarding | F8: P1 | G8: Major | H8: Persistence | I8: Authenticated | J8: user | K8: NEW_USER_01 | L8: Logged in. App URL available. Browser DevTools permitted. | M8: Closed Beta / QA Target | N8: Use approved test credentials from Test Accounts sheet. | O8: 1. Fill a step partially. 2. Refresh browser. 3. Observe resume behavior. | P8: 1. Partial data entered. 2. Page reloads. 3. Either resumes safely or restarts with clear state — no crash/blank. | Q8: Refresh during onboarding fails gracefully. | R8: Observable UI state matches expected results; no unexplained spinner; no silent failure; persistence verified via refresh where applicable. | S8: Screenshot of final state. On fail: URL, visible error, Network status if DevTools allowed. | U8: Not Run | W8: Venkat
A9: TC-ONB-008 | B9: Onboarding | C9: Onboarding | D9: Completed user does not see onboarding again | E9: Completed user does not see onboarding again | F9: P1 | G9: Major | H9: Positive | I9: Authenticated | J9: user | K9: FREE_USER_01 | L9: Logged in. App URL available. Browser DevTools permitted. | M9: Closed Beta / QA Target | N9: Use approved test credentials from Test Accounts sheet. | O9: 1. Login as FREE_USER_01 (fully onboarded). 2. Open https://clarify.ai.sltfinanceindia.com/onboarding if linked. 3. Confirm behavior is redirect or completed state. | P9: 1. Lands on app. 2. Onboarding not forced again. 3. No broken wizard. | Q9: Completed onboarding is not re-forced on normal login. | R9: Observable UI state matches expected results; no unexplained spinner; no silent failure; persistence verified via refresh where applicable. | S9: Screenshot of final state. On fail: URL, visible error, Network status if DevTools allowed. | U9: Not Run | W9: Venkat
A10: TC-ONB-003 | B10: Onboarding | C10: Onboarding | D10: Optional fields skippable | E10: Optional fields skippable | F10: P2 | G10: Minor | H10: Positive | I10: Authenticated | J10: user | K10: NEW_USER_01 | L10: Logged in. App URL available. Browser DevTools permitted. | M10: Closed Beta / QA Target | N10: Use approved test credentials from Test Accounts sheet. | O10: 1. Reach optional setup step if present. 2. Skip or leave optional fields blank. 3. Continue. | P10: 1. Optional step identifiable. 2. Skip allowed. 3. Progress continues. | Q10: Optional onboarding can be skipped. | R10: Observable UI state matches expected results; no unexplained spinner; no silent failure; persistence verified via refresh where applicable. | S10: Screenshot of final state. On fail: URL, visible error, Network status if DevTools allowed. | U10: Not Run | W10: Venkat
A11: TC-ONB-004 | B11: Onboarding | C11: Onboarding | D11: Back / Next navigation | E11: Back / Next navigation | F11: P2 | G11: Minor | H11: Positive | I11: Authenticated | J11: user | K11: NEW_USER_01 | L11: Logged in. App URL available. Browser DevTools permitted. | M11: Closed Beta / QA Target | N11: Use approved test credentials from Test Accounts sheet. | O11: 1. Move forward one step. 2. Use Back/Previous. 3. Confirm prior values retained if product preserves them. | P11: 1. Next advances. 2. Back returns. 3. Data retention matches product behavior (document actual). | Q11: Onboarding step navigation works without losing the flow. | R11: Observable UI state matches expected results; no unexplained spinner; no silent failure; persistence verified via refresh where applicable. | S11: Screenshot of final state. On fail: URL, visible error, Network status if DevTools allowed. | U11: Not Run | W11: Venkat
A12: TC-ONB-006 | B12: Onboarding | C12: Onboarding | D12: Browser back during onboarding | E12: Browser back during onboarding | F12: P2 | G12: Minor | H12: Positive | I12: Authenticated | J12: user | K12: NEW_USER_01 | L12: Logged in. App URL available. Browser DevTools permitted. | M12: Closed Beta / QA Target | N12: Use approved test credentials from Test Accounts sheet. | O12: 1. Advance two steps. 2. Use browser Back button. 3. Continue forward again. | P12: 1. Progressed. 2. Returns to prior step or safe state. 3. Can continue without stuck loop. | Q12: Browser back does not permanently trap the user. | R12: Observable UI state matches expected results; no unexplained spinner; no silent failure; persistence verified via refresh where applicable. | S12: Screenshot of final state. On fail: URL, visible error, Network status if DevTools allowed. | U12: Not Run | W12: Venkat

Sheet 09 Dashboard
A1: 09 Dashboard
A2: PRE-FILLED for you. ONLY update peach columns: Actual Result | Pass/Fail | Defect ID | Execution Date | Notes. Tester is pre-assigned (Anushka / Sultana / Venkat). Complete assigned work within 2 days. Mark section ALL FILLED on '00b Section Completion Gate' ONLY when every case has Pass/Fail ≠ Not Run AND Actual Result filled. Black-box only — no source/DB/server access. Opening a page is NOT Pass.
A4: Test Case ID | B4: Module | C4: Sub-Module | D4: Feature | E4: Workflow | F4: Priority | G4: Severity | H4: Test Type | I4: User Type | J4: Role | K4: Account ID | L4: Preconditions | M4: Test Environment | N4: Test Data | O4: Exact Steps | P4: Expected Result (per step) | Q4: Final Expected Result | R4: Validation Points | S4: Screenshot / Evidence Requirement | T4: Actual Result | U4: Pass / Fail | V4: Defect ID | W4: Tester | X4: Execution Date | Y4: Notes
A5: TC-DASH-001 | B5: Dashboard | C5: Dashboard | D5: Dashboard loads | E5: Dashboard loads | F5: P0 | G5: Critical | H5: Positive | I5: Authenticated | J5: user | K5: FREE_USER_01 | L5: Logged in. App URL available. Browser DevTools permitted. | M5: Closed Beta / QA Target | N5: Use approved test credentials from Test Accounts sheet. | O5: 1. Login FREE_USER_01. 2. Open https://clarify.ai.sltfinanceindia.com/app/dashboard. 3. Wait for widgets. | P5: 1. Authenticated. 2. Dashboard route loads. 3. Widgets/KPIs/shortcuts visible or honest empty states. | Q5: Dashboard renders without infinite loading. | R5: Observable UI state matches expected results; no unexplained spinner; no silent failure; persistence verified via refresh where applicable. | S5: Screenshot of final state. On fail: URL, visible error, Network status if DevTools allowed. | U5: Not Run | W5: Sultana
A6: TC-DASH-002 | B6: Dashboard | C6: Dashboard | D6: Credits / plan visible | E6: Credits / plan visible | F6: P1 | G6: Major | H6: Positive | I6: Authenticated | J6: user | K6: PRO_USER_01 | L6: Logged in. App URL available. Browser DevTools permitted. | M6: Closed Beta / QA Target | N6: Use approved test credentials from Test Accounts sheet. | O6: 1. On dashboard, locate credits/plan indicators. 2. Open Usage/Billing and compare visible balance roughly. | P6: 1. Credits/plan shown if product displays them. 2. No contradictory impossible values without explanation. | Q6: Dashboard credit/plan display is user-consistent. | R6: Observable UI state matches expected results; no unexplained spinner; no silent failure; persistence verified via refresh where applicable. | S6: Screenshot of final state. On fail: URL, visible error, Network status if DevTools allowed. | U6: Not Run | W6: Sultana
A7: TC-DASH-003 | B7: Dashboard | C7: Dashboard | D7: Recent sessions / activity | E7: Recent sessions / activity | F7: P1 | G7: Major | H7: Positive | I7: Authenticated | J7: user | K7: HISTORY_USER_01 | L7: Logged in. App URL available. Browser DevTools permitted. | M7: Closed Beta / QA Target | N7: Use approved test credentials from Test Accounts sheet. | O7: 1. As HISTORY_USER_01 open dashboard. 2. Open a recent session shortcut if present. 3. As NO_HISTORY_01 confirm empty state. | P7: 1. Recent items appear when history exists. 2. Navigation works. 3. Empty state clear — not an error. | Q7: Recent activity and empty states behave correctly. | R7: Observable UI state matches expected results; no unexplained spinner; no silent failure; persistence verified via refresh where applicable. | S7: Screenshot of final state. On fail: URL, visible error, Network status if DevTools allowed. | U7: Not Run | W7: Sultana
A8: TC-DASH-004 | B8: Dashboard | C8: Dashboard | D8: Shortcuts / CTAs | E8: Shortcuts / CTAs | F8: P1 | G8: Major | H8: Positive | I8: Authenticated | J8: user | K8: PRO_USER_01 | L8: Logged in. App URL available. Browser DevTools permitted. | M8: Closed Beta / QA Target | N8: Use approved test credentials from Test Accounts sheet. | O8: 1. Click each primary dashboard shortcut (Practice Coach, Mock, Gov Exams, Prep, etc.). 2. Confirm destination module loads. | P8: 1. Each shortcut navigates. 2. Destination is the expected module (or plan gate / coming soon — honest). | Q8: Dashboard shortcuts navigate to real modules. | R8: Observable UI state matches expected results; no unexplained spinner; no silent failure; persistence verified via refresh where applicable. | S8: Screenshot of final state. On fail: URL, visible error, Network status if DevTools allowed. | U8: Not Run | W8: Sultana | Y8: Do not Pass a shortcut that only opens a dead page.
A9: TC-DASH-005 | B9: Dashboard | C9: Dashboard | D9: Loading and error retry | E9: Loading and error retry | F9: P2 | G9: Minor | H9: Negative | I9: Authenticated | J9: user | K9: FREE_USER_01 | L9: Logged in. App URL available. Browser DevTools permitted. | M9: Closed Beta / QA Target | N9: Use approved test credentials from Test Accounts sheet. | O9: 1. Throttle network to Slow 3G (DevTools) if permitted. 2. Reload dashboard. 3. Restore network; use Retry if shown. | P9: 1. Network slowed. 2. Loading indicators appear; eventual error or success. 3. Retry recovers or shows clear failure. | Q9: Dashboard handles slow/error network gracefully. | R9: Observable UI state matches expected results; no unexplained spinner; no silent failure; persistence verified via refresh where applicable. | S9: Screenshot of final state. On fail: URL, visible error, Network status if DevTools allowed. | U9: Not Run | W9: Sultana
A10: TC-DASH-006 | B10: Dashboard | C10: Dashboard | D10: Interview Day page | E10: Interview Day page | F10: P2 | G10: Minor | H10: Positive | I10: Authenticated | J10: user | K10: FREE_USER_01 | L10: Logged in. App URL available. Browser DevTools permitted. | M10: Closed Beta / QA Target | N10: Use approved test credentials from Test Accounts sheet. | O10: 1. Open https://clarify.ai.sltfinanceindia.com/app/interview-day. 2. Verify layout and any scheduled items/empty state. | P10: 1. Page loads. 2. Content or empty state; no crash. | Q10: Interview Day page is usable. | R10: Observable UI state matches expected results; no unexplained spinner; no silent failure; persistence verified via refresh where applicable. | S10: Screenshot of final state. On fail: URL, visible error, Network status if DevTools allowed. | U10: Not Run | W10: Sultana
A11: TC-DASH-007 | B11: Dashboard | C11: Dashboard | D11: Notifications entry | E11: Notifications entry | F11: P2 | G11: Minor | H11: Positive | I11: Authenticated | J11: user | K11: FREE_USER_01 | L11: Logged in. App URL available. Browser DevTools permitted. | M11: Closed Beta / QA Target | N11: Use approved test credentials from Test Accounts sheet. | O11: 1. From dashboard/header open Notifications. 2. Verify list or empty state. | P11: 1. Notifications page/panel opens. 2. Readable list or empty state. | Q11: Notifications reachable from chrome. | R11: Observable UI state matches expected results; no unexplained spinner; no silent failure; persistence verified via refresh where applicable. | S11: Screenshot of final state. On fail: URL, visible error, Network status if DevTools allowed. | U11: Not Run | W11: Sultana
A12: TC-DASH-008 | B12: Dashboard | C12: Dashboard | D12: Referrals page | E12: Referrals page | F12: P2 | G12: Minor | H12: Persistence | I12: Authenticated | J12: user | K12: FREE_USER_01 | L12: Logged in. App URL available. Browser DevTools permitted. | M12: Closed Beta / QA Target | N12: Use approved test credentials from Test Accounts sheet. | O12: 1. Open https://clarify.ai.sltfinanceindia.com/app/referrals. 2. Copy referral code/link if shown. 3. Refresh; confirm code persists. | P12: 1. Page loads. 2. Code/link usable. 3. Persists after refresh. | Q12: Referrals page works and persists codes. | R12: Observable UI state matches expected results; no unexplained spinner; no silent failure; persistence verified via refresh where applicable. | S12: Screenshot of final state. On fail: URL, visible error, Network status if DevTools allowed. | U12: Not Run | W12: Sultana

Sheet 10 Practice Coach
A1: 10 Practice Coach
A2: PRE-FILLED for you. ONLY update peach columns: Actual Result | Pass/Fail | Defect ID | Execution Date | Notes. Tester is pre-assigned (Anushka / Sultana / Venkat). Complete assigned work within 2 days. Mark section ALL FILLED on '00b Section Completion Gate' ONLY when every case has Pass/Fail ≠ Not Run AND Actual Result filled. Black-box only — no source/DB/server access. Opening a page is NOT Pass.
A4: Test Case ID | B4: Module | C4: Sub-Module | D4: Feature | E4: Workflow | F4: Priority | G4: Severity | H4: Test Type | I4: User Type | J4: Role | K4: Account ID | L4: Preconditions | M4: Test Environment | N4: Test Data | O4: Exact Steps | P4: Expected Result (per step) | Q4: Final Expected Result | R4: Validation Points | S4: Screenshot / Evidence Requirement | T4: Actual Result | U4: Pass / Fail | V4: Defect ID | W4: Tester | X4: Execution Date | Y4: Notes
A5: TC-PC-001 | B5: Practice Coach | C5: Setup | D5: Setup wizard required fields | E5: Setup wizard required fields | F5: P0 | G5: Critical | H5: Positive | I5: Authenticated | J5: user | K5: SUFFICIENT_CREDIT_01 | L5: Logged in. App URL available. Browser DevTools permitted. | M5: Closed Beta / QA Target | N5: Use approved test credentials from Test Accounts sheet. | O5: 1. Open https://clarify.ai.sltfinanceindia.com/app/live. 2. Leave required fields empty; try Start. 3. Fill required fields with valid data. | P5: 1. Setup loads. 2. Validation blocks start. 3. Valid data enables start. | Q5: Setup validates required fields before start. | R5: Observable UI state matches expected results; no unexplained spinner; no silent failure; persistence verified via refresh where applicable. | S5: Screenshot of final state. On fail: URL, visible error, Network status if DevTools allowed. | U5: Not Run | W5: Anushka
A6: TC-PC-002 | B6: Practice Coach | C6: Audio | D6: Microphone permission denied | E6: Microphone permission denied | F6: P0 | G6: Critical | H6: Negative | I6: Authenticated | J6: user | K6: SUFFICIENT_CREDIT_01 | L6: Logged in. App URL available. Browser DevTools permitted. | M6: Closed Beta / QA Target | N6: Use approved test credentials from Test Accounts sheet. | O6: 1. Deny microphone in browser prompt. 2. Attempt to start Practice Coach. 3. Observe guidance. | P6: 1. Permission denied. 2. Start blocked or clear error. 3. User told how to enable mic — no silent hang. | Q6: Mic denial fails gracefully with actionable message. | R6: Observable UI state matches expected results; no unexplained spinner; no silent failure; persistence verified via refresh where applicable. | S6: Screenshot of final state. On fail: URL, visible error, Network status if DevTools allowed. | U6: Not Run | W6: Anushka
A7: TC-PC-003 | B7: Practice Coach | C7: Session | D7: Microphone permission granted — session starts | E7: Microphone permission granted — session starts | F7: P0 | G7: Critical | H7: Positive | I7: Authenticated | J7: user | K7: SUFFICIENT_CREDIT_01 | L7: Logged in. App URL available. Browser DevTools permitted. | M7: Closed Beta / QA Target | N7: Use approved test credentials from Test Accounts sheet. | O7: 1. Allow microphone. 2. Complete setup and start. 3. Confirm session UI / overlay appears. | P7: 1. Mic allowed. 2. Start succeeds (or clear credit/plan gate). 3. Live session UI visible. | Q7: With mic + credits, session starts. | R7: Observable UI state matches expected results; no unexplained spinner; no silent failure; persistence verified via refresh where applicable. | S7: Screenshot of final state. On fail: URL, visible error, Network status if DevTools allowed. | U7: Not Run | W7: Anushka
A8: TC-PC-005 | B8: Practice Coach | C8: AI Help | D8: Current question / hint / AI answer visible | E8: Current question / hint / AI answer visible | F8: P0 | G8: Critical | H8: Positive | I8: Authenticated | J8: user | K8: SUFFICIENT_CREDIT_01 | L8: Logged in. App URL available. Browser DevTools permitted. | M8: Closed Beta / QA Target | N8: Use approved test credentials from Test Accounts sheet. | O8: 1. In active session, trigger hint/AI help controls. 2. Speak or use chat if available. 3. Observe responses appear in UI. | P8: 1. Controls respond. 2. Input accepted. 3. AI content appears OR clear failure (not infinite Generating). | Q8: Hints/AI answers are real responses or honest failures. | R8: Observable UI state matches expected results; no unexplained spinner; no silent failure; persistence verified via refresh where applicable. | S8: Screenshot of final state. On fail: URL, visible error, Network status if DevTools allowed. | U8: Not Run | W8: Anushka | Y8: Bubble alone ≠ Pass.
A9: TC-PC-006 | B9: Practice Coach | C9: Transcript | D9: Transcript updates | E9: Transcript updates | F9: P0 | G9: Critical | H9: Positive | I9: Authenticated | J9: user | K9: SUFFICIENT_CREDIT_01 | L9: Logged in. App URL available. Browser DevTools permitted. | M9: Closed Beta / QA Target | N9: Use approved test credentials from Test Accounts sheet. | O9: 1. Speak a short phrase with mic on. 2. Watch transcript panel. 3. Pause speaking; confirm no runaway ghosts. | P9: 1. Audio captured. 2. Transcript text appears within reasonable time OR STT error shown. 3. Stable UI. | Q9: Transcript reflects speech or shows STT failure clearly. | R9: Observable UI state matches expected results; no unexplained spinner; no silent failure; persistence verified via refresh where applicable. | S9: Screenshot of final state. On fail: URL, visible error, Network status if DevTools allowed. | U9: Not Run | W9: Anushka
A10: TC-PC-010 | B10: Practice Coach | C10: End | D10: End session → summary | E10: End session → summary | F10: P0 | G10: Critical | H10: Persistence | I10: Authenticated | J10: user | K10: SUFFICIENT_CREDIT_01 | L10: Logged in. App URL available. Browser DevTools permitted. | M10: Closed Beta / QA Target | N10: Use approved test credentials from Test Accounts sheet. | O10: 1. End session via End control. 2. View summary. 3. Refresh summary/sessions list. 4. Reopen session record. | P10: 1. Session ends. 2. Summary shown. 3. Record persists. 4. Detail still available. | Q10: Ending session produces a persisted summary. | R10: Observable UI state matches expected results; no unexplained spinner; no silent failure; persistence verified via refresh where applicable. | S10: Screenshot of final state. On fail: URL, visible error, Network status if DevTools allowed. | U10: Not Run | W10: Anushka
A11: TC-PC-012 | B11: Practice Coach | C11: Credits | D11: Insufficient credits blocks AI | E11: Insufficient credits blocks AI | F11: P0 | G11: Critical | H11: Negative | I11: Authenticated | J11: user | K11: ZERO_CREDIT_01 | L11: Logged in. App URL available. Browser DevTools permitted. | M11: Closed Beta / QA Target | N11: Use approved test credentials from Test Accounts sheet. | O11: 1. Login ZERO_CREDIT_01. 2. Attempt Practice Coach AI features / start if credit-gated. 3. Observe messaging. | P11: 1. Zero balance visible. 2. Action blocked or upgrade prompt. 3. No false success; no infinite spinner. | Q11: Zero credits fail gracefully for credit-gated coach actions. | R11: Observable UI state matches expected results; no unexplained spinner; no silent failure; persistence verified via refresh where applicable. | S11: Screenshot of final state. On fail: URL, visible error, Network status if DevTools allowed. | U11: Not Run | W11: Anushka
A12: TC-PC-013 | B12: Practice Coach | C12: AI Fallback | D12: AI unavailable visible failure | E12: AI unavailable visible failure | F12: P0 | G12: Critical | H12: Negative | I12: Authenticated | J12: user | K12: SUFFICIENT_CREDIT_01 | L12: Logged in. App URL available. Browser DevTools permitted. | M12: Closed Beta / QA Target | N12: Use approved test credentials from Test Accounts sheet. | O12: 1. If QA lead provides AI-down window OR simulate offline after start. 2. Request AI hint/answer. 3. Observe UI for timeout ≤ product SLA. | P12: 1. Failure mode active. 2. Request attempted. 3. Clear error or fallback — never endless Generating; no false credit error if credits remain. | Q12: AI outage surfaces honest user-visible failure/fallback. | R12: Observable UI state matches expected results; no unexplained spinner; no silent failure; persistence verified via refresh where applicable. | S12: Screenshot of final state. On fail: URL, visible error, Network status if DevTools allowed. | U12: Not Run | W12: Anushka | Y12: Coordinate AI-down window with QA lead.
A13: TC-PC-014 | B13: Practice Coach | C13: STT | D13: Deepgram / STT unavailable | E13: Deepgram / STT unavailable | F13: P0 | G13: Critical | H13: Negative | I13: Authenticated | J13: user | K13: SUFFICIENT_CREDIT_01 | L13: Logged in. App URL available. Browser DevTools permitted. | M13: Closed Beta / QA Target | N13: Use approved test credentials from Test Accounts sheet. | O13: 1. During QA STT-down window (or deny/network block STT host if permitted). 2. Speak. 3. Observe status badge/error. | P13: 1. STT impaired. 2. Speech attempted. 3. Clear audio/STT error; session can be ended safely. | Q13: STT failure is visible and non-destructive. | R13: Observable UI state matches expected results; no unexplained spinner; no silent failure; persistence verified via refresh where applicable. | S13: Screenshot of final state. On fail: URL, visible error, Network status if DevTools allowed. | U13: Not Run | W13: Anushka
A14: TC-PC-004 | B14: Practice Coach | C14: Compliance | D14: Consent / compliance banner | E14: Consent / compliance banner | F14: P1 | G14: Major | H14: Positive | I14: Authenticated | J14: user | K14: SUFFICIENT_CREDIT_01 | L14: Logged in. App URL available. Browser DevTools permitted. | M14: Closed Beta / QA Target | N14: Use approved test credentials from Test Accounts sheet. | O14: 1. Start session. 2. Read consent/compliance messaging if shown. 3. Accept/continue as required. | P14: 1. Session path begins. 2. Consent visible when required. 3. Cannot proceed without required acknowledgment if product requires it. | Q14: Consent requirements are enforceable and visible. | R14: Observable UI state matches expected results; no unexplained spinner; no silent failure; persistence verified via refresh where applicable. | S14: Screenshot of final state. On fail: URL, visible error, Network status if DevTools allowed. | U14: Not Run | W14: Anushka
A15: TC-PC-007 | B15: Practice Coach | C15: Chat | D15: Chat during session | E15: Chat during session | F15: P1 | G15: Major | H15: Positive | I15: Authenticated | J15: user | K15: SUFFICIENT_CREDIT_01 | L15: Logged in. App URL available. Browser DevTools permitted. | M15: Closed Beta / QA Target | N15: Use approved test credentials from Test Accounts sheet. | O15: 1. Open session chat if present. 2. Send a message. 3. Wait for reply. 4. Duplicate-click Send once. | P15: 1. Chat opens. 2. Message sends. 3. Reply or clear error. 4. No duplicate charge storm / duplicate posts beyond product rules. | Q15: In-session chat works; duplicate send is safe. | R15: Observable UI state matches expected results; no unexplained spinner; no silent failure; persistence verified via refresh where applicable. | S15: Screenshot of final state. On fail: URL, visible error, Network status if DevTools allowed. | U15: Not Run | W15: Anushka
A16: TC-PC-009 | B16: Practice Coach | C16: Session | D16: Pause and resume | E16: Pause and resume | F16: P1 | G16: Major | H16: Positive | I16: Authenticated | J16: user | K16: SUFFICIENT_CREDIT_01 | L16: Logged in. App URL available. Browser DevTools permitted. | M16: Closed Beta / QA Target | N16: Use approved test credentials from Test Accounts sheet. | O16: 1. Start session. 2. Pause if control exists. 3. Resume. 4. Confirm timers/transcript behavior. | P16: 1. Active. 2. Paused state clear. 3. Resumes. 4. No corrupt UI state. | Q16: Pause/resume works without breaking the session. | R16: Observable UI state matches expected results; no unexplained spinner; no silent failure; persistence verified via refresh where applicable. | S16: Screenshot of final state. On fail: URL, visible error, Network status if DevTools allowed. | U16: Not Run | W16: Anushka
A17: TC-PC-011 | B17: Practice Coach | C17: Restore | D17: Refresh mid-session restore | E17: Refresh mid-session restore | F17: P1 | G17: Major | H17: Persistence | I17: Authenticated | J17: user | K17: SUFFICIENT_CREDIT_01 | L17: Logged in. App URL available. Browser DevTools permitted. | M17: Closed Beta / QA Target | N17: Use approved test credentials from Test Accounts sheet. | O17: 1. Start session; note session URL if present. 2. Refresh. 3. Observe restore or safe end. | P17: 1. Active. 2. Reload. 3. Either restores cleanly or ends with clear message — not a stuck blank overlay. | Q17: Refresh mid-session is recoverable. | R17: Observable UI state matches expected results; no unexplained spinner; no silent failure; persistence verified via refresh where applicable. | S17: Screenshot of final state. On fail: URL, visible error, Network status if DevTools allowed. | U17: Not Run | W17: Anushka
A18: TC-PC-015 | B18: Practice Coach | C18: Audio | D18: System/tab audio where supported | E18: System/tab audio where supported | F18: P1 | G18: Major | H18: Positive | I18: Authenticated | J18: user | K18: SUFFICIENT_CREDIT_01 | L18: Logged in. App URL available. Browser DevTools permitted. | M18: Closed Beta / QA Target | N18: Use approved test credentials from Test Accounts sheet. | O18: 1. Follow in-app guide for system/tab audio. 2. Grant or deny. 3. Record observed behavior. | P18: 1. Guide/steps available. 2. Permission path works. 3. Denial shows guidance; grant enables capture OR Unavailable if unsupported browser. | Q18: System/tab audio path is honest per browser support. | R18: Observable UI state matches expected results; no unexplained spinner; no silent failure; persistence verified via refresh where applicable. | S18: Screenshot of final state. On fail: URL, visible error, Network status if DevTools allowed. | U18: Not Run | W18: Anushka
A19: TC-PC-008 | B19: Practice Coach | C19: Hotkeys | D19: Hotkeys | E19: Hotkeys | F19: P2 | G19: Minor | H19: Positive | I19: Authenticated | J19: user | K19: SUFFICIENT_CREDIT_01 | L19: Logged in. App URL available. Browser DevTools permitted. | M19: Closed Beta / QA Target | N19: Use approved test credentials from Test Accounts sheet. | O19: 1. Open hotkey help if available. 2. Trigger documented hotkeys (hint, hide, end) where safe. 3. Confirm UI reacts. | P19: 1. Help lists keys. 2. Keys perform actions. 3. No stuck overlay. | Q19: Documented hotkeys work in session. | R19: Observable UI state matches expected results; no unexplained spinner; no silent failure; persistence verified via refresh where applicable. | S19: Screenshot of final state. On fail: URL, visible error, Network status if DevTools allowed. | U19: Not Run | W19: Anushka
A20: TC-PC-016 | B20: Practice Coach | C20: Limits | D20: Rate limit visible | E20: Rate limit visible | F20: P2 | G20: Minor | H20: Negative | I20: Authenticated | J20: user | K20: SUFFICIENT_CREDIT_01 | L20: Logged in. App URL available. Browser DevTools permitted. | M20: Closed Beta / QA Target | N20: Use approved test credentials from Test Accounts sheet. | O20: 1. Rapidly request AI help many times. 2. Observe rate-limit messaging if triggered. | P20: 1. Bursts sent. 2. 429/rate-limit message or throttle — app remains usable. | Q20: Rate limiting is user-visible and non-corrupting. | R20: Observable UI state matches expected results; no unexplained spinner; no silent failure; persistence verified via refresh where applicable. | S20: Screenshot of final state. On fail: URL, visible error, Network status if DevTools allowed. | U20: Not Run | W20: Anushka

Sheet 11 Live Copilot
A1: 11 Live Copilot
A2: PRE-FILLED for you. ONLY update peach columns: Actual Result | Pass/Fail | Defect ID | Execution Date | Notes. Tester is pre-assigned (Anushka / Sultana / Venkat). Complete assigned work within 2 days. Mark section ALL FILLED on '00b Section Completion Gate' ONLY when every case has Pass/Fail ≠ Not Run AND Actual Result filled. Black-box only — no source/DB/server access. Opening a page is NOT Pass.
A4: Test Case ID | B4: Module | C4: Sub-Module | D4: Feature | E4: Workflow | F4: Priority | G4: Severity | H4: Test Type | I4: User Type | J4: Role | K4: Account ID | L4: Preconditions | M4: Test Environment | N4: Test Data | O4: Exact Steps | P4: Expected Result (per step) | Q4: Final Expected Result | R4: Validation Points | S4: Screenshot / Evidence Requirement | T4: Actual Result | U4: Pass / Fail | V4: Defect ID | W4: Tester | X4: Execution Date | Y4: Notes
A5: TC-LIVE-001 | B5: Live Copilot | C5: Live Copilot | D5: Overlay opens | E5: Overlay opens | F5: P0 | G5: Critical | H5: Positive | I5: Authenticated | J5: user | K5: SUFFICIENT_CREDIT_01 | L5: Logged in. App URL available. Browser DevTools permitted. | M5: Closed Beta / QA Target | N5: Use approved test credentials from Test Accounts sheet. | O5: 1. From Practice Coach start path, open overlay (https://clarify.ai.sltfinanceindia.com/app/live/overlay if routed). 2. Confirm overlay chrome (question, hints, controls). | P5: 1. Overlay route/UI opens. 2. Core panels visible; not blank. | Q5: Live overlay UI loads. | R5: Observable UI state matches expected results; no unexplained spinner; no silent failure; persistence verified via refresh where applicable. | S5: Screenshot of final state. On fail: URL, visible error, Network status if DevTools allowed. | U5: Not Run | W5: Anushka
A6: TC-LIVE-002 | B6: Live Copilot | C6: Live Copilot | D6: Overlay hide / stealth controls | E6: Overlay hide / stealth controls | F6: P1 | G6: Major | H6: Positive | I6: Authenticated | J6: user | K6: SUFFICIENT_CREDIT_01 | L6: Logged in. App URL available. Browser DevTools permitted. | M6: Closed Beta / QA Target | N6: Use approved test credentials from Test Accounts sheet. | O6: 1. Use hide/stealth controls if present. 2. Restore visibility. 3. Confirm app still responsive. | P6: 1. Overlay hides/minimizes. 2. Restores. 3. No stuck invisible blocking layer. | Q6: Hide/show overlay works safely. | R6: Observable UI state matches expected results; no unexplained spinner; no silent failure; persistence verified via refresh where applicable. | S6: Screenshot of final state. On fail: URL, visible error, Network status if DevTools allowed. | U6: Not Run | W6: Anushka
A7: TC-LIVE-004 | B7: Live Copilot | C7: Live Copilot | D7: Network badge / offline | E7: Network badge / offline | F7: P1 | G7: Major | H7: Negative | I7: Authenticated | J7: user | K7: SUFFICIENT_CREDIT_01 | L7: Logged in. App URL available. Browser DevTools permitted. | M7: Closed Beta / QA Target | N7: Use approved test credentials from Test Accounts sheet. | O7: 1. Go offline mid-overlay (DevTools Offline). 2. Observe badge/error. 3. Go online; confirm recovery or safe end. | P7: 1. Offline. 2. Visible network error. 3. Recovers or ends cleanly. | Q7: Overlay handles offline visibly. | R7: Observable UI state matches expected results; no unexplained spinner; no silent failure; persistence verified via refresh where applicable. | S7: Screenshot of final state. On fail: URL, visible error, Network status if DevTools allowed. | U7: Not Run | W7: Anushka
A8: TC-LIVE-003 | B8: Live Copilot | C8: Live Copilot | D8: Overlay resize / position | E8: Overlay resize / position | F8: P2 | G8: Minor | H8: Positive | I8: Authenticated | J8: user | K8: SUFFICIENT_CREDIT_01 | L8: Logged in. App URL available. Browser DevTools permitted. | M8: Closed Beta / QA Target | N8: Use approved test credentials from Test Accounts sheet. | O8: 1. Drag/resize overlay if handles exist. 2. Refresh if session restores. 3. Note whether position persists. | P8: 1. Move/resize works. 2. Session recoverable. 3. Persistence matches product (document actual). | Q8: Overlay window management works. | R8: Observable UI state matches expected results; no unexplained spinner; no silent failure; persistence verified via refresh where applicable. | S8: Screenshot of final state. On fail: URL, visible error, Network status if DevTools allowed. | U8: Not Run | W8: Anushka
A9: TC-LIVE-005 | B9: Live Copilot | C9: Live Copilot | D9: Electron overlay note | E9: Electron overlay note | F9: P2 | G9: Minor | H9: Positive | I9: Authenticated | J9: user | K9: SUFFICIENT_CREDIT_01 | L9: Logged in. App URL available. Browser DevTools permitted. | M9: Closed Beta / QA Target | N9: Use approved test credentials from Test Accounts sheet. | O9: 1. If desktop app provided, launch overlay path. 2. If only web, mark Blocked by Environment for Electron-only checks. | P9: 1. Desktop path available or N/A. 2. Classification honest. | Q9: Electron-specific overlay tested only when desktop build provided. | R9: Observable UI state matches expected results; no unexplained spinner; no silent failure; persistence verified via refresh where applicable. | S9: Screenshot of final state. On fail: URL, visible error, Network status if DevTools allowed. | U9: Not Run | W9: Anushka | Y9: Web testers mark Electron-only as Blocked by Environment.

Sheet 12 Mock Interview
A1: 12 Mock Interview
A2: PRE-FILLED for you. ONLY update peach columns: Actual Result | Pass/Fail | Defect ID | Execution Date | Notes. Tester is pre-assigned (Anushka / Sultana / Venkat). Complete assigned work within 2 days. Mark section ALL FILLED on '00b Section Completion Gate' ONLY when every case has Pass/Fail ≠ Not Run AND Actual Result filled. Black-box only — no source/DB/server access. Opening a page is NOT Pass.
A4: Test Case ID | B4: Module | C4: Sub-Module | D4: Feature | E4: Workflow | F4: Priority | G4: Severity | H4: Test Type | I4: User Type | J4: Role | K4: Account ID | L4: Preconditions | M4: Test Environment | N4: Test Data | O4: Exact Steps | P4: Expected Result (per step) | Q4: Final Expected Result | R4: Validation Points | S4: Screenshot / Evidence Requirement | T4: Actual Result | U4: Pass / Fail | V4: Defect ID | W4: Tester | X4: Execution Date | Y4: Notes
A5: TC-MOCK-001 | B5: Mock Interview | C5: Mock Interview | D5: Setup and start | E5: Setup and start | F5: P0 | G5: Critical | H5: Positive | I5: Authenticated | J5: user | K5: SUFFICIENT_CREDIT_01 | L5: Logged in. App URL available. Browser DevTools permitted. | M5: Closed Beta / QA Target | N5: Use approved test credentials from Test Accounts sheet. | O5: 1. Open https://clarify.ai.sltfinanceindia.com/app/mock. 2. Complete setup. 3. Start mock (warmup if shown). | P5: 1. Setup loads. 2. Valid config accepted. 3. Session starts. | Q5: Mock interview can be configured and started. | R5: Observable UI state matches expected results; no unexplained spinner; no silent failure; persistence verified via refresh where applicable. | S5: Screenshot of final state. On fail: URL, visible error, Network status if DevTools allowed. | U5: Not Run | W5: Anushka
A6: TC-MOCK-002 | B6: Mock Interview | C6: Mock Interview | D6: TTS not treated as user answer | E6: TTS not treated as user answer | F6: P0 | G6: Critical | H6: Positive | I6: Authenticated | J6: user | K6: SUFFICIENT_CREDIT_01 | L6: Logged in. App URL available. Browser DevTools permitted. | M6: Closed Beta / QA Target | N6: Use approved test credentials from Test Accounts sheet. | O6: 1. Allow question TTS to play fully without speaking. 2. Observe whether answer advances incorrectly. 3. Provide a real answer afterward. | P6: 1. TTS plays. 2. TTS alone does not submit a user answer. 3. Real answer captured separately. | Q6: TTS audio is not mistaken for the candidate answer. | R6: Observable UI state matches expected results; no unexplained spinner; no silent failure; persistence verified via refresh where applicable. | S6: Screenshot of final state. On fail: URL, visible error, Network status if DevTools allowed. | U6: Not Run | W6: Anushka
A7: TC-MOCK-003 | B7: Mock Interview | C7: Mock Interview | D7: Next question | E7: Next question | F7: P0 | G7: Critical | H7: Positive | I7: Authenticated | J7: user | K7: SUFFICIENT_CREDIT_01 | L7: Logged in. App URL available. Browser DevTools permitted. | M7: Closed Beta / QA Target | N7: Use approved test credentials from Test Accounts sheet. | O7: 1. Answer or skip to enable Next. 2. Click Next once. 3. Confirm new question appears. | P7: 1. Ready for next. 2. Single advance. 3. Different question (unless bank exhausted — then clear message). | Q7: Next advances exactly one question. | R7: Observable UI state matches expected results; no unexplained spinner; no silent failure; persistence verified via refresh where applicable. | S7: Screenshot of final state. On fail: URL, visible error, Network status if DevTools allowed. | U7: Not Run | W7: Anushka
A8: TC-MOCK-004 | B8: Mock Interview | C8: Mock Interview | D8: Skip question | E8: Skip question | F8: P0 | G8: Critical | H8: Negative | I8: Authenticated | J8: user | K8: SUFFICIENT_CREDIT_01 | L8: Logged in. App URL available. Browser DevTools permitted. | M8: Closed Beta / QA Target | N8: Use approved test credentials from Test Accounts sheet. | O8: 1. Click Skip once. 2. Confirm advance. 3. Rapid double-click Skip. | P8: 1. Skip works. 2. One question skipped. 3. Double-click does not skip multiple unexpectedly. | Q8: Skip is single-step safe under double-click. | R8: Observable UI state matches expected results; no unexplained spinner; no silent failure; persistence verified via refresh where applicable. | S8: Screenshot of final state. On fail: URL, visible error, Network status if DevTools allowed. | U8: Not Run | W8: Anushka
A9: TC-MOCK-007 | B9: Mock Interview | C9: Mock Interview | D9: Question generation / retry | E9: Question generation / retry | F9: P0 | G9: Critical | H9: Positive | I9: Authenticated | J9: user | K9: SUFFICIENT_CREDIT_01 | L9: Logged in. App URL available. Browser DevTools permitted. | M9: Closed Beta / QA Target | N9: Use approved test credentials from Test Accounts sheet. | O9: 1. If generation spinner appears, wait. 2. On failure, use Retry. 3. Confirm questions arrive or clear failure. | P9: 1. Generating state temporary. 2. Retry available on fail. 3. No endless Generating. | Q9: Question generation completes or fails honestly. | R9: Observable UI state matches expected results; no unexplained spinner; no silent failure; persistence verified via refresh where applicable. | S9: Screenshot of final state. On fail: URL, visible error, Network status if DevTools allowed. | U9: Not Run | W9: Anushka
A10: TC-MOCK-008 | B10: Mock Interview | C10: Mock Interview | D10: End → score → result persist | E10: End → score → result persist | F10: P0 | G10: Critical | H10: Persistence | I10: Authenticated | J10: user | K10: SUFFICIENT_CREDIT_01 | L10: Logged in. App URL available. Browser DevTools permitted. | M10: Closed Beta / QA Target | N10: Use approved test credentials from Test Accounts sheet. | O10: 1. End mock. 2. View score/result. 3. Refresh. 4. Reopen from Sessions/history. | P10: 1. Ends. 2. Score/result visible. 3. Persists. 4. Reopenable. | Q10: Mock results persist after refresh and revisit. | R10: Observable UI state matches expected results; no unexplained spinner; no silent failure; persistence verified via refresh where applicable. | S10: Screenshot of final state. On fail: URL, visible error, Network status if DevTools allowed. | U10: Not Run | W10: Anushka
A11: TC-MOCK-005 | B11: Mock Interview | C11: Mock Interview | D11: Silence handling | E11: Silence handling | F11: P1 | G11: Major | H11: Positive | I11: Authenticated | J11: user | K11: SUFFICIENT_CREDIT_01 | L11: Logged in. App URL available. Browser DevTools permitted. | M11: Closed Beta / QA Target | N11: Use approved test credentials from Test Accounts sheet. | O11: 1. Remain silent for the silence timeout window. 2. Observe prompts/auto-advance behavior. | P11: 1. Silence. 2. Clear prompt, timer, or defined auto-behavior — session not permanently stuck. | Q11: Silence does not freeze the mock session. | R11: Observable UI state matches expected results; no unexplained spinner; no silent failure; persistence verified via refresh where applicable. | S11: Screenshot of final state. On fail: URL, visible error, Network status if DevTools allowed. | U11: Not Run | W11: Anushka
A12: TC-MOCK-006 | B12: Mock Interview | C12: Mock Interview | D12: Text answer input if available | E12: Text answer input if available | F12: P1 | G12: Major | H12: Positive | I12: Authenticated | J12: user | K12: SUFFICIENT_CREDIT_01 | L12: Logged in. App URL available. Browser DevTools permitted. | M12: Closed Beta / QA Target | N12: Use approved test credentials from Test Accounts sheet. | O12: 1. If text answer box exists, type an answer. 2. Submit. 3. Confirm acceptance. | P12: 1. Input available or N/A. 2. Submit works. 3. Answer reflected in session flow. | Q12: Text answers work when offered. | R12: Observable UI state matches expected results; no unexplained spinner; no silent failure; persistence verified via refresh where applicable. | S12: Screenshot of final state. On fail: URL, visible error, Network status if DevTools allowed. | U12: Not Run | W12: Anushka
A13: TC-MOCK-009 | B13: Mock Interview | C13: Mock Interview | D13: Unexpected question repeat | E13: Unexpected question repeat | F13: P1 | G13: Major | H13: Positive | I13: Authenticated | J13: user | K13: SUFFICIENT_CREDIT_01 | L13: Logged in. App URL available. Browser DevTools permitted. | M13: Closed Beta / QA Target | N13: Use approved test credentials from Test Accounts sheet. | O13: 1. Complete at least 5 questions. 2. Note question texts. 3. Flag unexpected immediate repeats. | P13: 1. Flow progresses. 2. Texts recorded. 3. No pathological immediate repeats unless bank size forces it (note bank size). | Q13: Questions do not repeat unexpectedly within a session. | R13: Observable UI state matches expected results; no unexplained spinner; no silent failure; persistence verified via refresh where applicable. | S13: Screenshot of final state. On fail: URL, visible error, Network status if DevTools allowed. | U13: Not Run | W13: Anushka
A14: TC-MOCK-010 | B14: Mock Interview | C14: Mock Interview | D14: Insufficient credits | E14: Insufficient credits | F14: P1 | G14: Major | H14: Negative | I14: Authenticated | J14: user | K14: ZERO_CREDIT_01 | L14: Logged in. App URL available. Browser DevTools permitted. | M14: Closed Beta / QA Target | N14: Use approved test credentials from Test Accounts sheet. | O14: 1. As ZERO_CREDIT_01 attempt mock start/AI scoring path. 2. Observe gate. | P14: 1. Attempt made. 2. Clear credit/plan message; no half-started corrupt session. | Q14: Zero credits block mock credit-gated paths cleanly. | R14: Observable UI state matches expected results; no unexplained spinner; no silent failure; persistence verified via refresh where applicable. | S14: Screenshot of final state. On fail: URL, visible error, Network status if DevTools allowed. | U14: Not Run | W14: Anushka

Sheet 13 Government Exams
A1: 13 Government Exams
A2: PRE-FILLED for you. ONLY update peach columns: Actual Result | Pass/Fail | Defect ID | Execution Date | Notes. Tester is pre-assigned (Anushka / Sultana / Venkat). Complete assigned work within 2 days. Mark section ALL FILLED on '00b Section Completion Gate' ONLY when every case has Pass/Fail ≠ Not Run AND Actual Result filled. Black-box only — no source/DB/server access. Opening a page is NOT Pass.
A4: Test Case ID | B4: Module | C4: Sub-Module | D4: Feature | E4: Workflow | F4: Priority | G4: Severity | H4: Test Type | I4: User Type | J4: Role | K4: Account ID | L4: Preconditions | M4: Test Environment | N4: Test Data | O4: Exact Steps | P4: Expected Result (per step) | Q4: Final Expected Result | R4: Validation Points | S4: Screenshot / Evidence Requirement | T4: Actual Result | U4: Pass / Fail | V4: Defect ID | W4: Tester | X4: Execution Date | Y4: Notes
A5: TC-GOV-001 | B5: Government Exams | C5: Hub | D5: Hub loads | E5: Hub loads | F5: P0 | G5: Critical | H5: Positive | I5: Authenticated | J5: user | K5: PRO_USER_01 | L5: Logged in. App URL available. Browser DevTools permitted. | M5: Closed Beta / QA Target | N5: Use approved test credentials from Test Accounts sheet. | O5: 1. Login PRO_USER_01. 2. Open https://clarify.ai.sltfinanceindia.com/app/mock-test. 3. Observe search/selector. | P5: 1. Auth ok. 2. Hub loads (or India region gate message). 3. Search/exam list usable. | Q5: Gov exam hub is reachable and usable. | R5: Observable UI state matches expected results; no unexplained spinner; no silent failure; persistence verified via refresh where applicable. | S5: Screenshot of final state. On fail: URL, visible error, Network status if DevTools allowed. | U5: Not Run | W5: Anushka
A6: TC-GOV-002 | B6: Government Exams | C6: Search | D6: Exam search — valid query | E6: Exam search — valid query | F6: P0 | G6: Critical | H6: Positive | I6: Authenticated | J6: user | K6: PRO_USER_01 | L6: Logged in. App URL available. Browser DevTools permitted. | M6: Closed Beta / QA Target | N6: Use approved test credentials from Test Accounts sheet. | O6: 1. Type a known exam name/alias (e.g. SSC/IBPS/UPSC if listed). 2. Select a result. 3. Open exam detail. | P6: 1. Suggestions appear. 2. Selection sticks. 3. Detail page shows exam info. | Q6: Exam search returns selectable results. | R6: Observable UI state matches expected results; no unexplained spinner; no silent failure; persistence verified via refresh where applicable. | S6: Screenshot of final state. On fail: URL, visible error, Network status if DevTools allowed. | U6: Not Run | W6: Anushka
A7: TC-GOV-005 | B7: Government Exams | C7: Configure | D7: Stage / paper / language config | E7: Stage / paper / language config | F7: P0 | G7: Critical | H7: Positive | I7: Authenticated | J7: user | K7: PRO_USER_01 | L7: Logged in. App URL available. Browser DevTools permitted. | M7: Closed Beta / QA Target | N7: Use approved test credentials from Test Accounts sheet. | O7: 1. Open configure (https://clarify.ai.sltfinanceindia.com/app/mock-test/configure) for a selected exam. 2. Set stage, paper, language. 3. Continue. | P7: 1. Config UI loads. 2. Options apply. 3. Proceeds to availability/generate. | Q7: Exam configuration options apply correctly. | R7: Observable UI state matches expected results; no unexplained spinner; no silent failure; persistence verified via refresh where applicable. | S7: Screenshot of final state. On fail: URL, visible error, Network status if DevTools allowed. | U7: Not Run | W7: Anushka
A8: TC-GOV-006 | B8: Government Exams | C8: Availability | D8: Availability / approved question count | E8: Availability / approved question count | F8: P0 | G8: Critical | H8: Positive | I8: Authenticated | J8: user | K8: PRO_USER_01 | L8: Logged in. App URL available. Browser DevTools permitted. | M8: Closed Beta / QA Target | N8: Use approved test credentials from Test Accounts sheet. | O8: 1. On Review/availability panel, record the available/approved count. 2. Open Generate for the same exam/config. 3. Compare the available number on Generate with Review. 4. Attempt generate when count insufficient. 5. Attempt when sufficient. | P8: 1. Counts visible. 2. Generate screen loads. 3. Review available == Generate available (same snapshot). 4. Insufficient blocked with CONTENT_INSUFFICIENT or clear message — not infinite Generating. 5. Sufficient allows generate. | Q8: Availability gates generation honestly and Review matches Generate. | R8: Observable UI state matches expected results; no unexplained spinner; no silent failure; persistence verified via refresh where applicable. | S8: Screenshot of final state. On fail: URL, visible error, Network status if DevTools allowed. | U8: Not Run | W8: Anushka | Y8: Disagreeing Review vs Generate counts is Fail. If Edge 404 mark Blocked BLK-EDGE.
A9: TC-GOV-007 | B9: Government Exams | C9: Generate | D9: Full Mock generation | E9: Full Mock generation | F9: P0 | G9: Critical | H9: Positive | I9: Authenticated | J9: user | K9: SUFFICIENT_CREDIT_01 | L9: Logged in. App URL available. Browser DevTools permitted. | M9: Closed Beta / QA Target | N9: Use approved test credentials from Test Accounts sheet. | O9: 1. Note credit balance. 2. Choose Full Mock mode. 3. Click Generate once. 4. Wait for completion (note time) or honest failure. 5. If completed, confirm Start Exam is enabled even if count is short of pattern (toast OK). 6. If Edge 404 / never completes, stop and classify Blocked — do not Fail for undeployed stack. | P9: 1. Balance recorded. 2. Mode selected. 3. Generating progress shown. 4. Completes or clear failure ≤ timeout (CONTENT_INSUFFICIENT is Pass if bank is short). 5. Start enabled when status=completed and mock_test_id exists. 6. BLK-EDGE / BLK-PY recorded if functions/worker not live. | Q9: Full Mock generates a startable paper or fails honestly. | R9: Observable UI state matches expected results; no unexplained spinner; no silent failure; persistence verified via refresh where applicable. | S9: Screenshot of final state. On fail: URL, visible error, Network status if DevTools allowed. | U9: Not Run | W9: Anushka | Y9: Credits reserved on create, finalized only when paper exists. Undeployed Edge/Python = Blocked.
A10: TC-GOV-008 | B10: Government Exams | C10: Generate | D10: Custom Practice generation | E10: Custom Practice generation | F10: P0 | G10: Critical | H10: Positive | I10: Authenticated | J10: user | K10: SUFFICIENT_CREDIT_01 | L10: Logged in. App URL available. Browser DevTools permitted. | M10: Closed Beta / QA Target | N10: Use approved test credentials from Test Accounts sheet. | O10: 1. Choose Custom Practice; set question count within allowed min/max. 2. Generate. 3. Verify count roughly matches request (Custom may reduce; Full Mock must not clamp this). 4. Confirm paper is startable. This is the P0 live-proof path. | P10: 1. Custom settings accepted. 2. Generation completes or honest fail. 3. Paper size matches config (or explains adjustment). 4. Start Exam available. | Q10: Custom Practice generation respects configured count. | R10: Observable UI state matches expected results; no unexplained spinner; no silent failure; persistence verified via refresh where applicable. | S10: Screenshot of final state. On fail: URL, visible error, Network status if DevTools allowed. | U10: Not Run | W10: Anushka | Y10: Release gate: one completed Custom/Full Mock paper on live URL. Else RELEASE BLOCKED.
A11: TC-GOV-010 | B11: Government Exams | C11: Generate | D11: Refresh during generation | E11: Refresh during generation | F11: P0 | G11: Critical | H11: Negative | I11: Authenticated | J11: user | K11: SUFFICIENT_CREDIT_01 | L11: Logged in. App URL available. Browser DevTools permitted. | M11: Closed Beta / QA Target | N11: Use approved test credentials from Test Accounts sheet. | O11: 1. Start Generate. 2. While Generating, refresh page. 3. Observe restore/fail/retry — not infinite Generating. | P11: 1. Generating. 2. Refresh. 3. Recoverable state with truthful status. | Q11: Refresh during generation does not trap the user. | R11: Observable UI state matches expected results; no unexplained spinner; no silent failure; persistence verified via refresh where applicable. | S11: Screenshot of final state. On fail: URL, visible error, Network status if DevTools allowed. | U11: Not Run | W11: Anushka
A12: TC-GOV-011 | B12: Government Exams | C12: Generate | D12: Generation failure / retry | E12: Generation failure / retry | F12: P0 | G12: Critical | H12: Negative | I12: Authenticated | J12: user | K12: SUFFICIENT_CREDIT_01 | L12: Logged in. App URL available. Browser DevTools permitted. | M12: Closed Beta / QA Target | N12: Use approved test credentials from Test Accounts sheet. | O12: 1. If failure occurs (or during induced outage), read error. 2. Click Retry. 3. Confirm no false 'insufficient credits' when balance remains. | P12: 1. Clear failure text. 2. Retry re-attempts. 3. Credit message only if credits actually insufficient. | Q12: Generation failures are truthful and retryable. | R12: Observable UI state matches expected results; no unexplained spinner; no silent failure; persistence verified via refresh where applicable. | S12: Screenshot of final state. On fail: URL, visible error, Network status if DevTools allowed. | U12: Not Run | W12: Anushka
A13: TC-GOV-012 | B13: Government Exams | C13: AI Fallback | D13: AI gap-fill / Python fallback (user-visible) | E13: AI gap-fill / Python fallback (user-visible) | F13: P0 | G13: Critical | H13: Negative | I13: Authenticated | J13: user | K13: SUFFICIENT_CREDIT_01 | L13: Logged in. App URL available. Browser DevTools permitted. | M13: Closed Beta / QA Target | N13: Use approved test credentials from Test Accounts sheet. | O13: 1. Generate a paper in a scenario QA lead marks as AI-impaired. 2. Observe whether a valid fallback paper appears OR clear failure. 3. Confirm not stuck Generating; confirm credit messaging truthful. | P13: 1. Generate under AI impairment. 2. Fallback paper OR honest failure. 3. No infinite Generating; no false credit error. | Q13: AI failure yields fallback paper or clear failure from user perspective. | R13: Observable UI state matches expected results; no unexplained spinner; no silent failure; persistence verified via refresh where applicable. | S13: Screenshot of final state. On fail: URL, visible error, Network status if DevTools allowed. | U13: Not Run | W13: Anushka
A14: TC-GOV-015 | B14: Government Exams | C14: Runner | D14: Timer | E14: Timer | F14: P0 | G14: Critical | H14: Positive | I14: Authenticated | J14: user | K14: SUFFICIENT_CREDIT_01 | L14: Logged in. App URL available. Browser DevTools permitted. | M14: Closed Beta / QA Target | N14: Use approved test credentials from Test Accounts sheet. | O14: 1. Start test; note timer and that Start Exam succeeded. 2. Observe countdown (server clock — client must not let you add time). 3. On expiry, observe auto-submit/lock behavior. | P14: 1. Timer running from server started_at/expires_at. 2. Decrements; refresh does not extend time. 3. Expiry handled (auto-submit or lock) — not editable forever. | Q14: Exam timer enforces time boundaries. | R14: Observable UI state matches expected results; no unexplained spinner; no silent failure; persistence verified via refresh where applicable. | S14: Screenshot of final state. On fail: URL, visible error, Network status if DevTools allowed. | U14: Not Run | W14: Anushka | Y14: If start-exam 404, Blocked BLK-EDGE.
A15: TC-GOV-016 | B15: Government Exams | C15: Runner | D15: Navigation palette | E15: Navigation palette | F15: P0 | G15: Critical | H15: Positive | I15: Authenticated | J15: user | K15: SUFFICIENT_CREDIT_01 | L15: Logged in. App URL available. Browser DevTools permitted. | M15: Closed Beta / QA Target | N15: Use approved test credentials from Test Accounts sheet. | O15: 1. Use question palette to jump. 2. Mark for review. 3. Return to marked question. 4. Confirm palette states: unanswered / answered / marked / answered+marked / current. | P15: 1. Jump works. 2. Marked state visible. 3. Return works. 4. All five states distinguishable. | Q15: Palette navigation and mark-for-review work. | R15: Observable UI state matches expected results; no unexplained spinner; no silent failure; persistence verified via refresh where applicable. | S15: Screenshot of final state. On fail: URL, visible error, Network status if DevTools allowed. | U15: Not Run | W15: Anushka
A16: TC-GOV-017 | B16: Government Exams | C16: Runner | D16: Answer autosave | E16: Answer autosave | F16: P0 | G16: Critical | H16: Persistence | I16: Authenticated | J16: user | K16: SUFFICIENT_CREDIT_01 | L16: Logged in. App URL available. Browser DevTools permitted. | M16: Closed Beta / QA Target | N16: Use approved test credentials from Test Accounts sheet. | O16: 1. Select an answer. 2. Navigate away to another question and back. 3. Mark for review on the same save. 4. Refresh mid-test and confirm restore. | P16: 1. Answer selected. 2. Answer retained on navigate. 3. Marked state saved with the answer. 4. Refresh restores answers or warns — never silent loss. Stale save skipped honestly. | Q16: Answers autosave across question navigation. | R16: Observable UI state matches expected results; no unexplained spinner; no silent failure; persistence verified via refresh where applicable. | S16: Screenshot of final state. On fail: URL, visible error, Network status if DevTools allowed. | U16: Not Run | W16: Anushka | Y16: Versioned save-test-answer. ATTEMPT_EXPIRED / SUBMISSION_CONFLICT must be readable.
A17: TC-GOV-018 | B17: Government Exams | C17: Submit | D17: Partial vs final submission | E17: Partial vs final submission | F17: P0 | G17: Critical | H17: Positive | I17: Authenticated | J17: user | K17: SUFFICIENT_CREDIT_01 | L17: Logged in. App URL available. Browser DevTools permitted. | M17: Closed Beta / QA Target | N17: Use approved test credentials from Test Accounts sheet. | O17: 1. Leave some unanswered. 2. Attempt submit; confirm warning if any. 3. Final submit. 4. Confirm cannot quietly resubmit altering score. | P17: 1. Partial paper. 2. Warning or allowed per product rules. 3. Submitted. 4. Result stable; no silent double-submit corruption. | Q17: Submission handles partial answers and prevents corrupt double-submit. | R17: Observable UI state matches expected results; no unexplained spinner; no silent failure; persistence verified via refresh where applicable. | S17: Screenshot of final state. On fail: URL, visible error, Network status if DevTools allowed. | U17: Not Run | W17: Anushka
A18: TC-GOV-019 | B18: Government Exams | C18: Results | D18: Result + history persistence | E18: Result + history persistence | F18: P0 | G18: Critical | H18: Persistence | I18: Authenticated | J18: user | K18: SUFFICIENT_CREDIT_01 | L18: Logged in. App URL available. Browser DevTools permitted. | M18: Closed Beta / QA Target | N18: Use approved test credentials from Test Accounts sheet. | O18: 1. After submit, open results page. 2. Logout/login. 3. Open history/results again. | P18: 1. Score/breakdown visible. 2. Re-auth. 3. Same result still available to the owner. | Q18: Results persist across logout/login. | R18: Observable UI state matches expected results; no unexplained spinner; no silent failure; persistence verified via refresh where applicable. | S18: Screenshot of final state. On fail: URL, visible error, Network status if DevTools allowed. | U18: Not Run | W18: Anushka
A19: TC-GOV-020 | B19: Government Exams | C19: Credits | D19: Credits deducted only on success path | E19: Credits deducted only on success path | F19: P0 | G19: Critical | H19: Positive | I19: Authenticated | J19: user | K19: SUFFICIENT_CREDIT_01 | L19: Logged in. App URL available. Browser DevTools permitted. | M19: Closed Beta / QA Target | N19: Use approved test credentials from Test Accounts sheet. | O19: 1. Note credit balance. 2. Generate successfully; wait until paper exists. 3. Note new balance (finalize only on completed paper). 4. Start a generate then Cancel OR wait for fail; confirm reserved credits return. 5. Failed generate must not show insufficient credits if balance was enough. | P19: 1. Balance recorded. 2. Success path completes. 3. Charge matches UI only after paper exists. 4. Fail/cancel releases reservation. 5. No false credit error. | Q19: Credit behavior around generation is truthful (reserve → finalize / release). | R19: Observable UI state matches expected results; no unexplained spinner; no silent failure; persistence verified via refresh where applicable. | S19: Screenshot of final state. On fail: URL, visible error, Network status if DevTools allowed. | U19: Not Run | W19: Anushka | Y19: BLK-MIG if reserve RPCs not on live DB.
A20: TC-GOV-023 | B20: Government Exams | C20: Plan Gate | D20: Free user plan gate | E20: Free user plan gate | F20: P0 | G20: Critical | H20: Security | I20: Authenticated | J20: user | K20: FREE_USER_01 | L20: Logged in. App URL available. Browser DevTools permitted. | M20: Closed Beta / QA Target | N20: Use approved test credentials from Test Accounts sheet. | O20: 1. As FREE_USER_01 open gov exam generate for a pro-gated action. 2. Observe upgrade/gate. | P20: 1. Attempt. 2. Clear plan gate or limited allowance — no unauthorized full generate if gated. | Q20: Free users cannot bypass paid gov-exam capabilities. | R20: Observable UI state matches expected results; no unexplained spinner; no silent failure; persistence verified via refresh where applicable. | S20: Screenshot of final state. On fail: URL, visible error, Network status if DevTools allowed. | U20: Not Run | W20: Anushka
A21: TC-GOV-025 | B21: Government Exams | C21: Security | D21: Cross-user result isolation | E21: Cross-user result isolation | F21: P0 | G21: Critical | H21: Security | I21: Authenticated | J21: user | K21: USER_A_01 | L21: Logged in. App URL available. Browser DevTools permitted. | M21: Closed Beta / QA Target | N21: Use approved test credentials from Test Accounts sheet. | O21: 1. As USER_A complete a test; copy results URL. 2. Login USER_B; paste URL. 3. Confirm access denied/not found. | P21: 1. A has result. 2. B opens URL. 3. No A data shown. | Q21: Gov exam results are not accessible cross-user via URL. | R21: Observable UI state matches expected results; no unexplained spinner; no silent failure; persistence verified via refresh where applicable. | S21: Screenshot of final state. On fail: URL, visible error, Network status if DevTools allowed. | U21: Not Run | W21: Anushka
A22: TC-GOV-003 | B22: Government Exams | C22: Search | D22: Exam search — nonsense query | E22: Exam search — nonsense query | F22: P1 | G22: Major | H22: Negative | I22: Authenticated | J22: user | K22: PRO_USER_01 | L22: Logged in. App URL available. Browser DevTools permitted. | M22: Closed Beta / QA Target | N22: Use approved test credentials from Test Accounts sheet. | O22: 1. Search 'zzzz-not-an-exam-qqq'. 2. Observe empty/no-result state. | P22: 1. Query entered. 2. Empty state; no crash; no random wrong exam auto-selected. | Q22: Nonsense search shows empty state safely. | R22: Observable UI state matches expected results; no unexplained spinner; no silent failure; persistence verified via refresh where applicable. | S22: Screenshot of final state. On fail: URL, visible error, Network status if DevTools allowed. | U22: Not Run | W22: Anushka
A23: TC-GOV-004 | B23: Government Exams | C23: Search | D23: Alias resolution | E23: Alias resolution | F23: P1 | G23: Major | H23: Positive | I23: Authenticated | J23: user | K23: PRO_USER_01 | L23: Logged in. App URL available. Browser DevTools permitted. | M23: Closed Beta / QA Target | N23: Use approved test credentials from Test Accounts sheet. | O23: 1. Search common aliases for a known exam. 2. Confirm same exam selectable. | P23: 1. Alias queried. 2. Correct exam found or clear miss — document actual aliases that work. | Q23: Aliases resolve to the intended exam when supported. | R23: Observable UI state matches expected results; no unexplained spinner; no silent failure; persistence verified via refresh where applicable. | S23: Screenshot of final state. On fail: URL, visible error, Network status if DevTools allowed. | U23: Not Run | W23: Anushka
A24: TC-GOV-009 | B24: Government Exams | C24: Configure | D24: Boundary — below min / above max questions | E24: Boundary — below min / above max questions | F24: P1 | G24: Major | H24: Boundary | I24: Authenticated | J24: user | K24: PRO_USER_01 | L24: Logged in. App URL available. Browser DevTools permitted. | M24: Closed Beta / QA Target | N24: Use approved test credentials from Test Accounts sheet. | O24: 1. Enter question count below minimum. 2. Enter above maximum. 3. Enter zero/empty. | P24: 1. Blocked with validation. 2. Blocked with validation. 3. Blocked with validation. | Q24: Question count boundaries are enforced in UI. | R24: Observable UI state matches expected results; no unexplained spinner; no silent failure; persistence verified via refresh where applicable. | S24: Screenshot of final state. On fail: URL, visible error, Network status if DevTools allowed. | U24: Not Run | W24: Anushka
A25: TC-GOV-013 | B25: Government Exams | C25: Quality | D25: Question uniqueness in paper | E25: Question uniqueness in paper | F25: P1 | G25: Major | H25: Positive | I25: Authenticated | J25: user | K25: SUFFICIENT_CREDIT_01 | L25: Logged in. App URL available. Browser DevTools permitted. | M25: Closed Beta / QA Target | N25: Use approved test credentials from Test Accounts sheet. | O25: 1. Open generated paper/session. 2. Spot-check for duplicate question stems. 3. Record duplicates if any. | P25: 1. Paper open. 2. Review performed. 3. No unexpected duplicates (flag if found). | Q25: Generated paper does not contain unexpected duplicate questions. | R25: Observable UI state matches expected results; no unexplained spinner; no silent failure; persistence verified via refresh where applicable. | S25: Screenshot of final state. On fail: URL, visible error, Network status if DevTools allowed. | U25: Not Run | W25: Anushka
A26: TC-GOV-014 | B26: Government Exams | C26: Scoring | D26: Blueprint / marks / negative marking display | E26: Blueprint / marks / negative marking display | F26: P1 | G26: Major | H26: Positive | I26: Authenticated | J26: user | K26: SUFFICIENT_CREDIT_01 | L26: Logged in. App URL available. Browser DevTools permitted. | M26: Closed Beta / QA Target | N26: Use approved test credentials from Test Accounts sheet. | O26: 1. Before/during test, locate marks and negative marking info. 2. Answer and review score explanation after submit. | P26: 1. Marking scheme visible or documented in UI. 2. Result scoring explanation consistent with scheme shown. | Q26: Marks and negative marking are visible and consistent. | R26: Observable UI state matches expected results; no unexplained spinner; no silent failure; persistence verified via refresh where applicable. | S26: Screenshot of final state. On fail: URL, visible error, Network status if DevTools allowed. | U26: Not Run | W26: Anushka
A27: TC-GOV-021 | B27: Government Exams | C27: Modes | D27: Official paper vs realistic mock modes | E27: Official paper vs realistic mock modes | F27: P1 | G27: Major | H27: Positive | I27: Authenticated | J27: user | K27: SUFFICIENT_CREDIT_01 | L27: Logged in. App URL available. Browser DevTools permitted. | M27: Closed Beta / QA Target | N27: Use approved test credentials from Test Accounts sheet. | O27: 1. If Official/Previous Year is offered, attempt generate. 2. Confirm fail-closed empty OR licensed PYQ — never AI-written questions labeled Official. 3. Run Realistic or Custom and confirm it is not labeled Official PYQ. | P27: 1. Mode selectable or hidden honestly. 2. Official empty/fail-closed is Pass; AI fill labeled Official is Fail. 3. Realistic/Custom labels match behavior. | Q27: Paper modes are distinguishable; Official is never AI-filled. | R27: Observable UI state matches expected results; no unexplained spinner; no silent failure; persistence verified via refresh where applicable. | S27: Screenshot of final state. On fail: URL, visible error, Network status if DevTools allowed. | U27: Not Run | W27: Anushka | Y27: BLK-BANK is accepted for empty Official AFTER a Custom/Full Mock paper exists.
A28: TC-GOV-022 | B28: Government Exams | C28: Secondary | D28: My questions / upload / revision / analytics pages | E28: My questions / upload / revision / analytics pages | F28: P1 | G28: Major | H28: Positive | I28: Authenticated | J28: user | K28: PRO_USER_01 | L28: Logged in. App URL available. Browser DevTools permitted. | M28: Closed Beta / QA Target | N28: Use approved test credentials from Test Accounts sheet. | O28: 1. Visit https://clarify.ai.sltfinanceindia.com/app/mock-test/my-questions, /upload, /revision, /analytics. 2. Perform one smoke action on each (list load / upload UI / revision item / chart). | P28: 1. Pages open. 2. Each shows real UI or honest empty — classify Partial if non-functional controls. | Q28: Secondary gov-exam pages are reachable and classifiable. | R28: Observable UI state matches expected results; no unexplained spinner; no silent failure; persistence verified via refresh where applicable. | S28: Screenshot of final state. On fail: URL, visible error, Network status if DevTools allowed. | U28: Not Run | W28: Anushka
A29: TC-GOV-024 | B29: Government Exams | C29: Generate | D29: Duplicate Generate click | E29: Duplicate Generate click | F29: P1 | G29: Major | H29: Negative | I29: Authenticated | J29: user | K29: SUFFICIENT_CREDIT_01 | L29: Logged in. App URL available. Browser DevTools permitted. | M29: Closed Beta / QA Target | N29: Use approved test credentials from Test Accounts sheet. | O29: 1. Click Generate. 2. Immediately double-click Generate again. 3. Observe single paper / clear handling. | P29: 1. First click. 2. Rapid second click. 3. No duplicate charge chaos; one in-flight generation or clear queue message. | Q29: Duplicate Generate clicks are safe. | R29: Observable UI state matches expected results; no unexplained spinner; no silent failure; persistence verified via refresh where applicable. | S29: Screenshot of final state. On fail: URL, visible error, Network status if DevTools allowed. | U29: Not Run | W29: Anushka

Sheet 14 AI Coach Chatbot
A1: 14 AI Coach Chatbot
A2: PRE-FILLED for you. ONLY update peach columns: Actual Result | Pass/Fail | Defect ID | Execution Date | Notes. Tester is pre-assigned (Anushka / Sultana / Venkat). Complete assigned work within 2 days. Mark section ALL FILLED on '00b Section Completion Gate' ONLY when every case has Pass/Fail ≠ Not Run AND Actual Result filled. Black-box only — no source/DB/server access. Opening a page is NOT Pass.
A4: Test Case ID | B4: Module | C4: Sub-Module | D4: Feature | E4: Workflow | F4: Priority | G4: Severity | H4: Test Type | I4: User Type | J4: Role | K4: Account ID | L4: Preconditions | M4: Test Environment | N4: Test Data | O4: Exact Steps | P4: Expected Result (per step) | Q4: Final Expected Result | R4: Validation Points | S4: Screenshot / Evidence Requirement | T4: Actual Result | U4: Pass / Fail | V4: Defect ID | W4: Tester | X4: Execution Date | Y4: Notes
A5: TC-AI-002 | B5: AI Coach / Chatbot | C5: AI Coach / Chatbot | D5: Send message → response | E5: Send message → response | F5: P0 | G5: Critical | H5: Positive | I5: Authenticated | J5: user | K5: SUFFICIENT_CREDIT_01 | L5: Logged in. App URL available. Browser DevTools permitted. | M5: Closed Beta / QA Target | N5: Use approved test credentials from Test Accounts sheet. | O5: 1. Send 'Say hello in one sentence.' 2. Wait for response. 3. Confirm streaming or final text. | P5: 1. Message sent. 2. Response arrives OR clear error. 3. Not infinite thinking. | Q5: Chat returns a real response or honest failure. | R5: Observable UI state matches expected results; no unexplained spinner; no silent failure; persistence verified via refresh where applicable. | S5: Screenshot of final state. On fail: URL, visible error, Network status if DevTools allowed. | U5: Not Run | W5: Anushka | Y5: Never Pass only because bubble opened.
A6: TC-AI-005 | B6: AI Coach / Chatbot | C6: AI Coach / Chatbot | D6: Zero credits | E6: Zero credits | F6: P0 | G6: Critical | H6: Negative | I6: Authenticated | J6: user | K6: ZERO_CREDIT_01 | L6: Logged in. App URL available. Browser DevTools permitted. | M6: Closed Beta / QA Target | N6: Use approved test credentials from Test Accounts sheet. | O6: 1. As ZERO_CREDIT_01 send chat message requiring credits. 2. Observe block. | P6: 1. Send attempted. 2. Clear insufficient credits; no fake reply billed. | Q6: Chat credit gate works. | R6: Observable UI state matches expected results; no unexplained spinner; no silent failure; persistence verified via refresh where applicable. | S6: Screenshot of final state. On fail: URL, visible error, Network status if DevTools allowed. | U6: Not Run | W6: Anushka
A7: TC-AI-006 | B7: AI Coach / Chatbot | C7: AI Coach / Chatbot | D7: AI unavailable / fallback | E7: AI unavailable / fallback | F7: P0 | G7: Critical | H7: Negative | I7: Authenticated | J7: user | K7: SUFFICIENT_CREDIT_01 | L7: Logged in. App URL available. Browser DevTools permitted. | M7: Closed Beta / QA Target | N7: Use approved test credentials from Test Accounts sheet. | O7: 1. During AI-down window, send a message. 2. Observe fallback or error. 3. Confirm not stuck. | P7: 1. Down mode. 2. Fallback/error visible. 3. UI recoverable. | Q7: Chat fails gracefully when AI unavailable. | R7: Observable UI state matches expected results; no unexplained spinner; no silent failure; persistence verified via refresh where applicable. | S7: Screenshot of final state. On fail: URL, visible error, Network status if DevTools allowed. | U7: Not Run | W7: Anushka
A8: TC-AI-001 | B8: AI Coach / Chatbot | C8: AI Coach / Chatbot | D8: Open chat | E8: Open chat | F8: P1 | G8: Major | H8: Positive | I8: Authenticated | J8: user | K8: SUFFICIENT_CREDIT_01 | L8: Logged in. App URL available. Browser DevTools permitted. | M8: Closed Beta / QA Target | N8: Use approved test credentials from Test Accounts sheet. | O8: 1. From supported surface (overlay/dashboard/support widget), open AI chat. 2. Confirm input visible. | P8: 1. Chat opens. 2. Composer ready — opening alone is not success of AI. | Q8: Chat UI opens with input. | R8: Observable UI state matches expected results; no unexplained spinner; no silent failure; persistence verified via refresh where applicable. | S8: Screenshot of final state. On fail: URL, visible error, Network status if DevTools allowed. | U8: Not Run | W8: Anushka
A9: TC-AI-003 | B9: AI Coach / Chatbot | C9: AI Coach / Chatbot | D9: Conversation continuity | E9: Conversation continuity | F9: P1 | G9: Major | H9: Positive | I9: Authenticated | J9: user | K9: SUFFICIENT_CREDIT_01 | L9: Logged in. App URL available. Browser DevTools permitted. | M9: Closed Beta / QA Target | N9: Use approved test credentials from Test Accounts sheet. | O9: 1. Send a fact ('My target role is backend'). 2. Ask 'What role did I just say?'. 3. Observe continuity. | P9: 1. Fact sent. 2. Follow-up sent. 3. Reply reflects prior turn OR product states statelessness clearly. | Q9: Multi-turn continuity works as designed. | R9: Observable UI state matches expected results; no unexplained spinner; no silent failure; persistence verified via refresh where applicable. | S9: Screenshot of final state. On fail: URL, visible error, Network status if DevTools allowed. | U9: Not Run | W9: Anushka
A10: TC-AI-004 | B10: AI Coach / Chatbot | C10: AI Coach / Chatbot | D10: Live vs Mock context | E10: Live vs Mock context | F10: P1 | G10: Major | H10: Positive | I10: Authenticated | J10: user | K10: SUFFICIENT_CREDIT_01 | L10: Logged in. App URL available. Browser DevTools permitted. | M10: Closed Beta / QA Target | N10: Use approved test credentials from Test Accounts sheet. | O10: 1. Open chat during Live session if available; ask about current question. 2. Repeat in Mock if available. 3. Compare context awareness. | P10: 1. Live context used or honestly absent. 2. Mock context used or honestly absent. 3. No fabricated session facts. | Q10: Chat context matches the active mode without inventing data. | R10: Observable UI state matches expected results; no unexplained spinner; no silent failure; persistence verified via refresh where applicable. | S10: Screenshot of final state. On fail: URL, visible error, Network status if DevTools allowed. | U10: Not Run | W10: Anushka
A11: TC-AI-008 | B11: AI Coach / Chatbot | C11: AI Coach / Chatbot | D11: Refresh mid-chat | E11: Refresh mid-chat | F11: P1 | G11: Major | H11: Persistence | I11: Authenticated | J11: user | K11: SUFFICIENT_CREDIT_01 | L11: Logged in. App URL available. Browser DevTools permitted. | M11: Closed Beta / QA Target | N11: Use approved test credentials from Test Accounts sheet. | O11: 1. Exchange 2 messages. 2. Refresh. 3. Check history restore if product keeps history. | P11: 1. History exists. 2. Refresh. 3. History restored or clear new-thread — no crash. | Q11: Refresh during chat is safe. | R11: Observable UI state matches expected results; no unexplained spinner; no silent failure; persistence verified via refresh where applicable. | S11: Screenshot of final state. On fail: URL, visible error, Network status if DevTools allowed. | U11: Not Run | W11: Anushka
A12: TC-AI-007 | B12: AI Coach / Chatbot | C12: AI Coach / Chatbot | D12: Duplicate send | E12: Duplicate send | F12: P2 | G12: Minor | H12: Negative | I12: Authenticated | J12: user | K12: SUFFICIENT_CREDIT_01 | L12: Logged in. App URL available. Browser DevTools permitted. | M12: Closed Beta / QA Target | N12: Use approved test credentials from Test Accounts sheet. | O12: 1. Type a message. 2. Double-click Send. 3. Check one logical send / safe dedupe. | P12: 1. Draft ready. 2. Double send. 3. No duplicate spam replies beyond product rules. | Q12: Duplicate send is safe. | R12: Observable UI state matches expected results; no unexplained spinner; no silent failure; persistence verified via refresh where applicable. | S12: Screenshot of final state. On fail: URL, visible error, Network status if DevTools allowed. | U12: Not Run | W12: Anushka

Sheet 15 Prep Lab
A1: 15 Prep Lab
A2: PRE-FILLED for you. ONLY update peach columns: Actual Result | Pass/Fail | Defect ID | Execution Date | Notes. Tester is pre-assigned (Anushka / Sultana / Venkat). Complete assigned work within 2 days. Mark section ALL FILLED on '00b Section Completion Gate' ONLY when every case has Pass/Fail ≠ Not Run AND Actual Result filled. Black-box only — no source/DB/server access. Opening a page is NOT Pass.
A4: Test Case ID | B4: Module | C4: Sub-Module | D4: Feature | E4: Workflow | F4: Priority | G4: Severity | H4: Test Type | I4: User Type | J4: Role | K4: Account ID | L4: Preconditions | M4: Test Environment | N4: Test Data | O4: Exact Steps | P4: Expected Result (per step) | Q4: Final Expected Result | R4: Validation Points | S4: Screenshot / Evidence Requirement | T4: Actual Result | U4: Pass / Fail | V4: Defect ID | W4: Tester | X4: Execution Date | Y4: Notes
A5: TC-PREP-002 | B5: Prep Lab | C5: STAR | D5: STAR Builder — does not invent facts | E5: STAR Builder — does not invent facts | F5: P0 | G5: Critical | H5: Positive | I5: Authenticated | J5: user | K5: SUFFICIENT_CREDIT_01 | L5: Logged in. App URL available. Browser DevTools permitted. | M5: Closed Beta / QA Target | N5: Use approved test credentials from Test Accounts sheet. | O5: 1. Open https://clarify.ai.sltfinanceindia.com/app/prep/star-builder. 2. Enter only: Situation='Led a 2-person bugfix for login timeout'. Leave other fields minimal. 3. Generate STAR. 4. Verify output does not invent employers, metrics, or tech not supplied. | P5: 1. Form opens. 2. Sparse input entered. 3. Output generated or error. 4. No fabricated facts beyond user input (flag hallucinations). | Q5: STAR AI does not invent unsourced facts. | R5: Observable UI state matches expected results; no unexplained spinner; no silent failure; persistence verified via refresh where applicable. | S5: Screenshot of final state. On fail: URL, visible error, Network status if DevTools allowed. | U5: Not Run | W5: Sultana
A6: TC-PREP-007 | B6: Prep Lab | C6: Prep Lab | D6: AI failure fallback | E6: AI failure fallback | F6: P0 | G6: Critical | H6: Negative | I6: Authenticated | J6: user | K6: SUFFICIENT_CREDIT_01 | L6: Logged in. App URL available. Browser DevTools permitted. | M6: Closed Beta / QA Target | N6: Use approved test credentials from Test Accounts sheet. | O6: 1. During AI-down window run STAR generate. 2. Observe fallback/error. 3. Confirm credits messaging truthful. | P6: 1. Down. 2. Fallback/error. 3. No false credit error. | Q6: Prep tools fail gracefully when AI is down. | R6: Observable UI state matches expected results; no unexplained spinner; no silent failure; persistence verified via refresh where applicable. | S6: Screenshot of final state. On fail: URL, visible error, Network status if DevTools allowed. | U6: Not Run | W6: Sultana
A7: TC-PREP-001 | B7: Prep Lab | C7: Prep Lab | D7: Hub loads | E7: Hub loads | F7: P1 | G7: Major | H7: Positive | I7: Authenticated | J7: user | K7: PRO_USER_01 | L7: Logged in. App URL available. Browser DevTools permitted. | M7: Closed Beta / QA Target | N7: Use approved test credentials from Test Accounts sheet. | O7: 1. Open https://clarify.ai.sltfinanceindia.com/app/prep. 2. Open each tool card (STAR, Project, Rephraser, Coding hints, System design). | P7: 1. Hub loads. 2. Each tool opens or shows gate — classify honestly. | Q7: Prep Lab tools are reachable. | R7: Observable UI state matches expected results; no unexplained spinner; no silent failure; persistence verified via refresh where applicable. | S7: Screenshot of final state. On fail: URL, visible error, Network status if DevTools allowed. | U7: Not Run | W7: Sultana
A8: TC-PREP-003 | B8: Prep Lab | C8: Rephraser | D8: Rephraser valid input | E8: Rephraser valid input | F8: P1 | G8: Major | H8: Positive | I8: Authenticated | J8: user | K8: SUFFICIENT_CREDIT_01 | L8: Logged in. App URL available. Browser DevTools permitted. | M8: Closed Beta / QA Target | N8: Use approved test credentials from Test Accounts sheet. | O8: 1. Open https://clarify.ai.sltfinanceindia.com/app/prep/rephraser. 2. Paste a short answer. 3. Rephrase. 4. Refresh and check history if any. | P8: 1. Opens. 2. Input accepted. 3. Improved text or clear error. 4. Persistence per product. | Q8: Rephraser returns improved text or honest failure. | R8: Observable UI state matches expected results; no unexplained spinner; no silent failure; persistence verified via refresh where applicable. | S8: Screenshot of final state. On fail: URL, visible error, Network status if DevTools allowed. | U8: Not Run | W8: Sultana
A9: TC-PREP-004 | B9: Prep Lab | C9: Project | D9: Project Builder | E9: Project Builder | F9: P1 | G9: Major | H9: Positive | I9: Authenticated | J9: user | K9: SUFFICIENT_CREDIT_01 | L9: Logged in. App URL available. Browser DevTools permitted. | M9: Closed Beta / QA Target | N9: Use approved test credentials from Test Accounts sheet. | O9: 1. Open project builder. 2. Fill required fields. 3. Generate. 4. Save if available; reopen. | P9: 1. Opens. 2. Validation works. 3. Output/error. 4. Persists if save offered. | Q9: Project Builder completes a saveable flow. | R9: Observable UI state matches expected results; no unexplained spinner; no silent failure; persistence verified via refresh where applicable. | S9: Screenshot of final state. On fail: URL, visible error, Network status if DevTools allowed. | U9: Not Run | W9: Sultana
A10: TC-PREP-005 | B10: Prep Lab | C10: System Design | D10: System design tool | E10: System design tool | F10: P1 | G10: Major | H10: Positive | I10: Authenticated | J10: user | K10: SUFFICIENT_CREDIT_01 | L10: Logged in. App URL available. Browser DevTools permitted. | M10: Closed Beta / QA Target | N10: Use approved test credentials from Test Accounts sheet. | O10: 1. Open system design. 2. Submit a prompt (e.g. URL shortener). 3. Observe diagram/text output. | P10: 1. Opens. 2. Prompt sent. 3. Useful output or clear failure — not infinite load. | Q10: System design tool produces output or honest failure. | R10: Observable UI state matches expected results; no unexplained spinner; no silent failure; persistence verified via refresh where applicable. | S10: Screenshot of final state. On fail: URL, visible error, Network status if DevTools allowed. | U10: Not Run | W10: Sultana
